Workbook

Sheet Лист1
A1: metric_code | B1: metric_name | C1: Юнит | D1: трайб | E1: product | F1: тип | G1: факт | H1: макс балл | I1: metric_group | J1: Column4 | K1: Column5 | L1: metric_subgroup | M1: metric_footer | N1: recommendation | O1: is_visible | P1: recommendation_group | Q1: sort | R1: flg
A2: 22 | B2: Оповещения по бизнес-метрикам | C2: УБ | D2: ДИиН | E2: БПИФ | F2: продукт | G2: 0 | H2: 1 | I2: Алерты | M2: Светофоры целей, драйверов, воронок | N2: Внедрить систему оповещений | O2: 1 | P2: 5 | Q2: 1 | R2: 1
A3: 22 | B3: Оповещения по бизнес-метрикам | C3: УБ | D3: ДББ | E3: Брокерский счет | F3: продукт | G3: 0 | H3: 1 | I3: Алерты | M3: Светофоры целей, драйверов, воронок | N3: Внедрить систему оповещений | O3: 1 | P3: 5 | Q3: 1 | R3: 1
A4: 22 | B4: Оповещения по бизнес-метрикам | C4: CBP | D4: Сбережения клиентов | E4: Вклады+НС | F4: продукт | G4: 0 | H4: 1 | I4: Алерты | M4: Светофоры целей, драйверов, воронок | N4: Внедрить систему оповещений | O4: 1 | P4: 5 | Q4: 1 | R4: 1
A5: 22 | B5: Оповещения по бизнес-метрикам | C5: DB | D5: Социальные и зарплатные решения | E5: Военная пенсия | F5: продукт | G5: 0 | H5: 1 | I5: Алерты | M5: Светофоры целей, драйверов, воронок | N5: Внедрить систему оповещений | O5: 1 | P5: 5 | Q5: 1 | R5: 1
A6: 22 | B6: Оповещения по бизнес-метрикам | C6: УБ | D6: ДЗСПиС | E6: ДСЖ КК | F6: продукт | G6: 0 | H6: 1 | I6: Алерты | M6: Светофоры целей, драйверов, воронок | N6: Внедрить систему оповещений | O6: 1 | P6: 5 | Q6: 1 | R6: 1
A7: 22 | B7: Оповещения по бизнес-метрикам | C7: УБ | D7: ДИиН | E7: ДУ | F7: продукт | G7: 0 | H7: 1 | I7: Алерты | M7: Светофоры целей, драйверов, воронок | N7: Внедрить систему оповещений | O7: 1 | P7: 5 | Q7: 1 | R7: 1
A8: 22 | B8: Оповещения по бизнес-метрикам | C8: DB | D8: Кошелёк клиента | E8: Дебетовая карта | F8: продукт | G8: 0 | H8: 1 | I8: Алерты | M8: Светофоры целей, драйверов, воронок | N8: Внедрить систему оповещений | O8: 1 | P8: 5 | Q8: 1 | R8: 1
A9: 22 | B9: Оповещения по бизнес-метрикам | C9: DB | D9: Кошелёк клиента | E9: Детская карта | F9: продукт | G9: 0 | H9: 1 | I9: Алерты | M9: Светофоры целей, драйверов, воронок | N9: Внедрить систему оповещений | O9: 1 | P9: 5 | Q9: 1 | R9: 1
A10: 22 | B10: Оповещения по бизнес-метрикам | C10: УБ | D10: ДИиН | E10: ЗПИФ | F10: продукт | G10: 0 | H10: 1 | I10: Алерты | M10: Светофоры целей, драйверов, воронок | N10: Внедрить систему оповещений | O10: 1 | P10: 5 | Q10: 1 | R10: 1
A11: 22 | B11: Оповещения по бизнес-метрикам | C11: DB | D11: Социальные и зарплатные решения | E11: Зарплатный продукт | F11: продукт | G11: 0 | H11: 1 | I11: Алерты | M11: Светофоры целей, драйверов, воронок | N11: Внедрить систему оповещений | O11: 1 | P11: 5 | Q11: 1 | R11: 1
A12: 22 | B12: Оповещения по бизнес-метрикам | C12: УБ | D12: ДИиН | E12: ИСЖ | F12: продукт | G12: 0 | H12: 1 | I12: Алерты | M12: Светофоры целей, драйверов, воронок | N12: Внедрить систему оповещений | O12: 1 | P12: 5 | Q12: 1 | R12: 1
A13: 22 | B13: Оповещения по бизнес-метрикам | C13: УБ | D13: РИБ | E13: ИнвестКопилка | F13: продукт | G13: 0 | H13: 1 | I13: Алерты | M13: Светофоры целей, драйверов, воронок | N13: Внедрить систему оповещений | O13: 1 | P13: 5 | Q13: 1 | R13: 1
... A313: 4 | B313: Факторный анализ — драйверы 1–2 ур. | C313: PC | D313: СберМобайл | E313: СберМобайл | F313: ДЗО | G313: 0,5 | H313: 1 | I313: Цели | M313: Драйверы согласно модели бизнес-планирования выведены в Навигатор | N313: Декомпозировать значения целей на драйверы, вывести в Навигатор | O313: 1 | P313: 7 | Q313: 2 | R313: 1
A314: 7 | B314: Факторный анализ — драйверы 1–2 ур. | C314: ДомКлик | D314: Лайфстайл | E314: Личный кабинет сопровождения ипотеки (далее - ЛКС) | F314: ДЗО | G314: 1 | H314: 1 | I314: Цели | K314: В навигаторе (покрытие >90% целей) | M314: Драйверы согласно модели бизнес-планирования выведены в Навигатор | N314: Декомпозировать значения целей на драйверы, вывести в Навигатор | O314: 0 | P314: 7 | Q314: 2 | R314: 0
A315: 7 | B315: Факторный анализ — драйверы 1–2 ур. | C315: ДомКлик | D315: Лайфстайл | E315: Моя Недвижимость | F315: ДЗО | G315: 1 | H315: 1 | I315: Цели | K315: В навигаторе (покрытие >90% целей) | M315: Драйверы согласно модели бизнес-планирования выведены в Навигатор | N315: Декомпозировать значения целей на драйверы, вывести в Навигатор | O315: 0 | P315: 7 | Q315: 2 | R315: 0
A316: 7 | B316: Факторный анализ — драйверы 1–2 ур. | C316: PC | D316: СберМобайл | E316: СберМобайл | F316: ДЗО | G316: 1 | H316: 1 | I316: Цели | K316: В навигаторе (покрытие >90% целей) | M316: Драйверы согласно модели бизнес-планирования выведены в Навигатор | N316: Декомпозировать значения целей на драйверы, вывести в Навигатор | O316: 0 | P316: 7 | Q316: 2 | R316: 0
A317: 4 | B317: Факторный анализ — драйверы 1–2 ур. | C317: CBP | D317: Авто | E317: Автокредит | F317: продукт | G317: =VLOOKUP(E317,Лист2!A:D,3,0) -> 0 | H317: 1 | I317: Цели | M317: Драйверы согласно модели бизнес-планирования выведены в Навигатор | N317: Декомпозировать значения целей на драйверы, вывести в Навигатор | O317: 1 | P317: 7 | Q317: 2 | R317: 1
A318: 7 | B318: Факторный анализ — драйверы 1–2 ур. | C318: PC | D318: Развитие сервиса в каналах | E318: Колл-центр | F318: Канал | G318: 1 | H318: 1 | I318: Цели | K318: В навигаторе (покрытие >90% целей) | M318: Драйверы согласно модели бизнес-планирования выведены в Навигатор | N318: Декомпозировать значения целей на драйверы, вывести в Навигатор | O318: 0 | P318: 7 | Q318: 2 | R318: 0
A319: 3 | B319: Цели выведены на мониторинг | C319: CBP | D319: Авто | E319: Автокредит | F319: продукт | G319: =VLOOKUP(E319,Лист2!A:B,2,0) -> 0 | H319: 1 | I319: Цели | M319: Регулярное обновление в Навигаторе | N319: Обогащение целей в Навигаторе | O319: 1 | P319: 2 | Q319: 1 | R319: 1
A320: 7 | B320: Факторный анализ — драйверы 1–2 ур. | C320: PC | D320: Развитие продаж в каналах | E320: Телемаркетинг | F320: Канал | G320: 1 | H320: 1 | I320: Цели | K320: В навигаторе (покрытие >90% целей) | M320: Драйверы согласно модели бизнес-планирования выведены в Навигатор | N320: Декомпозировать значения целей на драйверы, вывести в Навигатор | O320: 0 | P320: 7 | Q320: 2 | R320: 0
A321: 5 | B321: Прогноз по целям | C321: CBP | D321: Авто | E321: Автокредит | F321: продукт | G321: =VLOOKUP(E321,Лист2!A:D,4,0) -> 0.5 | H321: 1 | I321: Цели | M321: Прогноз выведен в Навигатор | N321: Сформировать прогнозные значения, вывести в Навигатор | O321: 1 | P321: 8 | Q321: 3 | R321: 1
A322: 7 | B322: Факторный анализ — драйверы 1–2 ур. | C322: PC | D322: Платформа Phygital | E322: Чат | F322: Канал | G322: 1 | H322: 1 | I322: Цели | K322: В навигаторе (покрытие >90% целей) | M322: Драйверы согласно модели бизнес-планирования выведены в Навигатор | N322: Декомпозировать значения целей на драйверы, вывести в Навигатор | O322: 0 | P322: 7 | Q322: 2 | R322: 0
A323: 4 | B323: Факторный анализ — драйверы 1–2 ур. | C323: УБ | D323: ДИиН | E323: БПИФ | F323: продукт | G323: =VLOOKUP(E323,Лист2!A:D,3,0) -> 0 | H323: 1 | I323: Цели | M323: Драйверы согласно модели бизнес-планирования выведены в Навигатор | N323: Декомпозировать значения целей на драйверы, вывести в Навигатор | O323: 1 | P323: 7 | Q323: 2 | R323: 1
A324: 7 | B324: Факторный анализ — драйверы 1–2 ур. | C324: DP | D324: СБОЛ | E324: СБОЛ | F324: Канал | G324: 0 | H324: 1 | I324: Цели | K324: В навигаторе (покрытие >90% целей) | M324: Драйверы согласно модели бизнес-планирования выведены в Навигатор | N324: Декомпозировать значения целей на драйверы, вывести в Навигатор | O324: 0 | P324: 7 | Q324: 2 | R324: 0
A325: 3 | B325: Цели выведены на мониторинг | C325: УБ | D325: ДИиН | E325: БПИФ | F325: продукт | G325: =VLOOKUP(E325,Лист2!A:B,2,0) -> 0.5 | H325: 1 | I325: Цели | M325: Регулярное обновление в Навигаторе | N325: Обогащение целей в Навигаторе | O325: 1 | P325: 2 | Q325: 1 | R325: 1
A326: 7 | B326: Факторный анализ — драйверы 1–2 ур. | C326: DP | D326: СберKids | E326: СберKids | F326: Канал | G326: 0 | H326: 1 | I326: Цели | K326: В навигаторе (покрытие >90% целей) | M326: Драйверы согласно модели бизнес-планирования выведены в Навигатор | N326: Декомпозировать значения целей на драйверы, вывести в Навигатор | O326: 0 | P326: 7 | Q326: 2 | R326: 0
A327: 5 | B327: Прогноз по целям | C327: УБ | D327: ДИиН | E327: БПИФ | F327: продукт | G327: =VLOOKUP(E327,Лист2!A:D,4,0) -> 0.5 | H327: 1 | I327: Цели | M327: Прогноз выведен в Навигатор | N327: Сформировать прогнозные значения, вывести в Навигатор | O327: 1 | P327: 8 | Q327: 3 | R327: 1
A328: 7 | B328: Факторный анализ — драйверы 1–2 ур. | C328: DP | D328: СберИнвестор | E328: СберИнвестор | F328: Канал | G328: 0 | H328: 1 | I328: Цели | K328: В навигаторе (покрытие >90% целей) | M328: Драйверы согласно модели бизнес-планирования выведены в Навигатор | N328: Декомпозировать значения целей на драйверы, вывести в Навигатор | O328: 0 | P328: 7 | Q328: 2 | R328: 0
A329: 4 | B329: Факторный анализ — драйверы 1–2 ур. | C329: УБ | D329: ДББ | E329: Брокерский счет | F329: продукт | G329: =VLOOKUP(E329,Лист2!A:D,3,0) -> 0 | H329: 1 | I329: Цели | M329: Драйверы согласно модели бизнес-планирования выведены в Навигатор | N329: Декомпозировать значения целей на драйверы, вывести в Навигатор | O329: 1 | P329: 7 | Q329: 2 | R329: 1
A330: 7 | B330: Факторный анализ — драйверы 1–2 ур. | C330: DP | D330: Уведомления | E330: Уведомления | F330: Канал | G330: 0 | H330: 1 | I330: Цели | K330: В навигаторе (покрытие >90% целей) | M330: Драйверы согласно модели бизнес-планирования выведены в Навигатор | N330: Декомпозировать значения целей на драйверы, вывести в Навигатор | O330: 0 | P330: 7 | Q330: 2 | R330: 0
A331: 4 | B331: Факторный анализ — драйверы 1–2 ур. | C331: CBP | D331: Товарное кредитование | E331: BNPL | F331: Продукт | G331: 0 | H331: 1 | I331: Цели | M331: Драйверы согласно модели бизнес-планирования выведены в Навигатор | N331: Декомпозировать значения целей на драйверы, вывести в Навигатор | O331: 1 | P331: 7 | Q331: 2 | R331: 1
A332: 7 | B332: Факторный анализ — драйверы 1–2 ур. | C332: CBP | D332: Товарное кредитование | E332: BNPL | F332: Продукт | G332: 0 | H332: 1 | I332: Цели | K332: В навигаторе (покрытие >90% целей) | M332: Драйверы согласно модели бизнес-планирования выведены в Навигатор | N332: Декомпозировать значения целей на драйверы, вывести в Навигатор | O332: 0 | P332: 7 | Q332: 2 | R332: 0
A333: 7 | B333: Факторный анализ — драйверы 1–2 ур. | C333: ДомКлик | D333: Аренда жилья | E333: Долгосрочная Аренда | F333: ДЗО | G333: 0 | H333: 1 | I333: Цели | K333: В навигаторе (покрытие >90% целей) | M333: Драйверы согласно модели бизнес-планирования выведены в Навигатор | N333: Декомпозировать значения целей на драйверы, вывести в Навигатор | O333: 0 | P333: 7 | Q333: 2 | R333: 0
A334: 4 | B334: Факторный анализ — драйверы 1–2 ур. | C334: DB | D334: Государственные продукты и сервисы | E334: Карта Жителя | F334: ДЗО | G334: 0 | H334: 1 | I334: Цели | M334: Драйверы согласно модели бизнес-планирования выведены в Навигатор | N334: Декомпозировать значения целей на драйверы, вывести в Навигатор | O334: 1 | P334: 7 | Q334: 2 | R334: 1
A335: 4 | B335: Факторный анализ — драйверы 1–2 ур. | C335: DB | D335: Платежи | E335: Телеком (Оплата сотовой связи) и сканер QR | F335: ДЗО | G335: 0 | H335: 1 | I335: Цели | M335: Драйверы согласно модели бизнес-планирования выведены в Навигатор | N335: Декомпозировать значения целей на драйверы, вывести в Навигатор | O335: 1 | P335: 7 | Q335: 2 | R335: 1
A336: 7 | B336: Факторный анализ — драйверы 1–2 ур. | C336: DB | D336: Государственные продукты и сервисы | E336: Карта Жителя | F336: ДЗО | G336: 0 | H336: 1 | I336: Цели | K336: В навигаторе (покрытие >90% целей) | M336: Драйверы согласно модели бизнес-планирования выведены в Навигатор | N336: Декомпозировать значения целей на драйверы, вывести в Навигатор | O336: 0 | P336: 7 | Q336: 2 | R336: 0
A337: 7 | B337: Факторный анализ — драйверы 1–2 ур. | C337: DB | D337: Платежи | E337: Телеком (Оплата сотовой связи) и сканер QR | F337: ДЗО | G337: 0 | H337: 1 | I337: Цели | K337: В навигаторе (покрытие >90% целей) | M337: Драйверы согласно модели бизнес-планирования выведены в Навигатор | N337: Декомпозировать значения целей на драйверы, вывести в Навигатор | O337: 0 | P337: 7 | Q337: 2 | R337: 0
A338: 4 | B338: Факторный анализ — драйверы 1–2 ур. | C338: DB | D338: Государственные продукты и сервисы | E338: Госуслуги | F338: Исключить | G338: 0 | H338: 1 | I338: Цели | M338: Драйверы согласно модели бизнес-планирования выведены в Навигатор | N338: Декомпозировать значения целей на драйверы, вывести в Навигатор | O338: 1 | P338: 7 | Q338: 2 | R338: 1
A339: 4 | B339: Факторный анализ — драйверы 1–2 ур. | C339: DB | D339: Социальные и зарплатные решения | E339: Демаркирование карт от зарплатного продукта | F339: Исключить | G339: 0 | H339: 1 | I339: Цели | M339: Драйверы согласно модели бизнес-планирования выведены в Навигатор | N339: Декомпозировать значения целей на драйверы, вывести в Навигатор | O339: 1 | P339: 7 | Q339: 2 | R339: 1
A340: 4 | B340: Факторный анализ — драйверы 1–2 ур. | C340: DB | D340: Социальные и зарплатные решения | E340: Зарплатный продукт B2B | F340: Исключить | G340: 0 | H340: 1 | I340: Цели | M340: Драйверы согласно модели бизнес-планирования выведены в Навигатор | N340: Декомпозировать значения целей на драйверы, вывести в Навигатор | O340: 1 | P340: 7 | Q340: 2 | R340: 1
A341: 4 | B341: Факторный анализ — драйверы 1–2 ур. | C341: DB | D341: Государственные продукты и сервисы | E341: Интегратор | F341: Исключить | G341: 0 | H341: 1 | I341: Цели | M341: Драйверы согласно модели бизнес-планирования выведены в Навигатор | N341: Декомпозировать значения целей на драйверы, вывести в Навигатор | O341: 1 | P341: 7 | Q341: 2 | R341: 1
A342: 4 | B342: Факторный анализ — драйверы 1–2 ур. | C342: DB | D342: Государственные продукты и сервисы | E342: Исполнительное производство (ГПС) | F342: Исключить | G342: 0 | H342: 1 | I342: Цели | M342: Драйверы согласно модели бизнес-планирования выведены в Навигатор | N342: Декомпозировать значения целей на драйверы, вывести в Навигатор | O342: 1 | P342: 7 | Q342: 2 | R342: 1
A343: 4 | B343: Факторный анализ — драйверы 1–2 ур. | C343: DB | D343: Государственные продукты и сервисы | E343: Наследство | F343: Исключить | G343: 0 | H343: 1 | I343: Цели | M343: Драйверы согласно модели бизнес-планирования выведены в Навигатор | N343: Декомпозировать значения целей на драйверы, вывести в Навигатор | O343: 1 | P343: 7 | Q343: 2 | R343: 1
A344: 4 | B344: Факторный анализ — драйверы 1–2 ур. | C344: DB | D344: Социальные и зарплатные решения | E344: Перевод зарплаты в Сбер в офисе и на выезде через СБОЛ.про | F344: Исключить | G344: 0 | H344: 1 | I344: Цели | M344: Драйверы согласно модели бизнес-планирования выведены в Навигатор | N344: Декомпозировать значения целей на драйверы, вывести в Навигатор | O344: 1 | P344: 7 | Q344: 2 | R344: 1
A345: 4 | B345: Факторный анализ — драйверы 1–2 ур. | C345: DB | D345: Альтернативные платежные методы | E345: Персонализированный офлайн | F345: Исключить | G345: 0 | H345: 1 | I345: Цели | M345: Драйверы согласно модели бизнес-планирования выведены в Навигатор | N345: Декомпозировать значения целей на драйверы, вывести в Навигатор | O345: 1 | P345: 7 | Q345: 2 | R345: 1
A346: 4 | B346: Факторный анализ — драйверы 1–2 ур. | C346: DB | D346: Социальные и зарплатные решения | E346: Самозанятые. Списочная регистрация | F346: Исключить | G346: 0 | H346: 1 | I346: Цели | M346: Драйверы согласно модели бизнес-планирования выведены в Навигатор | N346: Декомпозировать значения целей на драйверы, вывести в Навигатор | O346: 1 | P346: 7 | Q346: 2 | R346: 1
A347: 7 | B347: Факторный анализ — драйверы 1–2 ур. | C347: DB | D347: Государственные продукты и сервисы | E347: Госуслуги | F347: Исключить | G347: 0 | H347: 1 | I347: Цели | K347: В навигаторе (покрытие >90% целей) | M347: Драйверы согласно модели бизнес-планирования выведены в Навигатор | N347: Декомпозировать значения целей на драйверы, вывести в Навигатор | O347: 0 | P347: 7 | Q347: 2 | R347: 0
A348: 7 | B348: Факторный анализ — драйверы 1–2 ур. | C348: DB | D348: Социальные и зарплатные решения | E348: Демаркирование карт от зарплатного продукта | F348: Исключить | G348: 0 | H348: 1 | I348: Цели | K348: В навигаторе (покрытие >90% целей) | M348: Драйверы согласно модели бизнес-планирования выведены в Навигатор | N348: Декомпозировать значения целей на драйверы, вывести в Навигатор | O348: 0 | P348: 7 | Q348: 2 | R348: 0
A349: 7 | B349: Факторный анализ — драйверы 1–2 ур. | C349: DB | D349: Социальные и зарплатные решения | E349: Зарплатный продукт B2B | F349: Исключить | G349: 0 | H349: 1 | I349: Цели | K349: В навигаторе (покрытие >90% целей) | M349: Драйверы согласно модели бизнес-планирования выведены в Навигатор | N349: Декомпозировать значения целей на драйверы, вывести в Навигатор | O349: 0 | P349: 7 | Q349: 2 | R349: 0
A350: 7 | B350: Факторный анализ — драйверы 1–2 ур. | C350: DB | D350: Государственные продукты и сервисы | E350: Интегратор | F350: Исключить | G350: 0 | H350: 1 | I350: Цели | K350: В навигаторе (покрытие >90% целей) | M350: Драйверы согласно модели бизнес-планирования выведены в Навигатор | N350: Декомпозировать значения целей на драйверы, вывести в Навигатор | O350: 0 | P350: 7 | Q350: 2 | R350: 0
A351: 7 | B351: Факторный анализ — драйверы 1–2 ур. | C351: DB | D351: Государственные продукты и сервисы | E351: Исполнительное производство (ГПС) | F351: Исключить | G351: 0 | H351: 1 | I351: Цели | K351: В навигаторе (покрытие >90% целей) | M351: Драйверы согласно модели бизнес-планирования выведены в Навигатор | N351: Декомпозировать значения целей на драйверы, вывести в Навигатор | O351: 0 | P351: 7 | Q351: 2 | R351: 0
A352: 7 | B352: Факторный анализ — драйверы 1–2 ур. | C352: DB | D352: Государственные продукты и сервисы | E352: Наследство | F352: Исключить | G352: 0 | H352: 1 | I352: Цели | K352: В навигаторе (покрытие >90% целей) | M352: Драйверы согласно модели бизнес-планирования выведены в Навигатор | N352: Декомпозировать значения целей на драйверы, вывести в Навигатор | O352: 0 | P352: 7 | Q352: 2 | R352: 0
A353: 7 | B353: Факторный анализ — драйверы 1–2 ур. | C353: DB | D353: 0 | E353: Онбординг и сопровождение ЮЛ в зарплатном проекте канала СберБизнес | F353: Исключить | G353: 0 | H353: 1 | I353: Цели | K353: В навигаторе (покрытие >90% целей) | M353: Драйверы согласно модели бизнес-планирования выведены в Навигатор | N353: Декомпозировать значения целей на драйверы, вывести в Навигатор | O353: 0 | P353: 7 | Q353: 2 | R353: 0
A354: 7 | B354: Факторный анализ — драйверы 1–2 ур. | C354: DB | D354: Социальные и зарплатные решения | E354: Перевод зарплаты в Сбер в офисе и на выезде через СБОЛ.про | F354: Исключить | G354: 0 | H354: 1 | I354: Цели | K354: В навигаторе (покрытие >90% целей) | M354: Драйверы согласно модели бизнес-планирования выведены в Навигатор | N354: Декомпозировать значения целей на драйверы, вывести в Навигатор | O354: 0 | P354: 7 | Q354: 2 | R354: 0
A355: 7 | B355: Факторный анализ — драйверы 1–2 ур. | C355: DB | D355: Альтернативные платежные методы | E355: Персонализированный офлайн | F355: Исключить | G355: 0 | H355: 1 | I355: Цели | K355: В навигаторе (покрытие >90% целей) | M355: Драйверы согласно модели бизнес-планирования выведены в Навигатор | N355: Декомпозировать значения целей на драйверы, вывести в Навигатор | O355: 0 | P355: 7 | Q355: 2 | R355: 0
A356: 7 | B356: Факторный анализ — драйверы 1–2 ур. | C356: DB | D356: Социальные и зарплатные решения | E356: Самозанятые. Списочная регистрация | F356: Исключить | G356: 0 | H356: 1 | I356: Цели | K356: В навигаторе (покрытие >90% целей) | M356: Драйверы согласно модели бизнес-планирования выведены в Навигатор | N356: Декомпозировать значения целей на драйверы, вывести в Навигатор | O356: 0 | P356: 7 | Q356: 2 | R356: 0
A357: 3 | B357: Цели выведены на мониторинг | C357: УБ | D357: ДББ | E357: Брокерский счет | F357: продукт | G357: =VLOOKUP(E357,Лист2!A:B,2,0) -> 1 | H357: 1 | I357: Цели | M357: Регулярное обновление в Навигаторе | N357: Обогащение целей в Навигаторе | O357: 1 | P357: 2 | Q357: 1 | R357: 1
A358: 5 | B358: Прогноз по целям | C358: УБ | D358: ДББ | E358: Брокерский счет | F358: продукт | G358: =VLOOKUP(E358,Лист2!A:D,4,0) -> 0.5 | H358: 1 | I358: Цели | M358: Прогноз выведен в Навигатор | N358: Сформировать прогнозные значения, вывести в Навигатор | O358: 1 | P358: 8 | Q358: 3 | R358: 1
A359: 4 | B359: Факторный анализ — драйверы 1–2 ур. | C359: УБ | D359: ДЗСПиС | E359: ВЗР | F359: продукт | G359: =VLOOKUP(E359,Лист2!A:D,3,0) -> 0 | H359: 1 | I359: Цели | M359: Драйверы согласно модели бизнес-планирования выведены в Навигатор | N359: Декомпозировать значения целей на драйверы, вывести в Навигатор | O359: 1 | P359: 7 | Q359: 2 | R359: 1
A360: 3 | B360: Цели выведены на мониторинг | C360: УБ | D360: ДЗСПиС | E360: ВЗР | F360: продукт | G360: =VLOOKUP(E360,Лист2!A:B,2,0) -> 1 | H360: 1 | I360: Цели | M360: Регулярное обновление в Навигаторе | N360: Обогащение целей в Навигаторе | O360: 1 | P360: 2 | Q360: 1 | R360: 1
A361: 5 | B361: Прогноз по целям | C361: УБ | D361: ДЗСПиС | E361: ВЗР | F361: продукт | G361: =VLOOKUP(E361,Лист2!A:D,4,0) -> 1 | H361: 1 | I361: Цели | M361: Прогноз выведен в Навигатор | N361: Сформировать прогнозные значения, вывести в Навигатор | O361: 1 | P361: 8 | Q361: 3 | R361: 1
A362: 4 | B362: Факторный анализ — драйверы 1–2 ур. | C362: CBP | D362: Сбережения клиентов | E362: Вклады+НС | F362: продукт | G362: =VLOOKUP(E362,Лист2!A:D,3,0) -> 0.5 | H362: 1 | I362: Цели | M362: Драйверы согласно модели бизнес-планирования выведены в Навигатор | N362: Декомпозировать значения целей на драйверы, вывести в Навигатор | O362: 1 | P362: 7 | Q362: 2 | R362: 1
A363: 3 | B363: Цели выведены на мониторинг | C363: CBP | D363: Сбережения клиентов | E363: Вклады+НС | F363: продукт | G363: =VLOOKUP(E363,Лист2!A:B,2,0) -> 0 | H363: 1 | I363: Цели | M363: Регулярное обновление в Навигаторе | N363: Обогащение целей в Навигаторе | O363: 1 | P363: 2 | Q363: 1 | R363: 1
A364: 5 | B364: Прогноз по целям | C364: CBP | D364: Сбережения клиентов | E364: Вклады+НС | F364: продукт | G364: =VLOOKUP(E364,Лист2!A:D,4,0) -> 0 | H364: 1 | I364: Цели | M364: Прогноз выведен в Навигатор | N364: Сформировать прогнозные значения, вывести в Навигатор | O364: 1 | P364: 8 | Q364: 3 | R364: 1
A365: 4 | B365: Факторный анализ — драйверы 1–2 ур. | C365: DB | D365: Социальные и зарплатные решения | E365: Военная пенсия | F365: продукт | G365: =VLOOKUP(E365,Лист2!A:D,3,0) -> 0 | H365: 1 | I365: Цели | M365: Драйверы согласно модели бизнес-планирования выведены в Навигатор | N365: Декомпозировать значения целей на драйверы, вывести в Навигатор | O365: 1 | P365: 7 | Q365: 2 | R365: 1
A366: 3 | B366: Цели выведены на мониторинг | C366: DB | D366: Социальные и зарплатные решения | E366: Военная пенсия | F366: продукт | G366: =VLOOKUP(E366,Лист2!A:B,2,0) -> 0 | H366: 1 | I366: Цели | M366: Регулярное обновление в Навигаторе | N366: Обогащение целей в Навигаторе | O366: 1 | P366: 2 | Q366: 1 | R366: 1
A367: 5 | B367: Прогноз по целям | C367: DB | D367: Социальные и зарплатные решения | E367: Военная пенсия | F367: продукт | G367: =VLOOKUP(E367,Лист2!A:D,4,0) -> 0 | H367: 1 | I367: Цели | M367: Прогноз выведен в Навигатор | N367: Сформировать прогнозные значения, вывести в Навигатор | O367: 1 | P367: 8 | Q367: 3 | R367: 1
A368: 4 | B368: Факторный анализ — драйверы 1–2 ур. | C368: PC | D368: Клиентские документы | E368: Выписки, справки | F368: продукт | G368: =VLOOKUP(E368,Лист2!A:D,3,0) -> 1 | H368: 1 | I368: Цели | M368: Драйверы согласно модели бизнес-планирования выведены в Навигатор | N368: Декомпозировать значения целей на драйверы, вывести в Навигатор | O368: 1 | P368: 7 | Q368: 2 | R368: 1
A369: 3 | B369: Цели выведены на мониторинг | C369: PC | D369: Клиентские документы | E369: Выписки, справки | F369: продукт | G369: =VLOOKUP(E369,Лист2!A:B,2,0) -> 1 | H369: 1 | I369: Цели | M369: Регулярное обновление в Навигаторе | N369: Обогащение целей в Навигаторе | O369: 1 | P369: 2 | Q369: 1 | R369: 1
A370: 5 | B370: Прогноз по целям | C370: PC | D370: Клиентские документы | E370: Выписки, справки | F370: продукт | G370: =VLOOKUP(E370,Лист2!A:D,4,0) -> 0 | H370: 1 | I370: Цели | M370: Прогноз выведен в Навигатор | N370: Сформировать прогнозные значения, вывести в Навигатор | O370: 1 | P370: 8 | Q370: 3 | R370: 1
A371: 4 | B371: Факторный анализ — драйверы 1–2 ур. | C371: DB | D371: Кошелёк клиента | E371: Дебетовая карта | F371: продукт | G371: =VLOOKUP(E371,Лист2!A:D,3,0) -> 0.5 | H371: 1 | I371: Цели | M371: Драйверы согласно модели бизнес-планирования выведены в Навигатор | N371: Декомпозировать значения целей на драйверы, вывести в Навигатор | O371: 1 | P371: 7 | Q371: 2 | R371: 1
A372: 3 | B372: Цели выведены на мониторинг | C372: DB | D372: Кошелёк клиента | E372: Дебетовая карта | F372: продукт | G372: =VLOOKUP(E372,Лист2!A:B,2,0) -> 1 | H372: 1 | I372: Цели | M372: Регулярное обновление в Навигаторе | N372: Обогащение целей в Навигаторе | O372: 1 | P372: 2 | Q372: 1 | R372: 1
A373: 5 | B373: Прогноз по целям | C373: DB | D373: Кошелёк клиента | E373: Дебетовая карта | F373: продукт | G373: =VLOOKUP(E373,Лист2!A:D,4,0) -> 0 | H373: 1 | I373: Цели | M373: Прогноз выведен в Навигатор | N373: Сформировать прогнозные значения, вывести в Навигатор | O373: 1 | P373: 8 | Q373: 3 | R373: 1
A374: 407 | B374: Факторный анализ — драйверы 1–2 ур. | C374: СХ | D374: Дети и Молодежь | E374: Дети | F374: Сегмент | G374: =VLOOKUP(E374,Лист2!A:D,3,0) -> 1 | H374: 1 | I374: Цели | M374: Драйверы согласно модели бизнес-планирования выведены в Навигатор | N374: Декомпозировать значения целей на драйверы, вывести в Навигатор | O374: 1 | P374: 7 | Q374: 2 | R374: 1
A375: 406 | B375: Цели выведены на мониторинг | C375: СХ | D375: Дети и Молодежь | E375: Дети | F375: Сегмент | G375: =VLOOKUP(E375,Лист2!A:B,2,0) -> 0.5 | H375: 1 | I375: Цели | M375: Регулярное обновление в Навигаторе | N375: Обогащение целей в Навигаторе | O375: 1 | P375: 2 | Q375: 1 | R375: 1
A376: 408 | B376: Прогноз по целям | C376: СХ | D376: Дети и Молодежь | E376: Дети | F376: Сегмент | G376: =VLOOKUP(E376,Лист2!A:D,4,0) -> 0 | H376: 1 | I376: Цели | M376: Прогноз выведен в Навигатор | N376: Сформировать прогнозные значения, вывести в Навигатор | O376: 1 | P376: 8 | Q376: 3 | R376: 1
A377: 4 | B377: Факторный анализ — драйверы 1–2 ур. | C377: DB | D377: Кошелёк клиента | E377: Детская карта | F377: продукт | G377: =VLOOKUP(E377,Лист2!A:D,3,0) -> 0.5 | H377: 1 | I377: Цели | M377: Драйверы согласно модели бизнес-планирования выведены в Навигатор | N377: Декомпозировать значения целей на драйверы, вывести в Навигатор | O377: 1 | P377: 7 | Q377: 2 | R377: 1
A378: 3 | B378: Цели выведены на мониторинг | C378: DB | D378: Кошелёк клиента | E378: Детская карта | F378: продукт | G378: =VLOOKUP(E378,Лист2!A:B,2,0) -> 0.5 | H378: 1 | I378: Цели | M378: Регулярное обновление в Навигаторе | N378: Обогащение целей в Навигаторе | O378: 1 | P378: 2 | Q378: 1 | R378: 1
A379: 5 | B379: Прогноз по целям | C379: DB | D379: Кошелёк клиента | E379: Детская карта | F379: продукт | G379: =VLOOKUP(E379,Лист2!A:D,4,0) -> 0 | H379: 1 | I379: Цели | M379: Прогноз выведен в Навигатор | N379: Сформировать прогнозные значения, вывести в Навигатор | O379: 1 | P379: 8 | Q379: 3 | R379: 1
A380: 4 | B380: Факторный анализ — драйверы 1–2 ур. | C380: УБ | D380: ДЗСПиС | E380: ДСЖ КК | F380: продукт | G380: =VLOOKUP(E380,Лист2!A:D,3,0) -> 0 | H380: 1 | I380: Цели | M380: Драйверы согласно модели бизнес-планирования выведены в Навигатор | N380: Декомпозировать значения целей на драйверы, вывести в Навигатор | O380: 1 | P380: 7 | Q380: 2 | R380: 1
A381: 3 | B381: Цели выведены на мониторинг | C381: УБ | D381: ДЗСПиС | E381: ДСЖ КК | F381: продукт | G381: =VLOOKUP(E381,Лист2!A:B,2,0) -> 1 | H381: 1 | I381: Цели | M381: Регулярное обновление в Навигаторе | N381: Обогащение целей в Навигаторе | O381: 1 | P381: 2 | Q381: 1 | R381: 1
A382: 5 | B382: Прогноз по целям | C382: УБ | D382: ДЗСПиС | E382: ДСЖ КК | F382: продукт | G382: =VLOOKUP(E382,Лист2!A:D,4,0) -> 1 | H382: 1 | I382: Цели | M382: Прогноз выведен в Навигатор | N382: Сформировать прогнозные значения, вывести в Навигатор | O382: 1 | P382: 8 | Q382: 3 | R382: 1
A383: 4 | B383: Факторный анализ — драйверы 1–2 ур. | C383: УБ | D383: ДЗСПиС | E383: ДСЖ ПК | F383: продукт | G383: =VLOOKUP(E383,Лист2!A:D,3,0) -> 0 | H383: 1 | I383: Цели | M383: Драйверы согласно модели бизнес-планирования выведены в Навигатор | N383: Декомпозировать значения целей на драйверы, вывести в Навигатор | O383: 1 | P383: 7 | Q383: 2 | R383: 1
A384: 3 | B384: Цели выведены на мониторинг | C384: УБ | D384: ДЗСПиС | E384: ДСЖ ПК | F384: продукт | G384: =VLOOKUP(E384,Лист2!A:B,2,0) -> 1 | H384: 1 | I384: Цели | M384: Регулярное обновление в Навигаторе | N384: Обогащение целей в Навигаторе | O384: 1 | P384: 2 | Q384: 1 | R384: 1
A385: 5 | B385: Прогноз по целям | C385: УБ | D385: ДЗСПиС | E385: ДСЖ ПК | F385: продукт | G385: =VLOOKUP(E385,Лист2!A:D,4,0) -> 1 | H385: 1 | I385: Цели | M385: Прогноз выведен в Навигатор | N385: Сформировать прогнозные значения, вывести в Навигатор | O385: 1 | P385: 8 | Q385: 3 | R385: 1
A386: 4 | B386: Факторный анализ — драйверы 1–2 ур. | C386: УБ | D386: ДИиН | E386: ДУ | F386: продукт | G386: =VLOOKUP(E386,Лист2!A:D,3,0) -> 0 | H386: 1 | I386: Цели | M386: Драйверы согласно модели бизнес-планирования выведены в Навигатор | N386: Декомпозировать значения целей на драйверы, вывести в Навигатор | O386: 1 | P386: 7 | Q386: 2 | R386: 1
A387: 3 | B387: Цели выведены на мониторинг | C387: УБ | D387: ДИиН | E387: ДУ | F387: продукт | G387: =VLOOKUP(E387,Лист2!A:B,2,0) -> 1 | H387: 1 | I387: Цели | M387: Регулярное обновление в Навигаторе | N387: Обогащение целей в Навигаторе | O387: 1 | P387: 2 | Q387: 1 | R387: 1
A388: 5 | B388: Прогноз по целям | C388: УБ | D388: ДИиН | E388: ДУ | F388: продукт | G388: =VLOOKUP(E388,Лист2!A:D,4,0) -> 1 | H388: 1 | I388: Цели | M388: Прогноз выведен в Навигатор | N388: Сформировать прогнозные значения, вывести в Навигатор | O388: 1 | P388: 8 | Q388: 3 | R388: 1
A389: 4 | B389: Факторный анализ — драйверы 1–2 ур. | C389: УБ | D389: ЦКС | E389: Залоговое страхование (корпоративное страхование) | F389: продукт | G389: =VLOOKUP(E389,Лист2!A:D,3,0) -> 0 | H389: 1 | I389: Цели | M389: Драйверы согласно модели бизнес-планирования выведены в Навигатор | N389: Декомпозировать значения целей на драйверы, вывести в Навигатор | O389: 1 | P389: 7 | Q389: 2 | R389: 1
A390: 3 | B390: Цели выведены на мониторинг | C390: УБ | D390: ЦКС | E390: Залоговое страхование (корпоративное страхование) | F390: продукт | G390: =VLOOKUP(E390,Лист2!A:B,2,0) -> 1 | H390: 1 | I390: Цели | M390: Регулярное обновление в Навигаторе | N390: Обогащение целей в Навигаторе | O390: 1 | P390: 2 | Q390: 1 | R390: 1
A391: 5 | B391: Прогноз по целям | C391: УБ | D391: ЦКС | E391: Залоговое страхование (корпоративное страхование) | F391: продукт | G391: =VLOOKUP(E391,Лист2!A:D,4,0) -> 0 | H391: 1 | I391: Цели | M391: Прогноз выведен в Навигатор | N391: Сформировать прогнозные значения, вывести в Навигатор | O391: 1 | P391: 8 | Q391: 3 | R391: 1
A392: 4 | B392: Факторный анализ — драйверы 1–2 ур. | C392: DB | D392: Социальные и зарплатные решения | E392: Зарплатный продукт | F392: продукт | G392: =VLOOKUP(E392,Лист2!A:D,3,0) -> 0 | H392: 1 | I392: Цели | M392: Драйверы согласно модели бизнес-планирования выведены в Навигатор | N392: Декомпозировать значения целей на драйверы, вывести в Навигатор | O392: 1 | P392: 7 | Q392: 2 | R392: 1
A393: 3 | B393: Цели выведены на мониторинг | C393: DB | D393: Социальные и зарплатные решения | E393: Зарплатный продукт | F393: продукт | G393: =VLOOKUP(E393,Лист2!A:B,2,0) -> 0 | H393: 1 | I393: Цели | M393: Регулярное обновление в Навигаторе | N393: Обогащение целей в Навигаторе | O393: 1 | P393: 2 | Q393: 1 | R393: 1
A394: 5 | B394: Прогноз по целям | C394: DB | D394: Социальные и зарплатные решения | E394: Зарплатный продукт | F394: продукт | G394: =VLOOKUP(E394,Лист2!A:D,4,0) -> 0 | H394: 1 | I394: Цели | M394: Прогноз выведен в Навигатор | N394: Сформировать прогнозные значения, вывести в Навигатор | O394: 1 | P394: 8 | Q394: 3 | R394: 1
A395: 4 | B395: Факторный анализ — драйверы 1–2 ур. | C395: УБ | D395: ДЗСПиС | E395: ЗЛС | F395: продукт | G395: =VLOOKUP(E395,Лист2!A:D,3,0) -> 0 | H395: 1 | I395: Цели | M395: Драйверы согласно модели бизнес-планирования выведены в Навигатор | N395: Декомпозировать значения целей на драйверы, вывести в Навигатор | O395: 1 | P395: 7 | Q395: 2 | R395: 1
A396: 3 | B396: Цели выведены на мониторинг | C396: УБ | D396: ДЗСПиС | E396: ЗЛС | F396: продукт | G396: =VLOOKUP(E396,Лист2!A:B,2,0) -> 0 | H396: 1 | I396: Цели | M396: Регулярное обновление в Навигаторе | N396: Обогащение целей в Навигаторе | O396: 1 | P396: 2 | Q396: 1 | R396: 1
A397: 5 | B397: Прогноз по целям | C397: УБ | D397: ДЗСПиС | E397: ЗЛС | F397: продукт | G397: =VLOOKUP(E397,Лист2!A:D,4,0) -> 1 | H397: 1 | I397: Цели | M397: Прогноз выведен в Навигатор | N397: Сформировать прогнозные значения, вывести в Навигатор | O397: 1 | P397: 8 | Q397: 3 | R397: 1
A398: 4 | B398: Факторный анализ — драйверы 1–2 ур. | C398: УБ | D398: ДИиН | E398: ЗПИФ | F398: продукт | G398: =VLOOKUP(E398,Лист2!A:D,3,0) -> 0 | H398: 1 | I398: Цели | M398: Драйверы согласно модели бизнес-планирования выведены в Навигатор | N398: Декомпозировать значения целей на драйверы, вывести в Навигатор | O398: 1 | P398: 7 | Q398: 2 | R398: 1
A399: 3 | B399: Цели выведены на мониторинг | C399: УБ | D399: ДИиН | E399: ЗПИФ | F399: продукт | G399: =VLOOKUP(E399,Лист2!A:B,2,0) -> 1 | H399: 1 | I399: Цели | M399: Регулярное обновление в Навигаторе | N399: Обогащение целей в Навигаторе | O399: 1 | P399: 2 | Q399: 1 | R399: 1
...

Sheet Лист2
B1: Ответ продукта
A2: Продукт | B2: Цели уровня ЛЮ-ЛТ выведены на мониторинг | C2: Драйверы целей | D2: Прогноз по целям | F2: product | G2: факт
B3: в Навигатор 1 балл ( +90% целей) -< 90% 0 баллов (проверка по цифровым следам- учет ЦС) - своя отчетность 0,5 балл все метрики | F3: POS-кредиты | G3: 0 | H3: =VLOOKUP(F3,A:D,2,0) -> 1 | I3: =H3=G3 -> FALSE | K3: product | L3: тип | M3: факт
A4: Продукт | B4: 3 | C4: 4 | D4: 5 | F4: SberPay Вжух | G4: 0 | H4: =VLOOKUP(F4,A:D,2,0) -> 0 | I4: =H4=G4 -> FALSE | K4: POS-кредиты | L4: продукт | M4: =VLOOKUP(K4,A:D,2,0) -> 1
A5: ОСАГО | B5: 0.5 | C5: 0 | D5: 0.5 | F5: Автокредит | G5: 0 | H5: =VLOOKUP(F5,A:D,2,0) -> 0 | I5: =H5=G5 -> FALSE | K5: SberPay Вжух | L5: продукт | M5: =VLOOKUP(K5,A:D,2,0) -> 0
A6: КАСКО | B6: 0.5 | C6: 0.5 | D6: 0.5 | F6: Вклады+НС | G6: 0 | H6: =VLOOKUP(F6,A:D,2,0) -> 0 | I6: =H6=G6 -> FALSE | K6: Автокредит | L6: продукт | M6: =VLOOKUP(K6,A:D,2,0) -> 0
A7: ИнвестКопилка | B7: 1 | C7: 0 | D7: 0.5 | F7: Военная пенсия | G7: 0 | H7: =VLOOKUP(F7,A:D,2,0) -> 0 | I7: =H7=G7 -> FALSE | K7: Вклады+НС | L7: продукт | M7: =VLOOKUP(K7,A:D,2,0) -> 0
A8: СберСова | B8: 0 | C8: 0 | D8: 0 | F8: Дебетовая карта | G8: 0 | H8: =VLOOKUP(F8,A:D,2,0) -> 1 | I8: =H8=G8 -> FALSE | K8: Военная пенсия | L8: продукт | M8: =VLOOKUP(K8,A:D,2,0) -> 0
A9: Залоговое страхование (корпоративное страхование) | B9: 1 | C9: 0 | D9: 0 | F9: ЗЛС | G9: 0 | H9: =VLOOKUP(F9,A:D,2,0) -> 0 | I9: =H9=G9 -> FALSE | K9: Дебетовая карта | L9: продукт | M9: =VLOOKUP(K9,A:D,2,0) -> 1
A10: НСЖ | B10: 1 | C10: 0.5 | D10: 1 | F10: Зарплатный продукт | G10: 0 | H10: =VLOOKUP(F10,A:D,2,0) -> 0 | I10: =H10=G10 -> FALSE | K10: ЗЛС | L10: продукт | M10: =VLOOKUP(K10,A:D,2,0) -> 0
A11: ИСЖ | B11: 1 | C11: 0 | D11: 1 | F11: Как зарплатный | G11: 0 | H11: =VLOOKUP(F11,A:D,2,0) -> 0 | I11: =H11=G11 -> FALSE | K11: Зарплатный продукт | L11: продукт | M11: =VLOOKUP(K11,A:D,2,0) -> 0
A12: Страхование жизни | B12: 1 | C12: 0 | D12: 1 | F12: Пенсионный продукт | G12: 0 | H12: =VLOOKUP(F12,A:D,2,0) -> 0 | I12: =H12=G12 -> FALSE | K12: Как зарплатный | L12: продукт | M12: =VLOOKUP(K12,A:D,2,0) -> 0
A13: Брокерский счет | B13: 1 | C13: 0 | D13: 0.5 | F13: Платежи | G13: 0 | H13: =VLOOKUP(F13,A:D,2,0) -> 1 | I13: =H13=G13 -> FALSE | K13: Пенсионный продукт | L13: продукт | M13: =VLOOKUP(K13,A:D,2,0) -> 0
A14: БПИФ | B14: 0.5 | C14: 0 | D14: 0.5 | F14: СберСова | G14: 0 | H14: =VLOOKUP(F14,A:D,2,0) -> 0 | I14: =H14=G14 -> FALSE | K14: Платежи | L14: продукт | M14: =VLOOKUP(K14,A:D,2,0) -> 1
A15: ЗПИФ | B15: 1 | C15: 0 | D15: 1 | F15: Сценарии оплаты | G15: 0 | H15: =VLOOKUP(F15,A:D,2,0) -> 1 | I15: =H15=G15 -> FALSE | K15: СберСова | L15: продукт | M15: =VLOOKUP(K15,A:D,2,0) -> 0
... A80: Переводы по РФ | B80: 1 | C80: 0 | D80: 0.5 | F80: МВС | G80: 1 | H80: =VLOOKUP(F80,A:D,2,0) -> 1 | I80: =H80=G80 -> FALSE | K80: PB | L80: Сегмент | M80: =VLOOKUP(K80,A:D,2,0) -> 1
A81: Переводы подарков | B81: 0.5 | C81: 0 | D81: 0.5 | K81: МВС | L81: Сегмент | M81: =VLOOKUP(K81,A:D,2,0) -> 1
A82: Оплата улыбкой | B82: 0.5 | C82: 0.5 | D82: 0.5
A83: Торговый Эквайринг | B83: 0 | C83: 0 | D83: 0
A84: Дебетовая карта | B84: 1 | C84: 0.5 | D84: 0
A85: SberPay NFC | B85: 1 | C85: 0 | D85: 0.5
A86: Как зарплатный | B86: 0 | C86: 0 | D86: 0
A87: Сценарии оплаты | B87: 1 | C87: 0 | D87: 0
A88: Интернет-Эквайринг | B88: 0.5 | C88: 0 | D88: 0.5
A89: SberPay Ecom | B89: 1 | C89: 0.5 | D89: 0.5
A90: SberPay Вжух | B90: 0 | C90: 0 | D90: 0
A91: Пенсионный продукт | B91: 0 | C91: 0 | D91: 0
A92: Зарплатный продукт B2B | B92: 0 | C92: 0 | D92: 0.5
A93: СберЧаевые | B93: 0.5 | C93: 0.5 | D93: 0.5
... A99: СберСпасибо | B99: 1 | C99: 0.5 | D99: 0

Sheet Sheet1
A1: 22 | B1: Оповещения по системным сбоям
A2: 22 | B2: Оповещения по системным сбоям
A3: 22 | B3: Оповещения по системным сбоям
A4: 22 | B4: Оповещения по системным сбоям
A5: 22 | B5: Оповещения по системным сбоям
A6: 22 | B6: Оповещения по системным сбоям
A7: 22 | B7: Оповещения по системным сбоям
A8: 22 | B8: Оповещения по системным сбоям
A9: 22 | B9: Оповещения по системным сбоям
A10: 22 | B10: Оповещения по системным сбоям
A11: 22 | B11: Оповещения по системным сбоям
A12: 22 | B12: Оповещения по системным сбоям
... A183: 418 | B183: Оповещения по бизнес-метрикам
