Workbook

Sheet Группы_
G1: Ответ продукта | H1: Ответ продукта | I1: Ответ продукта | L1: Цифровые следы | O1: Ответ продукта | R1: Ответ продукта | U1: Ответ продукта | W1: Ответ продукта | AA1: Ответ продукта | AD1: Механники | AY1: Ответ продукта | BA1: кампейнинг /SS-Цифровые следы | BD1: Цифровые следы | BE1: Цифровые следы | BF1: Цифровые следы | BG1: Цифровые следы | BH1: Цифровые следы
B2: Юнит | C2: Продукт | D2: Оценка | E2: Группа | F2: тип | G2: Знание своих метрик | H2: Все основные метрики выведены в отчетность | I2: Цели уровня ЛЮ-ЛТ выведены на мониторинг | J2: Драйверы целей | K2: Прогноз по целям | L2: Цели уровня ЛЮ-ЛТ выведены на мониторинг (>90% покрытие) | M2: Драйверы целей | N2: Прогноз по целям | O2: Отчетность по воронке привечения | P2: Полнота отчета по воронке привлечения | Q2: Регулярность | R2: Отчетность по воронке оттока | S2: Полнота отчета по воронке оттока | T2: Регулярность | U2: Наличие бенчмарков | V2: Какие бенчмарки? | W2: Анализ воронки привлечения | X2: инициативы по привлечению | Y2: Анализ воронки оттока | Z2: инициативы по оттоку | AA2: Алерты по системным сбоям | AB2: Алерты по бизнес метрикам | AC2: Привлечения | AD2: Удержание клиентов | AE2: База для механники удержания | AF2: Настроена модель склонности к оттоку | AG2: Настроены предоттоковые автоматические сценарии | AH2: Ручной мониторинг | AI2: Информационная комуникация | AJ2: Создание ценности | AK2: Возврат клиентов | AL2: Информационная комуникация | AM2: Создание ценности | AN2: Перекрестные продажи (cross-sell) | AO2: В процессе оформления и после покупки | AP2: Только в процессе оформления | AQ2: Только после покупки | AR2: Допродажи (upsell) | AS2: Реагирования на жизненные события | AT2: Персонализации клиентского опыта | AU2: Есть метрики мониторинга механник | AV2: Примеры метрик мониторинга механник | AW2: Не релевантны предложенные механники | AX2: Возможно ли изменить набор опций по продукту без IT-разработки? | AY2: Доля задач DA, связанных с исследованиями (Discovery) ≥40% бэклога | AZ2: нет аналитиков | BA2: Наличие запусков Кампейнинг/SS | BB2: Наличие успешных запусков | BC2: Использование SS | BD2: Черновики в СБОЛ | BE2: СХ Score | BF2: Проведение A/B-тестов | BG2: Рейтинг DataDriven исследований ≥7,5 | BH2: Наличие доп инициатив сверх БП | BI2: Каких инструментов или какой поддержки не хватает вам для повышения уровня data driven вашего продукта? | BJ2: ФИО-кто проходил | BK2: Комментарий Штаба В2С | BL2: Комментарий Штаба Юнита
D3: =AVERAGE(D5:D136) -> 0.46346226 | G3: Оценивается +-5% попадания в верный ответ (проверка по отчетности в Навигаторе/Штаб Юнита) | H3: 0,5 балл- деш в Навигаторе/ или своя отчетность Если через Запрос аналитику 0,25 баллов | I3: в Навигатор 1 балл ( +90% целей) -< 90% 0 баллов (проверка по цифровым следам- учет ЦС) - своя отчетность 0,5 балл все метрики | O3: Да- 0,5 баллов (умножается на К регулярности) | P3: 0,5 -все 0,25 большая часть | Q3: Автоматически (daily или weekly) *1 если нет то *0,5 | R3: Да- 0,5 баллов (умножается на К регулярности) | S3: 0,5 -все 0,25 большая часть | T3: Автоматически (daily или weekly) *1 если нет то *0,5 | U3: цели/динамика/рыночный бенчмаркc 1 балл (оценка с учетом типа бенчмарка | W3: Комплексный 1 балл не полный 0,5 баллов | X3: Флаг1 -наличия 1 балл | Y3: Комплексный 1 балл не полный 0,5 баллов | Z3: Флаг1 -наличия 1 балл | AA3: 1 балл - да 0,5 баллов частично | AC3: Для сегментов | AD3: наличие механники (оценка по остовляющим) | AF3: Для сегментов 1- флаг наличия | AG3: Для сегментов 1- флаг наличия | AH3: Для сегментов 1- флаг наличия | AI3: Для продуктов Флаг1 -наличие механники 0,5 балл | AJ3: Для продуктов Флаг1 -наличие механники 0,5 балл | AK3: наличие механники (оценка по остовляющим) | AL3: Для продуктов Флаг1 -наличие механники 0,5 балл | AM3: Для продуктов Флаг1 -наличие механники 0,5 балл | AN3: Для продуктов наличие механники (оценка по остовляющим) | AO3: Для продуктов Флаг1 -наличие механники 1 балл | AP3: Для продуктов Флаг1 -наличие механники 0,5 балл | AQ3: Для продуктов Флаг1 -наличие механники 0,5 балл | AR3: Для продуктов наличие механники | AS3: Для сегментов | AT3: Для сегментов | AW3: для инфо | AY3: ≥40% 1 балл От 20 до 39% 0,5 баллов | AZ3: для инфо 1- нет аналитиков в команде | BA3: 0.5 | BB3: 0.5 | BC3: 0.5 | BD3: -покрытие ≥70% от потенциала продукта (1 балл) -покрытие <70% но больше 15% от потенциала продукта (0,5 баллов) Расчет по максимальному проценту за месяцы квартала | BE3: Зеленая зона СХ Score (1 балл) Желтая зона СХ Score (0,5 балл) | BF3: ≥80% (1 балл) ≥30% (0,5 балла) | BG3: Оценка исследований не ниже 7,5 (1 балл) (средний бал по исследованиям) С начала года | BH3: Доходные/Расходные инициативы 1 балл | BI3: Ответ из опроса
B4: Юнит | C4: Продукт | D4: Оценка | E4: Группа | F4: тип | G4: 1 | H4: 2 | I4: 3 | J4: 4 | K4: 5 | L4: 6 | M4: 7 | N4: 8 | O4: 9 | P4: 10 | Q4: 11 | R4: 12 | S4: 13 | T4: 14 | U4: 15 | V4: 16 | W4: 17 | X4: 18 | Y4: 19 | Z4: 20 | AA4: 21 | AB4: 22 | AC4: 222 | AD4: 23 | AE4: 500 | AF4: 500 | AG4: 501 | AH4: 502 | AI4: 24 | AJ4: 25 | AK4: 26 | AL4: 27 | AM4: 28 | AN4: 30 | AO4: 30 | AP4: 31 | AQ4: 32 | AR4: 33 | AS4: 223 | AT4: 224 | AU4: 48 | AW4: 34 | AX4: 47 | AY4: 35 | AZ4: 36 | BA4: 38 | BB4: 39 | BC4: 40 | BD4: 41 | BE4: 42 | BF4: 43 | BG4: 44 | BH4: 45 | BI4: 37 | BJ4: 1000 | BK4: 46
A5: 75 | B5: УБ | C5: ОСАГО | D5: 0.62574257 | E5: Зрелые | F5: продукт | G5: 0.3 | H5: 0.5 | I5: 0.5 | J5: 0 | K5: 0.5 | L5: 1 | M5: 0 | N5: 1 | O5: 1 | P5: 1 | Q5: 1 | R5: 1 | S5: 0 | T5: 1 | U5: 1 | V5: Успешный опыт конкурентов, исследование рынка, интервью | W5: 1 | X5: 1 | Y5: 1 | Z5: 1 | AA5: 1 | AB5: 1 | AC5: для продукта не включается в расчет | AD5: =IF(AI5="не релевантно","не релевантн",(AI5+AJ5)/2) -> 1 | AI5: 1 | AJ5: 1 | AK5: =IF(AL5="не релевантно","не релевантн",(AL5+AM5)/2) -> 1 | AL5: 1 | AM5: 1 | AN5: 0.5 | AO5: 0 | AP5: 1 | AQ5: 0 | AR5: 0 | AS5: для продукта не включается в расчет | AT5: для продукта не включается в расчет | AU5: 1 | AV5: CR, CTR, GPW | AW5: 0 | AX5: 0 | AY5: 0.5 | AZ5: 0 | BA5: 1 | BB5: 0 | BC5: 1 | BD5: 0.5 | BE5: 0.5 | BF5: TBD | BG5: 0 | BH5: 0 | BI5: Стабильная работа PXF Серверов | BJ5: Сипугин Николай Александрович | BK5: Проверить- должен быть кросс сейл в процессе оформления с ОСАГО на авто. По ответу продукта нет
A6: 80 | B6: УБ | C6: КАСКО | D6: 0.62574257 | E6: Зрелые | F6: продукт | G6: 0.3 | H6: 0.5 | I6: 0.5 | J6: 0.5 | K6: 0.5 | L6: 1 | M6: 0 | N6: 1 | O6: 1 | P6: 1 | Q6: 1 | R6: 1 | S6: 0 | T6: 1 | U6: 1 | V6: Успешный опыт конкурентов, исследование рынка, интервью | W6: 1 | X6: 1 | Y6: 1 | Z6: 1 | AA6: 1 | AB6: 1 | AC6: для продукта не включается в расчет | AD6: =IF(AI6="не релевантно","не релевантн",(AI6+AJ6)/2) -> 1 | AI6: 1 | AJ6: 1 | AK6: =IF(AL6="не релевантно","не релевантн",(AL6+AM6)/2) -> 1 | AL6: 1 | AM6: 1 | AN6: 0.5 | AO6: 0 | AP6: 1 | AQ6: 0 | AR6: 0 | AS6: для продукта не включается в расчет | AT6: для продукта не включается в расчет | AU6: 1 | AV6: CR, CTR, GPW | AW6: 0 | AX6: 0 | AY6: 0.5 | AZ6: 0 | BA6: 1 | BB6: 0 | BC6: 1 | BD6: 0.5 | BE6: 0.5 | BF6: TBD | BG6: 0 | BH6: 0 | BI6: Стабильная работа PXF Серверов | BJ6: Сипугин Николай Александрович | BK6: 0
A7: 85 | B7: УБ | C7: ИнвестКопилка | D7: 0.47640449 | E7: Развивающиеся | F7: продукт | G7: 0.6 | H7: 0.5 | I7: 1 | J7: 0 | K7: 0.5 | L7: 1 | M7: 0 | N7: 0 | O7: 0.5 | P7: 0.5 | Q7: 0.5 | R7: 1 | S7: 0 | T7: 1 | U7: 1 | V7: Сравнение с историческими значениями + ручное прогнозирование целевых бенчмарк показателей | W7: 1 | X7: 1 | Y7: 0.5 | Z7: 1 | AA7: 1 | AB7: 0 | AC7: для продукта не включается в расчет | AD7: =IF(AI7="не релевантно","не релевантн",(AI7+AJ7)/2) -> не релевантн | AI7: не релевантно | AJ7: не релевантно | AK7: =IF(AL7="не релевантно","не релевантн",(AL7+AM7)/2) -> не релевантн | AL7: не релевантно | AM7: не релевантно | AN7: не релевантно | AO7: 0 | AP7: 0 | AQ7: 0 | AR7: 0 | AS7: для продукта не включается в расчет | AT7: для продукта не включается в расчет | AU7: 1 | AV7: Воронка продаж | AW7: 1 | AX7: 0 | AY7: 0 | AZ7: 1 | BA7: 0 | BB7: 0 | BC7: 0 | BD7: 0.5 | BE7: нет продукта | BF7: TBD | BG7: 0 | BH7: 1 | BI7: Ресурс аналитиков данных. Очень трудно получить приоритет и фокус на решение сложных задач. Некоторые исследования были похорошены в стол из за отсутсвия ресурса. Также нужны: стабильность поставки данных в навигатор, автоматизация анализа притока ДС и NPV, автоматизация прогнозных оценок, методология расчета влияния сервисов на CLTV, инструмент работы над метчинг исследованиями | BJ7: Коробова Екатерина Вадимовна | BK7: Требуется проверить метрики в блоке-метрики продукта- продукт не выделен в ЕКМ Нет продуктовых механник? Подтвердить релевантны или нет
A8: 90 | B8: УБ | C8: СберСова | D8: 0.47293447 | E8: Развивающиеся | F8: продукт | G8: 1 | H8: 0.5 | I8: 0 | J8: 0 | K8: 0 | L8: 0 | M8: 0 | N8: 0 | O8: 0.5 | P8: 0.5 | Q8: 0.5 | R8: не релевантно | S8: не релевантно | T8: 0 | U8: 1 | V8: Маркетинговые отчеты и аналитика | W8: 0.5 | X8: 1 | Y8: не релевантно | AA8: 1 | AB8: 0.5 | AC8: для продукта не включается в расчет | AD8: =IF(AI8="не релевантно","не релевантн",(AI8+AJ8)/2) -> 0.5 | AI8: 0 | AJ8: 1 | AK8: =IF(AL8="не релевантно","не релевантн",(AL8+AM8)/2) -> 0.5 | AL8: 0 | AM8: 1 | AN8: 0.5 | AO8: 0 | AP8: 1 | AQ8: 0 | AR8: 0 | AS8: для продукта не включается в расчет | AT8: для продукта не включается в расчет | AU8: 1 | AV8: Retention Rate, метрика отказа | AW8: 0 | AX8: 0 | AY8: 0 | AZ8: 1 | BA8: не релевантно | BB8: не релевантно | BC8: не релевантно | BD8: не релевантно | BE8: нет продукта | BF8: TBD | BG8: 0 | BH8: не релевантно | BI8: Витрин данных | BJ8: Волков Дмитрий Александрович | BK8: 1.Отсутвует воронка оттока, но есть механника возврата и RR 2.Подтвердить какие продуктовые механники действительно не релевантны и должны быть исключены из общего расчета
A9: 95 | B9: УБ | C9: Залоговое страхование (корпоративное) | D9: 0.36082474 | E9: Требуют внимания | F9: продукт | G9: 1 | H9: 1 | I9: 1 | J9: 0 | K9: 0 | L9: 1 | M9: 0 | N9: 1 | O9: 0 | P9: 0 | Q9: 0 | R9: 1 | S9: 0 | T9: 1 | U9: 0 | W9: 0.5 | X9: 1 | Y9: 0.5 | Z9: 1 | AA9: 1 | AB9: 0.5 | AC9: для продукта не включается в расчет | AD9: =IF(AI9="не релевантно","не релевантн",(AI9+AJ9)/2) -> 0 | AI9: 0 | AJ9: 0 | AK9: =IF(AL9="не релевантно","не релевантн",(AL9+AM9)/2) -> 0 | AL9: 0 | AM9: 0 | AN9: 0 | AO9: 0 | AP9: 0 | AQ9: 0 | AR9: 1 | AS9: для продукта не включается в расчет | AT9: для продукта не включается в расчет | AU9: 1 | AV9: Рост среднего чека | AW9: 0 | AX9: 0 | AY9: 0 | AZ9: 1 | BA9: 0 | BB9: 0 | BC9: 0 | BD9: 0 | BE9: нет продукта | BF9: TBD | BG9: 0 | BH9: 0 | BI9: 0 | BJ9: Дубинина Татьяна Валерьевна | BK9: 1. Нет Воронки привлечения! 2. Есть Воронка оттока (пролонгации)- Детальный деш в Навигаторе! В разных разрезах 3 Требуется проверить метрики в блоке-метрики продукта- продукт не выделен в ЕКМ 4 Подтвердить UP-sell- подтвердить
A10: 100 | B10: УБ | C10: НСЖ | D10: 0.46419753 | E10: Развивающиеся | F10: продукт | G10: 0.4 | H10: 0.5 | I10: 1 | J10: 0.5 | K10: 1 | L10: 1 | M10: 0 | N10: 1 | O10: 0 | P10: 0 | Q10: 0 | R10: 1 | S10: 0 | T10: 1 | U10: 0 | W10: 1 | X10: 1 | Y10: 0.5 | Z10: 1 | AA10: 1 | AB10: 0 | AC10: для продукта не включается в расчет | AD10: =IF(AI10="не релевантно","не релевантн",(AI10+AJ10)/2) -> 0 | AI10: 0 | AJ10: 0 | AK10: =IF(AL10="не релевантно","не релевантн",(AL10+AM10)/2) -> 0 | AL10: 0 | AM10: 0 | AN10: не релевантно | AO10: 0 | AP10: 0 | AQ10: 0 | AR10: не релевантно | AS10: для продукта не включается в расчет | AT10: для продукта не включается в расчет | AU10: 1 | AV10: Доля сборов по продукту среди всех сборов в сегменте/канале | AW10: 1 | AX10: 0 | AY10: 0 | AZ10: 1 | BA10: 0 | BB10: 0 | BC10: 0 | BD10: 0 | BE10: нет продукта | BF10: TBD | BG10: 0 | BH10: 1 | BI10: Большая автоматизация отслеживания метрик | BJ10: Волобуев Андрей Николаевич | BK10: Отсутсвуют стандартные механники. Отсутвуют черновики (Формула жизни)- должны быть Вернуться с ОС - почему не релевантны механники cross-sell/up-sell?
A11: 105 | B11: УБ | C11: ИСЖ | D11: 0.46236559 | E11: Развивающиеся | F11: продукт | G11: 1 | H11: 0.5 | I11: 1 | J11: 0 | K11: 1 | L11: 1 | M11: 0 | N11: 1 | O11: 0.5 | P11: 0 | Q11: 0.5 | R11: 0 | S11: 0 | T11: 0 | U11: 0 | W11: 0.5 | X11: 1 | Y11: 0.5 | Z11: 1 | AA11: 1 | AB11: 0 | AC11: для продукта не включается в расчет | AD11: =IF(AI11="не релевантно","не релевантн",(AI11+AJ11)/2) -> 1 | AI11: 1 | AJ11: 1 | AK11: =IF(AL11="не релевантно","не релевантн",(AL11+AM11)/2) -> не релевантн | AL11: не релевантно | AM11: не релевантно | AN11: 0 | AO11: 0 | AP11: 0 | AQ11: 0 | AR11: 1 | AS11: для продукта не включается в расчет | AT11: для продукта не включается в расчет | AU11: 1 | AV11: отчет по воронкам кампейнинга | AW11: 0 | AX11: 0 | AY11: 0 | AZ11: 1 | BA11: 0 | BB11: 0 | BC11: 0 | BD11: 0 | BE11: нет продукта | BF11: TBD | BG11: 0 | BH11: 1 | BI11: нет ответа | BJ11: Клычева Олеся Олеговна | BK11: Отсутсвуют стандартные механники. Отсутвуют черновики (Формула жизни) Вернуться с ОС - почему не релевантны механники cross-sell/up-sell?
A12: 110 | B12: УБ | C12: Страхование жизни | D12: 0.4 | E12: Развивающиеся | F12: продукт | G12: 0.2 | H12: 0.5 | I12: 1 | J12: 0 | K12: 1 | L12: 1 | M12: 0 | N12: 1 | O12: 0 | P12: 0 | Q12: 0 | R12: 0 | S12: 0 | T12: 0 | U12: 0 | W12: 0.5 | X12: 1 | Y12: 0.5 | Z12: 0 | AA12: 1 | AB12: 1 | AC12: для продукта не включается в расчет | AD12: =IF(AI12="не релевантно","не релевантн",(AI12+AJ12)/2) -> 1 | AI12: 1 | AJ12: 1 | AK12: =IF(AL12="не релевантно","не релевантн",(AL12+AM12)/2) -> 0.5 | AL12: 1 | AM12: 0 | AN12: 0 | AO12: 0 | AP12: 0 | AQ12: 0 | AR12: 0 | AS12: для продукта не включается в расчет | AT12: для продукта не включается в расчет | AU12: 1 | AV12: % удержания клиентов после окончания страхового поиса | AW12: 0 | AX12: 0 | AY12: 0 | AZ12: 0 | BA12: 0 | BB12: 0 | BC12: 0 | BD12: 0.5 | BE12: нет продукта | BF12: TBD | BG12: 0 | BH12: 1 | BI12: Более тесного взаимодействия банк-ДЗО, есть структурно непраивльно выстроенные подразделения | BJ12: Кобзарь Игорь Викторович | BK12: 0
A13: 115 | B13: УБ | C13: Брокерский счет | D13: 0.42178218 | E13: Развивающиеся | F13: продукт | G13: 0.4 | H13: 0.5 | I13: 1 | J13: 0 | K13: 0.5 | L13: 1 | M13: 0 | N13: 1 | O13: 0.5 | P13: 0 | Q13: 0.5 | R13: 0 | S13: 0 | T13: 0 | U13: 0 | W13: 0.5 | X13: 1 | Y13: 0 | Z13: 0 | AA13: 1 | AB13: 0 | AC13: для продукта не включается в расчет | AD13: =IF(AI13="не релевантно","не релевантн",(AI13+AJ13)/2) -> 0 | AI13: 0 | AJ13: 0 | AK13: =IF(AL13="не релевантно","не релевантн",(AL13+AM13)/2) -> 0.5 | AL13: 1 | AM13: 0 | AN13: 1 | AO13: 1 | AP13: 0 | AQ13: 0 | AR13: 1 | AS13: для продукта не включается в расчет | AT13: для продукта не включается в расчет | AU13: 1 | AV13: Количество клиентов открывших счет, после догоняющих коммуникаций | AW13: 0 | AX13: 0 | AY13: 0 | AZ13: 1 | BA13: 1 | BB13: 0 | BC13: 1 | BD13: 0.5 | BE13: 0.5 | BF13: TBD | BG13: 0 | BH13: 1 | BI13: Не хватает self-service аналитики, удобных A/B-тестов, предиктивных ML-моделей (отток, конверсия в первую сделку) и единого обзора клиентского пути с продуктовыми метриками в реальном времени. | BJ13: Аганина Яна | BK13: Нет Воронки оттока
A14: 120 | B14: УБ | C14: БПИФ | D14: 0.48041237 | E14: Развивающиеся | F14: продукт | G14: 0.4 | H14: 0.5 | I14: 0.5 | J14: 0 | K14: 0.5 | L14: 1 | M14: 0 | N14: 1 | O14: 1 | P14: 0.5 | Q14: 1 | R14: 0 | S14: 0 | T14: 0 | U14: 0 | W14: 0.5 | X14: 1 | Y14: 0.5 | Z14: 1 | AA14: 1 | AB14: 0 | AC14: для продукта не включается в расчет | AD14: =IF(AI14="не релевантно","не релевантн",(AI14+AJ14)/2) -> 0.5 | AI14: 1 | AJ14: 0 | AK14: =IF(AL14="не релевантно","не релевантн",(AL14+AM14)/2) -> 0 | AL14: 0 | AM14: 0 | AN14: 1 | AO14: 1 | AP14: 0 | AQ14: 0 | AR14: 1 | AS14: для продукта не включается в расчет | AT14: для продукта не включается в расчет | AU14: 1 | AV14: кол-во показов, кол-во кликов | AW14: 0 | AX14: 0.5 | AY14: 0 | AZ14: 1 | BA14: 1 | BB14: 0 | BC14: 1 | BD14: 0 | BE14: нет продукта | BF14: TBD | BG14: 0 | BH14: 1 | BI14: сложно сказать | BJ14: Сулейманов Расим Орудж оглы | BK14: Требуется проверить метрики в блоке-метрики продукта- продукт не выделен в ЕКМ Подтвердить- действительно ли не релевантна механника Возврата 0 у ЗПИФ например есть -Акции кэшбеков и иных поощрений за возврат средств от погашенного фонда в другой наш продукт
A15: 125 | B15: УБ | C15: ЗПИФ | D15: 0.63505155 | E15: Зрелые | F15: продукт | G15: 0.4 | H15: 0.5 | I15: 1 | J15: 0 | K15: 1 | L15: 1 | M15: 0 | N15: 1 | O15: 0.5 | P15: 0.5 | Q15: 0.5 | R15: 1 | S15: 0 | T15: 1 | U15: 1 | V15: Цели по удержанию доли рынка, историческая динамика, бенчмарком может быть зарубежный рынок reit (но в РФ есть своя специфика) | W15: 1 | X15: 1 | Y15: 1 | Z15: 1 | AA15: 0.5 | AB15: 0 | AC15: для продукта не включается в расчет | AD15: =IF(AI15="не релевантно","не релевантн",(AI15+AJ15)/2) -> 1 | AI15: 1 | AJ15: 1 | AK15: =IF(AL15="не релевантно","не релевантн",(AL15+AM15)/2) -> 0.5 | AL15: 1 | AM15: 0 | AN15: 1 | AO15: 1 | AP15: 0 | AQ15: 0 | AR15: 1 | AS15: для продукта не включается в расчет | AT15: для продукта не включается в расчет | AU15: 1 | AV15: CR кампаний | AW15: 0 | AX15: 0.5 | AY15: 0 | AZ15: 1 | BA15: 1 | BB15: 0 | BC15: 1 | BD15: 0 | BE15: нет продукта | BF15: TBD | BG15: 0 | BH15: 1 | BI15: Бизнес-мониторинг (оповещение при отклонении бизнес-метрик от заданного порога), инструменты для связи метрик кликстрим с конкретными клиентами и объемами продаж (в рублях) | BJ15: Зырянская Валерия Юрьевна | BK15: Требуется проверить метрики в блоке-метрики продукта- продукт не выделен в ЕКМ Проверить соотвтетвие полноты механник
A16: 130 | B16: УБ | C16: ПДС | D16: 0.55483871 | E16: Развивающиеся | F16: продукт | G16: 0.4 | H16: 0.5 | I16: 1 | J16: 0 | K16: 1 | L16: 1 | M16: 0 | N16: 1 | O16: 1 | P16: 1 | Q16: 1 | R16: не релевантно | S16: не релевантно | T16: 0 | U16: 0 | W16: 1 | X16: 1 | Y16: 0 | Z16: 0 | AA16: 1 | AB16: 0 | AC16: для продукта не включается в расчет | AD16: =IF(AI16="не релевантно","не релевантн",(AI16+AJ16)/2) -> 1 | AI16: 1 | AJ16: 1 | AK16: =IF(AL16="не релевантно","не релевантн",(AL16+AM16)/2) -> 0 | AL16: 0 | AM16: 0 | AN16: 1 | AO16: 1 | AP16: 0 | AQ16: 0 | AR16: 1 | AS16: для продукта не включается в расчет | AT16: для продукта не включается в расчет | AU16: 1 | AV16: Сколько удержано в рублях и штуках. Воронка процесса удержания, тепловая карта процесса. | AW16: 0 | AX16: 0.5 | AY16: 0 | AZ16: 1 | BA16: 1 | BB16: 1 | BC16: 1 | BD16: 0 | BE16: нет продукта | BF16: TBD | BG16: 0 | BH16: 1 | BI16: Длинные сроки глубинных данных по клиентам, которые выгрцзить можно только через DS | BJ16: Процесс оформления ПДС | BK16: Не релевантна воронка оттока- не согласны, так как есть как прекращение пополнений или досрочный выход (с потерями) Прошу подтвердить Механника возврата также релевантна- прошу подтвердить
A17: 135 | B17: УБ | C17: ОПИФ | D17: 0.60990099 | E17: Зрелые | F17: продукт | G17: 0.4 | H17: 0.5 | I17: 1 | J17: 0 | K17: 1 | L17: 1 | M17: 0 | N17: 1 | O17: 0.5 | P17: 0.5 | Q17: 0.5 | R17: 1 | S17: 0 | T17: 1 | U17: 1 | V17: На стороне Управляющей компании: цели по завоеванию доли рынка, историческая динамика | W17: 1 | X17: 1 | Y17: 0.5 | Z17: 1 | AA17: 0.5 | AB17: 0 | AC17: для продукта не включается в расчет | AD17: =IF(AI17="не релевантно","не релевантн",(AI17+AJ17)/2) -> 1 | AI17: 1 | AJ17: 1 | AK17: =IF(AL17="не релевантно","не релевантн",(AL17+AM17)/2) -> 1 | AL17: 1 | AM17: 1 | AN17: 1 | AO17: 1 | AP17: 0 | AQ17: 0 | AR17: 1 | AS17: для продукта не включается в расчет | AT17: для продукта не включается в расчет | AU17: 1 | AV17: CR кампаний, % retention | AW17: 0 | AX17: 0.5 | AY17: 0 | AZ17: 1 | BA17: 1 | BB17: 0 | BC17: 1 | BD17: 0 | BE17: 0 | BF17: TBD | BG17: 0 | BH17: 1 | BI17: Оперативное отслеживание объемов продаж (в руб.) по метрикам кликстрим, оперативное оповещение в случае посадки бизнес-метрик | BJ17: Клочкова Ольга Владимировна | BK17: Требуется проверить метрики в блоке-метрики продукта- продукт не выделен в ЕКМ
A18: 140 | B18: УБ | C18: ВЗР | D18: 0.57029703 | E18: Развивающиеся | F18: продукт | G18: 0.9 | H18: 0.5 | I18: 1 | J18: 0 | K18: 1 | L18: 1 | M18: 0 | N18: 1 | O18: 0.5 | P18: 0.5 | Q18: 0.5 | R18: 0.5 | S18: 0.5 | T18: 0.5 | U18: 0 | W18: 1 | X18: 1 | Y18: 1 | Z18: 1 | AA18: 1 | AB18: 0.5 | AC18: для продукта не включается в расчет | AD18: =IF(AI18="не релевантно","не релевантн",(AI18+AJ18)/2) -> 1 | AI18: 1 | AJ18: 1 | AK18: =IF(AL18="не релевантно","не релевантн",(AL18+AM18)/2) -> 0.5 | AL18: 1 | AM18: 0 | AN18: 0.5 | AO18: 0 | AP18: 0 | AQ18: 1 | AR18: 1 | AS18: для продукта не включается в расчет | AT18: для продукта не включается в расчет | AU18: 1 | AV18: % повторных, CR по ЭФ оформления, CR в черновики, CSI, NPS | AW18: 0 | AX18: 0 | AY18: 0 | AZ18: 0 | BA18: 0 | BB18: 0 | BC18: 0 | BD18: 1 | BE18: 0.5 | BF18: TBD | BG18: 0 | BH18: 0 | BI18: Легких и простых процессов запуска пилотов, простых способов получения данных по продукту (вкл. источников данных для сбора кампаний) | BJ18: Мартусенко Игорь Викторович | BK18: Требуется проверить метрики в блоке-метрики продукта- продукт не выделен в ЕКМ
A19: 145 | B19: УБ | C19: ДУ | D19: 0.40449438 | E19: Развивающиеся | F19: продукт | G19: 1 | H19: 0.5 | I19: 1 | J19: 0 | K19: 1 | L19: 1 | M19: 0 | N19: 1 | O19: 0.5 | P19: 0.5 | Q19: 0.5 | R19: 1 | S19: 0 | T19: 1 | U19: 1 | V19: Цели УК Первая по завоеванию доли рынка + историческая динамика | W19: 0.5 | X19: 0 | Y19: 0.5 | Z19: 1 | AA19: 0.5 | AB19: 0 | AC19: для продукта не включается в расчет | AD19: =IF(AI19="не релевантно","не релевантн",(AI19+AJ19)/2) -> 0 | AI19: 0 | AJ19: 0 | AK19: =IF(AL19="не релевантно","не релевантн",(AL19+AM19)/2) -> 0.5 | AL19: 1 | AM19: 0 | AN19: Не релевантно | AO19: 0 | AP19: 0 | AQ19: 0 | AR19: 0 | AS19: для продукта не включается в расчет | AT19: для продукта не включается в расчет | AU19: 1 | AV19: CR кампейна | AW19: 0 | AX19: 0.5 | AY19: 0 | AZ19: 1 | BA19: 0 | BB19: 0 | BC19: 0 | BE19: нет продукта | BF19: TBD | BG19: 0 | BH19: 0 | BI19: нет ответа | BJ19: Казакова Елена Алексеевна | BK19: Требуется проверить метрики в блоке-метрики продукта- продукт не выделен в ЕКМ Нет механник кроме Возврата. Для ДУ длжны быть релевантны все- например Up-sell в ДУ — это не «купите более дорогой тариф», а увеличение активов под управлением и переход на более сложные стратегии Провеить есть ли кампейн и черновики? Из данных Навигатора не понятно- продукт не выделен
A20: 150 | B20: УБ | C20: Страхование залога (к ипотеке) | D20: 0.51546392 | E20: Развивающиеся | F20: продукт | G20: 1 | H20: 0.5 | I20: 1 | J20: 0 | K20: 1 | L20: 1 | M20: 0 | N20: 1 | O20: 0 | P20: 0 | Q20: 0 | R20: 1 | S20: 0 | T20: 1 | U20: 1 | V20: % удержания | W20: 0.5 | X20: 1 | Y20: 0.5 | Z20: 1 | AA20: 1 | AB20: 0 | AC20: для продукта не включается в расчет | AD20: =IF(AI20="не релевантно","не релевантн",(AI20+AJ20)/2) -> 0.5 | AI20: 1 | AJ20: 0 | AK20: =IF(AL20="не релевантно","не релевантн",(AL20+AM20)/2) -> 1 | AL20: 1 | AM20: 1 | AN20: 0.5 | AO20: 0 | AP20: 0 | AQ20: 1 | AR20: 1 | AS20: для продукта не включается в расчет | AT20: для продукта не включается в расчет | AU20: 1 | AV20: доля Перехвата | AW20: 0 | AX20: 0 | AY20: 0 | AZ20: 1 | BA20: 0 | BB20: 0 | BC20: 0 | BD20: 0.5 | BE20: нет продукта | BF20: TBD | BG20: 0 | BH20: 0 | BI20: не хватает единого инструмента, к которому можно подключиться/донастроить с учетом специфики продукта. Сейчас каждая команда с нуля собирает необходимые данные | BJ20: Казакова Кристина Юрьевна | BK20: 0
A21: 155 | B21: УБ | C21: Личная защита Плюс | D21: 0.60412371 | E21: Зрелые | F21: продукт | G21: 0.9 | H21: 0.5 | I21: 1 | J21: 0.5 | K21: 1 | L21: 1 | M21: 0 | N21: 1 | O21: 1 | P21: 0 | Q21: 1 | R21: 1 | S21: 0.5 | T21: 1 | U21: 1 | V21: Уровень пролонгации, уровень расторжений | W21: 1 | X21: 1 | Y21: 1 | Z21: 1 | AA21: 0.5 | AB21: 0.5 | AC21: для продукта не включается в расчет | AD21: =IF(AI21="не релевантно","не релевантн",(AI21+AJ21)/2) -> 1 | AI21: 1 | AJ21: 1 | AK21: =IF(AL21="не релевантно","не релевантн",(AL21+AM21)/2) -> 0 | AL21: 0 | AM21: 0 | AN21: 1 | AO21: 1 | AP21: 0 | AQ21: 0 | AR21: 1 | AS21: для продукта не включается в расчет | AT21: для продукта не включается в расчет | AU21: 1 | AV21: Уровень пролонгации, уровень расторжений, проникновение в кредитование, конверсия, GWP, ЧКД | AW21: 0 | AX21: 0 | AY21: 0.5 | AZ21: 0 | BA21: 0 | BB21: 0 | BC21: 0 | BD21: 0 | BE21: нет продукта | BF21: TBD | BG21: 0 | BH21: 0 | BI21: Более детальной отчетности по продукту в разных разрезах и по разным каналам продажи. Более понятные дашборды по кампаниям продаж | BJ21: Горбунова Екатерина Эдуардовна | BK21: 0
A22: 160 | B22: УБ | C22: Защита на любой случай | D22: 0.54491018 | E22: Развивающиеся | F22: продукт | G22: 0.5 | H22: 0.5 | I22: 0 | J22: 0 | K22: 1 | L22: 1 | M22: 0 | N22: 1 | O22: 1 | P22: 0.5 | Q22: 1 | R22: 1 | S22: 0 | T22: 1 | U22: 0 | W22: 1 | X22: 1 | Y22: 0.5 | Z22: 1 | AA22: 1 | AB22: 0.5 | AC22: для продукта не включается в расчет | AD22: =IF(AI22="не релевантно","не релевантн",(AI22+AJ22)/2) -> 1 | AI22: 1 | AJ22: 1 | AK22: =IF(AL22="не релевантно","не релевантн",(AL22+AM22)/2) -> 0.5 | AL22: 1 | AM22: 0 | AN22: 0.5 | AO22: 0 | AP22: 1 | AQ22: 0 | AR22: 1 | AS22: для продукта не включается в расчет | AT22: для продукта не включается в расчет | AU22: 1 | AV22: СRR, доля пролонгации, доля очередных взносов | AW22: 0 | AX22: 0 | AY22: 0 | AZ22: 1 | BA22: 1 | BB22: 1 | BC22: 1 | BD22: 0 | BE22: 1 | BF22: TBD | BG22: 0 | BH22: 0 | BI22: дата аналитиков, легких процессов работы с отчетностью и пилотами | BJ22: Корпачева Надежда Олеговна | BK22: 0
A23: 165 | B23: УБ | C23: ДСЖ ПК | D23: 0.55058824 | E23: Развивающиеся | F23: продукт | G23: 0.2 | H23: 0.5 | I23: 1 | J23: 0 | K23: 1 | L23: 1 | M23: 0 | N23: 1 | O23: 0.5 | P23: 0.5 | Q23: 0.5 | R23: 0.5 | S23: 0.5 | T23: 0.5 | U23: 1 | V23: показатель построен на ретро данных, показатель должен быть не выше заложенного в БП | W23: 0.5 | X23: 1 | Y23: 0.5 | Z23: 1 | AA23: 1 | AB23: 1 | AC23: для продукта не включается в расчет | AD23: =IF(AI23="не релевантно","не релевантн",(AI23+AJ23)/2) -> 1 | AI23: 1 | AJ23: 1 | AK23: =IF(AL23="не релевантно","не релевантн",(AL23+AM23)/2) -> не релевантн | AL23: Не релевантно | AM23: Не релевантно | AN23: Не релевантно | AO23: 0 | AP23: 0 | AQ23: 0 | AR23: 0 | AS23: для продукта не включается в расчет | AT23: для продукта не включается в расчет | AU23: 1 | AV23: % оттока | AW23: 0 | AX23: 0 | AY23: 0 | AZ23: 1 | BA23: 0 | BB23: 0 | BC23: 0 | BD23: не релевантно | BE23: нет продукта | BF23: TBD | BG23: 0 | BH23: 1 | BI23: нет аналитиков DA, внутри Трайба сложно встать в бэклог Команды Аналитика данных (DE УБ) | BJ23: Кузнецова Ольга Сергеевна | BK23: Отчеты по воронкам автоматической нет В комментарии отчетность в Навигаторе по продукту, но не по воронке Воронки как я поняла по запросу- прошу подтвердить Вернуться с ответом релевантна ли (возможна ли) механника cross-sell
A24: 170 | B24: УБ | C24: ДСЖ КК | D24: 0.56853933 | E24: Развивающиеся | F24: продукт | G24: 0.4 | H24: 0.5 | I24: 1 | J24: 0 | K24: 1 | L24: 1 | M24: 0 | N24: 1 | O24: 1 | P24: 0.5 | Q24: 1 | R24: 0.5 | S24: 0.5 | T24: 0.5 | U24: 1 | V24: Используются поставленные Цели (клиентские платы, GPW, проникновение, % выставленных счетов, уровень оплачиваемости, средний чек, % расторжений). Использование рыночного бенчмарка не релевантно, т.к. в Сбере используется подход прозрачных продаж и клиентоцентричности, конкуренты продают аналогичный продукт "под капотом" | W24: 1 | X24: 1 | Y24: 1 | Z24: 1 | AA24: 0.5 | AB24: 0 | AC24: для продукта не включается в расчет | AD24: =IF(AI24="не релевантно","не релевантн",(AI24+AJ24)/2) -> 1 | AI24: 1 | AJ24: 1 | AK24: =IF(AL24="не релевантно","не релевантн",(AL24+AM24)/2) -> не релевантн | AL24: Не релевантно | AM24: Не релевантно | AN24: Не релевантно | AO24: 0 | AP24: 0 | AQ24: 0 | AR24: 0 | AS24: для продукта не включается в расчет | AT24: для продукта не включается в расчет | AU24: 1 | AV24: Оценивался % снижения расторжений при внедрении механик | AW24: 0 | AX24: 0 | AY24: 0 | AZ24: 1 | BA24: 1 | BB24: 0 | BC24: 1 | BD24: 0 | BE24: нет продукта | BF24: TBD | BG24: 0 | BH24: 1 | BI24: Единого дэша для объединения всех аналитических срезов по всем активностям. Скорости внедрения изменений в аналитику/отчетность Навигатора | BJ24: Большакова Наталья Сергеевна | BK24: 0
A25: 175 | B25: УБ | C25: ЦФА | D25: 0.28808864 | E25: Требуют внимания | F25: продукт | G25: 0.25 | H25: 0.5 | I25: 1 | J25: 0 | K25: 0 | L25: 1 | M25: 0 | N25: 0 | O25: 0 | P25: 0 | Q25: 0 | R25: 0 | S25: 0 | T25: 0 | U25: 0 | W25: 0.5 | X25: 1 | Y25: не релевантно | Z25: 0 | AA25: 1 | AB25: 0 | AC25: для продукта не включается в расчет | AD25: =IF(AI25="не релевантно","не релевантн",(AI25+AJ25)/2) -> не релевантн | AI25: Не релевантно | AJ25: Не релевантно | AK25: =IF(AL25="не релевантно","не релевантн",(AL25+AM25)/2) -> не релевантн | AL25: Не релевантно | AM25: Не релевантно | AN25: Не релевантно | AO25: 0 | AP25: 0 | AQ25: 0 | AR25: не релевантно | AS25: для продукта не включается в расчет | AT25: для продукта не включается в расчет | AU25: 1 | AV25: Сборы, клиенты, AUM | AW25: 1 | AX25: 0 | AY25: 0 | AZ25: 1 | BA25: 0 | BB25: 0 | BC25: 0 | BE25: нет продукта | BF25: TBD | BG25: 0 | BH25: не реевантно | BI25: Необходимо, чтобы выстраивали централизованно прогнозные значения по метрикам с привлечением Штаба УБ | BJ25: Илларионов Артем Андреевич | BK25: Требуется проверить метрики в блоке-метрики продукта- продукт не выделен в ЕКМ Релеванты ли для продукта SS/компейн? Черновики? Релевантна ли воронка оттока/анализ оттока?
A26: 14 | B26: CBP | C26: Вклады+НС | D26: 0.38613861 | E26: Требуют внимания | F26: продукт | G26: 1 | H26: 0.5 | I26: 0 | J26: 0.5 | K26: 0 | L26: 0 | M26: 0 | N26: 0 | O26: 1 | P26: 0.5 | Q26: 1 | R26: 1 | S26: 0 | T26: 1 | U26: 0 | W26: 0.5 | X26: 1 | Y26: 0 | Z26: 0 | AA26: 1 | AB26: 0 | AC26: для продукта не включается в расчет | AD26: =IF(AI26="не релевантно","не релевантн",(AI26+AJ26)/2) -> 1 | AI26: 1 | AJ26: 1 | AK26: =IF(AL26="не релевантно","не релевантн",(AL26+AM26)/2) -> 1 | AL26: 1 | AM26: 1 | AN26: 0.5 | AO26: 0 | AP26: 1 | AQ26: 0 | AR26: 0 | AS26: для продукта не включается в расчет | AT26: для продукта не включается в расчет | AU26: 1 | AV26: доп объем, % удержания | AW26: 0 | AX26: 0.5 | AY26: 0 | AZ26: 1 | BA26: 1 | BB26: 0 | BC26: 1 | BD26: 0 | BE26: 0 | BF26: TBD | BG26: 0 | BH26: 0 | BI26: не хватает ПШЕ и времени | BJ26: Тырсина Юлия Игоревна | BK26: Прохождение через опроссо значительно ниже 1 тестовой версии Ильи Лащенкова- проверить Отсутвует воронка оттока??? Нет возможности без IT доработки менять опции(кроме ценообразования)???
A27: 19 | B27: CBP | C27: КП | D27: 0.65822785 | E27: Зрелые | F27: продукт | G27: 1 | H27: 1 | I27: 1 | J27: 0.5 | K27: 0.5 | L27: 1 | M27: 0 | N27: 0 | O27: 1 | P27: 0.5 | Q27: 1 | R27: не релевантно | S27: не релевантно | T27: 0 | U27: 0 | W27: 0.5 | X27: 1 | Y27: 0.5 | Z27: 1 | AA27: 0.5 | AB27: 0.5 | AC27: для продукта не включается в расчет | AD27: =IF(AI27="не релевантно","не релевантн",(AI27+AJ27)/2) -> не релевантн | AI27: не релевантно | AJ27: не релевантно | AK27: =IF(AL27="не релевантно","не релевантн",(AL27+AM27)/2) -> не релевантн | AL27: не релевантно | AM27: не релевантно | AN27: 0.5 | AO27: 0 | AP27: 0 | AQ27: 1 | AR27: 1 | AS27: для продукта не включается в расчет | AT27: для продукта не включается в расчет | AU27: 1 | AV27: Кол-во повторных расчетов КП, среднее кол-во расчетов КП за период, вхождение в MAU КП и т.д. | AW27: 0 | AX27: 0.5 | AY27: 0.5 | AZ27: 0 | BA27: не релевантно | BB27: не релевантно | BC27: не релевантно | BD27: не релевантно | BE27: 0 | BF27: TBD | BG27: 1 | BH27: 1 | BI27: ресурсов data-аналитиков (ограниченная команда, ad-hoc запросов всегда много) | BJ27: Кистерский Сергей Анатольевич | BK27: Требуется проверить метрики в блоке-метрики продукта- продукт не выделен в ЕКМ
A28: 24 | B28: CBP | C28: Конверсия | D28: 0.44444444 | E28: Развивающиеся | F28: продукт | G28: 1 | H28: 0.5 | I28: 0.5 | J28: 0.5 | K28: 0.5 | L28: 1 | M28: 0 | N28: 0 | O28: 1 | P28: 1 | Q28: 1 | R28: 0 | S28: 0 | T28: 0 | U28: 1 | V28: новые клиенты в СБОЛ (29000 в месяц), активные клиенты (220000 в месяц) | W28: 0 | X28: 0 | Y28: 0.5 | Z28: 0 | AA28: 0.5 | AB28: 0 | AC28: для продукта не включается в расчет | AD28: =IF(AI28="не релевантно","не релевантн",(AI28+AJ28)/2) -> не релевантн | AI28: не релевантно | AJ28: не релевантно | AK28: =IF(AL28="не релевантно","не релевантн",(AL28+AM28)/2) -> не релевантн | AL28: не релевантно | AM28: не релевантно | AN28: 0 | AO28: не релевантно | AP28: 0 | AQ28: 0 | AR28: 0 | AS28: для продукта не включается в расчет | AT28: для продукта не включается в расчет | AU28: 1 | AV28: нет ответа | AW28: 0 | AX28: 0 | AY28: 1 | AZ28: 0 | BA28: 1 | BB28: 0 | BC28: 1 | BD28: нерелевантно | BE28: 1 | BF28: TBD | BG28: 1 | BH28: 0 | BI28: нет ответа | BJ28: Савенков Илья Игоревич | BK28: Не возможно оценить метрики продукта- ответ по комплексу продуктов
A29: 29 | B29: CBP | C29: Сейфы | D29: 0.47524752 | E29: Развивающиеся | F29: продукт | G29: 1 | H29: 0.5 | I29: 0.5 | J29: 0.5 | K29: 0.5 | L29: 1 | M29: 0 | N29: 0 | O29: 1 | P29: 0 | Q29: 1 | R29: 0 | S29: 0 | T29: 0 | U29: 0 | W29: 1 | X29: 1 | Y29: 0.5 | Z29: 1 | AA29: 1 | AB29: 0 | AC29: для продукта не включается в расчет | AD29: =IF(AI29="не релевантно","не релевантн",(AI29+AJ29)/2) -> 0.5 | AI29: 1 | AJ29: 0 | AK29: =IF(AL29="не релевантно","не релевантн",(AL29+AM29)/2) -> 0.5 | AL29: 1 | AM29: 0 | AN29: 0 | AO29: 0 | AP29: 0 | AQ29: 0 | AR29: 0 | AS29: для продукта не включается в расчет | AT29: для продукта не включается в расчет | AU29: 1 | AV29: % замены сейфов от потенциальных для закрытия, продление договоров, конверсия | AW29: 0 | AX29: 0 | AY29: 1 | AZ29: 0 | BA29: 0 | BB29: 0 | BC29: 0 | BD29: 0 | BE29: 1 | BF29: TBD | BG29: 1 | BH29: 0 | BI29: Ресурсов аналитиков, обучения по имеющимся в банке практикам и инструментам | BJ29: Краснов Игорь Константинович | BK29: Подтвердить релевантность механники черновиков Требуется проверить метрики в блоке-метрики продукта- продукт не выделен в ЕКМ
A30: 34 | B30: CBP | C30: Монеты | D30: 0.54320988 | E30: Развивающиеся | F30: продукт | G30: 1 | H30: 0.5 | I30: 1 | J30: 0.5 | K30: 0.5 | L30: 1 | M30: 0 | N30: 0 | O30: не релевантно | P30: не релевантно | Q30: 0 | R30: не релевантно | S30: не релевантно | T30: 0 | V30: Конкуренты, котировки, остатки, бизнес-план продукта и канала | W30: 0.5 | X30: 1 | Y30: 0.5 | Z30: 1 | AA30: 1 | AB30: 0 | AC30: для продукта не включается в расчет | AD30: =IF(AI30="не релевантно","не релевантн",(AI30+AJ30)/2) -> 0 | AI30: 0 | AJ30: 0 | AK30: =IF(AL30="не релевантно","не релевантн",(AL30+AM30)/2) -> 0.5 | AL30: 1 | AM30: 0 | AN30: 1 | AO30: 1 | AP30: 0 | AQ30: 0 | AR30: 1 | AS30: для продукта не включается в расчет | AT30: для продукта не включается в расчет | AU30: 1 | AV30: ЧКД, конверсия отклика, CSI | AW30: 0 | AX30: 0 | AY30: 1 | AZ30: 0 | BA30: 0 | BB30: 0 | BC30: 0 | BD30: нет продукта | BE30: нет продукта | BF30: TBD | BG30: 0 | BH30: 0 | BI30: Ресурсов DA/DS | BJ30: Румянцева Ирина Викторовна | BK30: Подтвердить бэклог на исследования -От 40 до 79% (https://confluence.sberbank.ru/pages/viewpage.action?pageId=16315384978 ) Требуется проверить метрики в блоке-метрики продукта- продукт не выделен в ЕКМ
A31: 39 | B31: CBP | C31: ОМС | D31: 0.58415842 | E31: Развивающиеся | F31: продукт | G31: 1 | H31: 1 | I31: 1 | J31: 0 | K31: 0.5 | L31: 1 | M31: 0 | N31: 0 | O31: 1 | P31: 0.5 | Q31: 1 | R31: 1 | S31: 0.5 | T31: 1 | U31: 0 | W31: 1 | X31: 1 | Y31: 0.5 | Z31: 1 | AA31: 0.5 | AB31: 0.5 | AC31: для продукта не включается в расчет | AD31: =IF(AI31="не релевантно","не релевантн",(AI31+AJ31)/2) -> 1 | AI31: 1 | AJ31: 1 | AK31: =IF(AL31="не релевантно","не релевантн",(AL31+AM31)/2) -> 0 | AL31: 0 | AM31: 0 | AN31: 0.5 | AO31: 0 | AP31: 1 | AQ31: 0 | AR31: 0 | AS31: для продукта не включается в расчет | AT31: для продукта не включается в расчет | AU31: 1 | AV31: CTR ; CR; Доля в доп. NPV; Кол-во продаж; SCAT | AW31: 0 | AX31: 1 | AY31: 0 | AZ31: 0 | BA31: 1 | BB31: 0 | BC31: 1 | BD31: 0 | BE31: 1 | BF31: TBD | BG31: 1 | BH31: 0 | BI31: ресурса выделенного бизнес-аналитика | BJ31: Тояков Илья Николаевич | BK31: 0
A32: 223 | B32: CBP | C32: Слитки | D32: 0.29892473 | E32: Требуют внимания | F32: продукт | G32: 0.2 | H32: 0.5 | I32: 1 | J32: 0 | K32: 0 | L32: 1 | M32: 0 | N32: 0 | O32: 1 | P32: 0.5 | Q32: 1 | R32: 1 | S32: 0 | T32: 1 | U32: 0 | W32: 0.5 | X32: 1 | Y32: 0 | Z32: 0 | AA32: 0.5 | AB32: 0.5 | AC32: для продукта не включается в расчет | AD32: =IF(AI32="не релевантно","не релевантн",(AI32+AJ32)/2) -> 0 | AI32: 0 | AJ32: 0 | AK32: =IF(AL32="не релевантно","не релевантн",(AL32+AM32)/2) -> 0 | AL32: 0 | AM32: 0 | AN32: 0.5 | AO32: 0 | AP32: 0 | AQ32: 1 | AR32: 1 | AS32: для продукта не включается в расчет | AT32: для продукта не включается в расчет | AU32: 1 | AV32: Кол-во клиентов оформивших ИБС, после покупки слитка. Надбавка для клиентов которые открыли вклад, купили золото. | AW32: 0 | AX32: 0 | AY32: 0 | AZ32: 1 | BA32: 0 | BB32: 0 | BC32: 0 | BD32: не релевантно | BE32: нет продукта | BF32: TBD | BG32: 0 | BH32: 0 | BI32: Всего хватает | BJ32: Скворцов Виталий Михайлович | BK32: Релевантны ли Черновики?
A33: 44 | B33: CBP | C33: Потребительский кредит | D33: 0.76831683 | E33: Зрелые | F33: продукт | G33: 0.4 | H33: 0.5 | I33: 0.5 | J33: 0.5 | K33: 0.5 | L33: 1 | M33: 0 | N33: 0 | O33: 1 | P33: 1 | Q33: 1 | R33: 1 | S33: 0 | T33: 1 | U33: 1 | V33: Данные Frank RG по погашениям портфеля | W33: 1 | X33: 1 | Y33: 0.5 | Z33: 1 | AA33: 1 | AB33: 1 | AC33: для продукта не включается в расчет | AD33: =IF(AI33="не релевантно","не релевантн",(AI33+AJ33)/2) -> 1 | AI33: 1 | AJ33: 1 | AK33: =IF(AL33="не релевантно","не релевантн",(AL33+AM33)/2) -> 1 | AL33: 1 | AM33: 1 | AN33: 1 | AO33: 1 | AP33: 0 | AQ33: 0 | AR33: 1 | AS33: для продукта не включается в расчет | AT33: для продукта не включается в расчет | AU33: 1 | AV33: Uplift от коммуникаций Кампейнинга | AW33: 0 | AX33: 0 | AY33: 1 | AZ33: 0 | BA33: 1 | BB33: 0 | BC33: 1 | BD33: 0.5 | BE33: 0.5 | BF33: TBD | BG33: 1 | BH33: 1 | BI33: Легкий вывод дэшбордов в Навигатор | BJ33: Крамарский Алексей Сергеевич | BK33: Подтвердить бэклог на исследования -От 40 до 79% ссылки на бэклог нет! Подтвердить механнику кросс-сейла после покупки
A34: 49 | B34: CBP | C34: Автокредит | D34: 0.40430108 | E34: Развивающиеся | F34: продукт | G34: 0.4 | H34: 1 | I34: 0 | J34: 0 | K34: 0.5 | L34: 0 | M34: 0 | N34: 0 | O34: 1 | P34: 0.5 | Q34: 1 | R34: 0 | S34: 0 | T34: 0 | U34: 0 | W34: 0.5 | X34: 1 | Y34: 0 | Z34: 0 | AA34: 1 | AB34: 0.5 | AC34: для продукта не включается в расчет | AD34: =IF(AI34="не релевантно","не релевантн",(AI34+AJ34)/2) -> 0 | AI34: 0 | AJ34: 0 | AK34: =IF(AL34="не релевантно","не релевантн",(AL34+AM34)/2) -> 1 | AL34: 1 | AM34: 1 | AN34: 0 | AO34: 0 | AP34: 0 | AQ34: 0 | AR34: 0 | AS34: для продукта не включается в расчет | AT34: для продукта не включается в расчет | AU34: 1 | AV34: доля отказов на данном шаге | AW34: 0 | AX34: 0 | AY34: 0 | AZ34: 0 | BA34: 1 | BB34: 0 | BC34: 1 | BD34: 0 | BE34: нет продукта | BF34: TBD | BG34: 1 | BH34: 1 | BI34: оперативный сбор данных от внешних источников (как пример, БКИ) | BJ34: Бажанова Елена Олеговна | BK34: 0
A35: 54 | B35: CBP | C35: Объект Авто | D35: 0.34408602 | E35: Требуют внимания | F35: продукт | G35: 1 | H35: 0.5 | I35: 0.5 | J35: 0 | K35: 0.5 | L35: 0 | M35: 0 | N35: 0 | O35: 0 | P35: 0 | Q35: 0 | R35: 0 | S35: 0 | T35: 0 | U35: 1 | V35: Activation rate - 40% от новых пользователей раздела вошли в раздел, 15% воспользовались одним из сервисов в течение 60 дней. Retention похожих экосистемных сервисов ~ 30% на 3 мес | W35: 0.5 | X35: 1 | Y35: 0 | Z35: 0 | AA35: 0.5 | AB35: 0 | AC35: для продукта не включается в расчет | AD35: =IF(AI35="не релевантно","не релевантн",(AI35+AJ35)/2) -> 1 | AI35: 1 | AJ35: 1 | AK35: =IF(AL35="не релевантно","не релевантн",(AL35+AM35)/2) -> 1 | AL35: 1 | AM35: 1 | AN35: 0 | AO35: 0 | AP35: 0 | AQ35: 0 | AR35: 0 | AS35: для продукта не включается в расчет | AT35: для продукта не включается в расчет | AU35: 1 | AV35: Retention, CR в сервисы, MAU раздела | AW35: 0 | AX35: 0.5 | AY35: 0 | AZ35: 0 | BA35: 0 | BB35: 0 | BC35: 0 | BE35: нет продукта | BF35: TBD | BG35: 0 | BH35: 0 | BI35: возможности оперативно собирать дашборды и сквозные воронки в Навигаторе и кликстриме через пользовательский интерфейс, делать преднастроенные дашборды с воронками с динамикой показателей по периодам, описанного и удобного Feature store для сегментации клиентской базы и аналитики, оперативного получения данных из ДЗО и их использования в сквозных воронках, Process Mining в контуре Sigma | BJ35: Кравченко Анна Геннадьевна | BK35: 0
A36: 59 | B36: CBP | C36: POS-кредиты | D36: 0.49896907 | E36: Развивающиеся | F36: продукт | G36: 0.6 | H36: 1 | I36: 0 | J36: 0 | K36: 0 | L36: 0 | M36: 0 | N36: 0 | O36: 1 | P36: 0.5 | Q36: 1 | R36: 0 | S36: 0 | T36: 0 | U36: 1 | V36: партнерская воронка в разрезе платежных методов, брокеров и собственных решений | W36: 0.5 | X36: 1 | Y36: 0.5 | Z36: 1 | AA36: 1 | AB36: 1 | AC36: для продукта не включается в расчет | AD36: =IF(AI36="не релевантно","не релевантн",(AI36+AJ36)/2) -> 0.5 | AI36: 1 | AJ36: 0 | AK36: =IF(AL36="не релевантно","не релевантн",(AL36+AM36)/2) -> 0 | AL36: 0 | AM36: 0 | AN36: 1 | AO36: 1 | AP36: 0 | AQ36: 0 | AR36: 1 | AS36: для продукта не включается в расчет | AT36: для продукта не включается в расчет | AU36: 1 | AV36: анализ сквозной воронки от оффера до продажи | AW36: 0 | AX36: 0 | AY36: 0.5 | AZ36: 0 | BA36: 0 | BB36: 0 | BC36: 0 | BD36: 0 | BE36: 1 | BF36: TBD | BG36: 0 | BH36: 0 | BI36: ПШЕ аналитиков | BJ36: Блинов Дмитрий Игоревич | BK36: Нужно перепройти опрос отдельно по продукту сейчас все вместе POS/BNPL/КДЗП/Образоввательный кредит
A37: 64 | B37: CBP | C37: BNPL | D37: 0.43762376 | E37: Развивающиеся | F37: Исключить | G37: 0.8 | H37: 1 | I37: 0 | J37: 0 | K37: 0 | L37: 0 | M37: 0 | N37: 0 | O37: 0.5 | P37: 0.5 | Q37: 0.5 | R37: 0 | S37: 0 | T37: 0 | U37: 0 | W37: 1 | X37: 1 | Y37: 0.5 | Z37: 1 | AA37: 1 | AB37: 0.5 | AC37: для продукта не включается в расчет | AD37: =IF(AI37="не релевантно","не релевантн",(AI37+AJ37)/2) -> 0 | AI37: 0 | AJ37: 0 | AK37: =IF(AL37="не релевантно","не релевантн",(AL37+AM37)/2) -> 0 | AL37: 0 | AM37: 0 | AN37: 0.5 | AO37: 0 | AP37: 1 | AQ37: 0 | AR37: 1 | AS37: для продукта не включается в расчет | AT37: для продукта не включается в расчет | AU37: 1 | AV37: приобретение второго идентичного продукта, продажа смежного продукта | AW37: 0 | AX37: 0.5 | AY37: 0.5 | AZ37: 0 | BA37: 1 | BB37: 0 | BC37: 1 | BD37: 0 | BE37: 0.5 | BF37: TBD | BG37: 0 | BH37: 0 | BI37: автоматизации | BJ37: Блинов Дмитрий Игоревич | BK37: Нужно перепройти опрос отдельно по продукту сейчас все вместе POS/BNPL/КДЗП/Образоввательный кредит
A38: 69 | B38: CBP | C38: Образовательный кредит | D38: 0.091954023 | E38: Требуют внимания | F38: Исключить | G38: 1 | H38: 0 | I38: 1 | J38: 0 | K38: 0 | L38: 1 | M38: 0 | N38: 0 | O38: не релевантно | P38: не релевантно | Q38: 0 | R38: 0 | S38: 0 | T38: 0 | U38: 0 | W38: 0 | X38: 0 | Y38: 0 | AA38: 0 | AB38: 0 | AC38: для продукта не включается в расчет | AD38: =IF(AI38="не релевантно","не релевантн",(AI38+AJ38)/2) -> 0 | AI38: 0 | AJ38: 0 | AK38: =IF(AL38="не релевантно","не релевантн",(AL38+AM38)/2) -> 0 | AL38: 0 | AM38: 0 | AN38: 0 | AO38: не релевантно | AP38: 0 | AQ38: 0 | AR38: 0 | AS38: для продукта не включается в расчет | AT38: для продукта не включается в расчет | AU38: 0 | AV38: 0 | AW38: 0 | AX38: 0 | AY38: 0 | AZ38: 0 | BA38: 0 | BB38: 0 | BC38: 0 | BD38: 0 | BF38: TBD | BG38: 0 | BH38: 0 | BI38: 0 | BJ38: Блинов Дмитрий Игоревич | BK38: Нужно перепройти опрос отдельно по продукту сейчас все вместе POS/BNPL/КДЗП/Образоввательный кредит
A39: 181 | B39: ДомКлик | C39: Сделка с Первичным жильём | D39: 0.68041237 | E39: Зрелые | F39: продукт | G39: 1 | H39: 1 | I39: 1 | J39: 0.5 | K39: 0.5 | L39: 1 | M39: 1 | N39: 1 | O39: 1 | P39: 0.5 | Q39: 1 | R39: не релевантно | S39: не релевантно | T39: 0 | U39: 1 | V39: Роскадастр | W39: 0.5 | X39: 1 | Y39: 0.5 | Z39: 1 | AA39: 1 | AB39: 0 | AC39: для продукта не включается в расчет | AD39: =IF(AI39="не релевантно","не релевантн",(AI39+AJ39)/2) -> 0.5 | AI39: 1 | AJ39: 0 | AK39: =IF(AL39="не релевантно","не релевантн",(AL39+AM39)/2) -> не релевантн | AL39: не релевантно | AM39: не релевантно | AN39: 0.5 | AO39: 0 | AP39: 1 | AQ39: 0 | AR39: 1 | AS39: для продукта не включается в расчет | AT39: для продукта не включается в расчет | AU39: 1 | AV39: Уровень проникновения продукта в выдачу кредитов. доля клиентов, совершивших сделку с 1+ продуктом | AW39: 0 | AX39: 0 | AY39: 1 | AZ39: 0 | BA39: 1 | BB39: 1 | BC39: 0 | BD39: 1 | BE39: 1 | BF39: TBD | BG39: 1 | BH39: 0 | BI39: Отчётность по продуктам Управления торгового финансирования. (счета эскроу, аккредитивы) | BJ39: Поддубный Иван Сергеевич | BK39: 0
A40: 186 | B40: ДомКлик | C40: Много денег (НКПЗН) | D40: 0.6 | E40: Зрелые | F40: продукт | G40: 1 | H40: 1 | I40: 0 | J40: 0.5 | K40: 0.5 | L40: 0 | M40: 1 | N40: 0 | O40: 1 | P40: 1 | Q40: 1 | R40: 0 | S40: 0 | T40: 0 | U40: 1 | V40: Frank RG | W40: 0.5 | X40: 1 | Y40: 0 | Z40: 0 | AA40: 1 | AB40: 0 | AC40: для продукта не включается в расчет | AD40: =IF(AI40="не релевантно","не релевантн",(AI40+AJ40)/2) -> 1 | AI40: 1 | AJ40: 1 | AK40: =IF(AL40="не релевантно","не релевантн",(AL40+AM40)/2) -> 0 | AL40: 0 | AM40: 0 | AN40: 1 | AO40: 1 | AP40: 0 | AQ40: 0 | AR40: 1 | AS40: для продукта не включается в расчет | AT40: для продукта не включается в расчет | AU40: 1 | AV40: Кликабельность и конверсии, результат | AW40: 0 | AX40: 0.5 | AY40: 1 | AZ40: 0 | BA40: 1 | BB40: 1 | BC40: 0 | BD40: 1 | BE40: 1 | BF40: TBD | BG40: 1 | BH40: 0 | BI40: Собственые дата-инеженеры | BJ40: Спиваков Андрей Дмитриевич | BK40: Подтвердить релевантна или нет воронка оттока , Проверить релевантнрость механник- написать какие нужно исключить Черновики? Есть ли кампейнинг? Self service??
A41: 191 | B41: ДомКлик | C41: Сделка ИЖС | D41: 0.53465347 | E41: Развивающиеся | F41: ДЗО | G41: 1 | H41: 0.5 | I41: 1 | J41: 0.5 | K41: 0.5 | L41: 1 | M41: 1 | N41: 1 | O41: 1 | P41: 1 | Q41: 1 | R41: 0 | S41: 0 | T41: 0 | U41: 1 | V41: frank rg, Роскадастр | W41: 1 | X41: 0 | Y41: 0 | Z41: 0 | AA41: 0.5 | AB41: 0 | AC41: для продукта не включается в расчет | AD41: =IF(AI41="не релевантно","не релевантн",(AI41+AJ41)/2) -> 0.5 | AI41: 1 | AJ41: 0 | AK41: =IF(AL41="не релевантно","не релевантн",(AL41+AM41)/2) -> 0 | AL41: 0 | AM41: 0 | AN41: 0.5 | AO41: 0 | AP41: 1 | AQ41: 0 | AR41: 1 | AS41: для продукта не включается в расчет | AT41: для продукта не включается в расчет | AU41: 1 | AV41: Доля рынка неипотеки, Время на сделку, Доля продаж доп услуг | AW41: 0 | AX41: 0 | AY41: 0.5 | AZ41: 0 | BA41: 1 | BB41: 1 | BC41: 0 | BD41: 1 | BE41: 1 | BF41: TBD | BG41: 1 | BH41: 0 | BI41: нет ответа | BJ41: Стюарт Александр Александрович | BK41: Требуется проверить метрики в блоке-метрики продукта- продукт не выделен в ЕКМ. Подтвердить релевантна или нет воронка оттока , Проверить релевантнрость механник- написать какие нужно исключить. Черновики? Есть ли кампейнинг? Self service??
A42: 196 | B42: ДомКлик | C42: Моя Недвижимость | D42: 0.42268041 | E42: Развивающиеся | F42: ДЗО | G42: 1 | H42: 0.5 | I42: 1 | J42: 0.5 | K42: 0.5 | L42: 1 | M42: 1 | N42: 1 | O42: 1 | P42: 0.5 | Q42: 1 | R42: 0 | S42: 0 | T42: 0 | U42: 0 | W42: 0.5 | X42: 1 | Y42: 0 | Z42: 0 | AA42: 1 | AB42: 0 | AC42: для продукта не включается в расчет | AD42: =IF(AI42="не релевантно","не релевантн",(AI42+AJ42)/2) -> 0.5 | AI42: 1 | AJ42: 0 | AK42: =IF(AL42="не релевантно","не релевантн",(AL42+AM42)/2) -> 0 | AL42: 0 | AM42: 0 | AN42: 0 | AO42: 0 | AP42: 0 | AQ42: 0 | AR42: 0 | AS42: для продукта не включается в расчет | AT42: для продукта не включается в расчет | AU42: 1 | AV42: Кол-во привлеченных клиентов, конверсия в использование продукта, ретеншн привлеченных клиентов | AW42: 1 | AX42: 0 | AY42: 1 | AZ42: 0 | BA42: 1 | BB42: 1 | BC42: 0 | BD42: 0 | BE42: нет продукта | BF42: TBD | BG42: 1 | BH42: 0 | BI42: Кол-во аналитиков | BJ42: Ильин Павел Константинович | BK42: Требуется проверить метрики в блоке-метрики продукта- продукт не выделен в ЕКМ. Посмотреть релевантность механник. К какой группе относится продукт? К к ЛАйфстайл сервисам? В СХ Score участвует?
A43: 201 | B43: ДомКлик | C43: Личный кабинет сопровождения ипотеки (далее - ЛКС) | D43: 0.45544554 | E43: Развивающиеся | F43: ДЗО | G43: 1 | H43: 0.5 | I43: 0 | J43: 0.5 | K43: 0.5 | L43: 0 | M43: 1 | N43: 0 | O43: 1 | P43: 0 | Q43: 1 | R43: 0 | S43: 0 | T43: 0 | U43: 0 | W43: 0.5 | X43: 1 | Y43: 0 | Z43: 0 | AA43: 1 | AB43: 0 | AC43: для продукта не включается в расчет | AD43: =IF(AI43="не релевантно","не релевантн",(AI43+AJ43)/2) -> 1 | AI43: 1 | AJ43: 1 | AK43: =IF(AL43="не релевантно","не релевантн",(AL43+AM43)/2) -> 0 | AL43: 0 | AM43: 0 | AN43: 1 | AO43: 1 | AP43: 0 | AQ43: 0 | AR43: 1 | AS43: для продукта не включается в расчет | AT43: для продукта не включается в расчет | AU43: 1 | AV43: Открываемость (Open Rate); кликабельность (Click-Through Rate, CTR) и др | AW43: 0 | AX43: 0 | AY43: 0 | AZ43: 0 | BA43: 1 | BB43: 1 | BC43: 0 | BD43: 1 | BE43: нет продукта | BF43: TBD | BG43: 1 | BH43: 0 | BI43: нет ответа | BJ43: Кузьменко Марина Михайловна | BK43: Требуется проверить метрики в блоке-метрики продукта- продукт не выделен в ЕКМ. Проверить/подтвердить полноту механник (cross-sell-В процессе оформления и после покупки, удержания,upsell- как происходит? ). К какой группе относится продукт? К к ЛАйфстайл сервисам? проверить релевантность механники возврата?
A44: 206 | B44: ДомКлик | C44: Сделка вторичка | D44: 0.71428571 | E44: Зрелые | F44: продукт | G44: 1 | H44: 0.5 | I44: 1 | J44: 0.5 | K44: 0.5 | L44: 1 | M44: 1 | N44: 1 | O44: 1 | P44: 0.5 | Q44: 1 | R44: 0 | S44: 0 | T44: 0 | U44: 1 | V44: Роскадастр, Frank | W44: 0.5 | X44: 1 | Y44: 0.5 | Z44: 1 | AA44: 0.5 | AB44: 0 | AC44: для продукта не включается в расчет | AD44: =IF(AI44="не релевантно","не релевантн",(AI44+AJ44)/2) -> 0.5 | AI44: 1 | AJ44: 0 | AK44: =IF(AL44="не релевантно","не релевантн",(AL44+AM44)/2) -> 1 | AL44: 1 | AM44: 1 | AN44: 1 | AO44: 1 | AP44: 0 | AQ44: 0 | AR44: 1 | AS44: для продукта не включается в расчет | AT44: для продукта не включается в расчет | AU44: 1 | AV44: Доля рынка, время на сделку, кол-во продуктов на сделку, CSI, кол-во багов, | AW44: 0 | AX44: 0.5 | AY44: 1 | AZ44: 0 | BA44: 1 | BB44: 1 | BC44: 0 | BD44: 1 | BE44: 1 | BF44: TBD | BG44: 1 | BH44: 1 | BI44: нет ответа | BJ44: Комаров Сергей Андреевич | BK44: Нет инфомации в централизованном деше кампейнинга запусках и наличии Self service- прошу подтвердить есть ли кампейн (за 1 кв- сколько из них успешных/есть ли Self service?). Нет информации о работе механнике черновиков- доведение до продажи- прошу подтвердить наличие и % покрытия от потенциала продукта." воронка оттока- это воронка погашения/ погащения ЧПД/ЧПДП/просрочка
A45: 212 | B45: PC | C45: СберМобайл | D45: 0.54257426 | E45: Развивающиеся | F45: ДЗО | G45: 0.2 | H45: 1 | I45: 0 | J45: 0.5 | K45: 0 | L45: 0 | M45: 1 | N45: 0 | O45: 1 | P45: 1 | Q45: 1 | R45: 1 | S45: 0.5 | T45: 1 | U45: 0 | W45: 1 | X45: 1 | Y45: 0.5 | Z45: 1 | AA45: 1 | AB45: 0.5 | AC45: для продукта не включается в расчет | AD45: =IF(AI45="не релевантно","не релевантн",(AI45+AJ45)/2) -> 1 | AI45: 1 | AJ45: 1 | AK45: =IF(AL45="не релевантно","не релевантн",(AL45+AM45)/2) -> 0.5 | AL45: 1 | AM45: 0 | AN45: 1 | AO45: 1 | AP45: 0 | AQ45: 0 | AR45: 1 | AS45: для продукта не включается в расчет | AT45: для продукта не включается в расчет | AU45: 1 | AV45: cr к основному продукту для cross | AW45: 0 | AX45: 0 | AY45: 0 | AZ45: 1 | BA45: 0 | BB45: 0 | BC45: 1 | BD45: 0 | BE45: 0.5 | BF45: TBD | BG45: 0 | BH45: 1 | BI45: Подсвечивать лучшие практики. Очень полезный дайджест по баннерам в СБОЛе - выводы из него часто используем для построения коммуникаций. | BJ45: Смирнов Олег Александрович | BK45: ДЗО! Нет информации в ПАО по механнике черновиков- прошу подтвердить наличие/покрытие от потенциала. Прошу подтвердить Факторный анализ (собственная отчетность).
A46: 217 | B46: PC | C46: Выписки, справки | D46: 0.58801498 | E46: Развивающиеся | F46: продукт | G46: 1 | H46: 1 | I46: 1 | J46: 1 | K46: 0 | L46: 1 | M46: 1 | N46: 0 | O46: не релевантно | P46: не релевантно | Q46: 0 | R46: не релевантно | S46: не релевантно | T46: 0 | V46: 0 | W46: 0 | X46: 0 | Y46: Не релевантно | Z46: Не релевантно | AA46: 1 | AB46: 1 | AC46: для продукта не включается в расчет | AD46: =IF(AI46="не релевантно","не релевантн",(AI46+AJ46)/2) -> не релевантн | AI46: Не релевантно | AJ46: Не релевантно | AK46: =IF(AL46="не релевантно","не релевантн",(AL46+AM46)/2) -> не релевантн | AL46: Не релевантно | AM46: Не релевантно | AN46: 0.5 | AO46: 0 | AP46: 1 | AQ46: 0 | AR46: не релевантно | AS46: для продукта не включается в расчет | AT46: для продукта не включается в расчет | AU46: 1 | AV46: не релевантно для моего продукта | AW46: 0 | AX46: 1 | AY46: 0 | AZ46: 1 | BA46: не релевантно | BB46: не релевантно | BC46: не релевантно | BD46: не релевантно | BE46: не релевантно | BF46: TBD | BG46: 1 | BH46: 0 | BI46: затрудняюсь ответить | BJ46: Красильников Антон Владимирович | BK46: Требуется проверить метрики в блоке-метрики продукта- продукт не выделен в ЕКМ. Почему не реевантна воронка привлечения/оформления? Почему не релевантна механника кросс-сейла? Считаю что возможна. прошу подтвердить какие критерии не релевантны для данного продукта (специфичный) | BL46: с ДСР уже было обсуждение - остановились на том, что отток не используем в силу серфисной специфики и конкретной потребности клиента. Доступность и осведомленность измеряется Digital index
A47: 229 | B47: СХ | C47: СберПрайм | D47: 0.63917526 | E47: Зрелые | F47: продукт | G47: 0.5 | H47: 0.5 | I47: 0.5 | J47: 0 | K47: 0.5 | L47: 1 | M47: 0 | N47: 0 | O47: 1 | P47: 0.5 | Q47: 1 | R47: 1 | S47: 0.5 | T47: 1 | U47: 1 | V47: Цели, бенчмаркинг с яндексом | W47: 0.5 | X47: 1 | Y47: 1 | Z47: 1 | AA47: 0 | AB47: 0.5 | AC47: для продукта не включается в расчет | AD47: =IF(AI47="не релевантно","не релевантн",(AI47+AJ47)/2) -> 1 | AI47: 1 | AJ47: 1 | AK47: =IF(AL47="не релевантно","не релевантн",(AL47+AM47)/2) -> 0.5 | AL47: 1 | AM47: 0 | AN47: Не релевантно | AO47: 0 | AP47: 0 | AQ47: 0 | AR47: 1 | AS47: для продукта не включается в расчет | AT47: для продукта не включается в расчет | AU47: 1 | AV47: инкрементальные продажи, удержанные, выручка. Конверсия в продление подписки | AW47: 0 | AX47: 0 | AY47: 0.5 | AZ47: 0 | BA47: 1 | BB47: 0 | BC47: 1 | BD47: 0.5 | BE47: 0.5 | BF47: TBD | BG47: 1 | BH47: 1 | BI47: инструмента для АБ тестирования, возможности сегментировать пользователей на витринах и на уровне фабрики | BJ47: Першин Алексей | BK47: Приложите ссылку на бэклог DA
A48: 234 | B48: СХ | C48: Пакет услуг СберПремьер | D48: 0.58415842 | E48: Развивающиеся | F48: продукт | G48: 1 | H48: 0.5 | I48: 1 | J48: 0.5 | K48: 0 | L48: 1 | M48: 0 | N48: 0 | O48: 0.5 | P48: 1 | Q48: 0.5 | R48: 0 | S48: 0 | T48: 0 | U48: 1 | V48: регулярный отчет (1р/год) по рынку премиальных продуктов от Frank research group. есть агрегированные данные по притокам/оттокам в разрезе банков | W48: 1 | X48: 1 | Y48: 0.5 | Z48: 1 | AA48: 1 | AB48: 0 | AC48: для продукта не включается в расчет | AD48: =IF(AI48="не релевантно","не релевантн",(AI48+AJ48)/2) -> 0 | AI48: 0 | AJ48: 0 | AK48: =IF(AL48="не релевантно","не релевантн",(AL48+AM48)/2) -> 0 | AL48: 0 | AM48: 0 | AN48: 0 | AO48: 0 | AP48: 0 | AQ48: 0 | AR48: 1 | AS48: для продукта не включается в расчет | AT48: для продукта не включается в расчет | AU48: 1 | AV48: CR по докупкам уровней выше, доп КД | AW48: 0 | AX48: 1 | AY48: 0.5 | AZ48: 0 | BA48: 1 | BB48: 1 | BC48: 1 | BD48: 0 | BE48: 0.5 | BF48: TBD | BG48: 0 | BH48: 1 | BI48: - ресурс аналитиков для автоматизации отчетности - ресурс аналитиков для настраивания alert | BJ48: Козлова Диана Леонидовна | BK48: Приложите ссылку на бэклог DA. Уточнить релевантна ли механника cross-sell? У СБ1 по опроссу есть Изменела набор опций по продукту без IT-разработки возможно по СБП но не возможно по СБ1. Почему? Просьба проверить цифру потенциала в Сбере 3,5 млн и Потенциала в РФ 5 млн
A49: 239 | B49: СХ | C49: Пакет услуг СберПервый | D49: 0.45940594 | E49: Развивающиеся | F49: продукт | G49: 0.6 | H49: 0.5 | I49: 0.5 | J49: 0 | K49: 0.5 | L49: 1 | M49: 0 | N49: 0 | O49: 0.5 | P49: 0.5 | Q49: 0.5 | R49: 0 | S49: 0 | T49: 0 | U49: 0 | W49: 0.5 | X49: 0 | Y49: 0.5 | Z49: 0 | AA49: 1 | AB49: 0 | AC49: для продукта не включается в расчет | AD49: =IF(AI49="не релевантно","не релевантн",(AI49+AJ49)/2) -> 0.5 | AI49: 0 | AJ49: 1 | AK49: =IF(AL49="не релевантно","не релевантн",(AL49+AM49)/2) -> 0 | AL49: 0 | AM49: 0 | AN49: 1 | AO49: 1 | AP49: 0 | AQ49: 0 | AR49: 1 | AS49: для продукта не включается в расчет | AT49: для продукта не включается в расчет | AU49: 1 | AV49: 1) Количество клиентов в разрезе подсегментов (фондированные, SLA, платные, шеринговые) 2) AUM на клиента 3) Перетоки между уровнями 4) Привлечение на уровни 5) Закрытие пакета и др | AW49: 0 | AX49: 0 | AY49: 0.5 | AZ49: 0 | BA49: 1 | BB49: 1 | BC49: 1 | BD49: 0 | BE49: 1 | BF49: TBD | BG49: 0 | BH49: 1 | BI49: ресурса DA аналитика | BJ49: Аленцев Александр Михайлович | BK49: Вернуться- как осуществляется механника cross-sell. Изменение набора опций по продукту без IT-разработки возможно по СБП но не возможно по СБ1. Почему? Просьба проверить цифру потенциала в Сбере 0,3 млн и Потенциала в РФ 0,4 млн
A50: 13 | B50: СХ | C50: =свод_сегменты!K5 -> Дети | D50: =свод_сегменты!M4 -> 0.56589147 | E50: Развивающиеся | F50: Сегмент | G50: =VLOOKUP(G$4,свод_сегменты!$A:$AL,$A50,0) -> 0.75 | H50: =VLOOKUP(H$4,свод_сегменты!$A:$AL,$A50,0) -> 0.5 | I50: =VLOOKUP(I$4,свод_сегменты!$A:$AL,$A50,0) -> 0.5 | J50: =VLOOKUP(J$4,свод_сегменты!$A:$AL,$A50,0) -> 1 | K50: =VLOOKUP(K$4,свод_сегменты!$A:$AL,$A50,0) -> 0 | L50: =VLOOKUP(L$4,свод_сегменты!$A:$AL,$A50,0) -> 1 | M50: =VLOOKUP(M$4,свод_сегменты!$A:$AL,$A50,0) -> 1 | N50: =VLOOKUP(N$4,свод_сегменты!$A:$AL,$A50,0) -> 0 | ... P50: =VLOOKUP(P$4,свод_сегменты!$A:$AL,$A50,0) -> 0.5 | Q50: =IF(OR(O50=0,O50="не релевантно"),0,(VLOOKUP(Q$4,свод_сегменты!$A:$AL,$A50-1,0))) -> 1 | R50: =VLOOKUP(R$4,свод_сегменты!$A:$AL,$A50,0) -> 0.5 | S50: =VLOOKUP(S$4,свод_сегменты!$A:$AL,$A50,0) -> 0.5 | T50: =IF(OR(R50=0,R50="не релевантно"),0,(VLOOKUP(T$4,свод_сегменты!$A:$AL,$A50-1,0))) -> 0.5 | U50: =VLOOKUP(U$4,свод_сегменты!$A:$AL,$A50,0) -> 0 | V50: =IF(U50>0,VLOOKUP(V$4,свод_сегменты!$A:$AL,$A50-4,0),"") | W50: =VLOOKUP(W$4,свод_сегменты!$A:$AL,$A50,0) -> 1 | X50: =VLOOKUP(X$4,свод_сегменты!$A:$AL,$A50,0) -> 1 | Y50: =VLOOKUP(Y$4,свод_сегменты!$A:$AL,$A50,0) -> 1 | Z50: =VLOOKUP(Z$4,свод_сегменты!$A:$AL,$A50,0) -> 1 | AA50: не релевантно | AB50: =VLOOKUP(AB$4,свод_сегменты!$A:$AL,$A50,0) -> 0 | AC50: =VLOOKUP(AC$4,свод_сегменты!$A:$AL,$A50,0) -> 1 | AD50: =VLOOKUP(AD$4,свод_сегменты!$A:$AL,$A50,0) -> 0 | AE50: =VLOOKUP(AE$4,свод_сегменты!$A:$AL,$A50,0) -> 0 | AF50: =VLOOKUP(AF$4,свод_сегменты!$A:$AL,$A50-3,0) -> 0 | AG50: =VLOOKUP(AG$4,свод_сегменты!$A:$AL,$A50-3,0) -> 0 | AH50: =VLOOKUP(AH$4,свод_сегменты!$A:$AL,$A50-3,0) -> 0 | AK50: =VLOOKUP(AK$4,свод_сегменты!$A:$AL,$A50,0) | AS50: =VLOOKUP(AS$4,свод_сегменты!$A:$AL,$A50,0) -> 0 | AT50: =VLOOKUP(AT$4,свод_сегменты!$A:$AL,$A50,0) -> 1 | AU50: =VLOOKUP(AU$4,свод_сегменты!$A:$AL,$A50,0) -> 0 | AV50: =VLOOKUP(AU$4,свод_сегменты!$A:$AL,$A50-4,0) -> Дэш и оперативные вызовы | AX50: не релевантно | AY50: =VLOOKUP(AY$4,свод_сегменты!$A:$AL,$A50,0) -> 0.5 | AZ50: =VLOOKUP(AZ$4,свод_сегменты!$A:$AL,$A50-3,0) -> 0 | BC50: TBD | BD50: не релевантно | BE50: не релевантно | BF50: TBD | BG50: =VLOOKUP(BG$4,свод_сегменты!$A:$AL,$A50,0) -> 1 | BH50: не релевантно | BI50: =VLOOKUP(BI$4,свод_сегменты!$A:$AL,$A50-4,0) -> Оперативный запуск сложных дэш (не базовые х метрик), ресурсов на прокладку задач, доп прокопка без заказа | BJ50: =VLOOKUP(BJ$4,свод_сегменты!$A:$AL,$A50-2,0) -> #N/A | BK50: =VLOOKUP(BK$4,свод_сегменты!$A:$AL,$A50-2,0) -> Нет ссылки на воронку привлечния/оттока-прошу приложить Не написаны метрики мониторинга механник Нет ссылки на бэклог DA-просьба приложить Релевантна ли сегменту метрика 2+ нефин сервиса- Это Дети возможно вопрос не релевантен
A51: =свод_сегменты!R1 -> 18 | B51: СХ | C51: Молодежь | D51: =свод_сегменты!R4 -> 0.48091603 | E51: Развивающиеся | F51: Сегмент | G51: =VLOOKUP(G$4,свод_сегменты!$A:$AQ,$A51,0) -> 0.5 | H51: =VLOOKUP(H$4,свод_сегменты!$A:$AQ,$A51,0) -> 0.5 | I51: =VLOOKUP(I$4,свод_сегменты!$A:$AQ,$A51,0) -> 1 | J51: =VLOOKUP(J$4,свод_сегменты!$A:$AQ,$A51,0) -> 0.5 | K51: =VLOOKUP(K$4,свод_сегменты!$A:$AQ,$A51,0) -> 0 | L51: =VLOOKUP(L$4,свод_сегменты!$A:$AQ,$A51,0) -> 1 | M51: =VLOOKUP(M$4,свод_сегменты!$A:$AQ,$A51,0) -> 1 | N51: =VLOOKUP(N$4,свод_сегменты!$A:$AQ,$A51,0) -> 0 | ... P51: =VLOOKUP(P$4,свод_сегменты!$A:$AQ,$A51,0) -> 0.5 | Q51: =IF(OR(O51=0,O51="не релевантно"),0,(VLOOKUP(Q$4,свод_сегменты!$A:$AQ,$A51-1,0))) -> 0.5 | R51: =VLOOKUP(R$4,свод_сегменты!$A:$AQ,$A51,0) -> 0 | S51: =VLOOKUP(S$4,свод_сегменты!$A:$AQ,$A51,0) -> 0 | T51: =IF(OR(R51=0,R51="не релевантно"),0,(VLOOKUP(T$4,свод_сегменты!$A:$AQ,$A51-1,0))) -> 0 | U51: =VLOOKUP(U$4,свод_сегменты!$A:$AQ,$A51,0) -> 1 | V51: =IF(U51>0,VLOOKUP(V$4,свод_сегменты!$A:$AQ,$A51-4,0),"") -> другие сегменты + прошлый год | W51: =VLOOKUP(W$4,свод_сегменты!$A:$AQ,$A51,0) -> 0.5 | X51: =VLOOKUP(X$4,свод_сегменты!$A:$AQ,$A51,0) -> 1 | Y51: =VLOOKUP(Y$4,свод_сегменты!$A:$AQ,$A51,0) -> 0.5 | Z51: =VLOOKUP(Z$4,свод_сегменты!$A:$AQ,$A51,0) -> 1 | AA51: не релевантно | AB51: =VLOOKUP(AB$4,свод_сегменты!$A:$AQ,$A51,0) -> 0 | AC51: =VLOOKUP(AC$4,свод_сегменты!$A:$AQ,$A51,0) -> 0 | AD51: =VLOOKUP(AD$4,свод_сегменты!$A:$AQ,$A51,0) -> 1 | AE51: =VLOOKUP(AE$4,свод_сегменты!$A:$AQ,$A51,0) -> 0.5 | AF51: =VLOOKUP(AF$4,свод_сегменты!$A:$AQ,$A51-3,0) -> 1 | AG51: =VLOOKUP(AG$4,свод_сегменты!$A:$AQ,$A51-3,0) -> 0 | AH51: =VLOOKUP(AH$4,свод_сегменты!$A:$AQ,$A51-3,0) -> 0 | AK51: =VLOOKUP(AK$4,свод_сегменты!$A:$AQ,$A51,0) | AS51: =VLOOKUP(AS$4,свод_сегменты!$A:$AQ,$A51,0) -> 0 | AT51: =VLOOKUP(AT$4,свод_сегменты!$A:$AQ,$A51,0) -> 1 | AU51: =VLOOKUP(AU$4,свод_сегменты!$A:$AQ,$A51,0) -> 1 | AV51: =VLOOKUP(AU$4,свод_сегменты!$A:$AQ,$A51-4,0) -> CR ЩК Uplift | AX51: не релевантно | AY51: =VLOOKUP(AY$4,свод_сегменты!$A:$AQ,$A51,0) -> 0 | AZ51: =VLOOKUP(AZ$4,свод_сегменты!$A:$AQ,$A51-3,0) -> 0 | BC51: TBD | BD51: не релевантно | BE51: не релевантно | BF51: TBD | BG51: =VLOOKUP(BG$4,свод_сегменты!$A:$AQ,$A51,0) -> 0 | BH51: не релевантно | BI51: =VLOOKUP(BI$4,свод_сегменты!$A:$AQ,$A51-4,0) -> Количества проводимых AB тестов + дополнительных ресурсов аналитики | BJ51: =VLOOKUP(BJ$4,свод_сегменты!$A:$AQ,$A51-2,0) -> #N/A | BK51: =VLOOKUP(BK$4,свод_сегменты!$A:$AQ,$A51-2,0) -> 0
A52: =свод_сегменты!W1 -> 23 | B52: СХ | C52: Рабочий возраст | D52: =свод_сегменты!W4 -> 0.62287105 | E52: Зрелые | F52: Сегмент | G52: =VLOOKUP(G$4,свод_сегменты!$A:$AQ,$A52,0) -> 1 | H52: =VLOOKUP(H$4,свод_сегменты!$A:$AQ,$A52,0) -> 0.5 | I52: =VLOOKUP(I$4,свод_сегменты!$A:$AQ,$A52,0) -> 1 | J52: =VLOOKUP(J$4,свод_сегменты!$A:$AQ,$A52,0) -> 0.5 | K52: =VLOOKUP(K$4,свод_сегменты!$A:$AQ,$A52,0) -> 0 | L52: =VLOOKUP(L$4,свод_сегменты!$A:$AQ,$A52,0) -> 1 | M52: =VLOOKUP(M$4,свод_сегменты!$A:$AQ,$A52,0) -> 0 | N52: =VLOOKUP(N$4,свод_сегменты!$A:$AQ,$A52,0) -> 0 | ... P52: =VLOOKUP(P$4,свод_сегменты!$A:$AQ,$A52,0) -> 0.5 | Q52: =IF(OR(O52=0,O52="не релевантно"),0,(VLOOKUP(Q$4,свод_сегменты!$A:$AQ,$A52-1,0))) -> 0.5 | R52: =VLOOKUP(R$4,свод_сегменты!$A:$AQ,$A52,0) -> 0.5 | S52: =VLOOKUP(S$4,свод_сегменты!$A:$AQ,$A52,0) -> 0.5 | T52: =IF(OR(R52=0,R52="не релевантно"),0,(VLOOKUP(T$4,свод_сегменты!$A:$AQ,$A52-1,0))) -> 0.5 | U52: =VLOOKUP(U$4,свод_сегменты!$A:$AQ,$A52,0) -> 0 | V52: =IF(U52>0,VLOOKUP(V$4,свод_сегменты!$A:$AQ,$A52-4,0),"") | W52: =VLOOKUP(W$4,свод_сегменты!$A:$AQ,$A52,0) -> 1 | X52: =VLOOKUP(X$4,свод_сегменты!$A:$AQ,$A52,0) -> 1 | Y52: =VLOOKUP(Y$4,свод_сегменты!$A:$AQ,$A52,0) -> 1 | Z52: =VLOOKUP(Z$4,свод_сегменты!$A:$AQ,$A52,0) -> 1 | AA52: не релевантно | AB52: =VLOOKUP(AB$4,свод_сегменты!$A:$AQ,$A52,0) -> 0 | AC52: =VLOOKUP(AC$4,свод_сегменты!$A:$AQ,$A52,0) -> 0.5 | AD52: =VLOOKUP(AD$4,свод_сегменты!$A:$AQ,$A52,0) -> 1 | AE52: =VLOOKUP(AE$4,свод_сегменты!$A:$AQ,$A52,0) -> 0.5 | AF52: =VLOOKUP(AF$4,свод_сегменты!$A:$AQ,$A52-3,0) -> 1 | AG52: =VLOOKUP(AG$4,свод_сегменты!$A:$AQ,$A52-3,0) -> 0 | AH52: =VLOOKUP(AH$4,свод_сегменты!$A:$AQ,$A52-3,0) -> 1 | AK52: =VLOOKUP(AK$4,свод_сегменты!$A:$AQ,$A52,0) | AS52: =VLOOKUP(AS$4,свод_сегменты!$A:$AQ,$A52,0) -> 0 | AT52: =VLOOKUP(AT$4,свод_сегменты!$A:$AQ,$A52,0) -> 1 | AU52: =VLOOKUP(AU$4,свод_сегменты!$A:$AQ,$A52,0) -> 1 | AV52: =VLOOKUP(AU$4,свод_сегменты!$A:$AQ,$A52-4,0) -> сравнение ЦГ и КГ по переводу ЗП | AX52: не релевантно | AY52: =VLOOKUP(AY$4,свод_сегменты!$A:$AQ,$A52,0) -> 1 | AZ52: =VLOOKUP(AZ$4,свод_сегменты!$A:$AQ,$A52-3,0) -> 0 | BC52: TBD | BD52: не релевантно | BE52: не релевантно | BF52: TBD | BG52: =VLOOKUP(BG$4,свод_сегменты!$A:$AQ,$A52,0) -> 0 | BH52: не релевантно | BI52: =VLOOKUP(BI$4,свод_сегменты!$A:$AQ,$A52-4,0) -> 1. Технического обеспечения (скорости работы ПО и БД, объемов диска, глубины данных на КЭШ ЛД) 2. Оперативности вывода в пром витрин и модели (потребовалось 2 месяца плотной работы, чтобы вывести в пром витрину, по которой собирается ФОТ 4_25) - процессы настроены неоптимально. Если бы было больше времени, расписал бы подробнее. | BJ52: =VLOOKUP(BJ$4,свод_сегменты!$A:$AQ,$A52-2,0) -> #N/A | BK52: =VLOOKUP(BK$4,свод_сегменты!$A:$AQ,$A52-2,0) -> Подтвердить механнику удержания- Бесшовный переход Изменила К по воронкам- так как нет ссылки
A53: 28 | B53: СХ | C53: Зрелость | D53: =свод_сегменты!AB4 -> 0.40203562 | E53: Развивающиеся | F53: Сегмент | G53: =VLOOKUP(G$4,свод_сегменты!$A:$AQ,$A53,0) -> 1 | H53: =VLOOKUP(H$4,свод_сегменты!$A:$AQ,$A53,0) -> 1 | I53: =VLOOKUP(I$4,свод_сегменты!$A:$AQ,$A53,0) -> 1 | J53: =VLOOKUP(J$4,свод_сегменты!$A:$AQ,$A53,0) -> 0.5 | K53: =VLOOKUP(K$4,свод_сегменты!$A:$AQ,$A53,0) -> 0.5 | L53: =VLOOKUP(L$4,свод_сегменты!$A:$AQ,$A53,0) -> 1 | M53: =VLOOKUP(M$4,свод_сегменты!$A:$AQ,$A53,0) -> 0 | N53: =VLOOKUP(N$4,свод_сегменты!$A:$AQ,$A53,0) -> 0 | ... P53: =VLOOKUP(P$4,свод_сегменты!$A:$AQ,$A53,0) -> 0 | Q53: =IF(OR(O53=0,O53="не релевантно"),0,(VLOOKUP(Q$4,свод_сегменты!$A:$AQ,$A53-1,0))) -> 0 | R53: =VLOOKUP(R$4,свод_сегменты!$A:$AQ,$A53,0) -> 0 | S53: =VLOOKUP(S$4,свод_сегменты!$A:$AQ,$A53,0) -> 0 | T53: =IF(OR(R53=0,R53="не релевантно"),0,(VLOOKUP(T$4,свод_сегменты!$A:$AQ,$A53-1,0))) -> 0 | U53: =VLOOKUP(U$4,свод_сегменты!$A:$AQ,$A53,0) -> 0 | V53: =IF(U53>0,VLOOKUP(V$4,свод_сегменты!$A:$AQ,$A53-4,0),"") | W53: =VLOOKUP(W$4,свод_сегменты!$A:$AQ,$A53,0) -> 1 | X53: =VLOOKUP(X$4,свод_сегменты!$A:$AQ,$A53,0) -> 1 | Y53: =VLOOKUP(Y$4,свод_сегменты!$A:$AQ,$A53,0) -> 0 | Z53: =VLOOKUP(Z$4,свод_сегменты!$A:$AQ,$A53,0) -> 0 | AA53: не релевантно | AB53: =VLOOKUP(AB$4,свод_сегменты!$A:$AQ,$A53,0) -> 0 | AC53: =VLOOKUP(AC$4,свод_сегменты!$A:$AQ,$A53,0) -> 0 | AD53: =VLOOKUP(AD$4,свод_сегменты!$A:$AQ,$A53,0) -> 0.25 | AE53: =VLOOKUP(AE$4,свод_сегменты!$A:$AQ,$A53,0) -> 0 | AF53: =VLOOKUP(AF$4,свод_сегменты!$A:$AQ,$A53-3,0) -> 0 | AG53: =VLOOKUP(AG$4,свод_сегменты!$A:$AQ,$A53-3,0) -> 0 | AH53: =VLOOKUP(AH$4,свод_сегменты!$A:$AQ,$A53-3,0) -> 0 | AK53: =VLOOKUP(AK$4,свод_сегменты!$A:$AQ,$A53,0) | AS53: =VLOOKUP(AS$4,свод_сегменты!$A:$AQ,$A53,0) -> 0.5 | AT53: =VLOOKUP(AT$4,свод_сегменты!$A:$AQ,$A53,0) -> 0 | AU53: =VLOOKUP(AU$4,свод_сегменты!$A:$AQ,$A53,0) -> 1 | AV53: =VLOOKUP(AU$4,свод_сегменты!$A:$AQ,$A53-4,0) -> Uplift по проданным продуктам в рамках кампейнинга. | AX53: не релевантно | AY53: =VLOOKUP(AY$4,свод_сегменты!$A:$AQ,$A53,0) -> 0.5 | AZ53: =VLOOKUP(AZ$4,свод_сегменты!$A:$AQ,$A53-3,0) -> 0 | BC53: TBD | BD53: не релевантно | BE53: не релевантно | BF53: TBD | BG53: =VLOOKUP(BG$4,свод_сегменты!$A:$AQ,$A53,0) -> 1 | BH53: не релевантно | BI53: =VLOOKUP(BI$4,свод_сегменты!$A:$AQ,$A53-4,0) -> Не хватает ресурса аналитиков. Функция распределена между сотрудниками, обладающими компетенциями. | BJ53: =VLOOKUP(BJ$4,свод_сегменты!$A:$AQ,$A53-2,0) -> #N/A | BK53: =VLOOKUP(BK$4,свод_сегменты!$A:$AQ,$A53-2,0) -> Поянить как работает механника удержания. Предложенные в опроссе варианты не релевантны для данного сегмента Зона внимания- бэклог аналитиков офф-лайн
A54: 33 | B54: СХ | C54: Top Affluent | D54: =свод_сегменты!AG4 -> 0.55494505 | E54: Развивающиеся | F54: Сегмент | G54: =VLOOKUP(G$4,свод_сегменты!$A:$AQ,$A54,0) -> 0.875 | H54: =VLOOKUP(H$4,свод_сегменты!$A:$AQ,$A54,0) -> 1 | I54: =VLOOKUP(I$4,свод_сегменты!$A:$AQ,$A54,0) -> 1 | J54: =VLOOKUP(J$4,свод_сегменты!$A:$AQ,$A54,0) -> 0.5 | K54: =VLOOKUP(K$4,свод_сегменты!$A:$AQ,$A54,0) -> 0 | L54: =VLOOKUP(L$4,свод_сегменты!$A:$AQ,$A54,0) -> 1 | M54: =VLOOKUP(M$4,свод_сегменты!$A:$AQ,$A54,0) -> 0 | N54: =VLOOKUP(N$4,свод_сегменты!$A:$AQ,$A54,0) -> 0 | ... P54: =VLOOKUP(P$4,свод_сегменты!$A:$AQ,$A54,0) -> 0.5 | Q54: =IF(OR(O54=0,O54="не релевантно"),0,(VLOOKUP(Q$4,свод_сегменты!$A:$AQ,$A54-1,0))) -> 1 | R54: =VLOOKUP(R$4,свод_сегменты!$A:$AQ,$A54,0) -> 0 | S54: =VLOOKUP(S$4,свод_сегменты!$A:$AQ,$A54,0) -> 0 | T54: =IF(OR(R54=0,R54="не релевантно"),0,(VLOOKUP(T$4,свод_сегменты!$A:$AQ,$A54-1,0))) -> 0 | U54: =VLOOKUP(U$4,свод_сегменты!$A:$AQ,$A54,0) -> 1 | V54: =IF(U54>0,VLOOKUP(V$4,свод_сегменты!$A:$AQ,$A54-4,0),"") -> Рыночные бенчмарки в конверсию с точки зрения CR + исторический % отработки аналогичных задач и конверсии в них | W54: =VLOOKUP(W$4,свод_сегменты!$A:$AQ,$A54,0) -> 0.5 | X54: =VLOOKUP(X$4,свод_сегменты!$A:$AQ,$A54,0) -> 1 | Y54: =VLOOKUP(Y$4,свод_сегменты!$A:$AQ,$A54,0) -> 0.25 | Z54: =VLOOKUP(Z$4,свод_сегменты!$A:$AQ,$A54,0) -> 0 | AA54: не релевантно | AB54: =VLOOKUP(AB$4,свод_сегменты!$A:$AQ,$A54,0) -> 1 | AC54: =свод_сегменты!AG142 -> 1 | AD54: =свод_сегменты!AG143 -> 1 | AE54: =VLOOKUP(AE$4,свод_сегменты!$A:$AQ,$A54,0) -> 0.5 | AF54: =VLOOKUP(AF$4,свод_сегменты!$A:$AQ,$A54-3,0) -> 0 | AG54: =VLOOKUP(AG$4,свод_сегменты!$A:$AQ,$A54-3,0) -> 1 | AH54: =VLOOKUP(AH$4,свод_сегменты!$A:$AQ,$A54-3,0) -> 1 | AK54: =свод_сегменты!AG144 -> 0 | AS54: =свод_сегменты!AG146 -> 0.5 | AT54: =свод_сегменты!AG141 -> 0 | AU54: =VLOOKUP(AU$4,свод_сегменты!$A:$AQ,$A54,0) -> 1 | AV54: =VLOOKUP(AU$4,свод_сегменты!$A:$AQ,$A54-4,0) -> CR | AX54: не релевантно | AY54: =VLOOKUP(AY$4,свод_сегменты!$A:$AQ,$A54,0) -> 0.5 | AZ54: =VLOOKUP(AZ$4,свод_сегменты!$A:$AQ,$A54-3,0) -> 0 | BC54: TBD | BD54: не релевантно | BE54: не релевантно | BF54: TBD | BG54: =VLOOKUP(BG$4,свод_сегменты!$A:$AQ,$A54,0) -> 0 | BH54: не релевантно | BI54: =VLOOKUP(BI$4,свод_сегменты!$A:$AQ,$A54-4,0) -> Время) остальное решаемо по мере работы | BJ54: =VLOOKUP(BJ$4,свод_сегменты!$A:$AQ,$A54-2,0) -> #N/A | BK54: =VLOOKUP(BK$4,свод_сегменты!$A:$AQ,$A54-2,0) -> Не выбрана механника Персонализации клиентского опыта- скорее всего ошибка- прошу вернуться Не выбран тип механники Миграции вверх (повышения уровня)- прошу вернуться как действует механника?
A55: 38 | B55: СХ | C55: PB | D55: =свод_сегменты!AL4 -> 0.52247191 | E55: Развивающиеся | F55: Сегмент | G55: =VLOOKUP(G$4,свод_сегменты!$A:$AQ,$A55,0) -> 0.875 | H55: =VLOOKUP(H$4,свод_сегменты!$A:$AQ,$A55,0) -> 0.5 | I55: =VLOOKUP(I$4,свод_сегменты!$A:$AQ,$A55,0) -> 1 | J55: =VLOOKUP(J$4,свод_сегменты!$A:$AQ,$A55,0) -> 0.5 | K55: =VLOOKUP(K$4,свод_сегменты!$A:$AQ,$A55,0) -> 0.5 | L55: =VLOOKUP(L$4,свод_сегменты!$A:$AQ,$A55,0) -> 1 | M55: =VLOOKUP(M$4,свод_сегменты!$A:$AQ,$A55,0) -> 0 | N55: =VLOOKUP(N$4,свод_сегменты!$A:$AQ,$A55,0) -> 0 | ... P55: =VLOOKUP(P$4,свод_сегменты!$A:$AQ,$A55,0) -> 0.5 | Q55: =IF(OR(O55=0,O55="не релевантно"),0,(VLOOKUP(Q$4,свод_сегменты!$A:$AQ,$A55-1,0))) -> 1 | R55: =VLOOKUP(R$4,свод_сегменты!$A:$AQ,$A55,0) -> 1 | S55: =VLOOKUP(S$4,свод_сегменты!$A:$AQ,$A55,0) -> 0.5 | T55: =IF(OR(R55=0,R55="не релевантно"),0,(VLOOKUP(T$4,свод_сегменты!$A:$AQ,$A55-1,0))) -> 1 | U55: =VLOOKUP(U$4,свод_сегменты!$A:$AQ,$A55,0) -> 1 | V55: =IF(U55>0,VLOOKUP(V$4,свод_сегменты!$A:$AQ,$A55-4,0),"") -> Количество целевых Клиентов | W55: =VLOOKUP(W$4,свод_сегменты!$A:$AQ,$A55,0) -> 0.25 | X55: =VLOOKUP(X$4,свод_сегменты!$A:$AQ,$A55,0) -> 0 | Y55: =VLOOKUP(Y$4,свод_сегменты!$A:$AQ,$A55,0) -> 0.25 | Z55: =VLOOKUP(Z$4,свод_сегменты!$A:$AQ,$A55,0) -> 0 | AA55: не релевантно | AB55: =VLOOKUP(AB$4,свод_сегменты!$A:$AQ,$A55,0) -> 0 | AC55: =свод_сегменты!AL142 -> 1 | AD55: =свод_сегменты!AL143 -> 1 | AE55: =VLOOKUP(AE$4,свод_сегменты!$A:$AQ,$A55,0) -> 0.5 | AF55: =VLOOKUP(AF$4,свод_сегменты!$A:$AQ,$A55-3,0) -> 0 | AG55: =VLOOKUP(AG$4,свод_сегменты!$A:$AQ,$A55-3,0) -> 0 | AH55: =VLOOKUP(AH$4,свод_сегменты!$A:$AQ,$A55-3,0) -> 1 | AK55: =свод_сегменты!AL144 -> 0 | AS55: =свод_сегменты!AL146 -> 1 | AT55: =свод_сегменты!AL141 -> 0.5 | AU55: =VLOOKUP(AU$4,свод_сегменты!$A:$AQ,$A55,0) -> 1 | AV55: =VLOOKUP(AU$4,свод_сегменты!$A:$AQ,$A55-4,0) -> автоматически загружаются событийные и поздравительные кампании | AX55: не релевантно | AY55: =VLOOKUP(AY$4,свод_сегменты!$A:$AQ,$A55,0) -> 0 | AZ55: =VLOOKUP(AZ$4,свод_сегменты!$A:$AQ,$A55-3,0) -> 1 | BC55: TBD | BD55: не релевантно | BE55: не релевантно | BF55: TBD | BG55: =VLOOKUP(BG$4,свод_сегменты!$A:$AQ,$A55,0) -> 0 | BH55: не релевантно | BI55: =VLOOKUP(BI$4,свод_сегменты!$A:$AQ,$A55-4,0) -> Бизнес аналитиков в канале | BJ55: =VLOOKUP(BJ$4,свод_сегменты!$A:$AQ,$A55-2,0) -> #N/A | BK55: =VLOOKUP(BK$4,свод_сегменты!$A:$AQ,$A55-2,0) -> Нет аналитиков? Проводился полный анализ воронки привлечения/оттока,но нет сформированных мероприятий- как это может быть?
A56: 43 | B56: СХ | C56: МВС | D56: =свод_сегменты!AQ4 -> 0.41011236 | E56: Развивающиеся | F56: Сегмент | G56: =VLOOKUP(G$4,свод_сегменты!$A:$AQ,$A56,0) -> 0.875 | H56: =VLOOKUP(H$4,свод_сегменты!$A:$AQ,$A56,0) -> 1 | I56: =VLOOKUP(I$4,свод_сегменты!$A:$AQ,$A56,0) -> 1 | J56: =VLOOKUP(J$4,свод_сегменты!$A:$AQ,$A56,0) -> 0.5 | K56: =VLOOKUP(K$4,свод_сегменты!$A:$AQ,$A56,0) -> 0 | L56: =VLOOKUP(L$4,свод_сегменты!$A:$AQ,$A56,0) -> 1 | M56: =VLOOKUP(M$4,свод_сегменты!$A:$AQ,$A56,0) -> 0 | N56: =VLOOKUP(N$4,свод_сегменты!$A:$AQ,$A56,0) -> 0 | ... P56: =VLOOKUP(P$4,свод_сегменты!$A:$AQ,$A56,0) -> 0.5 | Q56: =IF(OR(O56=0,O56="не релевантно"),0,(VLOOKUP(Q$4,свод_сегменты!$A:$AQ,$A56-1,0))) -> 0.5 | R56: =VLOOKUP(R$4,свод_сегменты!$A:$AQ,$A56,0) -> 0 | S56: =VLOOKUP(S$4,свод_сегменты!$A:$AQ,$A56,0) -> 0 | T56: =IF(OR(R56=0,R56="не релевантно"),0,(VLOOKUP(T$4,свод_сегменты!$A:$AQ,$A56-1,0))) -> 0 | U56: =VLOOKUP(U$4,свод_сегменты!$A:$AQ,$A56,0) -> 0 | V56: =IF(U56>0,VLOOKUP(V$4,свод_сегменты!$A:$AQ,$A56-4,0),"") | W56: =VLOOKUP(W$4,свод_сегменты!$A:$AQ,$A56,0) -> 0.5 | X56: =VLOOKUP(X$4,свод_сегменты!$A:$AQ,$A56,0) -> 1 | Y56: =VLOOKUP(Y$4,свод_сегменты!$A:$AQ,$A56,0) -> 0.25 | Z56: =VLOOKUP(Z$4,свод_сегменты!$A:$AQ,$A56,0) -> 0 | AA56: не релевантно | AB56: =VLOOKUP(AB$4,свод_сегменты!$A:$AQ,$A56,0) -> 0 | AC56: =свод_сегменты!AQ142 -> 1 | AD56: =свод_сегменты!AQ143 -> 1 | AE56: =VLOOKUP(AE$4,свод_сегменты!$A:$AQ,$A56,0) -> 0.5 | AF56: =VLOOKUP(AF$4,свод_сегменты!$A:$AQ,$A56-3,0) -> 0 | AG56: =VLOOKUP(AG$4,свод_сегменты!$A:$AQ,$A56-3,0) -> 0 | AH56: =VLOOKUP(AH$4,свод_сегменты!$A:$AQ,$A56-3,0) -> 1 | AK56: =свод_сегменты!AQ144 -> 0 | AS56: =свод_сегменты!AQ146 -> 0.25 | AT56: =свод_сегменты!AQ141 -> 0 | AU56: =VLOOKUP(AU$4,свод_сегменты!$A:$AQ,$A56,0) -> 1 | AV56: =VLOOKUP(AU$4,свод_сегменты!$A:$AQ,$A56-4,0) -> например: мы смотрим сколько людей выбрали предложенные категории привилегий в ПУ (отличные от стандартных бизнес-залов) | AX56: не релевантно | AY56: =VLOOKUP(AY$4,свод_сегменты!$A:$AQ,$A56,0) -> 0 | AZ56: =VLOOKUP(AZ$4,свод_сегменты!$A:$AQ,$A56-3,0) -> 0 | BC56: TBD | BD56: не релевантно | BE56: не релевантно | BF56: TBD | BG56: =VLOOKUP(BG$4,свод_сегменты!$A:$AQ,$A56,0) -> 0 | BH56: не релевантно | BI56: =VLOOKUP(BI$4,свод_сегменты!$A:$AQ,$A56-4,0) -> Затрудняюсь ответить | BJ56: =VLOOKUP(BJ$4,свод_сегменты!$A:$AQ,$A56-2,0) -> #N/A | BK56: =VLOOKUP(BK$4,свод_сегменты!$A:$AQ,$A56-2,0) -> Не совсем понятно как трактовать ответ на вопрос Как работает механика реагирования на жизненные события? Стоит коммент-"владельцам ПУ или потенциальным предлагают выбрать привилегии исходя из их трат" Значит ли это отсутвие "Настроены релевантные предложения продуктов банка/спец.предложения/промо"? Нет аналитиков???
B57: DP | C57: СберKids | F57: Канал
A58: 245 | B58: DB | C58: Госуслуги | D58: 0.37313433 | E58: Требуют внимания | F58: Исключить | G58: 1 | H58: 0.5 | I58: 0 | J58: 0 | K58: 0.5 | L58: 0 | M58: 0 | N58: 0 | O58: 0.5 | P58: 0 | Q58: 0.5 | R58: не релевантно | S58: не релевантно | T58: 0 | U58: 1 | V58: Еженедельный отчет ЦБ о количестве согласий | W58: 0.5 | X58: 1 | Y58: не релевантно | Z58: не релевантно | AA58: 0.5 | AB58: 1 | AC58: для продукта не включается в расчет | AD58: =IF(AI58="не релевантно","не релевантн",(AI58+AJ58)/2) -> 0 | AI58: 0 | AJ58: 0 | AK58: =IF(AL58="не релевантно","не релевантн",(AL58+AM58)/2) -> 0 | AL58: 0 | AM58: 0 | AN58: 0 | AO58: не релевантно | AP58: 0 | AQ58: 0 | AR58: не релевантно | AS58: для продукта не включается в расчет | AT58: для продукта не включается в расчет | AU58: 1 | AV58: CR, количество собранных согласий | AW58: 0 | AX58: не релевантно | AY58: 0 | AZ58: 1 | BA58: не релевантно | BB58: не релевантно | BC58: не релевантно | BD58: не релевантно | BF58: TBD | BG58: 0 | BH58: 0 | BI58: Простоты реализации витрин в КАП. Большинство отчетов строится по ручным выгрузкам из прома, так как построение витрин и потока данных в КАП трудозатратный процесс не имеющий прямого финансового эффекта, поэтому данные задачи не проходят балансировку | BJ58: Усышкин Станислав Владимирович | BK58: Требуется проверить метрики в блоке-метрики продукта- продукт не выделен в ЕКМ. Посмотреть релевантность механник
A59: =A58+5 -> 250 | B59: DB | C59: Наследство | D59: 0.390681 | E59: Требуют внимания | F59: Исключить | G59: 1 | H59: 1 | I59: 0 | J59: 0 | K59: 0.5 | L59: 0 | M59: 0 | N59: 0 | O59: не релевантно | P59: не релевантно | Q59: 0 | R59: не релевантно | S59: не релевантно | T59: 0 | V59: 0 | W59: 0.5 | X59: 1 | Y59: 0.5 | Z59: 1 | AA59: 1 | AB59: 0 | AC59: для продукта не включается в расчет | AD59: =IF(AI59="не релевантно","не релевантн",(AI59+AJ59)/2) -> 0 | AI59: 0 | AJ59: 0 | AK59: =IF(AL59="не релевантно","не релевантн",(AL59+AM59)/2) -> 0 | AL59: 0 | AM59: 0 | AO59: не релевантно | AP59: 0 | AQ59: 0 | AS59: для продукта не включается в расчет | AT59: для продукта не включается в расчет | AU59: 1 | AV59: нет ответа | AW59: 1 | AX59: 0 | AY59: 0 | AZ59: 1 | BA59: не релевантно | BB59: не релевантно | BC59: не релевантно | BD59: не релевантно | BF59: TBD | BG59: 0 | BH59: 0 | BI59: вего хватает, нужно перестроить mindset | BJ59: Невмержицкая Е.А. | BK59: Требуется проверить метрики в блоке-метрики продукта- продукт не выделен в ЕКМ. Прошу указать какие механики релевантны для данного продукта (специфичный). Что такое воронка отттока для продукта Наследство? Какой анализ делает продукт?
A60: =A59+5 -> 255 | B60: DB | C60: Карта Жителя | D60: 0.22988506 | E60: Требуют внимания | F60: ДЗО | G60: 1 | H60: 1 | I60: 0 | J60: 0 | K60: 0.5 | L60: 0 | M60: 0 | N60: 0 | O60: 0 | P60: 0 | Q60: 0 | R60: 0 | S60: 0 | T60: 0 | U60: 0 | W60: 0 | X60: 0 | Y60: 0 | Z60: 0 | AA60: 1 | AB60: 0 | AC60: для продукта не включается в расчет | AD60: =IF(AI60="не релевантно","не релевантн",(AI60+AJ60)/2) -> 0.5 | AI60: 1 | AJ60: 0 | AK60: =IF(AL60="не релевантно","не релевантн",(AL60+AM60)/2) -> 0 | AL60: 0 | AM60: 0 | AN60: 0.5 | AO60: 0 | AP60: 1 | AQ60: 0 | AR60: 1 | AS60: для продукта не включается в расчет | AT60: для продукта не включается в расчет | AU60: 0 | AV60: мау | AW60: 0 | AX60: 0 | AY60: 0 | AZ60: 1 | BD60: нерелевантно | BF60: TBD | BG60: 0 | BH60: 0 | BI60: аналитика | BJ60: Комароми Мария Андреевна | BK60: Требуется проверить метрики в блоке-метрики продукта- продукт не выделен в ЕКМ.
A61: =A60+5 -> 260 | B61: DB | C61: Трансграничный эквайринг | D61: 0.34457831 | E61: Требуют внимания | F61: продукт | G61: 0.9 | H61: 1 | I61: 0 | J61: 0 | K61: 0 | L61: 0 | M61: 0 | N61: 0 | O61: 0 | P61: 0 | Q61: 0 | R61: не релевантно | S61: не релевантно | T61: 0 | U61: 0 | W61: 1 | X61: 1 | Y61: 1 | Z61: 1 | AA61: 1 | AB61: 0 | AC61: для продукта не включается в расчет | AD61: =IF(AI61="не релевантно","не релевантн",(AI61+AJ61)/2) -> 0 | AI61: 0 | AJ61: 0 | AK61: =IF(AL61="не релевантно","не релевантн",(AL61+AM61)/2) -> 0 | AL61: 0 | AM61: 0 | AN61: 0 | AO61: не релевантно | AP61: 0 | AQ61: 0 | AR61: 0 | AS61: для продукта не включается в расчет | AT61: для продукта не включается в расчет | AU61: 1 | AV61: Оборот, кол-во оплат, ЧКД, конверсия, MAU | AW61: 0 | AX61: 0.5 | AY61: 0 | AZ61: 1 | BA61: нерелевантно | BB61: нерелевантно | BC61: нерелевантно | BD61: нерелевантно | BF61: TBD | BG61: 0 | BH61: 0 | BI61: ежедневной отчетности в навигаторе, нет ресурсов аналитиков на исследование, нет ресурсов Бизнес и ИТ. на развитие продукта, нет РО по продукту. ЛК является РО. | BJ61: Забегаев Михаил Евгеньевич | BK61: Требуется проверить метрики в блоке-метрики продукта- продукт не выделен в ЕКМ. Посмотреть релевантность механник. Почему не реевантны воронки привлечения и оттока?
A62: =A61+5 -> 265 | B62: DB | C62: Персонализированный офлайн | D62: 0.098850575 | E62: Требуют внимания | F62: Исключить | G62: 0.9 | H62: 1 | I62: 0.5 | J62: 0 | K62: 0 | L62: 0 | M62: 0 | N62: 0 | O62: 0 | P62: 0 | Q62: 0 | R62: 0 | S62: 0 | T62: 0 | U62: 0 | W62: 0 | X62: 0 | Y62: 0 | Z62: 0 | AA62: 0 | AB62: 0 | AC62: для продукта не включается в расчет | AD62: =IF(AI62="не релевантно","не релевантн",(AI62+AJ62)/2) -> 0 | AI62: 0 | AJ62: 0 | AK62: =IF(AL62="не релевантно","не релевантн",(AL62+AM62)/2) -> 0 | AL62: 0 | AM62: 0 | AN62: 0 | AO62: не релевантно | AP62: 0 | AQ62: 0 | AR62: 0 | AS62: для продукта не включается в расчет | AT62: для продукта не включается в расчет | AU62: 1 | AV62: Будем следить за удержанием привлеченных клиентов | AW62: 1 | AX62: 0 | AY62: 0 | AZ62: 0 | BF62: TBD | BG62: 0 | BH62: 0 | BI62: Инструментов хватает | BJ62: Колаев Виталий Александрович | BK62: Требуется проверить метрики в блоке-метрики продукта- продукт не выделен в ЕКМ.
A63: =A62+5 -> 270 | B63: DB | C63: Демаркирование карт от зарплатного продукта | D63: 0.18491484 | E63: Требуют внимания | F63: Исключить | G63: 1 | H63: 0.5 | I63: 0 | J63: 0 | K63: 0 | L63: 0 | M63: 0 | N63: 0 | O63: 0 | P63: 0 | Q63: 0 | R63: не релевантно | S63: не релевантно | T63: 0 | U63: 0 | W63: 0.5 | X63: 1 | Y63: 0 | Z63: 0 | AA63: 0 | AB63: 0 | AC63: для продукта не включается в расчет | AD63: =IF(AI63="не релевантно","не релевантн",(AI63+AJ63)/2) -> 0.5 | AI63: 1 | AJ63: 0 | AK63: =IF(AL63="не релевантно","не релевантн",(AL63+AM63)/2) -> 0.5 | AL63: 1 | AM63: 0 | AN63: 0 | AO63: не релевантно | AP63: 0 | AQ63: 0 | AR63: 0 | AS63: для продукта не включается в расчет | AT63: для продукта не включается в расчет | AU63: 1 | AV63: Факт получение зарплатного зачисления | AW63: 0 | AX63: 0 | AY63: 0 | AZ63: 1 | BF63: TBD | BG63: 0 | BH63: 0 | BI63: Ограниченный ресурс data аналитиков, отсутствие информации/инструкций по возможным инструментам внутри банка | BJ63: Пятков Сергей Валерьевич | BK63: 0
A64: =A63+5 -> 275 | B64: DB | C64: Онбординг и сопровождение ЮЛ в зарплатном проекте канала СберБизнес | D64: 0.34939759 | E64: Требуют внимания | F64: Исключить | G64: 1 | H64: 1 | I64: 0.5 | J64: 0.5 | K64: 0.5 | L64: 0 | M64: 0 | N64: 0 | O64: 1 | P64: 0 | Q64: 1 | R64: не релевантно | S64: не релевантно | T64: 0 | U64: 0 | W64: 0.5 | X64: 1 | Y64: 0 | Z64: 0 | AA64: 1 | AB64: 0 | AC64: для продукта не включается в расчет | AD64: =IF(AI64="не релевантно","не релевантн",(AI64+AJ64)/2) -> 0 | AI64: 0 | AJ64: 0 | AK64: =IF(AL64="не релевантно","не релевантн",(AL64+AM64)/2) -> 0 | AL64: 0 | AM64: 0 | AN64: 1 | AO64: 1 | AP64: 0 | AQ64: 0 | AR64: 0 | AS64: для продукта не включается в расчет | AT64: для продукта не включается в расчет | AU64: 1 | AV64: подключление ЗД при подключении расчетного счета | AW64: 0 | AX64: 0 | AY64: 0 | AZ64: 1 | BF64: TBD | BG64: 0 | BH64: 0 | BI64: А\В тестирования в СберБизнес Реализация сформулированного дерева метрик в виде дашбордов | BJ64: Погода Вадим Александрович | BK64: Требуется проверить метрики в блоке-метрики продукта- продукт не выделен в ЕКМ. К какому разделу с целями в Навигаторе относится продукт?
A65: =A64+5 -> 280 | B65: DB | C65: Военная пенсия | D65: 0.27586207 | E65: Требуют внимания | F65: продукт | G65: 1 | H65: 0.5 | I65: 0 | J65: 0 | K65: 0 | L65: 0 | M65: 0 | N65: 0 | O65: 1 | P65: 0.5 | Q65: 1 | R65: 0.5 | S65: 0 | T65: 0.5 | U65: 1 | V65: Медиана по историческим данным за прошлые года | W65: 0.5 | X65: 0 | Y65: 0.5 | Z65: 1 | AA65: 0.5 | AB65: 0 | AC65: для продукта не включается в расчет | AD65: =IF(AI65="не релевантно","не релевантн",(AI65+AJ65)/2) -> 0 | AI65: 0 | AJ65: 0 | AK65: =IF(AL65="не релевантно","не релевантн",(AL65+AM65)/2) -> 0 | AL65: 0 | AM65: 0 | AN65: 0 | AO65: не релевантно | AP65: 0 | AQ65: 0 | AR65: 0 | AS65: для продукта не включается в расчет | AT65: для продукта не включается в расчет | AU65: 1 | AV65: Не используем механики | AW65: 0 | AX65: 0 | AY65: 0 | AZ65: 1 | BF65: TBD | BG65: 0 | BH65: 0 | BI65: 1. Реализовать репликацию данных продукта в КАП. 2. Упростить процесс получения данных по зачислениям из 4.25, сейчас это задача на штаб, а хотелось бы закинуть промпт: собери данные по зачислениям военной пенсии (код зачисления 9) за 2026 год, помесячно, с указанием источника зачисления (ВТБ или СБЕР), перечень полей в выгрузке: месяц, ТБ, ГОСБ, источник зачисления, уникальное кол-во ФЛ, сумма. Результат пришли в виде таблицы на почту. Было бы классно так сделать) | BJ65: Мерзликин Иван Сергеевич | BK65: Требуется проверить метрики в блоке-метрики продукта- продукт не выделен в ЕКМ. Посмотреть релевантность механник (специфичный продукт). Почему не реевантна воронки привлечения?
A66: =A65+5 -> 285 | B66: DB | C66: Транспортный эквайринг | D66: 0.24050633 | E66: Требуют внимания | F66: продукт | G66: 1 | H66: 0.5 | I66: 0 | J66: 0.5 | K66: 0.5 | L66: 0 | M66: 0 | N66: 0 | O66: не релевантно | P66: не релевантно | Q66: 0 | R66: 0.5 | S66: 0 | T66: 0.5 | V66: 0 | W66: 0 | X66: 0 | Y66: 0 | Z66: 0 | AA66: 1 | AB66: 0 | AC66: для продукта не включается в расчет | AD66: =IF(AI66="не релевантно","не релевантн",(AI66+AJ66)/2) -> 0.5 | AI66: 1 | AJ66: 0 | AK66: =IF(AL66="не релевантно","не релевантн",(AL66+AM66)/2) -> 0.5 | AL66: 1 | AM66: 0 | AN66: 0 | AO66: не релевантно | AP66: 0 | AQ66: 0 | AR66: 0 | AS66: для продукта не включается в расчет | AT66: для продукта не включается в расчет | AU66: 1 | AV66: Возврат\удержание партнера | AW66: 0 | AX66: 0 | AY66: 0 | AZ66: 1 | BA66: нерелевантно | BB66: нерелевантно | BC66: нерелевантно | BD66: нерелевантно | BF66: TBD | BG66: 0 | BH66: 0 | BI66: Автоматический мониторинг, регулярные исследования (нет собственных аналитиков) | BJ66: Паренков Алексей Анатольевич | BK66: Требуется проверить метрики в блоке-метрики продукта- продукт не выделен в ЕКМ. Почему не реевантна воронка привлечения?
A67: =A66+5 -> 290 | B67: DB | C67: Школьные сервисы | D67: 0.36781609 | E67: Требуют внимания | F67: продукт | G67: 1 | H67: 0.5 | I67: 0 | J67: 0 | K67: 0 | L67: 0 | M67: 0 | N67: 0 | O67: 0.5 | P67: 0.5 | Q67: 0.5 | R67: 0 | S67: 0 | T67: 0 | U67: 1 | V67: Доля рынка конкурентов по питанию, СКУД и дневникам | W67: 0.5 | X67: 1 | Y67: 0.5 | Z67: 1 | AA67: 0.5 | AB67: 0 | AC67: для продукта не включается в расчет | AD67: =IF(AI67="не релевантно","не релевантн",(AI67+AJ67)/2) -> 0 | AI67: 0 | AJ67: 0 | AK67: =IF(AL67="не релевантно","не релевантн",(AL67+AM67)/2) -> 1 | AL67: 1 | AM67: 1 | AN67: 0.5 | AO67: 0 | AP67: 1 | AQ67: 0 | AR67: 0 | AS67: для продукта не включается в расчет | AT67: для продукта не включается в расчет | AU67: 1 | AV67: количество возврата клиентов для оттока, количество новых клиентов с учетом доп.продаж | AW67: 0 | AX67: 0 | AY67: 0 | AZ67: 1 | BF67: TBD | BG67: 0 | BH67: 0 | BI67: Не хватает ресурсов дата-аналитиков для создания отчетности в Навигаторе, для проведения аналитических исследований на основании ретро данных. | BJ67: Торукало Анна Юрьевна | BK67: Требуется проверить метрики в блоке-метрики продукта- продукт не выделен в ЕКМ. Посмотреть релевантность механник Почему не релевантна механника удержания? Почему не релевантна воронка оттока? Кампейн есть или нет?
A68: =A67+5 -> 295 | B68: DB | C68: Телеком (Оплата сотовой связи) и сканер QR | D68: 0.5049505 | E68: Развивающиеся | F68: ДЗО | G68: 1 | H68: 1 | I68: 0 | J68: 0 | K68: 0.5 | L68: 0 | M68: 0 | N68: 0 | O68: 0.5 | P68: 0.5 | Q68: 0.5 | R68: 0.5 | S68: 0.5 | T68: 0.5 | U68: 1 | V68: Динамика к АППГ | W68: 0.5 | X68: 1 | Y68: 0.5 | Z68: 1 | AA68: 0.5 | AB68: 0 | AC68: для продукта не включается в расчет | AD68: =IF(AI68="не релевантно","не релевантн",(AI68+AJ68)/2) -> 1 | AI68: 1 | AJ68: 1 | AK68: =IF(AL68="не релевантно","не релевантн",(AL68+AM68)/2) -> 1 | AL68: 1 | AM68: 1 | AN68: 0 | AO68: не релевантно | AP68: 0 | AQ68: 0 | AR68: 1 | AS68: для продукта не включается в расчет | AT68: для продукта не включается в расчет | AU68: 1 | AV68: Roling Retention | AW68: 0 | AX68: 0 | AY68: 0 | AZ68: 1 | BA68: 1 | BB68: 0 | BC68: 1 | BD68: 0 | BE68: 1 | BF68: TBD | BG68: 0 | BH68: 0 | BI68: Старый куб по платежам в MIS. С новым инструментом очень сложно работать, пока нет доверия. Добавить МАУ в куб по платежам, дорабатывать кликстрим, чтобы он был не хожу яндекс. Метрики | BJ68: Лысова Дарья Дмитриевна | BK68: Требуется проверить метрики в блоке-метрики продукта- продукт не выделен в ЕКМ. Данные по кампейну и SS в целом по платежам- требуется разделить по субпродуктам
A69: =A68+5 -> 300 | B69: DB | C69: Кредитные карты | D69: 0.57623762 | E69: Развивающиеся | F69: продукт | G69: 0.3 | H69: 0.5 | I69: 0.5 | J69: 0 | K69: 0.5 | L69: 0 | M69: 0 | N69: 0 | O69: 1 | P69: 1 | Q69: 1 | R69: 1 | S69: 0.5 | T69: 1 | U69: 0 | W69: 1 | X69: 1 | Y69: 1 | Z69: 1 | AA69: 1 | AB69: 1 | AC69: для продукта не включается в расчет | AD69: =IF(AI69="не релевантно","не релевантн",(AI69+AJ69)/2) -> 0.5 | AI69: 1 | AJ69: 0 | AK69: =IF(AL69="не релевантно","не релевантн",(AL69+AM69)/2) -> 0.5 | AL69: 1 | AM69: 0 | AN69: 0.5 | AO69: 0 | AP69: 1 | AQ69: 0 | AR69: 1 | AS69: для продукта не включается в расчет | AT69: для продукта не включается в расчет | AU69: 1 | AV69: Конверсионная воронка (CTR, СR) | AW69: 0 | AX69: 0 | AY69: 0 | AZ69: 0 | BA69: 1 | BB69: 0 | BC69: 1 | BD69: 0 | BE69: 0.5 | BF69: TBD | BG69: 0 | BH69: 1 | BI69: есть стандартный инструмент проведения АБ тестов в СБОЛ, который на текущий момент содержит только базовый набор механик (рандомное распределение базы данных, CTR, CR и т.д.), при этом нет возможности учитывать продуктовые особенности и метрические показатели (например, доля грейсовиков, ЧКД, ЧПД, выход клиента на просрочку и т.д.) | BJ69: Кононов Иван Сергеевич | BK69: 0
A70: =A69+5 -> 305 | B70: DB | C70: Исполнительное производство (ГПС) | D70: 0.24574209 | E70: Требуют внимания | F70: Исключить | G70: 1 | H70: 0 | I70: 0 | J70: 0 | K70: 0.5 | L70: 0 | M70: 0 | N70: 0 | O70: не релевантно | P70: не релевантно | Q70: 0 | R70: 0 | S70: 0 | T70: 0 | U70: 0 | W70: 0.5 | X70: 1 | Y70: 0 | Z70: 0 | AA70: 1 | AB70: 0.5 | AC70: для продукта не включается в расчет | AD70: =IF(AI70="не релевантно","не релевантн",(AI70+AJ70)/2) -> 0 | AI70: 0 | AJ70: 0 | AK70: =IF(AL70="не релевантно","не релевантн",(AL70+AM70)/2) -> 0 | AL70: 0 | AM70: 0 | AN70: 0 | AO70: не релевантно | AP70: 0 | AQ70: 0 | AR70: 0 | AS70: для продукта не включается в расчет | AT70: для продукта не включается в расчет | AU70: 1 | AV70: Не релевантно для продукта | AW70: 1 | AX70: 0 | AY70: 0.5 | AZ70: 0 | BF70: TBD | BG70: 0 | BH70: 0 | BI70: Всего хватает, но необходимо первостепенно решить задачи в рамках регуляторной повестке | BJ70: Тутунов Билал Мирзаевич | BK70: Требуется проверить метрики в блоке-метрики продукта- продукт не выделен в ЕКМ.
A71: =A70+5 -> 310 | B71: DB | C71: Интегратор | D71: 0.11764706 | E71: Требуют внимания | F71: Исключить | G71: 1 | H71: 0.5 | I71: 0 | J71: 0 | K71: 0 | L71: 0 | M71: 0 | N71: 0 | O71: не релевантно | P71: не релевантно | Q71: 0 | R71: не релевантно | S71: не релевантно | T71: 0 | U71: 0 | W71: 0 | X71: 0 | Y71: 0 | Z71: 0 | AA71: 1 | AB71: 0 | AC71: для продукта не включается в расчет | AD71: =IF(AI71="не релевантно","не релевантн",(AI71+AJ71)/2) -> 0 | AI71: 0 | AJ71: 0 | AK71: =IF(AL71="не релевантно","не релевантн",(AL71+AM71)/2) -> 0 | AL71: 0 | AM71: 0 | AN71: 0 | AO71: не релевантно | AP71: 0 | AQ71: 0 | AR71: 0 | AS71: для продукта не включается в расчет | AT71: для продукта не включается в расчет | AU71: 1 | AV71: Основной метрикой продукта явлдяется объем запросов между банком и госорганом, время исполнения запросов, количество ошибок | AW71: 1 | AX71: 0 | AY71: 0 | AZ71: 0 | BF71: TBD | BG71: 0 | BH71: 0 | BI71: нет ответа | BJ71: Гаевский Иван Владимирович | BK71: Требуется проверить метрики в блоке-метрики продукта- продукт не выделен в ЕКМ. Какие механники релевантны?
A72: =A71+5 -> 315 | B72: DB | C72: Трансграничные переводы | D72: 0.38202247 | E72: Требуют внимания | F72: продукт | G72: 1 | H72: 1 | I72: 0 | J72: 0 | K72: 0.5 | L72: 0 | M72: 0 | N72: 0 | O72: не релевантно | P72: не релевантно | Q72: 0 | R72: 0.5 | S72: 0 | T72: 0.5 | U72: 0 | W72: 0.5 | X72: 1 | Y72: 0 | Z72: 0 | AA72: 1 | AB72: 0 | AC72: для продукта не включается в расчет | AD72: =IF(AI72="не релевантно","не релевантн",(AI72+AJ72)/2) -> 0 | AI72: 0 | AJ72: 0 | AK72: =IF(AL72="не релевантно","не релевантн",(AL72+AM72)/2) -> 1 | AL72: 1 | AM72: 1 | AN72: 0 | AO72: не релевантно | AP72: 0 | AQ72: 0 | AR72: 0 | AS72: для продукта не включается в расчет | AT72: для продукта не включается в расчет | AU72: 1 | AV72: мау, кд, когортный ретеншн, конверсия | AW72: 0 | AX72: 0 | AY72: 0 | AZ72: 1 | BA72: 0 | BD72: 1 | BE72: 1 | BF72: TBD | BG72: 0 | BH72: 1 | BI72: все хватает | BJ72: Сидорова Ксения Евгеньевна | BK72: Требуется проверить метрики в блоке-метрики продукта- продукт не выделен в ЕКМ. Посмотреть релевантность механник Почему не релевантны остальные механики, по аналогии с Переводами по РФ? Почему не релевантна воронка привлечения? СХ Score в целом по переводам!
A73: =A72+5 -> 320 | B73: DB | C73: Платежи | D73: 0.36831683 | E73: Требуют внимания | F73: продукт | G73: 0.8 | H73: 0.5 | I73: 0 | J73: 0 | K73: 0 | L73: 0 | M73: 0 | N73: 0 | O73: 0 | P73: 0 | Q73: 0 | R73: 0 | S73: 0 | T73: 0 | U73: 1 | V73: Аналитика рынка Телеком в части приложений операторов Банка и инсайты проникновения оплаты связи в других Банках, Аналитика СБП | W73: 0.5 | X73: 1 | Y73: 0 | Z73: 0 | AA73: 1 | AB73: 0 | AC73: для продукта не включается в расчет | AD73: =IF(AI73="не релевантно","не релевантн",(AI73+AJ73)/2) -> 1 | AI73: 1 | AJ73: 1 | AK73: =IF(AL73="не релевантно","не релевантн",(AL73+AM73)/2) -> 0 | AL73: 0 | AM73: 0 | AN73: 1 | AO73: 1 | AP73: 0 | AQ73: 0 | AR73: 0 | AS73: для продукта не включается в расчет | AT73: для продукта не включается в расчет | AU73: 1 | AV73: CtR, CR, дельта RR между ЦГ и КГ | AW73: 0 | AX73: 0.5 | AY73: 0 | AZ73: 1 | BA73: 1 | BB73: 0 | BC73: 1 | BD73: 0 | BE73: 1 | BF73: TBD | BG73: 0 | BH73: 0 | BI73: "Старого" mis куба, BI инструмента с возможностью быстрого вывода дэшбордов для каждого участника команды с T2M в 1 день (no code решение, поддержка всех источников данных), ежедневного автоматического расчета регулярных метрки подпродуктов (сейчас ручной расчета data-аналитиками со средней частотой 1 раз в месяц) | BJ73: Балцану Михаил Васильевич | BK73: Требуется проверить метрики в блоке-метрики продукта- продукт не выделен в ЕКМ.
A74: =A73+5 -> 325 | B74: DB | C74: Переводы по РФ | D74: 0.70309278 | E74: Зрелые | F74: продукт | G74: 0.8 | H74: 1 | I74: 1 | J74: 0 | K74: 0.5 | L74: 1 | M74: 0 | N74: 0 | O74: 0 | P74: 0 | Q74: 0 | R74: 1 | S74: 0 | T74: 1 | U74: 0 | W74: 1 | X74: 1 | Y74: 0.5 | Z74: 1 | AA74: 1 | AB74: 0 | AC74: для продукта не включается в расчет | AD74: =IF(AI74="не релевантно","не релевантн",(AI74+AJ74)/2) -> 1 | AI74: 1 | AJ74: 1 | AK74: =IF(AL74="не релевантно","не релевантн",(AL74+AM74)/2) -> 0.5 | AL74: 0 | AM74: 1 | AN74: 0.5 | AO74: 0 | AP74: 0 | AQ74: 1 | AR74: 1 | AS74: для продукта не включается в расчет | AT74: для продукта не включается в расчет | AU74: 1 | AV74: СR/ср время операции | AW74: 0 | AX74: 1 | AY74: 1 | AZ74: 0 | BA74: 1 | BB74: 0 | BC74: 1 | BD74: нерелевантно | BE74: 1 | BF74: TBD | BG74: 1 | BH74: 1 | BI74: Перестаньте урезать расходы на мощности для кластеров для DA. Увеличьте размер команд, которые могут выводить аналитику в дашборды. Сделайте функцию уведомлений в навигаторе, приведите в человеческий вид навигатор для мобильного телефона (без слез не взглянешь). | BJ74: Невелич Дмитрий Игоревич | BK74: Почему не релевантна воронка привлечения?
A75: =A74+5 -> 330 | B75: DB | C75: Переводы подарков | D75: 0.38515081 | E75: Требуют внимания | F75: продукт | G75: 1 | H75: 0.5 | I75: 0.5 | J75: 0 | K75: 0.5 | L75: 1 | M75: 0 | N75: 0 | O75: 0.5 | P75: 1 | Q75: 0.5 | R75: 0 | S75: 0 | T75: 0 | U75: 0 | W75: 1 | X75: 1 | Y75: 1 | Z75: 1 | AA75: 0 | AB75: 0 | AC75: для продукта не включается в расчет | AD75: =IF(AI75="не релевантно","не релевантн",(AI75+AJ75)/2) -> 0 | AI75: 0 | AJ75: 0 | AK75: =IF(AL75="не релевантно","не релевантн",(AL75+AM75)/2) -> 0 | AL75: 0 | AM75: 0 | AN75: 0 | AO75: не релевантно | AP75: 0 | AQ75: 0 | AR75: 0 | AS75: для продукта не включается в расчет | AT75: для продукта не включается в расчет | AU75: 0 | AV75: N/A | AW75: 0 | AX75: 0.5 | AY75: 1 | AZ75: 0 | BF75: TBD | BG75: 0 | BH75: 0 | BI75: Ответи аналогичен по продукту "Переводы РФ" | BJ75: Невелич Дмитрий Игоревич | BK75: Требуется проверить метрики в блоке-метрики продукта- продукт не выделен в ЕКМ. Посмотреть релевантность механник Что это за трайб? Есть ли метрики в Навигаторе?
A76: =A75+5 -> 335 | B76: DB | C76: Оплата улыбкой | D76: 0.65822785 | E76: Зрелые | F76: продукт | G76: 0.5 | H76: 1 | I76: 0.5 | J76: 0.5 | K76: 0.5 | L76: 1 | M76: 0 | N76: 0 | O76: 0.5 | P76: 1 | Q76: 0.5 | R76: 0.5 | S76: 0.5 | T76: 0.5 | U76: 1 | V76: На ежемесячной основе анализируем причины оттока клиентов (ошибки из-за которых они ушли, работа/ встречаемость терминалов), влияние новых фич и коммуникаций на отток | W76: 0.5 | X76: 1 | Y76: 0.5 | Z76: 1 | AA76: 1 | AB76: 0.5 | AC76: для продукта не включается в расчет | AD76: =IF(AI76="не релевантно","не релевантн",(AI76+AJ76)/2) -> 1 | AI76: 1 | AJ76: 1 | AK76: =IF(AL76="не релевантно","не релевантн",(AL76+AM76)/2) -> 1 | AL76: 1 | AM76: 1 | AN76: не релевантно | AO76: не релевантно | AP76: 0 | AQ76: 0 | AR76: не релевантно | AS76: для продукта не включается в расчет | AT76: для продукта не включается в расчет | AU76: 1 | AV76: По итогам запущенной коммуникации анализируем, сколько клиентов сделали целевое действие (оплатили по био) -в %, так же смотрим на MAU, DAU, отток и RR после запуска коммуникации | AW76: 0 | AX76: 0 | AY76: 0.5 | AZ76: 0 | BF76: TBD | BG76: 1 | BH76: 0 | BI76: Все есть, "наращиваем силу" на текущие инструменты | BJ76: Терсков Павел Алексеевич | BK76: Посмотреть релевантность механник. Почему не релевантны механики перекрестных продаж и допродаж?
A77: =A76+5 -> 340 | B77: DB | C77: Торговый Эквайринг | D77: 0.62650602 | E77: Зрелые | F77: продукт | G77: 1 | H77: 0.5 | I77: 0 | J77: 0 | K77: 0 | L77: 0 | M77: 0 | N77: 0 | O77: 0.5 | P77: 0.5 | Q77: 0.5 | R77: не релевантно | S77: не релевантно | T77: 0 | U77: 1 | V77: Пиратская станция, приток/отток в разрезе ТОП банков, динамика доли рынка, основные каналы продаж, выполнение бизнес-плана, конвертация продаж в канале Безналичные Решения, сроки имплементации, NPS/CSI | W77: 0.5 | X77: 1 | Y77: 0.5 | Z77: 1 | AA77: 1 | AB77: 0 | AC77: для продукта не включается в расчет | AD77: =IF(AI77="не релевантно","не релевантн",(AI77+AJ77)/2) -> 1 | AI77: 1 | AJ77: 1 | AK77: =IF(AL77="не релевантно","не релевантн",(AL77+AM77)/2) -> 1 | AL77: 1 | AM77: 1 | AN77: 1 | AO77: 1 | AP77: 0 | AQ77: 0 | AR77: 1 | AS77: для продукта не включается в расчет | AT77: для продукта не включается в расчет | AU77: 1 | AV77: доля рынка в ИНН/Объеме, конвертация задач, приток/отток клиентов | AW77: 0 | AX77: 0 | AY77: 0 | AZ77: 1 | BF77: TBD | BG77: 1 | BH77: 1 | BI77: наличие отдельно выделенной команды Data инженеров (сейчас 1 человек в централизованной функции на весь трайб), отсутствие ресурса разработки для встраивания реперных точек контроля клиентского пути и его эффективности, технологическая сложность и ресурсоемкость задачи на передачу данных из централизованных систем (ПКАП) в UI-системы (АС Навигатор) (например, для дистрибуции одной витрины данных требуется квартал) | BJ77: Фисенко Владислав Николаевич | BK77: Требуется проверить метрики в блоке-метрики продукта- продукт не выделен в ЕКМ. Почему не релевантна воронка оттока?
A78: =A77+5 -> 345 | B78: DB | C78: Дебетовая карта | D78: 0.55643564 | E78: Развивающиеся | F78: продукт | G78: 0.8 | H78: 0.5 | I78: 0 | J78: 0.5 | K78: 0 | L78: 0 | M78: 0 | N78: 0 | O78: 0.5 | P78: 0.5 | Q78: 0.5 | R78: 1 | S78: 0.5 | T78: 1 | U78: 0 | W78: 1 | X78: 1 | Y78: 0.5 | Z78: 1 | AA78: 1 | AB78: 0 | AC78: для продукта не включается в расчет | AD78: =IF(AI78="не релевантно","не релевантн",(AI78+AJ78)/2) -> 1 | AI78: 1 | AJ78: 1 | AK78: =IF(AL78="не релевантно","не релевантн",(AL78+AM78)/2) -> 0.5 | AL78: 1 | AM78: 0 | AN78: 1 | AO78: 1 | AP78: 0 | AQ78: 0 | AR78: 0 | AS78: для продукта не включается в расчет | AT78: для продукта не включается в расчет | AU78: 1 | AV78: CR отклика на предложение, пост контроль активации клиента - POS активность. | AW78: 0 | AX78: 0 | AY78: 0 | AZ78: 1 | BA78: 1 | BB78: 0 | BC78: 1 | BD78: 0 | BE78: 1 | BF78: TBD | BG78: 1 | BH78: 1 | BI78: BА - текущие кубы имеют ограничения не позволяющие заниматься исследованием и поиском корреляций данных | BJ78: Яковлев Сергей Викторович | BK78: 0
A79: =A78+5 -> 350 | B79: DB | C79: SberPay NFC | D79: 0.77367206 | E79: Зрелые | F79: продукт | G79: 0.55555556 | H79: 0.5 | I79: 1 | J79: 0 | K79: 0.5 | L79: 1 | M79: 0 | N79: 0 | O79: 1 | P79: 0.5 | Q79: 1 | R79: 0.5 | S79: 0.5 | T79: 0.5 | U79: 1 | V79: SberPay NFC - №1 по кол-ву активных пользователей, и уровню удержания клиента (95%) | W79: 1 | X79: 1 | Y79: 1 | Z79: 1 | AA79: 1 | AB79: 1 | AC79: для продукта не включается в расчет | AD79: =IF(AI79="не релевантно","не релевантн",(AI79+AJ79)/2) -> 1 | AI79: 1 | AJ79: 1 | AK79: =IF(AL79="не релевантно","не релевантн",(AL79+AM79)/2) -> 1 | AL79: 1 | AM79: 1 | AN79: 1 | AO79: 1 | AP79: 0 | AQ79: 0 | AR79: 1 | AS79: для продукта не включается в расчет | AT79: для продукта не включается в расчет | AU79: 1 | AV79: Охват, отклик, конверсия. | AW79: 0 | AX79: 0 | AY79: 1 | AZ79: 0 | BA79: нерелевантно | BB79: нерелевантно | BC79: нерелевантно | BD79: нерелевантно | BF79: TBD | BG79: 1 | BH79: 0 | BI79: Создание ИИ агента позволяющего в онлайн получать любую продуктовую аналитику, из любых источников, с автоматизированным поиском зависимостей, инсайтов и формирования выводов. В том числе по смежным продуктам. | BJ79: Маманков Максим Сергеевич | BK79: 0
A80: =A79+5 -> 355 | B80: DB | C80: Как зарплатный | D80: 0.37078652 | E80: Требуют внимания | F80: продукт | G80: 1 | H80: 1 | I80: 0 | J80: 0 | K80: 0 | L80: 0 | M80: 0 | N80: 0 | O80: 1 | P80: 1 | Q80: 1 | R80: не релевантно | S80: не релевантно | T80: 0 | U80: 0 | W80: 0.5 | X80: 1 | Y80: 0.5 | Z80: 0 | AA80: 1 | AB80: 0.5 | AC80: для продукта не включается в расчет | AD80: =IF(AI80="не релевантно","не релевантн",(AI80+AJ80)/2) -> не релевантн | AI80: не релевантно | AJ80: не релевантно | AK80: =IF(AL80="не релевантно","не релевантн",(AL80+AM80)/2) -> не релевантн | AL80: не релевантно | AM80: не релевантно | AN80: 0.5 | AO80: 0 | AP80: 0 | AQ80: 1 | AR80: 0 | AS80: для продукта не включается в расчет | AT80: для продукта не включается в расчет | AU80: 1 | AV80: затрудняюсь ответить | AW80: 0 | AX80: 0.5 | AY80: 0 | AZ80: 0 | BA80: 1 | BB80: 0 | BC80: 0 | BD80: 0 | BE80: 0.5 | BF80: TBD | BG80: 0 | BH80: 0 | BI80: актуальный триггеров привлечения и оттока | BJ80: Киселева Мария Николаевна, Иванов Михаил Владимирович | BK80: Требуется проверить метрики в блоке-метрики продукта- продукт не выделен в ЕКМ. Посмотреть релевантность механник. Почему не релевантны механики удержания и возврата? Почему не релевантна воронка оттока?
A81: =A80+5 -> 360 | B81: DB | C81: Сценарии оплаты | D81: 0.47524752 | E81: Развивающиеся | F81: продукт | G81: 1 | H81: 0.5 | I81: 0 | J81: 0 | K81: 0 | L81: 0 | M81: 0 | N81: 0 | O81: 0.5 | P81: 0 | Q81: 0.5 | R81: 1 | S81: 0.5 | T81: 1 | U81: 0 | W81: 1 | X81: 1 | Y81: 0.5 | Z81: 1 | AA81: 1 | AB81: 0 | AC81: для продукта не включается в расчет | AD81: =IF(AI81="не релевантно","не релевантн",(AI81+AJ81)/2) -> 1 | AI81: 1 | AJ81: 1 | AK81: =IF(AL81="не релевантно","не релевантн",(AL81+AM81)/2) -> 0 | AL81: 0 | AM81: 0 | AN81: 1 | AO81: 1 | AP81: 0 | AQ81: 0 | AR81: 1 | AS81: для продукта не включается в расчет | AT81: для продукта не включается в расчет | AU81: 1 | AV81: CR; CTR в целевое действие | AW81: 0 | AX81: 0 | AY81: 0 | AZ81: 0 | BA81: 1 | BB81: 0 | BC81: 1 | BD81: 0 | BE81: 1 | BF81: TBD | BG81: 0 | BH81: 0 | BI81: Оповещений в случае отклонений. Автоматизация отчетности. | BJ81: Юрковский Роберт Юрьевич | BK81: Посмотреть релевантность механник. Почему не релевантна механика возврата?
A82: =A81+5 -> 365 | B82: DB | C82: Интернет-Эквайринг | D82: 0.37349398 | E82: Требуют внимания | F82: продукт | G82: 1 | H82: 1 | I82: 0.5 | J82: 0 | K82: 0.5 | L82: 0 | M82: 0 | N82: 0 | O82: 0 | P82: 0 | Q82: 0 | R82: не релевантно | S82: не релевантно | T82: 0 | U82: 0 | W82: 0.5 | X82: 1 | Y82: 0.5 | Z82: 1 | AA82: 1 | AB82: 0 | AC82: для продукта не включается в расчет | AD82: =IF(AI82="не релевантно","не релевантн",(AI82+AJ82)/2) -> 0 | AI82: 0 | AJ82: 0 | AK82: =IF(AL82="не релевантно","не релевантн",(AL82+AM82)/2) -> 0 | AL82: 0 | AM82: 0 | AN82: 0 | AO82: не релевантно | AP82: 0 | AQ82: 0 | AR82: 0 | AS82: для продукта не включается в расчет | AT82: для продукта не включается в расчет | AU82: 1 | AV82: нет ответа по механикам | AW82: 1 | AX82: 0 | AY82: 0 | AZ82: 0 | BD82: нерелевантно | BF82: TBD | BG82: 0 | BH82: 1 | BI82: затрудняюсь ответить | BJ82: Кравченко Тимофей Викторович | BK82: Требуется проверить метрики в блоке-метрики продукта- продукт не выделен в ЕКМ. Посмотреть релевантность продуктовых механник, почему не актуальны? Описать свой вариант. Почему не релевантны воронки привлечения и оттока?
A83: =A82+5 -> 370 | B83: DB | C83: SberPay Ecom | D83: 0.43544304 | E83: Развивающиеся | F83: продукт | G83: 0.6 | H83: 0.5 | I83: 1 | J83: 0.5 | K83: 0.5 | L83: 1 | M83: 0 | N83: 0 | O83: не релевантно | P83: не релевантно | Q83: 0 | R83: не релевантно | S83: не релевантно | T83: 0 | U83: 0 | W83: 0 | X83: 1 | Y83: 0.5 | Z83: 1 | AA83: 1 | AB83: 1 | AC83: для продукта не включается в расчет | AD83: =IF(AI83="не релевантно","не релевантн",(AI83+AJ83)/2) -> 0 | AI83: 0 | AJ83: 0 | AK83: =IF(AL83="не релевантно","не релевантн",(AL83+AM83)/2) -> 0 | AL83: 0 | AM83: 0 | AN83: 0 | AO83: не релевантно | AP83: 0 | AQ83: 0 | AR83: 0 | AS83: для продукта не включается в расчет | AT83: для продукта не включается в расчет | AU83: 1 | AV83: доля в безнале, оборот, доля в usonus | AW83: 1 | AX83: 0 | AY83: 0 | AZ83: 1 | BD83: нерелевантно | BF83: TBD | BG83: 1 | BH83: 0 | BI83: исследования клиентского поведения, метрик отклика на фичи, внедрения на новых партнерах | BJ83: Ведерникова Ю.А., Кравченко Т.В. | BK83: Посмотреть релевантность механник, почему не актуальны? Почему не релевантны воронки привлечения и оттока?
A84: =A83+5 -> 375 | B84: DB | C84: SberPay Вжух | D84: 0.42068966 | E84: Развивающиеся | F84: продукт | G84: 0.4 | H84: 0.5 | I84: 0 | J84: 0 | K84: 0 | L84: 0 | M84: 0 | N84: 0 | O84: 1 | P84: 0.5 | Q84: 1 | R84: 0 | S84: 0 | T84: 0 | U84: 0 | W84: 0.5 | X84: 1 | Y84: 0.5 | Z84: 1 | AA84: 1 | AB84: 0.5 | AC84: для продукта не включается в расчет | AD84: =IF(AI84="не релевантно","не релевантн",(AI84+AJ84)/2) -> 1 | AI84: 1 | AJ84: 1 | AK84: =IF(AL84="не релевантно","не релевантн",(AL84+AM84)/2) -> 1 | AL84: 1 | AM84: 1 | AN84: 0 | AO84: не релевантно | AP84: 0 | AQ84: 0 | AR84: 0 | AS84: для продукта не включается в расчет | AT84: для продукта не включается в расчет | AU84: 1 | AV84: Конверсия в покупку клиентов, на которых была направлена коммуникация | AW84: 0 | AX84: 0 | AY84: 0 | AZ84: 0 | BD84: нерелевантно | BF84: TBD | BG84: 0 | BH84: 1 | BI84: Ресурса аналитиков | BJ84: Дрожжина Валентина Юрьевна | BK84: Посмотреть релевантность механник. Почему не актуальны перекрестные продажи и допродажи? Почему не релевантны воронки привлечения и оттока?
A85: =A84+5 -> 380 | B85: DB | C85: Пенсионный продукт | D85: 0.33195876 | E85: Требуют внимания | F85: продукт | G85: 0.8 | H85: 1 | I85: 0 | J85: 0 | K85: 0 | L85: 0 | M85: 0 | N85: 0 | O85: 1 | P85: 0 | Q85: 1 | R85: 1 | S85: 0 | T85: 1 | U85: 0 | W85: 0.5 | X85: 1 | Y85: 0.5 | Z85: 1 | AA85: 1 | AB85: 0 | AC85: для продукта не включается в расчет | AD85: =IF(AI85="не релевантно","не релевантн",(AI85+AJ85)/2) -> 0.5 | AI85: 1 | AJ85: 0 | AK85: =IF(AL85="не релевантно","не релевантн",(AL85+AM85)/2) -> 0 | AL85: 0 | AM85: 0 | AN85: 0 | AO85: не релевантно | AP85: 0 | AQ85: 0 | AR85: 0 | AS85: для продукта не включается в расчет | AT85: для продукта не включается в расчет | AU85: 1 | AV85: Сокращение оттока: https://navigator.sigma.sbrf.ru/gdash/1000000495/1000044123?dtDateN1=2026-12-31&sSet=2&dtDateN=2026-02-28&sSet1=3 | AW85: 0 | AX85: 0 | AY85: 0 | AZ85: 1 | BA85: 1 | BB85: 0 | BC85: 1 | BD85: 0 | BF85: TBD | BG85: 0 | BH85: 0 | BI85: Пока всего хватает | BJ85: Мерзликин Иван Сергеевич | BK85: Посмотреть релевантность механник. Почему не актуальны перекрестные продажи, когда есть ПДС, и его предлагают?
A86: =A85+5 -> 385 | B86: DB | C86: ЗП b2b | D86: 0.49677419 | E86: Развивающиеся | F86: Исключить | G86: 0.8 | H86: 1 | I86: 0 | J86: 0 | K86: 0.5 | L86: 0 | M86: 0 | N86: 0 | O86: 0 | P86: 0 | Q86: 0 | R86: 0 | S86: 0 | T86: 0 | U86: 1 | V86: метрики прошлых периодов | W86: 1 | X86: 1 | Y86: 1 | Z86: 1 | AA86: 0.5 | AB86: 0.5 | AC86: для продукта не включается в расчет | AD86: =IF(AI86="не релевантно","не релевантн",(AI86+AJ86)/2) -> 1 | AI86: 1 | AJ86: 1 | AK86: =IF(AL86="не релевантно","не релевантн",(AL86+AM86)/2) -> 0 | AL86: 0 | AM86: 0 | AN86: 1 | AO86: 1 | AP86: 0 | AQ86: 0 | AR86: 1 | AS86: для продукта не включается в расчет | AT86: для продукта не включается в расчет | AU86: 1 | AV86: Цг vs КГ | AW86: 0 | AX86: 0 | AY86: 0.5 | AZ86: 0 | BA86: 0 | BB86: 0 | BC86: 0 | BF86: TBD | BG86: 0 | BH86: 0 | BI86: Регулярной отчетности по инн | BJ86: Сауткин Андрей Юрьевич | BK86: Проверить воронки привлечения и оттока?
A87: =A86+5 -> 390 | B87: DB | C87: СберЧаевые | D87: 0.39354839 | E87: Требуют внимания | F87: продукт | G87: 0.4 | H87: 0.5 | I87: 0.5 | J87: 0.5 | K87: 0.5 | L87: 1 | M87: 0 | N87: 0 | O87: 1 | P87: 0.5 | Q87: 1 | R87: 1 | S87: 0 | T87: 1 | U87: 0 | W87: 0.5 | X87: 1 | Y87: 0.5 | Z87: 1 | AA87: 0.5 | AB87: 0 | AC87: для продукта не включается в расчет | AD87: =IF(AI87="не релевантно","не релевантн",(AI87+AJ87)/2) -> 0 | AI87: 0 | AJ87: 0 | AK87: =IF(AL87="не релевантно","не релевантн",(AL87+AM87)/2) -> 0 | AL87: 0 | AM87: 0 | AN87: 0 | AO87: не релевантно | AP87: 0 | AQ87: 0 | AR87: 0 | AS87: для продукта не включается в расчет | AT87: для продукта не включается в расчет | AU87: 1 | AV87: Доля рынка, доля платежных методов Сбера, Анализ транзакционной активности. | AW87: 1 | AX87: 0 | AY87: 1 | AZ87: 0 | BA87: 0 | BB87: 0 | BC87: 0 | BD87: нерелевантно | BF87: TBD | BG87: 0 | BH87: 1 | BI87: Вычислительных ресурсов в проекте DataLab. Приоритетов у смежных подразделений. | BJ87: Губин Юрий Сергеевич | BK87: Посмотреть релевантность механник (специфический продукт)
A88: =A87+5 -> 395 | B88: DB | C88: Самозанятые. Списочная регистрация | D88: 0.051522248 | E88: Требуют внимания | F88: Исключить | G88: 1 | H88: 0.5 | I88: 0 | J88: 0 | K88: 0 | L88: 0 | M88: 0 | N88: 0 | O88: не релевантно | P88: не релевантно | Q88: 0 | R88: не релевантно | S88: не релевантно | T88: 0 | U88: 0 | W88: 0 | X88: 0 | Y88: 0 | Z88: 0 | AA88: 0 | AB88: 0 | AC88: для продукта не включается в расчет | AD88: =IF(AI88="не релевантно","не релевантн",(AI88+AJ88)/2) -> 0 | AI88: 0 | AJ88: 0 | AK88: =IF(AL88="не релевантно","не релевантн",(AL88+AM88)/2) -> 0 | AL88: 0 | AM88: 0 | AN88: 0 | AO88: не релевантно | AP88: 0 | AQ88: 0 | AR88: 0 | AS88: для продукта не включается в расчет | AT88: для продукта не включается в расчет | AU88: 1 | AV88: нет ответа | AW88: 1 | AX88: 0 | AY88: 0 | AZ88: 1 | BA88: 0 | BB88: 0 | BC88: 0 | BE88: 0.5 | BF88: TBD | BG88: 0 | BH88: 0 | BI88: нет ответа | BJ88: Алексеева Анастасия Викторовна | BK88: Требуется проверить метрики в блоке-метрики продукта- продукт не выделен в ЕКМ. Посмотреть релевантность механник (специфичный продукт) Это полноценный продукт Самозанятые? Или часть этого продукта?
A89: =A88+5 -> 400 | B89: DB | C89: Перевод зарплаты в Сбер в офисе и на выезде через СБОЛ.про | D89: 0.39325843 | E89: Требуют внимания | F89: Исключить | G89: 1 | H89: 0.5 | I89: 0.5 | J89: 0 | K89: 0.5 | L89: 0 | M89: 0 | N89: 0 | O89: 1 | P89: 0.5 | Q89: 1 | R89: не релевантно | S89: не релевантно | T89: 0 | U89: 0 | W89: 0.5 | X89: 1 | Y89: 0.5 | Z89: 0 | AA89: 1 | AB89: 0 | AC89: для продукта не включается в расчет | AD89: =IF(AI89="не релевантно","не релевантн",(AI89+AJ89)/2) -> 0 | AI89: 0 | AJ89: 0 | AK89: =IF(AL89="не релевантно","не релевантн",(AL89+AM89)/2) -> 0 | AL89: 0 | AM89: 0 | AN89: 0 | AO89: не релевантно | AP89: 0 | AQ89: 0 | AR89: 1 | AS89: для продукта не включается в расчет | AT89: для продукта не включается в расчет | AU89: 1 | AV89: не использует | AW89: 0 | AX89: 0 | AY89: 0.5 | AZ89: 0 | BA89: 1 | BB89: 0 | BC89: 1 | BF89: TBD | BG89: 0 | BH89: 0 | BI89: Недостаточно ресурсов data аналитика | BJ89: Егоров Александр Сергеевич | BK89: Требуется проверить метрики в блоке-метрики продукта- продукт не выделен в ЕКМ. Посмотреть релевантность механник. Почему не релевантна механика перекрестных продаж?
A90: =A89+5 -> 405 | B90: DB | C90: Зарплатный продукт | D90: 0.30232558 | E90: Требуют внимания | F90: продукт | G90: 1 | H90: 1 | I90: 0 | J90: 0 | K90: 0 | L90: 0 | M90: 0 | N90: 0 | O90: 0 | P90: 0 | Q90: 0 | R90: 0 | S90: 0 | T90: 0 | U90: 0 | W90: 0.5 | X90: 1 | Y90: 0 | Z90: 1 | AA90: 0 | AB90: 0 | AC90: для продукта не включается в расчет | AD90: =IF(AI90="не релевантно","не релевантн",(AI90+AJ90)/2) -> 1 | AI90: 1 | AJ90: 1 | AK90: =IF(AL90="не релевантно","не релевантн",(AL90+AM90)/2) -> 0 | AL90: 0 | AM90: 0 | AN90: 0.5 | AO90: 0 | AP90: 1 | AQ90: 0 | AR90: 0 | AS90: для продукта не включается в расчет | AT90: для продукта не включается в расчет | AU90: 1 | AV90: Отслеживание происходит со стороны смежных коллег | AW90: 0 | AX90: 0.5 | AY90: 0 | AZ90: 0 | BA90: 1 | BB90: 0 | BC90: 1 | BD90: 0 | BF90: TBD | BG90: 0 | BH90: 0 | BI90: Нет информации | BJ90: Шматов Никита Иванович | BK90: Требуется проверить метрики в блоке-метрики продукта- продукт не выделен в ЕКМ. Проверить воронки привлечения и оттока?
A91: =A90+5 -> 410 | B91: DB | C91: Детская карта | D91: 0.39148073 | E91: Требуют внимания | F91: продукт | G91: 1 | H91: 0.5 | I91: 0.5 | J91: 0.5 | K91: 0 | L91: 0 | M91: 0 | N91: 0 | O91: 1 | P91: 0.5 | Q91: 1 | R91: 0 | S91: 0 | T91: 0 | U91: 0 | W91: 0.5 | X91: 1 | Y91: 0.5 | Z91: 1 | AA91: 1 | AB91: 0 | AC91: для продукта не включается в расчет | AD91: =IF(AI91="не релевантно","не релевантн",(AI91+AJ91)/2) -> 0 | AI91: 0 | AJ91: 0 | AK91: =IF(AL91="не релевантно","не релевантн",(AL91+AM91)/2) -> 0.5 | AL91: 1 | AM91: 0 | AN91: 0.5 | AO91: 0 | AP91: 0 | AQ91: 1 | AR91: 0 | AS91: для продукта не включается в расчет | AT91: для продукта не включается в расчет | AU91: 1 | AV91: Вход в процесс, нажатие баннера, активная клиентская база | AW91: 0 | AX91: 0 | AY91: 0.5 | AZ91: 0 | BA91: 0 | BB91: 0 | BC91: 0 | BD91: 0 | BE91: 1 | BF91: TBD | BG91: 0 | BH91: 0 | BI91: Поддержки и экспертизы в поисках источников данных | BJ91: Фомин Андрей Евгеньевич | BK91: Требуется проверить метрики в блоке-метрики продукта- продукт не выделен в ЕКМ. Проверить воронки привлечения и оттока?
A92: =A91+5 -> 415 | B92: ДомКлик | C92: Долгосрочная Аренда | D92: 0.55723542 | E92: Развивающиеся | F92: ДЗО | G92: 1 | H92: 1 | I92: 0 | J92: 0.5 | K92: 0.5 | L92: 0 | M92: 0 | N92: 0 | O92: 1 | P92: 0.5 | Q92: 1 | R92: не релевантно | S92: не релевантно | T92: 0 | U92: 1 | V92: рынок РФ, внутренние каналы | W92: 1 | X92: 1 | Y92: 1 | Z92: 1 | AA92: 0 | AB92: 0 | AC92: для продукта не включается в расчет | AD92: =IF(AI92="не релевантно","не релевантн",(AI92+AJ92)/2) -> 1 | AI92: 1 | AJ92: 1 | AK92: =IF(AL92="не релевантно","не релевантн",(AL92+AM92)/2) -> 1 | AL92: 1 | AM92: 1 | AN92: 0 | AO92: не релевантно | AP92: 0 | AQ92: 0 | AR92: 0 | AS92: для продукта не включается в расчет | AT92: для продукта не включается в расчет | AU92: 1 | AV92: в зависимости от механики, например, если про ценность - какой интерес к этой ценности (соклько увидели, как CR в клик, сколько дошли до конца и оформили "ценность") | AW92: 0 | AX92: 0 | AY92: 0.5 | AZ92: 0 | BA92: 1 | BB92: 1 | BC92: 0 | BE92: 0 | BF92: TBD | BG92: 1 | BH92: 0 | BI92: не хватает скорости работы с данными сбера. Это просто дикий ад - доступы, витрины, непонятно где и что искать, приходится с протянутой рукой ходить по коллегам и спрашивтаь может кто-то знает, где все лежит. ПРи успешном получении доступов начинаются инфраструктцурные проблемы - скорость ну и т д | BJ92: Нечаева Анна Александровна | BK92: Требуется проверить метрики в блоке-метрики продукта- продукт не выделен в ЕКМ. Проверить воронки привлечения и оттока?
A93: =A92+5 -> 420 | B93: СХ | C93: СберСпасибо | D93: 0.68493151 | E93: Зрелые | F93: продукт | G93: 1 | H93: 0.5 | I93: 1 | J93: 0.5 | K93: 0 | L93: 1 | M93: 0 | N93: 0 | O93: 0.5 | P93: 0.5 | Q93: 0.5 | R93: не релевантно | S93: не релевантно | T93: 0 | U93: 0 | W93: 0.5 | X93: 1 | AA93: 1 | AB93: 0.5 | AC93: для продукта не включается в расчет | AD93: =IF(AI93="не релевантно","не релевантн",(AI93+AJ93)/2) -> 0 | AI93: 0 | AJ93: 0 | AK93: =IF(AL93="не релевантно","не релевантн",(AL93+AM93)/2) -> 0 | AL93: 0 | AM93: 0 | AN93: 1 | AO93: 1 | AP93: 0 | AQ93: 0 | AR93: 1 | AS93: для продукта не включается в расчет | AT93: для продукта не включается в расчет | AU93: 1 | AV93: Конверсия в продажу подписок Прайм и ПУ Премьер | AW93: 0 | AX93: 0 | AY93: 1 | AZ93: 0 | BA93: 1 | BB93: 0 | BC93: 1 | BD93: нерелевантно | BF93: TBD | BG93: 1 | BH93: 1 | BI93: 1. Аналитики лояльности не имеют собственного пространства для работы с БД, часто заканчивается место, как следствие задачи делаются долго. 2. Не хватает нормального BI инструмента, Навигатор имеет много ограничений, в частности возможность подкладывать только агрегированные данные. | BJ93: Савицкий Евгений Михайлович | BK93: Для данного продукта в чистом виде не релевантна воронка оттока- но релеванна Воронка потери активности и ценности в программе лояльности

Sheet свод_каналы
F2: 5 | G2: 6 | H2: 7 | I2: 8 | J2: 9
G3: =H3 -> СБерKids | H3: =F18 -> СБерKids
G4: СберKids | H4: =SUM(H33:H176)+H17+SUM(H189:H192)-H43-H44-H45-H60-H75-H89-H157-H161 -> 27.25 | I4: =SUM(I33:I176)+I17+SUM(I189:I192)-I60-I75-I89-I157-I161 -> 14.5 | J4: =I4/H4 -> 0.53211009
D5: Вопрос | F5: Ответ | G5: Комментарий | H5: =F18 -> СБерKids
C6: Вводные данные | D6: id | F6: 6 | H6: макс балл | I6: факт | J6: %
D7: Представьтесь, пожалуйста | F7: Бессонов Кирилл Павлович | H7: =F7 -> Бессонов Кирилл Павлович
D8: Выберете ваш юнит | F8: Занять и сберегать (Core Banking)
F9: Развитие клиентского опыта (CX)
F10: Транзакционный банкинг (Daily Banking)
F11: Данные и рекомендательные системы (Data)
F12: Забота о клиентах (Phygital channels)
F13: Домклик
F14: Цифровые каналы (Digital channels) | G14: 1
F15: Управление благосостояния
F16: eCom
A17: 1 | F17: Индустрии рекламы и развлечений (Entertainment) | H17: =SUM(H19:H32) -> 1 | I17: =SUM(I19:I32) -> 1 | J17: =I17/H17 -> 1
D18: Укажите, пожалуйста, владельцем какого канала вы являетесь | F18: СБерKids | I18: =F18 -> СБерKids
C19: Блок 1. Общие метрики канала | D19: Напишите процент проникновения вашего канала в клиентскую базу Сбера | F19: Укажите процент проникновения: ЦА - Дети 6-13 лет включительно. MAU канала ~3 млн | G19: 1 | H19: 0.1 | I19: 0.1 | J19: =I19/H19 -> 1
F20: Не релевантно для вашего канала
D21: Какое MAU у вашего канала? | F21: Укажите общий MAU канала - 2,8 млн | G21: 1 | H21: 0.1 | I21: 0.1 | J21: =I21/H21 -> 1
F22: При наличии, укажите MAU IOS - 2,3 млн | G22: 1 | H22: 0.1 | I22: 0.1 | J22: =I22/H22 -> 1
F23: При наличии, укажите MAU Android - 500к | G23: 1 | H23: 0.1 | I23: 0.1 | J23: =I23/H23 -> 1
F24: При наличии, укажите MAU Web | H24: 0.1 | I24: 0.1 | J24: =I24/H24 -> 1
F25: Не релевантно для вашего канала
D26: Какое DAU у вашего канала? | F26: Укажите общий DAU канала - 700К | G26: 1 | H26: 0.1 | I26: 0.1 | J26: =I26/H26 -> 1
F27: При наличии, укажите DAU IOS - 150К | G27: 1 | H27: 0.1 | I27: 0.1 | J27: =I27/H27 -> 1
F28: При наличии, укажите DAU Android - 550К | G28: 1 | H28: 0.1 | I28: 0.1 | J28: =I28/H28 -> 1
F29: При наличии, укажите DAU Web | H29: 0.1 | I29: 0.1 | J29: =I29/H29 -> 1
F30: Не релевантно для вашего канала
D31: Какое отношение DAU/MAU (липкость) у вашего канала? | F31: Укажите отношение DAU/MAU - 25% | G31: 1 | H31: 0.1 | I31: 0.1 | J31: =I31/H31 -> 1
F32: Не релевантно для вашего канала
A33: 2 | D33: Какими инструментами вы пользуетесь для мониторинга метрик из вопросов выше: | F33: Дашборд в Навигаторе (доступны все метрики) | G33: 1 | H33: 0.5 | I33: =IF(G33=1,0.5,IF(AND(G38=1,G36=""),0.5,IF(OR(G35=1,G34=1),0.25,0))) -> 0.5 | J33: =IFERROR(IF(H33=0,"",I33/H33),"") -> 1
F34: Дашборд в Навигаторе (доступна часть метрик) | J34: =IFERROR(IF(H34=0,"",I34/H34),"")
F35: Запрашиваете необходимую информацию у аналитиков | G35: 1 | J35: =IFERROR(IF(H35=0,"",I35/H35),"")
F36: Собственная отчетность канала (не Навигатор)
F37: Свой вариант ответа | G37: 1
F38: Затрудняюсь ответить
C39: Блок 2. Цели, факторный анализ, прогноз | D39: Отчетность по целям/драйверам/прогнозам продукта уровня ЛЮ-ЛТ выведена на мониторинг и доступна владельцу продукта | F39: Цели | G39: В Навигаторе | H39: 1 | I39: =IF(G39="Отсутствует",0,IF(AND(G39="В Навигаторе",I193=1),1,IF(AND(G39="В Навигаторе",I193<>1),0,IF(G39="Не в Навигаторе",0.5,0)))) -> 0 | J39: =IFERROR(IF(H39=0,"",I39/H39),"") -> 0
F40: Факторный анализ | G40: В Навигаторе | H40: 1 | I40: =IF(G40="Отсутствует",0,IF(AND(G40="В Навигаторе",I162=1),1,IF(AND(G40="В Навигаторе",I162<>1),0,IF(G40="Не в Навигаторе",0.5,0)))) -> 0 | J40: =IFERROR(IF(H40=0,"",I40/H40),"") -> 0
F41: Прогноз по целям | G41: В Навигаторе | H41: 1 | I41: =IF(G41="Отсутствует",0,IF(AND(G41="В Навигаторе",I163=1),1,IF(AND(G41="В Навигаторе",I163<>1),0,IF(G41="Не в Навигаторе",0.5,0)))) -> 0 | J41: =IFERROR(IF(H41=0,"",I41/H41),"") -> 0
F42: Прогноз по драйверам | G42: В Навигаторе
C43: Блок 3. Воронки привлечения, онбординга и активации | D43: Какие типы воронок вы отслеживаете? | F43: Воронка по каналам привлечения | G43: 1 | H43: =IF(G$47=1,"не релевантно",1) -> 1
F44: Воронка онбординга | G44: 1 | H44: =IF(G$47=1,"не релевантно",1) -> 1
F45: Воронка оттока (снижения активности в канале) | G45: 1 | H45: =IF(G$47=1,"не релевантно",1) -> 1
F46: Что-то еще? Напишите
F47: Затрудняюсь ответить
D48: Настроена ли регулярная отчётность по воронке по каналам привлечения? | F48: Да | G48: 1 | H48: =IF(G50=1,"не релевантно",0.5) -> 0.5 | I48: =IF(G48=1,0.5,0)*I60 -> 0.5 | J48: =IFERROR(IF(H48="Не релевантно",H48,IF(H48=0,"",I48/H48)),"") -> 1
F49: Нет
F50: Не релевантно для моего канала
F51: Затрудняюсь ответить
D52: Что включает воронка по каналам привлечения? | F52: Каналы привлечения | H52: 0.5 | I52: =IF(SUM(G52:G58)>6,0.5,IF(SUM(G52:G58)>3,0.25,0)) -> 0 | J52: =IFERROR(IF(H52=0,"",I52/H52),"") -> 0
F53: Пошаговая воронка
F54: CR и CTR
F55: Объёмы коммуникаций
F56: Количество целевых действий
F57: Сегментный/ кагортный разрез | G57: 1
F58: UX/UI-дизайн
F59: Затрудняюсь ответить
D60: Какая регулярность обновления отчета по воронке по каналам привлечения? | F60: Автоматически (daily или weekly) | G60: 1 | I60: =IF(G60=1,1,0.5) -> 1
F61: По запросу
F62: Затрудняюсь ответить
F63: Приложите ссылку на отчет воронки привлечения: https://navigator.sigma.sbrf.ru/gdash/1000002729/1000029287?dtDate=20260531&nDynamicTypeID=3&sSet=3&tab_1=1&plat=ios&version=3.x%7C%7C%7C4.x%7C%7C%7C5.0.0%7C%7C%7C5.1.0%7C%7C%7C5.2.0%7C%7C%7C5.4.0 | G63: 1
D64: Настроена ли регулярная отчётность по воронке онбординга? | F64: Да | H64: =IF(G66=1,"не релевантно",0.5) -> 0.5 | I64: =IF(G64=1,0.5,0)*I75 -> 0 | J64: =IFERROR(IF(H64="Не релевантно",H64,IF(H64=0,"",I64/H64)),"") -> 0
F65: Нет | G65: 1
F66: Не релевантно для моего канала
F67: Затрудняюсь ответить
D68: Что включает воронка онбординга? | F68: Источники привлечения | G68: не релевантно | H68: 0.5 | I68: =IF(SUM(G68:G74)>6,0.5,IF(SUM(G68:G74)>3,0.25,0)) -> 0 | J68: =IFERROR(IF(H68=0,"",I68/H68),"") -> 0
F69: Количество входов
F70: Пошаговая воронка
F71: Количество (доля) клиентов с целевым действием
F72: Время до целевого действия
F73: UX/UI
F74: Затрудняюсь ответить
D75: Какая регулярность обновления отчета по воронке онбординга? | F75: Автоматически (daily или weekly) | I75: =IF(G75=1,1,0.5) -> 0.5
F76: По запросу
F77: Затрудняюсь ответить
F78: Приложите ссылку на отчет воронки онбординга
D79: Настроена ли регулярная отчётность по воронке оттока (анализа снижения активности в канале)? | F79: Да | G79: 1 | H79: =IF(G81=1,"не релевантно",0.5) -> 0.5 | I79: =IF(G79=1,0.5,0)*I89 -> 0.5 | J79: =IFERROR(IF(H79="Не релевантно",H79,IF(H79=0,"",I79/H79)),"") -> 1
F80: Нет
F81: Не релевантно для моего канала
F82: Затрудняюсь ответить
D83: Что включает воронка оттока (анализа снижения активности в канале)? | F83: Определение предотточных клиентов | G83: 1 | H83: 0.5 | I83: =IF(SUM(G83:G87)>4,0.5,IF(SUM(G83:G87)>1,0.25,0)) -> 0.25 | J83: =IFERROR(IF(H83=0,"",I83/H83),"") -> 0.5
F84: Сегментный/когортный разрез | G84: 1
F85: Когортный retention
F86: Механики удержания
F87: % оттока
F88: Затрудняюсь ответить
D89: Какая регулярность обновления отчета по воронке оттока (анализа снижения активности в канале)? | F89: Автоматически (daily или weekly) | G89: 1 | I89: =IF(G89=1,1,0.5) -> 1
F90: По запросу
F91: Затрудняюсь ответить
F92: Приложите ссылку на отчет воронки оттока (анализа снижения активности в канале)? https://navigator.sigma.sbrf.ru/gdash/1000002729/1000029287?dtDate=20260531&nDynamicTypeID=3&sSet=3&tab_1=1&plat=ios&version=3.x%7C%7C%7C4.x%7C%7C%7C5.0.0%7C%7C%7C5.1.0%7C%7C%7C5.2.0%7C%7C%7C5.4.0 | G92: 1
D93: Есть ли бенчмарки по метрикам воронок оттока и привлечения? | F93: Да | H93: 1 | I93: =IF(G93=1,1,0) -> 0 | J93: =IFERROR(IF(H93=0,"",I93/H93),"") -> 0
F94: Нет | G94: 1
F95: Затрудняюсь ответить
D96: Опишите, какие бенчмарки используются | G96: не релевантно
C97: Блок 4. Анализ воронок, мероприятия | D97: Проводился ли за последний квартал анализ воронки привлечения? | F97: Сравнение с конкурентами процесса оформления продукта, условий продукта или мониторинг новых фичей | H97: 1 | I97: =IF(G103=1,1,IF(SUM(G97:G101)=0,0,IF(G105=1,0,IF(SUM(G97:G101)>4,1,IF(SUM(G97:G101)<3,0.5,0))))) -> 0.5 | J97: =IFERROR(IF(H97=0,"",I97/H97),"") -> 0.5
F98: По кампаниям продаж: воронка внутри кампаний, количество достигших целевого действия, оценка результативности компаний | G98: 1
F99: A/B тесты
F100: Сегментный/Когортный анализ | G100: 1
F101: UX/UI
...

Sheet свод_сегменты
I1: 9 | J1: 10 | K1: 11 | L1: 12 | M1: 13 | N1: 14 | O1: 15 | P1: 16 | Q1: 17 | R1: 18 | S1: 19 | T1: 20 | U1: 21 | V1: 22 | W1: 23 | X1: 24 | Y1: 25 | Z1: 26 | AA1: 27 | AB1: 28 | AC1: 29 | AD1: 30 | AE1: 31 | AF1: 32 | AG1: 33 | AH1: 34 | AI1: 35 | AJ1: 36 | AK1: 37 | AL1: 38 | AM1: 39 | AN1: 40 | AO1: 41 | AP1: 42 | AQ1: 43
K2: Возрастной | P2: Возрастной | U2: Возрастной | Z2: Возрастной | AE2: Доходный | AJ2: Доходный | AO2: Доходный
K3: Дети | P3: Молодежь | U3: =S23 -> Рабочий возраст | Z3: =X24 -> Зрелость | AE3: =AE19 -> Top Affluent | AJ3: =AH18 -> PB | AO3: МВС
K4: =SUM(K25:K216)+K222 -> 19.35 | L4: =SUM(L25:L216)-L86-L101-L164-L195-L149-L163+L222 -> 10.95 | M4: =L4/K4 -> 0.56589147 | P4: =SUM(P25:P216)+P222 -> 19.65 | Q4: =SUM(Q25:Q216)-Q86-Q101-Q164-Q195-Q149+Q222 -> 9.45 | R4: =Q4/P4 -> 0.48091603 | U4: =SUM(U25:U216)+U222 -> 20.55 | V4: =SUM(V25:V216)-V86-V101-V164-V195-V163-V149+V222 -> 12.8 | W4: =V4/U4 -> 0.62287105 | Z4: =SUM(Z25:Z216)+Z222 -> 19.65 | AA4: =SUM(AA25:AA216)-AA86-AA101-AA164-AA195-AA149+AA222 -> 7.9 | AB4: =AA4/Z4 -> 0.40203562 | AE4: =SUM(AE25:AE216)+AE222 -> 22.75 | AF4: =SUM(AF25:AF216)-AF86-AF101-AF149-AF169-AF195-AF185-AF156+AF222 -> 12.625 | AG4: =AF4/AE4 -> 0.55494505 | AJ4: =SUM(AJ25:AJ216)+AJ222 -> 22.25 | AK4: =SUM(AK25:AK216)-AK86-AK101-AK149-AK169-AK195-AK185-AK156+AK222 -> 11.625 | AL4: =AK4/AJ4 -> 0.52247191 | AO4: =SUM(AO25:AO216)+AO222 -> 22.25 | AP4: =SUM(AP25:AP216)-AP86-AP101-AP149-AP169-AP163-AP195-AP185-AP156+AP222 -> 9.125 | AQ4: =AP4/AO4 -> 0.41011236
D5: Вопрос | E5: Ответ | G5: Оценка | I5: Ответ | J5: Комментарий | K5: =K3 -> Дети | N5: Ответ | O5: Комментарий | P5: =P3 -> Молодежь | S5: Ответ | T5: Комментарий | U5: =U3 -> Рабочий возраст | X5: Ответ | Y5: Комментарий | Z5: =Z3 -> Зрелость | AC5: Ответ | AD5: Комментарий | AE5: =AE3 -> Top Affluent | AH5: Ответ | AI5: Комментарий | AJ5: =AJ3 -> PB | AM5: Ответ | AN5: Комментарий | AO5: =AO3 -> МВС
B6: Вводные данные | D6: id | I6: 8 | K6: макс балл | L6: факт | M6: % | N6: 11 | P6: макс балл | Q6: факт | R6: % | S6: 16 | U6: макс балл | V6: факт | W6: % | X6: 19 | Z6: макс балл | AA6: факт | AB6: % | AC6: 13 | AE6: макс балл | AF6: факт | AG6: % | AH6: 17 | AJ6: макс балл | AK6: факт | AL6: % | AM6: 21 | AO6: макс балл | AP6: факт | AQ6: %
A7: 100 | D7: Представьтесь, пожалуйста | I7: Буканова | K7: =I7 -> Буканова | N7: Водяницкий Андрей Андреевич | P7: =N7 -> Водяницкий Андрей Андреевич | S7: Кудряшов Грант Андреевич | U7: =S7 -> Кудряшов Грант Андреевич | X7: Серебряников Антон Олегович | Z7: =X7 -> Серебряников Антон Олегович | AC7: Багдасарян Артем Робертович | AE7: =AC7 -> Багдасарян Артем Робертович | AH7: Арташес Маркарьян | AJ7: =AH7 -> Арташес Маркарьян | AM7: Бахтанов Андрей Юрьевич | AO7: =AM7 -> Бахтанов Андрей Юрьевич
D8: Выберете ваш юнит | E8: Занять и сберегать (Core Banking) | I8: Занять и сберегать (Core Banking) | N8: Занять и сберегать (Core Banking) | S8: Занять и сберегать (Core Banking) | X8: Занять и сберегать (Core Banking) | AC8: Занять и сберегать (Core Banking) | AH8: Занять и сберегать (Core Banking) | AM8: Занять и сберегать (Core Banking)
E9: Развитие клиентского опыта (CX) | I9: Развитие клиентского опыта (CX) | J9: 1 | N9: Развитие клиентского опыта (CX) | O9: 1 | S9: Развитие клиентского опыта (CX) | T9: 1 | X9: Развитие клиентского опыта (CX) | Y9: 1 | AC9: Развитие клиентского опыта (CX) | AD9: 1 | AH9: Развитие клиентского опыта (CX) | AI9: 1 | AM9: Развитие клиентского опыта (CX) | AN9: 1
E10: Транзакционный банкинг (Daily Banking) | I10: Транзакционный банкинг (Daily Banking) | N10: Транзакционный банкинг (Daily Banking) | S10: Транзакционный банкинг (Daily Banking) | X10: Транзакционный банкинг (Daily Banking) | AC10: Транзакционный банкинг (Daily Banking) | AH10: Транзакционный банкинг (Daily Banking) | AM10: Транзакционный банкинг (Daily Banking)
E11: Данные и рекомендательные системы (Data) | I11: Данные и рекомендательные системы (Data) | N11: Данные и рекомендательные системы (Data) | S11: Данные и рекомендательные системы (Data) | X11: Данные и рекомендательные системы (Data) | AC11: Данные и рекомендательные системы (Data) | AH11: Данные и рекомендательные системы (Data) | AM11: Данные и рекомендательные системы (Data)
E12: Забота о клиентах (Phygital channels) | I12: Забота о клиентах (Phygital channels) | N12: Забота о клиентах (Phygital channels) | S12: Забота о клиентах (Phygital channels) | X12: Забота о клиентах (Phygital channels) | AC12: Забота о клиентах (Phygital channels) | AH12: Забота о клиентах (Phygital channels) | AM12: Забота о клиентах (Phygital channels)
E13: Домклик | I13: Домклик | N13: Домклик | S13: Домклик | X13: Домклик | AC13: Домклик | AH13: Домклик | AM13: Домклик
E14: Цифровые каналы (Digital channels) | I14: Цифровые каналы (Digital channels) | N14: Цифровые каналы (Digital channels) | S14: Цифровые каналы (Digital channels) | X14: Цифровые каналы (Digital channels) | AC14: Цифровые каналы (Digital channels) | AH14: Цифровые каналы (Digital channels) | AM14: Цифровые каналы (Digital channels)
E15: Управление благосостояния | I15: Управление благосостояния | N15: Управление благосостояния | S15: Управление благосостояния | X15: Управление благосостояния | AC15: Управление благосостояния | AH15: Управление благосостояния | AM15: Управление благосостояния
E16: eCom | I16: eCom | N16: eCom | S16: eCom | X16: eCom | AC16: eCom | AH16: eCom | AM16: eCom
E17: Индустрии рекламы и развлечений (Entertainment) | I17: Индустрии рекламы и развлечений (Entertainment) | N17: Индустрии рекламы и развлечений (Entertainment) | S17: Индустрии рекламы и развлечений (Entertainment) | X17: Индустрии рекламы и развлечений (Entertainment) | AC17: Индустрии рекламы и развлечений (Entertainment) | AH17: Индустрии рекламы и развлечений (Entertainment) | AM17: Индустрии рекламы и развлечений (Entertainment)
D18: Выберете, пожалуйста, владельцем какого сегмента вы являетесь | E18: PB | I18: PB | K18: =IF(J18=1,I18,"") | N18: PB | P18: =IF(O18=1,N18,"") | S18: PB | U18: =IF(T18=1,S18,"") | X18: PB | Z18: =IF(Y18=1,X18,"") | AC18: PB | AE18: =IF(AD18=1,AC18,"") | AH18: PB | AI18: 1 | AJ18: =IF(AI18=1,AH18,"") -> PB | AM18: PB | AO18: =IF(AN18=1,AM18,"")
E19: Top Affluent | I19: Top Affluent | K19: =IF(J19=1,I19,"") | N19: Top Affluent | P19: =IF(O19=1,N19,"") | S19: Top Affluent | U19: =IF(T19=1,S19,"") | X19: Top Affluent | Z19: =IF(Y19=1,X19,"") | AC19: Top Affluent | AD19: 1 | AE19: =IF(AD19=1,AC19,"") -> Top Affluent | AH19: Top Affluent | AJ19: =IF(AI19=1,AH19,"") | AM19: Top Affluent | AO19: =IF(AN19=1,AM19,"")
E20: МВС | I20: МВС | K20: =IF(J20=1,I20,"") | N20: МВС | P20: =IF(O20=1,N20,"") | S20: МВС | U20: =IF(T20=1,S20,"") | X20: МВС | Z20: =IF(Y20=1,X20,"") | AC20: МВС | AE20: =IF(AD20=1,AC20,"") | AH20: МВС | AJ20: =IF(AI20=1,AH20,"") | AM20: МВС | AN20: 1 | AO20: =IF(AN20=1,AM20,"") -> МВС
E21: Дети | I21: Дети | J21: 1 | K21: =IF(J21=1,I21,"") -> Дети | N21: Дети | P21: =IF(O21=1,N21,"") | S21: Дети | U21: =IF(T21=1,S21,"") | X21: Дети | Z21: =IF(Y21=1,X21,"") | AC21: Дети | AE21: =IF(AD21=1,AC21,"") | AH21: Дети | AJ21: =IF(AI21=1,AH21,"") | AM21: Дети | AO21: =IF(AN21=1,AM21,"")
E22: Молодежь | I22: Молодежь | K22: =IF(J22=1,I22,"") | N22: Молодежь | O22: 1 | P22: =IF(O22=1,N22,"") -> Молодежь | S22: Молодежь | U22: =IF(T22=1,S22,"") | X22: Молодежь | Z22: =IF(Y22=1,X22,"") | AC22: Молодежь | AE22: =IF(AD22=1,AC22,"") | AH22: Молодежь | AJ22: =IF(AI22=1,AH22,"") | AM22: Молодежь | AO22: =IF(AN22=1,AM22,"")
E23: Рабочий возраст | I23: Рабочий возраст | K23: =IF(J23=1,I23,"") | N23: Рабочий возраст | P23: =IF(O23=1,N23,"") | S23: Рабочий возраст | T23: 1 | U23: =IF(T23=1,S23,"") -> Рабочий возраст | X23: Рабочий возраст | Z23: =IF(Y23=1,X23,"") | AC23: Рабочий возраст | AE23: =IF(AD23=1,AC23,"") | AH23: Рабочий возраст | AJ23: =IF(AI23=1,AH23,"") | AM23: Рабочий возраст | AO23: =IF(AN23=1,AM23,"")
A24: 1 | E24: Зрелость | I24: Зрелость | K24: =SUM(K25:K64) -> 0.6 | L24: =SUM(L25:L64) -> 0.45 | M24: =L24/K24 -> 0.75 | N24: Зрелость | P24: =SUM(P25:P64) -> 0.9 | Q24: =SUM(Q25:Q64) -> 0.45 | R24: =Q24/P24 -> 0.5 | S24: Зрелость | U24: =SUM(U25:U64) -> 1.8 | V24: =SUM(V25:V64) -> 1.8 | W24: =V24/U24 -> 1 | X24: Зрелость | Y24: 1 | Z24: =SUM(Z25:Z64) -> 0.9 | AA24: =SUM(AA25:AA64) -> 0.9 | AB24: =AA24/Z24 -> 1 | AC24: Зрелость | AE24: =SUM(AE25:AE64) -> 1 | AF24: =SUM(AF25:AF64) -> 0.875 | AG24: =AF24/AE24 -> 0.875 | AH24: Зрелость | AJ24: =SUM(AJ25:AJ64) -> 1 | AK24: =SUM(AK25:AK64) -> 0.875 | AL24: =AK24/AJ24 -> 0.875 | AM24: Зрелость | AO24: =SUM(AO25:AO64) -> 1 | AP24: =SUM(AP25:AP64) -> 0.875 | AQ24: =AP24/AO24 -> 0.875
B25: Блок 1. Общие метрики сегмента | C25: Возрастной | D25: Метрика "Активная клиентская база" сегмента. На сколько активно вы работаете с данной метрикой? (только для возрастных) | E25: Знаю значение, могу быстро найти в отчетности (укажите в поле ввода ниже) | F25: (1 балл) | G25: 1 | I25: Знаю значение, могу быстро найти в отчетности (укажите в поле ввода ниже) | J25: 1 | K25: 0.3 | L25: =K25*IF(AND(J25=1,J28=0),0.5,(IF(J25=1,$G25,IF(J26=1,$G26,IF(J27=1,$G27,""))))) -> 0.3 | M25: =L25/K25 -> 1 | N25: Знаю значение, могу быстро найти в отчетности (укажите в поле ввода ниже) | O25: 1 | P25: 0.3 | Q25: =P25*IF(AND(O25=1,O28=0),0.5,(IF(O25=1,$G25,IF(O26=1,$G26,IF(O27=1,$G27,""))))) -> 0.15 | R25: =Q25/P25 -> 0.5 | S25: Знаю значение, могу быстро найти в отчетности (укажите в поле ввода ниже) | T25: 1 | U25: 0.3 | V25: =U25*IF(AND(T25=1,T28=0),0.5,(IF(T25=1,$G25,IF(T26=1,$G26,IF(T27=1,$G27,""))))) -> 0.3 | W25: =V25/U25 -> 1 | X25: Знаю значение, могу быстро найти в отчетности (укажите в поле ввода ниже) | Y25: 1 | Z25: 0.3 | AA25: =Z25*IF(AND(Y25=1,Y28=0),0.5,(IF(Y25=1,$G25,IF(Y26=1,$G26,IF(Y27=1,$G27,""))))) -> 0.3 | AB25: =AA25/Z25 -> 1 | AC25: Знаю значение, могу быстро найти в отчетности (укажите в поле ввода ниже) | AD25: не релевантно | AE25: =IF($C25=AE$2,0.3,"") | AH25: Знаю значение, могу быстро найти в отчетности (укажите в поле ввода ниже) | AI25: не релевантно | AJ25: =IF($C25=AJ$2,0.3,"") | AM25: Знаю значение, могу быстро найти в отчетности (укажите в поле ввода ниже) | AN25: не релевантно | AO25: =IF($C25=AO$2,0.3,"")
C26: Возрастной | E26: Знаю что за метрика, но актуального значения нет под рукой | F26: (0,5 балл) | G26: 0.5 | I26: Знаю что за метрика, но актуального значения нет под рукой | N26: Знаю что за метрика, но актуального значения нет под рукой | S26: Знаю что за метрика, но актуального значения нет под рукой | X26: Знаю что за метрика, но актуального значения нет под рукой | AC26: Знаю что за метрика, но актуального значения нет под рукой | AH26: Знаю что за метрика, но актуального значения нет под рукой | AM26: Знаю что за метрика, но актуального значения нет под рукой
C27: Возрастной | E27: Практически не работаю с этой метрикой напрямую | F27: (0 балл) | G27: 0 | I27: Практически не работаю с этой метрикой напрямую | N27: Практически не работаю с этой метрикой напрямую | S27: Практически не работаю с этой метрикой напрямую | X27: Практически не работаю с этой метрикой напрямую | AC27: Практически не работаю с этой метрикой напрямую | AH27: Практически не работаю с этой метрикой напрямую | AM27: Практически не работаю с этой метрикой напрямую
C28: Возрастной | E28: Введите значение | I28: Введите значение - Навигатор | J28: 0 Релевантно, одна из целей сегмента вес цели 2Q 10% https://navigator.sigma.sbrf.ru/gdash/1000003450/1000035954?vmetric=%D0%90%D0%BA%D1%82%D0%B8%D0%B2%D0%BD%D0%B0%D1%8F%20%D0%BA%D0%BB%D0%B8%D0%B5%D0%BD%D1%82%D1%81%D0%BA%D0%B0%D1%8F%20%D0%B1%D0%B0%D0%B7%D0%B0%2C%20%D0%BC%D0%BB%D0%BD%20%D1%87%D0%B5%D0%BB&vMode=1 | N28: Введите значение - В навигаторе, но там есть лаг по времени на месяц | O28: 0 | P28: релеватно, вес цели 2Q 10% https://navigator.sigma.sbrf.ru/gdash/1000003450/1000035954?vmetric=%D0%90%D0%BA%D1%82%D0%B8%D0%B2%D0%BD%D0%B0%D1%8F%20%D0%BA%D0%BB%D0%B8%D0%B5%D0%BD%D1%82%D1%81%D0%BA%D0%B0%D1%8F%20%D0%B1%D0%B0%D0%B7%D0%B0%2C%20%D0%BC%D0%BB%D0%BD%20%D1%87%D0%B5%D0%BB&vQrt=2&vMode=1 | S28: Введите значение - 65 млн | T28: 1 | U28: релевантно -https://navigator.sigma.sbrf.ru/gdash/1000003450/1000035578?vmetric=%D0%90%D0%BA%D1%82%D0%B8%D0%B2%D0%BD%D0%B0%D1%8F%20%D0%BA%D0%BB%D0%B8%D0%B5%D0%BD%D1%82%D1%81%D0%BA%D0%B0%D1%8F%20%D0%B1%D0%B0%D0%B7%D0%B0%2C%20%D0%BC%D0%BB%D0%BD%20%D1%87%D0%B5%D0%BB&vQrt=2&vMode=1 | X28: Введите значение - https://navigator.sigma.sbrf.ru/gdash/1000003450/1000035956 | Y28: 1 | Z28: релевантно, https://navigator.sigma.sbrf.ru/gdash/1000003450/1000035956?vmetric=%D0%90%D0%BA%D1%82%D0%B8%D0%B2%D0%BD%D0%B0%D1%8F%20%D0%BA%D0%BB%D0%B8%D0%B5%D0%BD%D1%82%D1%81%D0%BA%D0%B0%D1%8F%20%D0%B1%D0%B0%D0%B7%D0%B0%2C%20%D0%BC%D0%BB%D0%BD%20%D1%87%D0%B5%D0%BB&vQrt=2&vMode=1 | AC28: Введите значение | AH28: Введите значение | AM28: Введите значение
C29: Возрастной | D29: Метрика количества Major клиентов сегмента. На сколько активно вы работаете с данной метрикой? (только для возрастных) | E29: Знаю значение, могу быстро найти в отчетности (укажите в поле ввода ниже) | F29: (1 балл) | G29: 1 | I29: Знаю значение, могу быстро найти в отчетности (укажите в поле ввода ниже) | K29: 0.3 | L29: =K29*IF(AND(J29=1,J32=0),0.5,(IF(J29=1,$G29,IF(J30=1,$G30,IF(J31=1,$G31,""))))) -> 0.15 | M29: =L29/K29 -> 0.5 | N29: Знаю значение, могу быстро найти в отчетности (укажите в поле ввода ниже) | O29: 1 | P29: 0.3 | Q29: =P29*IF(AND(O29=1,O32=0),0.5,(IF(O29=1,$G29,IF(O30=1,$G30,IF(O31=1,$G31,""))))) -> 0.15 | R29: =Q29/P29 -> 0.5 | S29: Знаю значение, могу быстро найти в отчетности (укажите в поле ввода ниже) | T29: 1 | U29: 0.3 | V29: =U29*IF(AND(T29=1,T32=0),0.5,(IF(T29=1,$G29,IF(T30=1,$G30,IF(T31=1,$G31,""))))) -> 0.3 | W29: =V29/U29 -> 1 | X29: Знаю значение, могу быстро найти в отчетности (укажите в поле ввода ниже) | Y29: 1 | Z29: 0.3 | AA29: =Z29*IF(AND(Y29=1,Y32=0),0.5,(IF(Y29=1,$G29,IF(Y30=1,$G30,IF(Y31=1,$G31,""))))) -> 0.3 | AB29: =AA29/Z29 -> 1 | AC29: Знаю значение, могу быстро найти в отчетности (укажите в поле ввода ниже) | AD29: не релевантно | AE29: =IF($C29=AE$2,0.3,"") | AH29: Знаю значение, могу быстро найти в отчетности (укажите в поле ввода ниже) | AI29: не релевантно | AJ29: =IF($C29=AJ$2,0.3,"") | AM29: Знаю значение, могу быстро найти в отчетности (укажите в поле ввода ниже) | AN29: не релевантно | AO29: =IF($C29=AO$2,0.3,"")
C30: Возрастной | E30: Знаю что за метрика, но актуального значения нет под рукой | F30: (0,5 балл) | G30: 0.5 | I30: Знаю что за метрика, но актуального значения нет под рукой | J30: 1 | N30: Знаю что за метрика, но актуального значения нет под рукой | S30: Знаю что за метрика, но актуального значения нет под рукой | X30: Знаю что за метрика, но актуального значения нет под рукой | AC30: Знаю что за метрика, но актуального значения нет под рукой | AH30: Знаю что за метрика, но актуального значения нет под рукой | AM30: Знаю что за метрика, но актуального значения нет под рукой
C31: Возрастной | E31: Практически не работаю с этой метрикой напрямую | F31: (0 балл) | G31: 0 | I31: Практически не работаю с этой метрикой напрямую | N31: Практически не работаю с этой метрикой напрямую | S31: Практически не работаю с этой метрикой напрямую | X31: Практически не работаю с этой метрикой напрямую | AC31: Практически не работаю с этой метрикой напрямую | AH31: Практически не работаю с этой метрикой напрямую | AM31: Практически не работаю с этой метрикой напрямую
C32: Возрастной | E32: Введите значение | I32: Введите значение | J32: 0 Релевантно, одна из целей сегмента вес цели 2Q 10% https://navigator.sigma.sbrf.ru/gdash/1000003450/1000035954?vmetric=%D0%90%D0%BA%D1%82%D0%B8%D0%B2%D0%BD%D0%B0%D1%8F%20%D0%BA%D0%BB%D0%B8%D0%B5%D0%BD%D1%82%D1%81%D0%BA%D0%B0%D1%8F%20%D0%B1%D0%B0%D0%B7%D0%B0%2C%20%D0%BC%D0%BB%D0%BD%20%D1%87%D0%B5%D0%BB&vMode=1 | N32: Введите значение - Знаю где искать, но есть лаг по времени ее отображения | O32: 0 | P32: релеватно, вес цели 2Q 10% https://navigator.sigma.sbrf.ru/gdash/1000003450/1000035954?vmetric=%D0%90%D0%BA%D1%82%D0%B8%D0%B2%D0%BD%D0%B0%D1%8F%20%D0%BA%D0%BB%D0%B8%D0%B5%D0%BD%D1%82%D1%81%D0%BA%D0%B0%D1%8F%20%D0%B1%D0%B0%D0%B7%D0%B0%2C%20%D0%BC%D0%BB%D0%BD%20%D1%87%D0%B5%D0%BB&vQrt=2&vMode=1 | S32: Введите значение - 29 | T32: 1 | U32: релевантно -https://navigator.sigma.sbrf.ru/gdash/1000003450/1000035578?vmetric=%D0%90%D0%BA%D1%82%D0%B8%D0%B2%D0%BD%D0%B0%D1%8F%20%D0%BA%D0%BB%D0%B8%D0%B5%D0%BD%D1%82%D1%81%D0%BA%D0%B0%D1%8F%20%D0%B1%D0%B0%D0%B7%D0%B0%2C%20%D0%BC%D0%BB%D0%BD%20%D1%87%D0%B5%D0%BB&vQrt=2&vMode=1 | X32: Введите значение - https://navigator.sigma.sbrf.ru/gdash/1000003450/1000035956 | Y32: 1 | Z32: релевантно, https://navigator.sigma.sbrf.ru/gdash/1000003450/1000035956?vmetric=%D0%90%D0%BA%D1%82%D0%B8%D0%B2%D0%BD%D0%B0%D1%8F%20%D0%BA%D0%BB%D0%B8%D0%B5%D0%BD%D1%82%D1%81%D0%BA%D0%B0%D1%8F%20%D0%B1%D0%B0%D0%B7%D0%B0%2C%20%D0%BC%D0%BB%D0%BD%20%D1%87%D0%B5%D0%BB&vQrt=2&vMode=1 | AC32: Введите значение | AH32: Введите значение | AM32: Введите значение
C33: Возрастной | D33: Метрика количества клиентов сегмента с 2+ нефинансовыми сервисами. На сколько активно вы работаете с данной метрикой? (только для возрастных) | E33: Знаю значение, могу быстро найти в отчетности (укажите в поле ввода ниже) | F33: (1 балл) | G33: 1 | I33: Знаю значение, могу быстро найти в отчетности (укажите в поле ввода ниже) | L33: =K33*IF(AND(J33=1,J36=0),0.5,(IF(J33=1,$G33,IF(J34=1,$G34,IF(J35=1,$G35,""))))) -> 0 | N33: Знаю значение, могу быстро найти в отчетности (укажите в поле ввода ниже) | P33: 0.3 | Q33: =P33*IF(AND(O33=1,O36=0),0.5,(IF(O33=1,$G33,IF(O34=1,$G34,IF(O35=1,$G35,""))))) -> 0.15 | R33: =Q33/P33 -> 0.5 | S33: Знаю значение, могу быстро найти в отчетности (укажите в поле ввода ниже) | T33: 1 | U33: 0.3 | V33: =U33*IF(AND(T33=1,T36=0),0.5,(IF(T33=1,$G33,IF(T34=1,$G34,IF(T35=1,$G35,""))))) -> 0.3 | W33: =V33/U33 -> 1 | X33: Знаю значение, могу быстро найти в отчетности (укажите в поле ввода ниже) | Y33: 1 | Z33: 0.3 | AA33: =Z33*IF(AND(Y33=1,Y36=0),0.5,(IF(Y33=1,$G33,IF(Y34=1,$G34,IF(Y35=1,$G35,""))))) -> 0.3 | AB33: =AA33/Z33 -> 1 | AC33: Знаю значение, могу быстро найти в отчетности (укажите в поле ввода ниже) | AD33: не релевантно | AE33: =IF($C33=AE$2,0.3,"") | AH33: Знаю значение, могу быстро найти в отчетности (укажите в поле ввода ниже) | AI33: не релевантно | AJ33: =IF($C33=AJ$2,0.3,"") | AM33: Знаю значение, могу быстро найти в отчетности (укажите в поле ввода ниже) | AN33: не релевантно | AO33: =IF($C33=AO$2,0.3,"")
C34: Возрастной | E34: Знаю что за метрика, но актуального значения нет под рукой | F34: (0,5 балл) | G34: 0.5 | I34: Знаю что за метрика, но актуального значения нет под рукой | N34: Знаю что за метрика, но актуального значения нет под рукой | O34: 1 | S34: Знаю что за метрика, но актуального значения нет под рукой | X34: Знаю что за метрика, но актуального значения нет под рукой | AC34: Знаю что за метрика, но актуального значения нет под рукой | AH34: Знаю что за метрика, но актуального значения нет под рукой | AM34: Знаю что за метрика, но актуального значения нет под рукой
C35: Возрастной | E35: Практически не работаю с этой метрикой напрямую | F35: (0 балл) | G35: 0 | I35: Практически не работаю с этой метрикой напрямую | J35: 1 | N35: Практически не работаю с этой метрикой напрямую | S35: Практически не работаю с этой метрикой напрямую | X35: Практически не работаю с этой метрикой напрямую | AC35: Практически не работаю с этой метрикой напрямую | AH35: Практически не работаю с этой метрикой напрямую | AM35: Практически не работаю с этой метрикой напрямую
C36: Возрастной | E36: Введите значение | I36: Введите значение | J36: 0 Релеватно для Подростков не для детей | N36: Введите значение | O36: 0 | P36: релеватно, вес цели 2Q 2,5% https://navigator.sigma.sbrf.ru/gdash/1000003450/1000035954?vmetric=%D0%90%D0%BA%D1%82%D0%B8%D0%B2%D0%BD%D0%B0%D1%8F%20%D0%BA%D0%BB%D0%B8%D0%B5%D0%BD%D1%82%D1%81%D0%BA%D0%B0%D1%8F%20%D0%B1%D0%B0%D0%B7%D0%B0%2C%20%D0%BC%D0%BB%D0%BD%20%D1%87%D0%B5%D0%BB&vQrt=2&vMode=1 | S36: Введите значение - 4,2 | T36: 1 | U36: релевантно -https://navigator.sigma.sbrf.ru/gdash/1000003450/1000035578?vmetric=%D0%90%D0%BA%D1%82%D0%B8%D0%B2%D0%BD%D0%B0%D1%8F%20%D0%BA%D0%BB%D0%B8%D0%B5%D0%BD%D1%82%D1%81%D0%BA%D0%B0%D1%8F%20%D0%B1%D0%B0%D0%B7%D0%B0%2C%20%D0%BC%D0%BB%D0%BD%20%D1%87%D0%B5%D0%BB&vQrt=2&vMode=1 | X36: Введите значение - https://navigator.sigma.sbrf.ru/gdash/1000003450/1000035956 | Y36: 1 | Z36: релевантно, https://navigator.sigma.sbrf.ru/gdash/1000003450/1000035956?vmetric=%D0%90%D0%BA%D1%82%D0%B8%D0%B2%D0%BD%D0%B0%D1%8F%20%D0%BA%D0%BB%D0%B8%D0%B5%D0%BD%D1%82%D1%81%D0%BA%D0%B0%D1%8F%20%D0%B1%D0%B0%D0%B7%D0%B0%2C%20%D0%BC%D0%BB%D0%BD%20%D1%87%D0%B5%D0%BB&vQrt=2&vMode=1 | AC36: Введите значение | AH36: Введите значение | AM36: Введите значение
C37: Рабочий возраст | D37: Метрика количества получателей заработной платы. На сколько активно вы работаете с данной метрикой? (только рабочий возраст) | E37: Знаю значение, могу быстро найти в отчетности (укажите в поле ввода ниже) | F37: (1 балл) | G37: 1 | I37: Знаю значение, могу быстро найти в отчетности (укажите в поле ввода ниже) | J37: не релевантно | N37: Знаю значение, могу быстро найти в отчетности (укажите в поле ввода ниже) | O37: не релевантно | S37: Знаю значение, могу быстро найти в отчетности (укажите в поле ввода ниже) | T37: 1 | U37: 0.3 | V37: =U37*IF(AND(T37=1,T40=0),0.5,(IF(T37=1,$G37,IF(T38=1,$G38,IF(T39=1,$G39,""))))) -> 0.3 | W37: =V37/U37 -> 1 | X37: Знаю значение, могу быстро найти в отчетности (укажите в поле ввода ниже) | Y37: не релевантно | AC37: Знаю значение, могу быстро найти в отчетности (укажите в поле ввода ниже) | AD37: не релевантно | AE37: =IF($C37=AE$2,0.3,"") | AH37: Знаю значение, могу быстро найти в отчетности (укажите в поле ввода ниже) | AI37: не релевантно | AJ37: =IF($C37=AJ$2,0.3,"") | AM37: Знаю значение, могу быстро найти в отчетности (укажите в поле ввода ниже) | AN37: не релевантно | AO37: =IF($C37=AO$2,0.3,"")
C38: Рабочий возраст | E38: Знаю что за метрика, но актуального значения нет под рукой | F38: (0,5 балл) | G38: 0.5 | I38: Знаю что за метрика, но актуального значения нет под рукой | N38: Знаю что за метрика, но актуального значения нет под рукой | S38: Знаю что за метрика, но актуального значения нет под рукой | X38: Знаю что за метрика, но актуального значения нет под рукой | AC38: Знаю что за метрика, но актуального значения нет под рукой | AH38: Знаю что за метрика, но актуального значения нет под рукой | AM38: Знаю что за метрика, но актуального значения нет под рукой
C39: Рабочий возраст | E39: Практически не работаю с этой метрикой напрямую | F39: (0 балл) | G39: 0 | I39: Практически не работаю с этой метрикой напрямую | N39: Практически не работаю с этой метрикой напрямую | S39: Практически не работаю с этой метрикой напрямую | X39: Практически не работаю с этой метрикой напрямую | AC39: Практически не работаю с этой метрикой напрямую | AH39: Практически не работаю с этой метрикой напрямую | AM39: Практически не работаю с этой метрикой напрямую
C40: Рабочий возраст | E40: Введите значение | I40: Введите значение | N40: Введите значение | S40: Введите значение - 30,5 в логике (epk-ИНН-ГОСБ), 29 млн уникальных | T40: 1 | U40: релевантно -https://navigator.sigma.sbrf.ru/gdash/1000003450/1000035578?vmetric=%D0%90%D0%BA%D1%82%D0%B8%D0%B2%D0%BD%D0%B0%D1%8F%20%D0%BA%D0%BB%D0%B8%D0%B5%D0%BD%D1%82%D1%81%D0%BA%D0%B0%D1%8F%20%D0%B1%D0%B0%D0%B7%D0%B0%2C%20%D0%BC%D0%BB%D0%BD%20%D1%87%D0%B5%D0%BB&vQrt=2&vMode=1 | X40: Введите значение | AC40: Введите значение | AH40: Введите значение | AM40: Введите значение
C41: Рабочий возраст | D41: Метрика доли рынка ФОТ, %. На сколько активно вы работаете с данной метрикой? (только рабочий возраст) | E41: Знаю значение, могу быстро найти в отчетности (укажите в поле ввода ниже) | F41: (1 балл) | G41: 1 | I41: Знаю значение, могу быстро найти в отчетности (укажите в поле ввода ниже) | J41: не релевантно | N41: Знаю значение, могу быстро найти в отчетности (укажите в поле ввода ниже) | O41: не релевантно | S41: Знаю значение, могу быстро найти в отчетности (укажите в поле ввода ниже) | T41: 1 | U41: 0.3 | V41: =U41*IF(AND(T41=1,T44=0),0.5,(IF(T41=1,$G41,IF(T42=1,$G42,IF(T43=1,$G43,""))))) -> 0.3 | W41: =V41/U41 -> 1 | X41: Знаю значение, могу быстро найти в отчетности (укажите в поле ввода ниже) | Y41: не релевантно | AC41: Знаю значение, могу быстро найти в отчетности (укажите в поле ввода ниже) | AD41: не релевантно | AE41: =IF($C41=AE$2,0.3,"") | AH41: Знаю значение, могу быстро найти в отчетности (укажите в поле ввода ниже) | AI41: не релевантно | AJ41: =IF($C41=AJ$2,0.3,"") | AM41: Знаю значение, могу быстро найти в отчетности (укажите в поле ввода ниже) | AN41: не релевантно | AO41: =IF($C41=AO$2,0.3,"")
C42: Рабочий возраст | E42: Знаю что за метрика, но актуального значения нет под рукой | F42: (0,5 балл) | G42: 0.5 | I42: Знаю что за метрика, но актуального значения нет под рукой | N42: Знаю что за метрика, но актуального значения нет под рукой | S42: Знаю что за метрика, но актуального значения нет под рукой | X42: Знаю что за метрика, но актуального значения нет под рукой | AC42: Знаю что за метрика, но актуального значения нет под рукой | AH42: Знаю что за метрика, но актуального значения нет под рукой | AM42: Знаю что за метрика, но актуального значения нет под рукой
C43: Рабочий возраст | E43: Практически не работаю с этой метрикой напрямую | F43: (0 балл) | G43: 0 | I43: Практически не работаю с этой метрикой напрямую | N43: Практически не работаю с этой метрикой напрямую | S43: Практически не работаю с этой метрикой напрямую | X43: Практически не работаю с этой метрикой напрямую | AC43: Практически не работаю с этой метрикой напрямую | AH43: Практически не работаю с этой метрикой напрямую | AM43: Практически не работаю с этой метрикой напрямую
C44: Рабочий возраст | E44: Введите значение | I44: Введите значение | N44: Введите значение | S44: Введите значение - 46 | T44: 1 | U44: релевантно -https://navigator.sigma.sbrf.ru/gdash/1000003450/1000035578?vmetric=%D0%90%D0%BA%D1%82%D0%B8%D0%B2%D0%BD%D0%B0%D1%8F%20%D0%BA%D0%BB%D0%B8%D0%B5%D0%BD%D1%82%D1%81%D0%BA%D0%B0%D1%8F%20%D0%B1%D0%B0%D0%B7%D0%B0%2C%20%D0%BC%D0%BB%D0%BD%20%D1%87%D0%B5%D0%BB&vQrt=2&vMode=1 | X44: Введите значение | AC44: Введите значение | AH44: Введите значение | AM44: Введите значение
C45: Рабочий возраст | D45: Метрика объема зачислений ФОТ. На сколько активно вы работаете с данной метрикой? (только рабочий возраст) | E45: Знаю значение, могу быстро найти в отчетности (укажите в поле ввода ниже) | F45: (1 балл) | G45: 1 | I45: Знаю значение, могу быстро найти в отчетности (укажите в поле ввода ниже) | J45: не релевантно | N45: Знаю значение, могу быстро найти в отчетности (укажите в поле ввода ниже) | O45: не релевантно | S45: Знаю значение, могу быстро найти в отчетности (укажите в поле ввода ниже) | T45: 1 | U45: 0.3 | V45: =U45*IF(AND(T45=1,T48=0),0.5,(IF(T45=1,$G45,IF(T46=1,$G46,IF(T47=1,$G47,""))))) -> 0.3 | W45: =V45/U45 -> 1 | X45: Знаю значение, могу быстро найти в отчетности (укажите в поле ввода ниже) | Y45: не релевантно | AC45: Знаю значение, могу быстро найти в отчетности (укажите в поле ввода ниже) | AD45: не релевантно | AE45: =IF($C45=AE$2,0.3,"") | AH45: Знаю значение, могу быстро найти в отчетности (укажите в поле ввода ниже) | AI45: не релевантно | AJ45: =IF($C45=AJ$2,0.3,"") | AM45: Знаю значение, могу быстро найти в отчетности (укажите в поле ввода ниже) | AN45: не релевантно | AO45: =IF($C45=AO$2,0.3,"")
C46: Рабочий возраст | E46: Знаю что за метрика, но актуального значения нет под рукой | F46: (0,5 балл) | G46: 0.5 | I46: Знаю что за метрика, но актуального значения нет под рукой | N46: Знаю что за метрика, но актуального значения нет под рукой | S46: Знаю что за метрика, но актуального значения нет под рукой | X46: Знаю что за метрика, но актуального значения нет под рукой | AC46: Знаю что за метрика, но актуального значения нет под рукой | AH46: Знаю что за метрика, но актуального значения нет под рукой | AM46: Знаю что за метрика, но актуального значения нет под рукой
C47: Рабочий возраст | E47: Практически не работаю с этой метрикой напрямую | F47: (0 балл) | G47: 0 | I47: Практически не работаю с этой метрикой напрямую | N47: Практически не работаю с этой метрикой напрямую | S47: Практически не работаю с этой метрикой напрямую | X47: Практически не работаю с этой метрикой напрямую | AC47: Практически не работаю с этой метрикой напрямую | AH47: Практически не работаю с этой метрикой напрямую | AM47: Практически не работаю с этой метрикой напрямую
C48: Рабочий возраст | E48: Введите значение | I48: Введите значение | N48: Введите значение | S48: Введите значение - 2406 | T48: 1 | U48: релевантно -https://navigator.sigma.sbrf.ru/gdash/1000003450/1000035578?vmetric=%D0%90%D0%BA%D1%82%D0%B8%D0%B2%D0%BD%D0%B0%D1%8F%20%D0%BA%D0%BB%D0%B8%D0%B5%D0%BD%D1%82%D1%81%D0%BA%D0%B0%D1%8F%20%D0%B1%D0%B0%D0%B7%D0%B0%2C%20%D0%BC%D0%BB%D0%BD%20%D1%87%D0%B5%D0%BB&vQrt=2&vMode=1 | X48: Введите значение | AC48: Введите значение | AH48: Введите значение | AM48: Введите значение
C49: Доходный | D49: Метрика "Активная клиентская база" сегмента. На сколько активно вы работаете с данной метрикой? (только для доходных) | E49: Знаю значение, могу быстро найти в отчетности (укажите в поле ввода ниже) | F49: (1 балл) | G49: 1 | I49: Знаю значение, могу быстро найти в отчетности (укажите в поле ввода ниже) | J49: не релевантно | N49: Знаю значение, могу быстро найти в отчетности (укажите в поле ввода ниже) | O49: не релевантно | S49: Знаю значение, могу быстро найти в отчетности (укажите в поле ввода ниже) | T49: не релевантно | X49: Знаю значение, могу быстро найти в отчетности (укажите в поле ввода ниже) | Y49: не релевантно | AC49: Знаю значение, могу быстро найти в отчетности (укажите в поле ввода ниже) | AD49: 1 | AE49: =IF($C49=AE$2,0.25,"") -> 0.25 | AF49: =AE49*IF(AND(AD49=1,AD52=0),0.5,(IF(AD49=1,$G49,IF(AD50=1,$G50,IF(AD51=1,$G51,""))))) -> 0.25 | AG49: =AF49/AE49 -> 1 | AH49: Знаю значение, могу быстро найти в отчетности (укажите в поле ввода ниже) | AI49: 1 | AJ49: 0.25 | AK49: =AJ49*IF(AND(AI49=1,AI52=0),0.5,(IF(AI49=1,$G49,IF(AI50=1,$G50,IF(AI51=1,$G51,""))))) -> 0.25 | AL49: =AK49/AJ49 -> 1 | AM49: Знаю значение, могу быстро найти в отчетности (укажите в поле ввода ниже) | AN49: 1 | AO49: 0.25 | AP49: =AO49*IF(AND(AN49=1,AN52=0),0.5,(IF(AN49=1,$G49,IF(AN50=1,$G50,IF(AN51=1,$G51,""))))) -> 0.25 | AQ49: =AP49/AO49 -> 1
C50: Доходный | E50: Знаю что за метрика, но актуального значения нет под рукой | F50: (0,5 балл) | G50: 0.5 | I50: Знаю что за метрика, но актуального значения нет под рукой | N50: Знаю что за метрика, но актуального значения нет под рукой | S50: Знаю что за метрика, но актуального значения нет под рукой | X50: Знаю что за метрика, но актуального значения нет под рукой | AC50: Знаю что за метрика, но актуального значения нет под рукой | AH50: Знаю что за метрика, но актуального значения нет под рукой | AM50: Знаю что за метрика, но актуального значения нет под рукой
C51: Доходный | E51: Практически не работаю с этой метрикой напрямую | F51: (0 балл) | G51: 0 | I51: Практически не работаю с этой метрикой напрямую | N51: Практически не работаю с этой метрикой напрямую | S51: Практически не работаю с этой метрикой напрямую | X51: Практически не работаю с этой метрикой напрямую | AC51: Практически не работаю с этой метрикой напрямую | AH51: Практически не работаю с этой метрикой напрямую | AM51: Практически не работаю с этой метрикой напрямую
C52: Доходный | E52: Введите значение | I52: Введите значение | N52: Введите значение | S52: Введите значение | X52: Введите значение | AC52: Введите значение - Есть в собственном дэше сегмента на главном экране (https://navigator.sigma.sbrf.ru/gdash/1000000135) и в дэше CX (https://navigator.sigma.sbrf.ru/gdash/1000000301/1000002898) | AD52: 1 | AH52: 0,021615. https://navigator.sigma.sbrf.ru/gdash/1000000301/1000002898?segment=PB | AI52: 1 | AJ52: релевантно https://navigator.sigma.sbrf.ru/gdash/1000003450/1000038574?vmetric=%D0%90%D0%BA%D1%82%D0%B8%D0%B2%D0%BD%D0%B0%D1%8F%20%D0%BA%D0%BB%D0%B8%D0%B5%D0%BD%D1%82%D1%81%D0%BA%D0%B0%D1%8F%20%D0%B1%D0%B0%D0%B7%D0%B0%2C%20%D0%BC%D0%BB%D0%BD%20%D1%87%D0%B5%D0%BB&vQrt=2&vMode=1 | AM52: 4,45. https://navigator.sigma.sbrf.ru/gdash/12137/1000001022 | AN52: 1
C53: Доходный | D53: Метрика количества Major клиентов сегмента. На сколько активно вы работаете с данной метрикой? (только для доходных) | E53: Знаю значение, могу быстро найти в отчетности (укажите в поле ввода ниже) | F53: (1 балл) | G53: 1 | I53: Знаю значение, могу быстро найти в отчетности (укажите в поле ввода ниже) | J53: не релевантно | N53: Знаю значение, могу быстро найти в отчетности (укажите в поле ввода ниже) | O53: не релевантно | S53: Знаю значение, могу быстро найти в отчетности (укажите в поле ввода ниже) | T53: не релевантно | X53: Знаю значение, могу быстро найти в отчетности (укажите в поле ввода ниже) | Y53: не релевантно | AC53: Знаю значение, могу быстро найти в отчетности (укажите в поле ввода ниже) | AD53: 1 | AE53: 0.25 | AF53: =AE53*IF(AND(AD53=1,AD56=0),0.5,(IF(AD53=1,$G53,IF(AD54=1,$G54,IF(AD55=1,$G55,""))))) -> 0.25 | AG53: =AF53/AE53 -> 1 | AH53: Знаю значение, могу быстро найти в отчетности (укажите в поле ввода ниже) | AJ53: 0.25 | AK53: 0.25 | AL53: =AK53/AJ53 -> 1 | AM53: Знаю значение, могу быстро найти в отчетности (укажите в поле ввода ниже) | AN53: 1 | AO53: 0.25 | AP53: 0.25 | AQ53: =AP53/AO53 -> 1
C54: Доходный | E54: Знаю что за метрика, но актуального значения нет под рукой | F54: (0,5 балл) | G54: 0.5 | I54: Знаю что за метрика, но актуального значения нет под рукой | N54: Знаю что за метрика, но актуального значения нет под рукой | S54: Знаю что за метрика, но актуального значения нет под рукой | X54: Знаю что за метрика, но актуального значения нет под рукой | AC54: Знаю что за метрика, но актуального значения нет под рукой | AH54: Знаю что за метрика, но актуального значения нет под рукой | AI54: 1 | AM54: Знаю что за метрика, но актуального значения нет под рукой
C55: Доходный | E55: Практически не работаю с этой метрикой напрямую | F55: (0 балл) | G55: 0 | I55: Практически не работаю с этой метрикой напрямую | N55: Практически не работаю с этой метрикой напрямую | S55: Практически не работаю с этой метрикой напрямую | X55: Практически не работаю с этой метрикой напрямую | AC55: Практически не работаю с этой метрикой напрямую | AH55: Практически не работаю с этой метрикой напрямую | AI55: 1 | AM55: Практически не работаю с этой метрикой напрямую
C56: Доходный | E56: Введите значение | I56: Введите значение | N56: Введите значение | S56: Введите значение | X56: Введите значение | AC56: Введите значение - Есть в собственном дэше сегмента (https://navigator.sigma.sbrf.ru/gdash/1000000135) и в дэше УКО (https://navigator.sigma.sbrf.ru/gdash/1000000247/1000002344) | AD56: 1 | AH56: 0,01787. https://navigator.sigma.sbrf.ru/gdash/1000002349?type_of_view=1 | AI56: 1 | AM56: 2 543. https://navigator.sigma.sbrf.ru/gdash/12137/1000001022 | AN56: 1
C57: Доходный | D57: Метрика количества клиентов сегмента с 2+ нефинансовыми сервисами. На сколько активно вы работаете с данной метрикой? (только для доходных) | E57: Знаю значение, могу быстро найти в отчетности (укажите в поле ввода ниже) | F57: (1 балл) | G57: 1 | I57: Знаю значение, могу быстро найти в отчетности (укажите в поле ввода ниже) | J57: не релевантно | N57: Знаю значение, могу быстро найти в отчетности (укажите в поле ввода ниже) | O57: не релевантно | S57: Знаю значение, могу быстро найти в отчетности (укажите в поле ввода ниже) | T57: не релевантно | X57: Знаю значение, могу быстро найти в отчетности (укажите в поле ввода ниже) | Y57: не релевантно | AC57: Знаю значение, могу быстро найти в отчетности (укажите в поле ввода ниже) | AD57: 1 | AE57: 0.25 | AF57: =AE57*IF(AND(AD57=1,AD60=0),0.5,(IF(AD57=1,$G57,IF(AD58=1,$G58,IF(AD59=1,$G59,""))))) -> 0.25 | AG57: =AF57/AE57 -> 1 | AH57: Знаю значение, могу быстро найти в отчетности (укажите в поле ввода ниже) | AJ57: 0.25 | AK57: =AJ57*IF(AND(AI57=1,AI60=0),0.5,(IF(AI57=1,$G57,IF(AI58=1,$G58,IF(AI59=1,$G59,""))))) -> 0.125 | AL57: =AK57/AJ57 -> 0.5 | AM57: Знаю значение, могу быстро найти в отчетности (укажите в поле ввода ниже) | AN57: 1 | AO57: 0.25 | AP57: =AO57*IF(AND(AN57=1,AN60=0),0.5,(IF(AN57=1,$G57,IF(AN58=1,$G58,IF(AN59=1,$G59,""))))) -> 0.25 | AQ57: =AP57/AO57 -> 1
C58: Доходный | E58: Знаю что за метрика, но актуального значения нет под рукой | F58: (0,5 балл) | G58: 0.5 | I58: Знаю что за метрика, но актуального значения нет под рукой | N58: Знаю что за метрика, но актуального значения нет под рукой | S58: Знаю что за метрика, но актуального значения нет под рукой | X58: Знаю что за метрика, но актуального значения нет под рукой | AC58: Знаю что за метрика, но актуального значения нет под рукой | AH58: Знаю что за метрика, но актуального значения нет под рукой | AI58: 1 | AM58: Знаю что за метрика, но актуального значения нет под рукой
C59: Доходный | E59: Практически не работаю с этой метрикой напрямую | F59: (0 балл) | G59: 0 | I59: Практически не работаю с этой метрикой напрямую | N59: Практически не работаю с этой метрикой напрямую | S59: Практически не работаю с этой метрикой напрямую | X59: Практически не работаю с этой метрикой напрямую | AC59: Практически не работаю с этой метрикой напрямую | AH59: Практически не работаю с этой метрикой напрямую | AM59: Практически не работаю с этой метрикой напрямую
C60: Доходный | E60: Введите значение | I60: Введите значение | J60: не релевантно | N60: Введите значение | S60: Введите значение | X60: Введите значение | AC60: 60,05 | AD60: 1 | AE60: релевантно. Ссылка https://navigator.sigma.sbrf.ru/gdash/1000003450/1000038580?vmetric=%D0%90%D0%BA%D1%82%D0%B8%D0%B2%D0%BD%D0%B0%D1%8F%20%D0%BA%D0%BB%D0%B8%D0%B5%D0%BD%D1%82%D1%81%D0%BA%D0%B0%D1%8F%20%D0%B1%D0%B0%D0%B7%D0%B0%2C%20%D0%BC%D0%BB%D0%BD%20%D1%87%D0%B5%D0%BB&vQrt=2&vMode=1и | AH60: 0,003658. Запрос в Штабе у анаитиков | AI60: 1 | AM60: 0,48. https://navigator.sigma.sbrf.ru/gdash/12137/1000001022 | AN60: 1 | AO60: релевантно https://navigator.sigma.sbrf.ru/gdash/1000003450/1000038574?vmetric=%D0%90%D0%BA%D1%82%D0%B8%D0%B2%D0%BD%D0%B0%D1%8F%20%D0%BA%D0%BB%D0%B8%D0%B5%D0%BD%D1%82%D1%81%D0%BA%D0%B0%D1%8F%20%D0%B1%D0%B0%D0%B7%D0%B0%2C%20%D0%BC%D0%BB%D0%BD%20%D1%87%D0%B5%D0%BB&vQrt=2&vMode=1
C61: Доходный | D61: Метрика среднего дохода на одного клиента сегмента в месяц. На сколько активно вы работаете с данной метрикой? (только для доходных) | E61: Знаю значение, могу быстро найти в отчетности (укажите в поле ввода ниже) | F61: (1 балл) | G61: 1 | I61: Знаю значение, могу быстро найти в отчетности (укажите в поле ввода ниже) | N61: Знаю значение, могу быстро найти в отчетности (укажите в поле ввода ниже) | O61: не релевантно | S61: Знаю значение, могу быстро найти в отчетности (укажите в поле ввода ниже) | T61: не релевантно | X61: Знаю значение, могу быстро найти в отчетности (укажите в поле ввода ниже) | Y61: не релевантно | AC61: Знаю значение, могу быстро найти в отчетности (укажите в поле ввода ниже) | AE61: 0.25 | AF61: =AE61*IF(AND(AD61=1,AD64=0),0.5,(IF(AD61=1,$G61,IF(AD62=1,$G62,IF(AD63=1,$G63,""))))) -> 0.125 | AG61: =AF61/AE61 -> 0.5 | AH61: Знаю значение, могу быстро найти в отчетности (укажите в поле ввода ниже) | AI61: 1 | AJ61: 0.25 | AK61: =AJ61*IF(AND(AI61=1,AI64=0),0.5,(IF(AI61=1,$G61,IF(AI62=1,$G62,IF(AI63=1,$G63,""))))) -> 0.25 | AL61: =AK61/AJ61 -> 1 | AM61: Знаю значение, могу быстро найти в отчетности (укажите в поле ввода ниже) | AO61: 0.25 | AP61: =AO61*IF(AND(AN61=1,AN64=0),0.5,(IF(AN61=1,$G61,IF(AN62=1,$G62,IF(AN63=1,$G63,""))))) -> 0.125 | AQ61: =AP61/AO61 -> 0.5
C62: Доходный | E62: Знаю что за метрика, но актуального значения нет под рукой | F62: (0,5 балл) | G62: 0.5 | I62: Знаю что за метрика, но актуального значения нет под рукой | N62: Знаю что за метрика, но актуального значения нет под рукой | S62: Знаю что за метрика, но актуального значения нет под рукой | X62: Знаю что за метрика, но актуального значения нет под рукой | AC62: Знаю что за метрика, но актуального значения нет под рукой | AD62: 1 | AH62: Знаю что за метрика, но актуального значения нет под рукой | AM62: Знаю что за метрика, но актуального значения нет под рукой | AN62: 1
C63: Доходный | E63: Практически не работаю с этой метрикой напрямую | F63: (0 балл) | G63: 0 | I63: Практически не работаю с этой метрикой напрямую | N63: Практически не работаю с этой метрикой напрямую | S63: Практически не работаю с этой метрикой напрямую | X63: Практически не работаю с этой метрикой напрямую | AC63: Практически не работаю с этой метрикой напрямую | AH63: Практически не работаю с этой метрикой напрямую | AM63: Практически не работаю с этой метрикой напрямую
C64: Доходный | E64: Введите значение | I64: Введите значение | N64: Введите значение | S64: Введите значение | X64: Введите значение | AC64: Введите значение - https://sm.data.omega.sbrf.ru/subscriptions/2726be70-66c5-44a2-a1de-4c2b5823bf9c | AD64: 1 | AH64: 220 739. https://navigator.sigma.sbrf.ru/gdash/1000000301/1000002898?segment=PB | AI64: 1 | AM64: https://navigator.sigma.sbrf.ru/gdash/12137/1000001022 | AN64: 1 | AO64: релевантно https://navigator.sigma.sbrf.ru/gdash/1000003450/1000038574?vmetric=%D0%90%D0%BA%D1%82%D0%B8%D0%B2%D0%BD%D0%B0%D1%8F%20%D0%BA%D0%BB%D0%B8%D0%B5%D0%BD%D1%82%D1%81%D0%BA%D0%B0%D1%8F%20%D0%B1%D0%B0%D0%B7%D0%B0%2C%20%D0%BC%D0%BB%D0%BD%20%D1%87%D0%B5%D0%BB&vQrt=2&vMode=1
A65: 2 | D65: Какими инструментами вы пользуетесь для мониторинга метрик из вопросов выше: | E65: Дашборд в Навигаторе (доступны все метрики) | H65: 0.5 | I65: Дашборд в Навигаторе (доступны все метрики) | K65: 0.5 | L65: =IF(J65=1,0.5,IF(AND(J68=1,J67=""),0.5,IF(OR(J67=1,J66=1),0.25,0))) -> 0.25 | M65: =IFERROR(IF(K65=0,"",L65/K65),"") -> 0.5 | N65: Дашборд в Навигаторе (доступны все метрики) | P65: 0.5 | Q65: =IF(O65=1,0.5,IF(AND(O68=1,O67=""),0.5,IF(OR(O67=1,O66=1),0.25,0))) -> 0.25 | R65: =IFERROR(IF(P65=0,"",Q65/P65),"") -> 0.5 | S65: Дашборд в Навигаторе (доступны все метрики) | U65: 0.5 | V65: =IF(T65=1,0.5,IF(AND(T68=1,T67=""),0.5,IF(OR(T67=1,T66=1),0.25,0))) -> 0.25 | W65: =IFERROR(IF(U65=0,"",V65/U65),"") -> 0.5 | X65: Дашборд в Навигаторе (доступны все метрики) | Z65: 0.5 | AA65: =IF(Y65=1,0.5,IF(AND(Y68=1,Y67=""),0.5,IF(OR(Y67=1,Y66=1),0.25,0))) -> 0.5 | AB65: =IFERROR(IF(Z65=0,"",AA65/Z65),"") -> 1 | AC65: Дашборд в Навигаторе (доступны все метрики) | AD65: 1 | AE65: 0.5 | AF65: =IF(AD65=1,0.5,IF(AND(AD68=1,AD67=""),0.5,IF(OR(AD67=1,AD66=1),0.25,0))) -> 0.5 | AG65: =IFERROR(IF(AE65=0,"",AF65/AE65),"") -> 1 | AH65: Дашборд в Навигаторе (доступны все метрики) | AJ65: 0.5 | AK65: =IF(AI65=1,0.5,IF(AND(AI68=1,AI67=""),0.5,IF(OR(AI67=1,AI66=1),0.25,0))) -> 0.25 | AL65: =IFERROR(IF(AJ65=0,"",AK65/AJ65),"") -> 0.5 | AM65: Дашборд в Навигаторе (доступны все метрики) | AN65: 1 | AO65: 0.5 | AP65: =IF(AN65=1,0.5,IF(AND(AN68=1,AN67=""),0.5,IF(OR(AN67=1,AN66=1),0.25,0))) -> 0.5 | AQ65: =IFERROR(IF(AO65=0,"",AP65/AO65),"") -> 1
E66: Дашборд в Навигаторе (доступна часть метрик) | I66: Дашборд в Навигаторе (доступна часть метрик) | J66: 1 | N66: Дашборд в Навигаторе (доступна часть метрик) | O66: 1 | S66: Дашборд в Навигаторе (доступна часть метрик) | T66: 1 | X66: Дашборд в Навигаторе (доступна часть метрик) | Y66: 1 | AC66: Дашборд в Навигаторе (доступна часть метрик) | AH66: Дашборд в Навигаторе (доступна часть метрик) | AI66: 1 | AM66: Дашборд в Навигаторе (доступна часть метрик)
E67: Запрашиваете необходимую информацию у аналитиков | I67: Запрашиваете необходимую информацию у аналитиков | J67: 1 | N67: Запрашиваете необходимую информацию у аналитиков | O67: 1 | S67: Запрашиваете необходимую информацию у аналитиков | T67: 1 | X67: Запрашиваете необходимую информацию у аналитиков | AC67: Запрашиваете необходимую информацию у аналитиков | AH67: Запрашиваете необходимую информацию у аналитиков | AI67: 1 | AM67: Запрашиваете необходимую информацию у аналитиков
E68: Собственная отчетность сегмента (не Навигатор) | I68: Собственная отчетность сегмента (не Навигатор) | N68: Собственная отчетность сегмента (не Навигатор) | O68: 1 | S68: Собственная отчетность сегмента (не Навигатор) | T68: 1 | X68: Собственная отчетность сегмента (не Навигатор) | Y68: 1 | AC68: Собственная отчетность сегмента (не Навигатор) | AH68: Собственная отчетность сегмента (не Навигатор) | AM68: Собственная отчетность сегмента (не Навигатор) | AN68: 1
E69: Свой вариант ответа | I69: Свой вариант ответа | N69: Свой вариант ответа | S69: Свой вариант ответа | X69: Свой вариант ответа | AC69: Свой вариант ответа | AH69: Свой вариант ответа | AM69: Свой вариант ответа
E70: Затрудняюсь ответить | I70: Затрудняюсь ответить | N70: Затрудняюсь ответить | S70: Затрудняюсь ответить | X70: Затрудняюсь ответить | Y70: КАП, Greenplum | AC70: Затрудняюсь ответить | AH70: Затрудняюсь ответить | AM70: Затрудняюсь ответить
A71: 3 | B71: Блок 2. Цели, факторный анализ, прогноз | D71: Цели выведены на мониторинг | E71: Цели уровня ЛЮ-ЛТ выведены на мониторинг- настроено регулярное обновление (1 балл) - выведено в Навигатор *1 ( +90% целей) - своя отчетность *0,5 | H71: 1 | I71: Цели | J71: Не в Навигаторе | K71: =$H71 -> 1 | L71: =IF(J71="Отсутствует",0,IF(AND(J71="В Навигаторе",L223=1),1,IF(AND(J71="В Навигаторе",L223<>1),0,IF(J71="Не в Навигаторе",0.5,0)))) -> 0.5 | M71: =IFERROR(IF(K71=0,"",L71/K71),"") -> 0.5 | N71: Цели | O71: В Навигаторе | P71: =$H71 -> 1 | Q71: =IF(O71="Отсутствует",0,IF(AND(O71="В Навигаторе",Q223=1),1,IF(AND(O71="В Навигаторе",Q223<>1),0,IF(O71="Не в Навигаторе",0.5,0)))) -> 1 | R71: =IFERROR(IF(P71=0,"",Q71/P71),"") -> 1 | S71: Цели | T71: В Навигаторе | U71: =$H71 -> 1 | V71: =IF(T71="Отсутствует",0,IF(AND(T71="В Навигаторе",V223=1),1,IF(AND(T71="В Навигаторе",V223<>1),0,IF(T71="Не в Навигаторе",0.5,0)))) -> 1 | W71: =IFERROR(IF(U71=0,"",V71/U71),"") -> 1 | X71: Цели | Y71: В Навигаторе | Z71: =$H71 -> 1 | AA71: =IF(Y71="Отсутствует",0,IF(AND(Y71="В Навигаторе",AA223=1),1,IF(AND(Y71="В Навигаторе",AA223<>1),0,IF(Y71="Не в Навигаторе",0.5,0)))) -> 1 | AB71: =IFERROR(IF(Z71=0,"",AA71/Z71),"") -> 1 | AC71: Цели | AD71: В Навигаторе | AE71: =$H71 -> 1 | AF71: =IF(AD71="Отсутствует",0,IF(AND(AD71="В Навигаторе",AF223=1),1,IF(AND(AD71="В Навигаторе",AF223<>1),0,IF(AD71="Не в Навигаторе",0.5,0)))) -> 1 | AG71: =IFERROR(IF(AE71=0,"",AF71/AE71),"") -> 1 | AH71: Цели | AI71: В Навигаторе | AJ71: =$H71 -> 1 | AK71: =IF(AI71="Отсутствует",0,IF(AND(AI71="В Навигаторе",AK223=1),1,IF(AND(AI71="В Навигаторе",AK223<>1),0,IF(AI71="Не в Навигаторе",0.5,0)))) -> 1 | AL71: =IFERROR(IF(AJ71=0,"",AK71/AJ71),"") -> 1 | AM71: Цели | AN71: В Навигаторе | AO71: =$H71 -> 1 | AP71: =IF(AN71="Отсутствует",0,IF(AND(AN71="В Навигаторе",AP223=1),1,IF(AND(AN71="В Навигаторе",AP223<>1),0,IF(AN71="Не в Навигаторе",0.5,0)))) -> 1 | AQ71: =IFERROR(IF(AO71=0,"",AP71/AO71),"") -> 1
A72: 4 | D72: По целям есть факторный анализ (драйверы 1-2 уровня) | E72: драйверы согласно модели БП (1 балл) - выведено в Навигатор *1 ( +90% целей) - своя отчетность *0,5 | H72: 1 | I72: Факторный анализ (драйверы 1-2 уровня согласно модели БП) | J72: В Навигаторе | K72: =$H72 -> 1 | L72: =IF(J72="Отсутствует",0,IF(AND(J72="В Навигаторе",L224=1),1,IF(AND(J72="В Навигаторе",L224<>1),0,IF(J72="Не в Навигаторе",0.5,0)))) -> 1 | M72: =IFERROR(IF(K72=0,"",L72/K72),"") -> 1 | N72: Факторный анализ (драйверы 1-2 уровня согласно модели БП) | O72: Не в Навигаторе | P72: =$H72 -> 1 | Q72: =IF(O72="Отсутствует",0,IF(AND(O72="В Навигаторе",Q224=1),1,IF(AND(O72="В Навигаторе",Q224<>1),0,IF(O72="Не в Навигаторе",0.5,0)))) -> 0.5 | R72: =IFERROR(IF(P72=0,"",Q72/P72),"") -> 0.5 | S72: Факторный анализ (драйверы 1-2 уровня согласно модели БП) | T72: Не в Навигаторе | U72: =$H72 -> 1 | V72: =IF(T72="Отсутствует",0,IF(AND(T72="В Навигаторе",V224=1),1,IF(AND(T72="В Навигаторе",V224<>1),0,IF(T72="Не в Навигаторе",0.5,0)))) -> 0.5 | W72: =IFERROR(IF(U72=0,"",V72/U72),"") -> 0.5 | X72: Факторный анализ (драйверы 1-2 уровня согласно модели БП) | Y72: Не в Навигаторе | Z72: =$H72 -> 1 | AA72: =IF(Y72="Отсутствует",0,IF(AND(Y72="В Навигаторе",AA224=1),1,IF(AND(Y72="В Навигаторе",AA224<>1),0,IF(Y72="Не в Навигаторе",0.5,0)))) -> 0.5 | AB72: =IFERROR(IF(Z72=0,"",AA72/Z72),"") -> 0.5 | AC72: Факторный анализ (драйверы 1-2 уровня согласно модели БП) | AD72: Не в Навигаторе | AE72: =$H72 -> 1 | AF72: =IF(AD72="Отсутствует",0,IF(AND(AD72="В Навигаторе",AF224=1),1,IF(AND(AD72="В Навигаторе",AF224<>1),0,IF(AD72="Не в Навигаторе",0.5,0)))) -> 0.5 | AG72: =IFERROR(IF(AE72=0,"",AF72/AE72),"") -> 0.5 | AH72: Факторный анализ (драйверы 1-2 уровня согласно модели БП) | AI72: Не в Навигаторе | AJ72: =$H72 -> 1 | AK72: =IF(AI72="Отсутствует",0,IF(AND(AI72="В Навигаторе",AK224=1),1,IF(AND(AI72="В Навигаторе",AK224<>1),0,IF(AI72="Не в Навигаторе",0.5,0)))) -> 0.5 | AL72: =IFERROR(IF(AJ72=0,"",AK72/AJ72),"") -> 0.5 | AM72: Факторный анализ (драйверы 1-2 уровня согласно модели БП) | AN72: Не в Навигаторе | AO72: =$H72 -> 1 | AP72: =IF(AN72="Отсутствует",0,IF(AND(AN72="В Навигаторе",AP224=1),1,IF(AND(AN72="В Навигаторе",AP224<>1),0,IF(AN72="Не в Навигаторе",0.5,0)))) -> 0.5 | AQ72: =IFERROR(IF(AO72=0,"",AP72/AO72),"") -> 0.5
A73: 5 | D73: Есть прогноз по целям | E73: прогноз по целям (1 балла) - выведено в Навигатор *1 (+90% целей) - своя отчетность *0,5 | H73: 1 | I73: Прогноз по целям | J73: В Навигаторе | K73: =$H73 -> 1 | L73: =IF(J73="Отсутствует",0,IF(AND(J73="В Навигаторе",L225=1),1,IF(AND(J73="В Навигаторе",L225<>1),0,IF(J73="Не в Навигаторе",0.5,0)))) -> 0 | M73: =IFERROR(IF(K73=0,"",L73/K73),"") -> 0 | N73: Прогноз по целям | O73: В Навигаторе | P73: =$H73 -> 1 | Q73: =IF(O73="Отсутствует",0,IF(AND(O73="В Навигаторе",Q225=1),1,IF(AND(O73="В Навигаторе",Q225<>1),0,IF(O73="Не в Навигаторе",0.5,0)))) -> 0 | R73: =IFERROR(IF(P73=0,"",Q73/P73),"") -> 0 | S73: Прогноз по целям | T73: В Навигаторе | U73: =$H73 -> 1 | V73: =IF(T73="Отсутствует",0,IF(AND(T73="В Навигаторе",V225=1),1,IF(AND(T73="В Навигаторе",V225<>1),0,IF(T73="Не в Навигаторе",0.5,0)))) -> 0 | W73: =IFERROR(IF(U73=0,"",V73/U73),"") -> 0 | X73: Прогноз по целям | Y73: Не в Навигаторе | Z73: =$H73 -> 1 | AA73: =IF(Y73="Отсутствует",0,IF(AND(Y73="В Навигаторе",AA225=1),1,IF(AND(Y73="В Навигаторе",AA225<>1),0,IF(Y73="Не в Навигаторе",0.5,0)))) -> 0.5 | AB73: =IFERROR(IF(Z73=0,"",AA73/Z73),"") -> 0.5 | AC73: Прогноз по целям | AD73: В Навигаторе | AE73: =$H73 -> 1 | AF73: =IF(AD73="Отсутствует",0,IF(AND(AD73="В Навигаторе",AF225=1),1,IF(AND(AD73="В Навигаторе",AF225<>1),0,IF(AD73="Не в Навигаторе",0.5,0)))) -> 0 | AG73: =IFERROR(IF(AE73=0,"",AF73/AE73),"") -> 0 | AH73: Прогноз по целям | AI73: Не в Навигаторе | AJ73: =$H73 -> 1 | AK73: =IF(AI73="Отсутствует",0,IF(AND(AI73="В Навигаторе",AK225=1),1,IF(AND(AI73="В Навигаторе",AK225<>1),0,IF(AI73="Не в Навигаторе",0.5,0)))) -> 0.5 | AL73: =IFERROR(IF(AJ73=0,"",AK73/AJ73),"") -> 0.5 | AM73: Прогноз по целям | AN73: В Навигаторе | AO73: =$H73 -> 1 | AP73: =IF(AN73="Отсутствует",0,IF(AND(AN73="В Навигаторе",AP225=1),1,IF(AND(AN73="В Навигаторе",AP225<>1),0,IF(AN73="Не в Навигаторе",0.5,0)))) -> 0 | AQ73: =IFERROR(IF(AO73=0,"",AP73/AO73),"") -> 0
E74: Прогноз по драйверам | I74: Прогноз по драйверам | N74: Прогноз по драйверам | O74: Не в Навигаторе | S74: Прогноз по драйверам | T74: В Навигаторе | X74: Прогноз по драйверам | Y74: Не в Навигаторе | AC74: Прогноз по драйверам | AD74: Не в Навигаторе | AH74: Прогноз по драйверам | AI74: Данные с задержкой на 1 мес и более | AM74: Прогноз по драйверам | AN74: Не в Навигаторе
A75: 9 | B75: Блок 3. Воронки привлечения и оттока | C75: Отчетность по воронке привечения | D75: Настроена ли регулярная отчётность по воронке привлечения? | E75: Да | H75: 0.5 | I75: Да | J75: 1 | K75: =IF(J77=1,"не релевантно",0.5) -> 0.5 | L75: =IF(J75=1,0.5,0)*L86 -> 0.5 | M75: =IFERROR(IF(K75="Не релевантно",K75,IF(K75=0,"",L75/K75)),"") -> 1 | N75: Да | O75: 1 | P75: =IF(O77=1,"не релевантно",0.5) -> 0.5 | Q75: =IF(O75=1,0.5,0)*Q86 -> 0.25 | R75: =IFERROR(IF(P75="Не релевантно",P75,IF(P75=0,"",Q75/P75)),"") -> 0.5 | S75: Да | T75: 1 | U75: =IF(T77=1,"не релевантно",0.5) -> 0.5 | V75: =IF(T75=1,0.5,0)*V86 -> 0.25 | W75: =IFERROR(IF(U75="Не релевантно",U75,IF(U75=0,"",V75/U75)),"") -> 0.5 | X75: Да | Z75: =IF(Y77=1,"не релевантно",0.5) -> 0.5 | AA75: =IF(Y75=1,0.5,0)*AA86 -> 0 | AB75: =IFERROR(IF(Z75="Не релевантно",Z75,IF(Z75=0,"",AA75/Z75)),"") -> 0 | AC75: Да | AD75: 1 | AE75: =IF(AD77=1,"не релевантно",0.5) -> 0.5 | AF75: =IF(AD75=1,0.5,0)*AF86 -> 0.5 | AG75: =IFERROR(IF(AE75="Не релевантно",AE75,IF(AE75=0,"",AF75/AE75)),"") -> 1 | AH75: Да | AI75: 1 | AJ75: =IF(AI77=1,"не релевантно",0.5) -> 0.5 | AK75: =IF(AI75=1,0.5,0)*AK86 -> 0.5 | AL75: =IFERROR(IF(AJ75="Не релевантно",AJ75,IF(AJ75=0,"",AK75/AJ75)),"") -> 1 | AM75: Да | AN75: 1 | AO75: =IF(AN77=1,"не релевантно",0.5) -> 0.5 | AP75: =IF(AN75=1,0.5,0)*AP86 -> 0.25 | AQ75: =IFERROR(IF(AO75="Не релевантно",AO75,IF(AO75=0,"",AP75/AO75)),"") -> 0.5
E76: Нет | I76: Нет | N76: Нет | S76: Нет | X76: Нет | Y76: 1 | AC76: Нет | AH76: Нет | AM76: Нет
E77: Не релевантно для вашего сегмента | I77: Не релевантно для вашего сегмента | N77: Не релевантно для вашего сегмента | S77: Не релевантно для вашего сегмента | X77: Не релевантно для вашего сегмента | AC77: Не релевантно для вашего сегмента | AH77: Не релевантно для вашего сегмента | AM77: Не релевантно для вашего сегмента
E78: Затрудняюсь ответить | I78: Затрудняюсь ответить | N78: Затрудняюсь ответить | S78: Затрудняюсь ответить | X78: Затрудняюсь ответить | AC78: Затрудняюсь ответить | AH78: Затрудняюсь ответить | AM78: Затрудняюсь ответить
A79: 10 | C79: Полнота отчета по воронке | D79: Что включает воронка привлечения? | E79: Источники привлечения (самоходы, внешние привлечения, кампейнинг, кросс-перетоки) | H79: 0.5 | I79: Источники привлечения (самоходы, внешние привлечения, кампейнинг, кросс-перетоки) | J79: 1 | K79: 0.5 | L79: =IF(SUM(J79:J84) >5,0.5,IF(SUM(J79:J84) >2,0.25,0)) -> 0.25 | M79: =IFERROR(IF(K79=0,"",L79/K79),"") -> 0.5 | N79: Источники привлечения (самоходы, внешние привлечения, кампейнинг, кросс-перетоки) | P79: 0.5 | Q79: =IF(SUM(O79:O84) >5,0.5,IF(SUM(O79:O84) >2,0.25,0)) -> 0.25 | R79: =IFERROR(IF(P79=0,"",Q79/P79),"") -> 0.5 | S79: Источники привлечения (самоходы, внешние привлечения, кампейнинг, кросс-перетоки) | T79: 1 | U79: 0.5 | V79: =IF(SUM(T79:T84) >5,0.5,IF(SUM(T79:T84) >2,0.25,0)) -> 0.25 | W79: =IFERROR(IF(U79=0,"",V79/U79),"") -> 0.5 | X79: Источники привлечения (самоходы, внешние привлечения, кампейнинг, кросс-перетоки) | Y79: не релевантно | Z79: 0.5 | AA79: =IF(SUM(Y79:Y84) >5,0.5,IF(SUM(Y79:Y84) >2,0.25,0)) -> 0 | AB79: =IFERROR(IF(Z79=0,"",AA79/Z79),"") -> 0 | AC79: Источники привлечения (самоходы, внешние привлечения, кампейнинг, кросс-перетоки) | AE79: 0.5 | AF79: =IF(SUM(AD79:AD84) >5,0.5,IF(SUM(AD79:AD84) >2,0.25,0)) -> 0.25 | AG79: =IFERROR(IF(AE79=0,"",AF79/AE79),"") -> 0.5 | AH79: Источники привлечения (самоходы, внешние привлечения, кампейнинг, кросс-перетоки) | AI79: Данные по источникам привлечения частично реализованы в разрезе механики привлечения. Тип привлечения в процессе реализации | AJ79: 0.5 | AK79: =IF(SUM(AI79:AI84) >5,0.5,IF(SUM(AI79:AI84) >2,0.25,0)) -> 0.25 | AL79: =IFERROR(IF(AJ79=0,"",AK79/AJ79),"") -> 0.5 | AM79: Источники привлечения (самоходы, внешние привлечения, кампейнинг, кросс-перетоки) | AO79: 0.5 | AP79: =IF(SUM(AN79:AN84) >5,0.5,IF(SUM(AN79:AN84) >2,0.25,0)) -> 0.25 | AQ79: =IFERROR(IF(AO79=0,"",AP79/AO79),"") -> 0.5
E80: Пошаговая воронка (CJM клиентский путь) | I80: Пошаговая воронка (CJM клиентский путь) | J80: 1 | N80: Пошаговая воронка (CJM клиентский путь) | O80: 1 | S80: Пошаговая воронка (CJM клиентский путь) | T80: 1 | X80: Пошаговая воронка (CJM клиентский путь) | AC80: Пошаговая воронка (CJM клиентский путь) | AH80: Пошаговая воронка (CJM клиентский путь) | AM80: Пошаговая воронка (CJM клиентский путь)
E81: CR (% конверсии) | I81: CR (% конверсии) | N81: CR (% конверсии) | O81: 1 | S81: CR (% конверсии) | T81: 1 | X81: CR (% конверсии) | AC81: CR (% конверсии) | AD81: 1 | AH81: CR (% конверсии) | AI81: 1 | AM81: CR (% конверсии) | AN81: 1
E82: Объёмы | I82: Объёмы | N82: Объёмы | O82: 1 | S82: Объёмы | T82: 1 | X82: Объёмы | AC82: Объёмы | AD82: 1 | AH82: Объёмы | AI82: 1 | AM82: Объёмы | AN82: 1
E83: Механики привлечения | I83: Механики привлечения | J83: 1 | N83: Механики привлечения | S83: Механики привлечения | X83: Механики привлечения | AC83: Механики привлечения | AD83: 1 | AH83: Механики привлечения | AI83: 1 | AM83: Механики привлечения | AN83: 1
E84: Сегментный/ кагортный разрез | I84: Сегментный/ кагортный разрез | N84: Сегментный/ кагортный разрез | O84: 1 | S84: Сегментный/ кагортный разрез | T84: 1 | X84: Сегментный/ кагортный разрез | AC84: Сегментный/ кагортный разрез | AH84: Сегментный/ кагортный разрез | AI84: 1 | AM84: Сегментный/ кагортный разрез | AN84: 1
E85: Затрудняюсь ответить | I85: Затрудняюсь ответить | N85: Затрудняюсь ответить | S85: Затрудняюсь ответить | X85: Затрудняюсь ответить | AC85: Затрудняюсь ответить | AD85: Изменила | AH85: Затрудняюсь ответить | AM85: Затрудняюсь ответить | AN85: Изменила
A86: 11 | D86: Какая регулярность обновления отчета по воронке привлечения? | E86: Автоматически (daily или weekly) | H86: 1 | I86: Автоматически (daily или weekly) | J86: 1 | L86: =IF(J86=1,1,0.5) -> 1 | N86: Автоматически (daily или weekly) | Q86: =IF(O86=1,1,0.5) -> 0.5 | S86: Автоматически (daily или weekly) | V86: =IF(T86=1,1,0.5) -> 0.5 | X86: Автоматически (daily или weekly) | Y86: не релевантно | AA86: =IF(Y86=1,1,0.5) -> 0.5 | AC86: Автоматически (daily или weekly) | AD86: 1 | AF86: =IF(AD86=1,1,0.5) -> 1 | AH86: Автоматически (daily или weekly) | AI86: 1 | AK86: =IF(AI86=1,1,0.5) -> 1 | AM86: Автоматически (daily или weekly) | AP86: =IF(AN86=1,1,0.5) -> 0.5
E87: По запросу | I87: По запросу | N87: По запросу | O87: 1 | S87: По запросу | T87: 1 | X87: По запросу | AC87: По запросу | AH87: По запросу | AM87: По запросу | AN87: 1
E88: Затрудняюсь ответить | I88: Затрудняюсь ответить | N88: Затрудняюсь ответить | S88: Затрудняюсь ответить | X88: Затрудняюсь ответить | AC88: Затрудняюсь ответить | AH88: Затрудняюсь ответить | AM88: Затрудняюсь ответить
D89: Приложите ссылку на отчет воронки привлечения | I89: нет ответа | N89: рассылка в почте от аналитиков, вручную еженедельно | S89: Отчет будет обновляться ежемесячно. Дашборд выводится в пром до 30.06. Пока ссылки нет. Часть В2С - воронка по оттокам | T89: Изменила | U89: ссылка на дэшборд оттока зарплатников (воронки оттоков) https://navigator.sigma.sbrf.ru/gdash/1000006592#eyJ3aWRnZXRzIjp7IjEwMDA1MjYyNTQiOnsibW9kaWZpZWRSb3dzIjp7IjUiOjAsIjkiOjB9fX19 | Y89: не релевантно | AC89: https://navigator.sigma.sbrf.ru/gdash/1000000135/1000046561 | AH89: Еженедельно. по запросу, по факту закрытия кампании | AM89: https://confluence.sberbank.ru/pages/viewpage.action?pageId=6699321962
A90: 12 | D90: Настроена ли регулярная отчётность по воронке оттока? | E90: Да | I90: Да | J90: 1 | K90: =IF(J92=1,"не релевантно",0.5) -> 0.5 | L90: =IF(J90=1,0.5,0)*L101 -> 0.25 | M90: =IFERROR(IF(K90="Не релевантно",K90,IF(K90=0,"",L90/K90)),"") -> 0.5 | N90: Да | P90: =IF(O92=1,"не релевантно",0.5) -> 0.5 | Q90: =IF(O90=1,0.5,0)*Q101 -> 0 | R90: =IFERROR(IF(P90="Не релевантно",P90,IF(P90=0,"",Q90/P90)),"") -> 0 | S90: Да | T90: 1 | U90: =IF(T92=1,"не релевантно",0.5) -> 0.5 | V90: =IF(T90=1,0.5,0)*V101 -> 0.25 | W90: =IFERROR(IF(U90="Не релевантно",U90,IF(U90=0,"",V90/U90)),"") -> 0.5 | X90: Да | Z90: =IF(Y92=1,"не релевантно",0.5) -> 0.5 | AA90: =IF(Y90=1,0.5,0)*AA101 -> 0 | AB90: =IFERROR(IF(Z90="Не релевантно",Z90,IF(Z90=0,"",AA90/Z90)),"") -> 0 | AC90: Да | AE90: =IF(AD92=1,"не релевантно",0.5) -> 0.5 | AF90: =IF(AD90=1,0.5,0)*AF101 -> 0 | AG90: =IFERROR(IF(AE90="Не релевантно",AE90,IF(AE90=0,"",AF90/AE90)),"") -> 0 | AH90: Да | AI90: 1 | AJ90: =IF(AI92=1,"не релевантно",0.5) -> 0.5 | AK90: =IF(AI90=1,0.5,0)*AK101 -> 0.5 | AL90: =IFERROR(IF(AJ90="Не релевантно",AJ90,IF(AJ90=0,"",AK90/AJ90)),"") -> 1 | AM90: Да | AO90: =IF(AN92=1,"не релевантно",0.5) -> 0.5 | AP90: =IF(AN90=1,0.5,0)*AP101 -> 0 | AQ90: =IFERROR(IF(AO90="Не релевантно",AO90,IF(AO90=0,"",AP90/AO90)),"") -> 0
E91: Нет | I91: Нет | N91: Нет | O91: 1 | S91: Нет | X91: Нет | Y91: 1 | AC91: Нет | AD91: 1 | AH91: Нет | AM91: Нет | AN91: 1
E92: Не релевантно для вашего сегмента | I92: Не релевантно для вашего сегмента | N92: Не релевантно для вашего сегмента | S92: Не релевантно для вашего сегмента | X92: Не релевантно для вашего сегмента | AC92: Не релевантно для вашего сегмента | AH92: Не релевантно для вашего сегмента | AM92: Не релевантно для вашего сегмента
E93: Затрудняюсь ответить | I93: Затрудняюсь ответить | N93: Затрудняюсь ответить | S93: Затрудняюсь ответить | X93: Затрудняюсь ответить | AC93: Затрудняюсь ответить | AH93: Затрудняюсь ответить | AM93: Затрудняюсь ответить
A94: 13 | D94: Что включает воронка оттока? | E94: Предотточные клиенты | I94: Предотточные клиенты | J94: 1 | K94: =IF(K90="не релевантно","",0.5) -> 0.5 | L94: =IF(SUM(J94:J99)>5,0.5,IF(SUM(J94:J99)>2,0.25,0)) -> 0.25 | M94: =IFERROR(IF(K94="Не релевантно",K94,IF(K94=0,"",L94/K94)),"") -> 0.5 | N94: Предотточные клиенты | O94: не релевантно | P94: =IF(P90="не релевантно","",0.5) -> 0.5 | Q94: =IF(SUM(O94:O99)>5,0.5,IF(SUM(O94:O99)>2,0.25,0)) -> 0 | R94: =IFERROR(IF(P94="Не релевантно",P94,IF(P94=0,"",Q94/P94)),"") -> 0 | S94: Предотточные клиенты | T94: 1 | U94: =IF(U90="не релевантно","",0.5) -> 0.5 | V94: =IF(SUM(T94:T99)>5,0.5,IF(SUM(T94:T99)>2,0.25,0)) -> 0.25 | W94: =IFERROR(IF(U94="Не релевантно",U94,IF(U94=0,"",V94/U94)),"") -> 0.5 | X94: Предотточные клиенты | Y94: не релевантно | Z94: =IF(Z90="не релевантно","",0.5) -> 0.5 | AA94: =IF(SUM(Y94:Y99)>5,0.5,IF(SUM(Y94:Y99)>2,0.25,0)) -> 0 | AB94: =IFERROR(IF(Z94="Не релевантно",Z94,IF(Z94=0,"",AA94/Z94)),"") -> 0 | AC94: Предотточные клиенты | AD94: не релевантно | AE94: =IF(AE90="не релевантно","",0.5) -> 0.5 | AF94: =IF(SUM(AD94:AD99)>5,0.5,IF(SUM(AD94:AD99)>2,0.25,0)) -> 0 | AG94: =IFERROR(IF(AE94="Не релевантно",AE94,IF(AE94=0,"",AF94/AE94)),"") -> 0 | AH94: Предотточные клиенты | AJ94: =IF(AJ90="не релевантно","",0.5) -> 0.5 | AK94: =IF(SUM(AI94:AI99)>5,0.5,IF(SUM(AI94:AI99)>2,0.25,0)) -> 0.25 | AL94: =IFERROR(IF(AJ94="Не релевантно",AJ94,IF(AJ94=0,"",AK94/AJ94)),"") -> 0.5 | AM94: Предотточные клиенты | AN94: не релевантно | AO94: =IF(AO90="не релевантно","",0.5) -> 0.5 | AP94: =IF(SUM(AN94:AN99)>5,0.5,IF(SUM(AN94:AN99)>2,0.25,0)) -> 0 | AQ94: =IFERROR(IF(AO94="Не релевантно",AO94,IF(AO94=0,"",AP94/AO94)),"") -> 0
E95: Пошаговая воронка | I95: Пошаговая воронка | N95: Пошаговая воронка | S95: Пошаговая воронка | T95: 1 | X95: Пошаговая воронка | AC95: Пошаговая воронка | AH95: Пошаговая воронка | AM95: Пошаговая воронка
E96: % оттока | I96: % оттока | J96: 1 | N96: % оттока | S96: % оттока | T96: 1 | X96: % оттока | AC96: % оттока | AH96: % оттока | AI96: 1 | AM96: % оттока
E97: Объёмы | I97: Объёмы | J97: 1 | N97: Объёмы | S97: Объёмы | T97: 1 | X97: Объёмы | AC97: Объёмы | AH97: Объёмы | AI97: 1 | AM97: Объёмы
E98: Когортный retention | I98: Когортный retention | N98: Когортный retention | S98: Когортный retention | X98: Когортный retention | AC98: Когортный retention | AH98: Когортный retention | AM98: Когортный retention
E99: Кампании | I99: Кампании | N99: Кампании | S99: Кампании | X99: Кампании | AC99: Кампании | AH99: Кампании | AI99: 1 | AM99: Кампании
E100: Затрудняюсь ответить | I100: Затрудняюсь ответить | N100: Затрудняюсь ответить | S100: Затрудняюсь ответить | X100: Затрудняюсь ответить | AC100: Затрудняюсь ответить | AH100: Затрудняюсь ответить | AM100: Затрудняюсь ответить
...

Sheet свод_продукты
FB1: Защита на любой случай | HV1: Пакет СБП | HW1: Пакеты услуг | HX1: премиальное обслуживание уровни 1-3 | IA1: Пакет СБ1 | IC1: Пакет услуг СберПервый; Уровни 4 и 5 ПУ Премиальное обслуживание | LP1: подарок сертификатов СБОЛ | OL1: Зарплатные проекты
I2: 9 | J2: 10 | K2: 11 | L2: 12 | M2: 13 | N2: 14 | O2: 15 | P2: 16 | Q2: 17 | R2: 18 | S2: 19 | T2: 20 | U2: 21 | V2: 22 | W2: 23 | X2: 24 | Y2: 25 | Z2: 26 | AA2: 27 | AB2: 28 | AC2: 29 | AD2: 30 | AE2: 31 | AF2: 32 | AG2: 33 | AH2: 34 | AI2: 35 | AJ2: 36 | AK2: 37 | AL2: 38 | AM2: 39 | AN2: 40 | AO2: 41 | AP2: 42 | AQ2: 43 | AR2: 44 | AS2: 45 | AT2: 46 | AU2: 47 | AV2: 48 | AW2: 49 | AX2: 50 | AY2: 51 | AZ2: 52 | BA2: 53 | BB2: 54 | BC2: 55 | BD2: 56 | BE2: 57 | BF2: 58 | BG2: 59 | BH2: 60 | BI2: 61 | BJ2: 62 | BK2: 63 | BL2: 64 | BM2: 65 | BN2: 66 | BO2: 67 | BP2: 68 | BQ2: 69 | BR2: 70 | BS2: 71 | BT2: 72 | BU2: 73 | BV2: 74 | BW2: 75 | BX2: 76 | BY2: 77 | BZ2: 78 | CA2: 79 | CB2: 80 | CC2: 81 | CD2: 82 | CE2: 83 | CF2: 84 | CG2: 85 | CH2: 86 | CI2: 87 | CJ2: 88 | CK2: 89 | CL2: 90 | CM2: 91 | CN2: 92 | CO2: 93 | CP2: 94 | CQ2: 95 | CR2: 96 | CS2: 97 | CT2: 98 | CU2: 99 | CV2: 100 | CW2: 101 | CX2: 102 | CY2: 103 | CZ2: 104 | DA2: 105 | DB2: 106 | DC2: 107 | DD2: 108 | DE2: 109 | DF2: 110 | DG2: 111 | DH2: 112 | DI2: 113 | DJ2: 114 | DK2: 115 | DL2: 116 | DM2: 117 | DN2: 118 | DO2: 119 | DP2: 120 | DQ2: 121 | DR2: 122 | DS2: 123 | DT2: 124 | DU2: 125 | DV2: 126 | DW2: 127 | DX2: 128 | DY2: 129 | DZ2: 130 | EA2: 131 | EB2: 132 | EC2: 133 | ED2: 134 | EE2: 135 | EF2: 136 | EG2: 137 | EH2: 138 | EI2: 139 | EJ2: 140 | EK2: 141 | EL2: 142 | EM2: 143 | EN2: 144 | EO2: 145 | EP2: 146 | EQ2: 147 | ER2: 148 | ES2: 149 | ET2: 150 | EU2: 151 | EV2: 152 | EW2: 153 | EX2: 154 | EY2: 155 | EZ2: 156 | FA2: 157 | FB2: 158 | FC2: 159 | FD2: 160 | FE2: 161 | FF2: 162 | FG2: 163 | FH2: 164 | FI2: 165 | FJ2: 166 | FK2: 167 | FL2: 168 | FM2: 169 | FN2: 170 | FO2: 171 | FP2: 172 | FQ2: 173 | FR2: 174 | FS2: 175 | FT2: 176 | FU2: 177 | FV2: 178 | FW2: 179 | FX2: 180 | FY2: 181 | FZ2: 182 | GA2: 183 | GB2: 184 | GC2: 185 | GD2: 186 | GE2: 187 | GF2: 188 | GG2: 189 | GH2: 190 | GI2: 191 | GJ2: 192 | GK2: 193 | GL2: 194 | GM2: 195 | GN2: 196 | GO2: 197 | GP2: 198 | GQ2: 199 | GR2: 200 | GS2: 201 | GT2: 202 | GU2: 203 | GV2: 204 | GW2: 205 | GX2: 206 | GY2: 207 | GZ2: 208 | HA2: 209 | HB2: 210 | HC2: 211 | HD2: 212 | HE2: 213 | HF2: 214 | HG2: 215 | HH2: 216 | HI2: 217 | HJ2: 218 | HK2: 219 | HL2: 220 | HM2: 221 | HN2: 222 | HO2: 223 | HP2: 224 | HQ2: 225 | HR2: 226 | HS2: 227 | HT2: 228 | HU2: 229 | HV2: 230 | HW2: 231 | HX2: 232 | HY2: 233 | HZ2: 234 | IA2: 235 | IB2: 236 | IC2: 237 | ID2: 238 | IE2: 239 | IF2: 240 | IG2: 241 | IH2: 242 | II2: 243 | IJ2: 244 | IK2: 245 | IL2: 246 | IM2: 247 | IN2: 248 | IO2: 249 | IP2: 250 | IQ2: 251 | IR2: 252 | IS2: 253 | IT2: 254 | IU2: 255 | IV2: 256 | IW2: 257 | IX2: 258 | IY2: 259 | IZ2: 260 | JA2: 261 | JB2: 262 | JC2: 263 | JD2: 264 | JE2: 265 | JF2: 266 | JG2: 267 | JH2: 268 | JI2: 269 | JJ2: 270 | JK2: 271 | JL2: 272 | JM2: 273 | JN2: 274 | JO2: 275 | JP2: 276 | JQ2: 277 | JR2: 278 | JS2: 279 | JT2: 280 | JU2: 281 | JV2: 282 | JW2: 283 | JX2: 284 | JY2: 285 | JZ2: 286 | KA2: 287 | KB2: 288 | KC2: 289 | KD2: 290 | KE2: 291 | KF2: 292 | KG2: 293 | KH2: 294 | KI2: 295 | KJ2: 296 | KK2: 297 | KL2: 298 | KM2: 299 | KN2: 300 | KO2: 301 | KP2: 302 | KQ2: 303 | KR2: 304 | KS2: 305 | KT2: 306 | KU2: 307 | KV2: 308 | KW2: 309 | KX2: 310 | KY2: 311 | KZ2: 312 | LA2: 313 | LB2: 314 | LC2: 315 | LD2: 316 | LE2: 317 | LF2: 318 | LG2: 319 | LH2: 320 | LI2: 321 | LJ2: 322 | LK2: 323 | LL2: 324 | LM2: 325 | LN2: 326 | LO2: 327 | LP2: 328 | LQ2: 329 | LR2: 330 | LS2: 331 | LT2: 332 | LU2: 333 | LV2: 334 | LW2: 335 | LX2: 336 | LY2: 337 | LZ2: 338 | MA2: 339 | MB2: 340 | MC2: 341 | MD2: 342 | ME2: 343 | MF2: 344 | MG2: 345 | MH2: 346 | MI2: 347 | MJ2: 348 | MK2: 349 | ML2: 350 | MM2: 351 | MN2: 352 | MO2: 353 | MP2: 354 | MQ2: 355 | MR2: 356 | MS2: 357 | MT2: 358 | MU2: 359 | MV2: 360 | MW2: 361 | MX2: 362 | MY2: 363 | MZ2: 364 | NA2: 365 | NB2: 366 | NC2: 367 | ND2: 368 | NE2: 369 | NF2: 370 | NG2: 371 | NH2: 372 | NI2: 373 | NJ2: 374 | NK2: 375 | NL2: 376 | NM2: 377 | NN2: 378 | NO2: 379 | NP2: 380 | NQ2: 381 | NR2: 382 | NS2: 383 | NT2: 384 | NU2: 385 | NV2: 386 | NW2: 387 | NX2: 388 | NY2: 389 | NZ2: 390 | OA2: 391 | OB2: 392 | OC2: 393 | OD2: 394 | OE2: 395 | OF2: 396 | OG2: 397 | OH2: 398 | OI2: 399 | OJ2: 400 | OK2: 401 | OL2: 402 | OM2: 403 | ON2: 404 | OO2: 405 | OP2: 406 | OQ2: 407 | OR2: 408 | OS2: 409 | OT2: 410 | OU2: 411 | OV2: 412 | OW2: 413 | OX2: 414 | OY2: 415 | OZ2: 416 | PA2: 417 | PB2: 418 | PC2: 419 | PD2: 420 | PE2: 421 | PF2: 422 | PG2: 423 | PH2: 424 | PI2: 425 | PJ2: 426 | PK2: 427 | PL2: 428 | PM2: 429 | PN2: 430
I3: CBP | L3: Вклады | BE3: POS | BJ3: BNPL | BO3: Образовательный кредит | BR3: УБ | EW3: ЦКС (корп страхование) | GY3: PH | IF3: DB | NM3: Перевод пенсии
