Workbook

Sheet титул
B1: Юнит | C1: Продукт | D1: Оценка | E1: Группа | F1: тип
A2: 75 | B2: УБ | C2: ОСАГО | D2: 0.62574257 | E2: Зрелые | F2: продукт
A3: 80 | B3: УБ | C3: КАСКО | D3: 0.62574257 | E3: Зрелые | F3: продукт
A4: 85 | B4: УБ | C4: ИнвестКопилка | D4: 0.47640449 | E4: Развивающиеся | F4: продукт
A5: 90 | B5: УБ | C5: СберСова | D5: 0.47293447 | E5: Развивающиеся | F5: продукт
A6: 95 | B6: УБ | C6: Залоговое страхование (корпоративное) | D6: 0.36082474 | E6: Требуют внимания | F6: продукт
A7: 100 | B7: УБ | C7: НСЖ | D7: 0.46419753 | E7: Развивающиеся | F7: продукт
A8: 105 | B8: УБ | C8: ИСЖ | D8: 0.46236559 | E8: Развивающиеся | F8: продукт
A9: 110 | B9: УБ | C9: Страхование жизни | D9: 0.4 | E9: Развивающиеся | F9: продукт
A10: 115 | B10: УБ | C10: Брокерский счет | D10: 0.42178218 | E10: Развивающиеся | F10: продукт
A11: 120 | B11: УБ | C11: БПИФ | D11: 0.47010309 | E11: Развивающиеся | F11: продукт
A12: 125 | B12: УБ | C12: ЗПИФ | D12: 0.63505155 | F12: продукт
A13: 130 | B13: УБ | C13: ПДС | D13: 0.53195876 | E13: Развивающиеся | F13: продукт
A14: 135 | B14: УБ | C14: ОПИФ | D14: 0.60990099 | E14: Зрелые | F14: продукт
A15: 140 | B15: УБ | C15: ВЗР | D15: 0.57029703 | E15: Развивающиеся | F15: продукт
A16: 145 | B16: УБ | C16: ДУ | D16: 0.38651685 | E16: Требуют внимания | F16: продукт
A17: 150 | B17: УБ | C17: Страхование залога (к ипотеке) | D17: 0.51546392 | E17: Развивающиеся | F17: продукт
A18: 155 | B18: УБ | C18: Личная защита Плюс | D18: 0.59381443 | E18: Развивающиеся | F18: продукт
A19: 160 | B19: УБ | C19: Защита на любой случай | D19: 0.54491018 | E19: Развивающиеся | F19: продукт
A20: 165 | B20: УБ | C20: ДСЖ ПК | D20: 0.53882353 | E20: Развивающиеся | F20: продукт
A21: 170 | B21: УБ | C21: ДСЖ КК | D21: 0.55730337 | E21: Развивающиеся | F21: продукт
A22: 175 | B22: УБ | C22: ЦФА | D22: 0.28808864 | E22: Требуют внимания | F22: продукт
A23: 14 | B23: CBP | C23: Вклады+НС | D23: 0.39805825 | E23: Развивающиеся | F23: продукт
A24: 19 | B24: CBP | C24: КП | D24: 0.60759494 | E24: Зрелые | F24: продукт
... A69: 420 | B69: СХ | C69: СберСпасибо | D69: 0.68493151 | E69: Зрелые | F69: продукт

Sheet деталка
A1: fake_id | B1: perc_id | C1: value_id | D1: max_value_id | E1: Юнит | F1: Продукт | G1: metric | H1: metric_name | I1: value | J1: max_value | K1: metric_group | L1: metric_subgroup | M1: metric_footer | N1: recommendation | O1: recommendation_group | P1: type | Q1: sort
A2: 18 | B2: 19 | C2: 18 | D2: 17 | E2: CX | F2: Молодежь | G2: 99 | H2: Активная клиентская база | I2: 0.15 | J2: 0.3 | K2: =VLOOKUP(H2,metric_dict!A:B,2,0) -> Знание ключевых метрик | L2: =IF(VLOOKUP(H2,metric_dict!A:C,3,0)=0,"",VLOOKUP(H2,metric_dict!A:C,3,0)) | M2: =VLOOKUP(H2,metric_dict!A:AA,4,0) -> Знание значения метрики активной клиентской базы | N2: =VLOOKUP(H2,metric_dict!A:AA,5,0) -> Знание метрик и инструментов | O2: =VLOOKUP(H2,metric_dict!A:AA,6,0) -> 1 | P2: segment | Q2: =VLOOKUP(H2,metric_dict!A:AA,7,0) -> 5
A3: 18 | B3: 19 | C3: 18 | D3: 17 | E3: CX | F3: Молодежь | G3: 98 | H3: Кол-во Major клиентов | I3: 0.15 | J3: 0.3 | K3: =VLOOKUP(H3,metric_dict!A:B,2,0) -> Знание ключевых метрик | L3: =IF(VLOOKUP(H3,metric_dict!A:C,3,0)=0,"",VLOOKUP(H3,metric_dict!A:C,3,0)) | M3: =VLOOKUP(H3,metric_dict!A:AA,4,0) -> Знание метрики Major | N3: =VLOOKUP(H3,metric_dict!A:AA,5,0) -> Знание метрик и инструментов | O3: =VLOOKUP(H3,metric_dict!A:AA,6,0) -> 1 | P3: segment | Q3: =VLOOKUP(H3,metric_dict!A:AA,7,0) -> 6
A4: 18 | B4: 19 | C4: 18 | D4: 17 | E4: CX | F4: Молодежь | G4: 97 | H4: Кол-во клиентов с 2+ нефин. сервисов | I4: 0.15 | J4: 0.3 | K4: =VLOOKUP(H4,metric_dict!A:B,2,0) -> Знание ключевых метрик | L4: =IF(VLOOKUP(H4,metric_dict!A:C,3,0)=0,"",VLOOKUP(H4,metric_dict!A:C,3,0)) | M4: =VLOOKUP(H4,metric_dict!A:AA,4,0) -> Знание метрики кол-во клиентов с 2+ нефин.сервисов | N4: =VLOOKUP(H4,metric_dict!A:AA,5,0) -> Знание метрик и инструментов | O4: =VLOOKUP(H4,metric_dict!A:AA,6,0) -> 1 | P4: segment | Q4: =VLOOKUP(H4,metric_dict!A:AA,7,0) -> 7
A5: 18 | B5: 19 | C5: 18 | D5: 17 | E5: CX | F5: Молодежь | G5: 2 | H5: Знание об отчетности в Навигаторе | I5: 0.25 | J5: 0.5 | K5: =VLOOKUP(H5,metric_dict!A:B,2,0) -> Знание ключевых метрик | L5: =IF(VLOOKUP(H5,metric_dict!A:C,3,0)=0,"",VLOOKUP(H5,metric_dict!A:C,3,0)) | M5: =VLOOKUP(H5,metric_dict!A:AA,4,0) -> Понимание доступной отчетности и регулярного мониторинга | N5: =VLOOKUP(H5,metric_dict!A:AA,5,0) -> Знание метрик и инструментов | O5: =VLOOKUP(H5,metric_dict!A:AA,6,0) -> 1 | P5: segment | Q5: =VLOOKUP(H5,metric_dict!A:AA,7,0) -> 13
A6: 18 | B6: 19 | C6: 18 | D6: 17 | E6: CX | F6: Молодежь | G6: 3 | H6: Цели выведены на мониторинг | I6: 1 | J6: 1 | K6: =VLOOKUP(H6,metric_dict!A:B,2,0) -> Цели | L6: =IF(VLOOKUP(H6,metric_dict!A:C,3,0)=0,"",VLOOKUP(H6,metric_dict!A:C,3,0)) | M6: =VLOOKUP(H6,metric_dict!A:AA,4,0) -> Регулярное обновление в Навигаторе | N6: =VLOOKUP(H6,metric_dict!A:AA,5,0) -> Обогащение целей/драйверов/прогнозов в Навигаторе | O6: =VLOOKUP(H6,metric_dict!A:AA,6,0) -> 2 | P6: segment | Q6: =VLOOKUP(H6,metric_dict!A:AA,7,0) -> 1
A7: 18 | B7: 19 | C7: 18 | D7: 17 | E7: CX | F7: Молодежь | G7: 4 | H7: Факторный анализ — драйверы 1–2 ур. | I7: 0.5 | J7: 1 | K7: =VLOOKUP(H7,metric_dict!A:B,2,0) -> Цели | L7: =IF(VLOOKUP(H7,metric_dict!A:C,3,0)=0,"",VLOOKUP(H7,metric_dict!A:C,3,0)) | M7: =VLOOKUP(H7,metric_dict!A:AA,4,0) -> Согласно модели бизнес-процесса | N7: =VLOOKUP(H7,metric_dict!A:AA,5,0) -> Декомпозировать значения целей на драйверы | O7: =VLOOKUP(H7,metric_dict!A:AA,6,0) -> 7 | P7: segment | Q7: =VLOOKUP(H7,metric_dict!A:AA,7,0) -> 2
A8: 18 | B8: 19 | C8: 18 | D8: 17 | E8: CX | F8: Молодежь | G8: 5 | H8: Прогноз по целям | I8: 0 | J8: 1 | K8: =VLOOKUP(H8,metric_dict!A:B,2,0) -> Цели | L8: =IF(VLOOKUP(H8,metric_dict!A:C,3,0)=0,"",VLOOKUP(H8,metric_dict!A:C,3,0)) | M8: =VLOOKUP(H8,metric_dict!A:AA,4,0) -> Прогноз выведен в Навигатор | N8: =VLOOKUP(H8,metric_dict!A:AA,5,0) -> Сформировать прогнозные значения по целям | O8: =VLOOKUP(H8,metric_dict!A:AA,6,0) -> 8 | P8: segment | Q8: =VLOOKUP(H8,metric_dict!A:AA,7,0) -> 3
A9: 18 | B9: 19 | C9: 18 | D9: 17 | E9: CX | F9: Молодежь | G9: 9 | H9: Привлечение.Регулярная отчётность | I9: 0.25 | J9: 0.5 | K9: =VLOOKUP(H9,metric_dict!A:B,2,0) -> Воронка привлечения | L9: =IF(VLOOKUP(H9,metric_dict!A:C,3,0)=0,"",VLOOKUP(H9,metric_dict!A:C,3,0)) -> Отчетность | M9: =VLOOKUP(H9,metric_dict!A:AA,4,0) -> Настроена по воронке | N9: =VLOOKUP(H9,metric_dict!A:AA,5,0) -> Настроить мониторинг по воронке привлечения | O9: =VLOOKUP(H9,metric_dict!A:AA,6,0) -> 2 | P9: segment | Q9: =VLOOKUP(H9,metric_dict!A:AA,7,0) -> 1
A10: 18 | B10: 19 | C10: 18 | D10: 17 | E10: CX | F10: Молодежь | G10: 10 | H10: Привлечение.Полнота отчёта | I10: 0.25 | J10: 0.5 | K10: =VLOOKUP(H10,metric_dict!A:B,2,0) -> Воронка привлечения | L10: =IF(VLOOKUP(H10,metric_dict!A:C,3,0)=0,"",VLOOKUP(H10,metric_dict!A:C,3,0)) -> Отчетность | M10: =VLOOKUP(H10,metric_dict!A:AA,4,0) -> Источники, CR, объёмы, сегменты | N10: =VLOOKUP(H10,metric_dict!A:AA,5,0) -> Донасытить метриками мониторинг по воронке привлечения | O10: =VLOOKUP(H10,metric_dict!A:AA,6,0) -> 3 | P10: segment | Q10: =VLOOKUP(H10,metric_dict!A:AA,7,0) -> 2
A11: 18 | B11: 19 | C11: 18 | D11: 17 | E11: CX | F11: Молодежь | G11: 12 | H11: Отток.Регулярная отчётность | I11: 0 | J11: 0.5 | K11: =VLOOKUP(H11,metric_dict!A:B,2,0) -> Воронка оттока | L11: =IF(VLOOKUP(H11,metric_dict!A:C,3,0)=0,"",VLOOKUP(H11,metric_dict!A:C,3,0)) -> Отчетность | M11: =VLOOKUP(H11,metric_dict!A:AA,4,0) -> Настроена по воронке | N11: =VLOOKUP(H11,metric_dict!A:AA,5,0) -> Настроить мониторинг по воронке оттока | O11: =VLOOKUP(H11,metric_dict!A:AA,6,0) -> 2 | P11: segment | Q11: =VLOOKUP(H11,metric_dict!A:AA,7,0) -> 1
A12: 18 | B12: 19 | C12: 18 | D12: 17 | E12: CX | F12: Молодежь | G12: 13 | H12: Отток.Полнота отчёта | I12: 0 | J12: 0.5 | K12: =VLOOKUP(H12,metric_dict!A:B,2,0) -> Воронка оттока | L12: =IF(VLOOKUP(H12,metric_dict!A:C,3,0)=0,"",VLOOKUP(H12,metric_dict!A:C,3,0)) -> Отчетность | M12: =VLOOKUP(H12,metric_dict!A:AA,4,0) -> Retention, CR, удержание | N12: =VLOOKUP(H12,metric_dict!A:AA,5,0) -> Донасытить метриками мониторинг по воронке оттока | O12: =VLOOKUP(H12,metric_dict!A:AA,6,0) -> 3 | P12: segment | Q12: =VLOOKUP(H12,metric_dict!A:AA,7,0) -> 2
A13: 18 | B13: 19 | C13: 18 | D13: 17 | E13: CX | F13: Молодежь | G13: 15 | H13: Наличие бенчмарков | I13: 1 | J13: 1 | K13: =VLOOKUP(H13,metric_dict!A:B,2,0) -> BENCHMARKS | L13: =IF(VLOOKUP(H13,metric_dict!A:C,3,0)=0,"",VLOOKUP(H13,metric_dict!A:C,3,0)) | M13: =VLOOKUP(H13,metric_dict!A:AA,4,0) -> Цели / динамика / рынок | N13: =VLOOKUP(H13,metric_dict!A:AA,5,0) -> Сформировать бенчмарки по продуктовым метрикам | O13: =VLOOKUP(H13,metric_dict!A:AA,6,0) -> 5 | P13: segment | Q13: =VLOOKUP(H13,metric_dict!A:AA,7,0) -> 6
... A104: 229 | B104: 230 | C104: 229 | D104: 228 | E104: CX | F104: СберПрайм | G104: 29 | H104: Мониторинг механик | I104: 0 | J104: 0 | K104: =VLOOKUP(H104,metric_dict!A:B,2,0) -> Механики | L104: =IF(VLOOKUP(H104,metric_dict!A:C,3,0)=0,"",VLOOKUP(H104,metric_dict!A:C,3,0)) | M104: =VLOOKUP(H104,metric_dict!A:AA,4,0) -> Настроен по ключевым механикам работы с клиентской базой | N104: =VLOOKUP(H104,metric_dict!A:AA,5,0) -> Настроить мониторинг по ключевым механикам | O104: =VLOOKUP(H104,metric_dict!A:AA,6,0) -> 2 | P104: product | Q104: =VLOOKUP(H104,metric_dict!A:AA,7,0) -> 22
A105: 229 | B105: 230 | C105: 229 | D105: 228 | E105: CX | F105: СберПрайм | G105: 30 | H105: Cross-sell | I105: 0 | J105: Не релевантно | K105: =VLOOKUP(H105,metric_dict!A:B,2,0) -> Механики | L105: =IF(VLOOKUP(H105,metric_dict!A:C,3,0)=0,"",VLOOKUP(H105,metric_dict!A:C,3,0)) | M105: =VLOOKUP(H105,metric_dict!A:AA,4,0) -> В оформлении и после покупки | N105: =VLOOKUP(H105,metric_dict!A:AA,5,0) -> Проработать механики кросс-продаж | O105: =VLOOKUP(H105,metric_dict!A:AA,6,0) -> 5 | P105: product | Q105: =VLOOKUP(H105,metric_dict!A:AA,7,0) -> 8
A106: 229 | B106: 230 | C106: 229 | D106: 228 | E106: CX | F106: СберПрайм | G106: 31 | H106: Cross-sell | I106: 0 | J106: 0 | K106: =VLOOKUP(H106,metric_dict!A:B,2,0) -> Механики | L106: =IF(VLOOKUP(H106,metric_dict!A:C,3,0)=0,"",VLOOKUP(H106,metric_dict!A:C,3,0)) | M106: =VLOOKUP(H106,metric_dict!A:AA,4,0) -> В оформлении и после покупки | N106: =VLOOKUP(H106,metric_dict!A:AA,5,0) -> Проработать механики кросс-продаж | O106: =VLOOKUP(H106,metric_dict!A:AA,6,0) -> 5 | P106: product | Q106: =VLOOKUP(H106,metric_dict!A:AA,7,0) -> 8
A107: 229 | B107: 230 | C107: 229 | D107: 228 | E107: CX | F107: СберПрайм | G107: 32 | H107: Cross-sell | I107: 0 | J107: 0 | K107: =VLOOKUP(H107,metric_dict!A:B,2,0) -> Механики | L107: =IF(VLOOKUP(H107,metric_dict!A:C,3,0)=0,"",VLOOKUP(H107,metric_dict!A:C,3,0)) | M107: =VLOOKUP(H107,metric_dict!A:AA,4,0) -> В оформлении и после покупки | N107: =VLOOKUP(H107,metric_dict!A:AA,5,0) -> Проработать механики кросс-продаж | O107: =VLOOKUP(H107,metric_dict!A:AA,6,0) -> 5 | P107: product | Q107: =VLOOKUP(H107,metric_dict!A:AA,7,0) -> 8
A108: 229 | B108: 230 | C108: 229 | D108: 228 | E108: CX | F108: СберПрайм | G108: 33 | H108: Допродажи (upsell) | I108: 1 | J108: 1 | K108: =VLOOKUP(H108,metric_dict!A:B,2,0) -> Механики | L108: =IF(VLOOKUP(H108,metric_dict!A:C,3,0)=0,"",VLOOKUP(H108,metric_dict!A:C,3,0)) | M108: =VLOOKUP(H108,metric_dict!A:AA,4,0) -> Переход клиента на более ценный продукт или расширенный пакет услуг | N108: =VLOOKUP(H108,metric_dict!A:AA,5,0) -> Настроить мониторинг по ключевым механикам | O108: =VLOOKUP(H108,metric_dict!A:AA,6,0) -> 5 | P108: product | Q108: =VLOOKUP(H108,metric_dict!A:AA,7,0) -> 10
A109: 229 | B109: 230 | C109: 229 | D109: 228 | E109: CX | F109: СберПрайм | G109: 34 | H109: Мониторинг механик | I109: 0 | J109: 0 | K109: =VLOOKUP(H109,metric_dict!A:B,2,0) -> Механики | L109: =IF(VLOOKUP(H109,metric_dict!A:C,3,0)=0,"",VLOOKUP(H109,metric_dict!A:C,3,0)) | M109: =VLOOKUP(H109,metric_dict!A:AA,4,0) -> Настроен по ключевым механикам работы с клиентской базой | N109: =VLOOKUP(H109,metric_dict!A:AA,5,0) -> Настроить мониторинг по ключевым механикам | O109: =VLOOKUP(H109,metric_dict!A:AA,6,0) -> 2 | P109: product | Q109: =VLOOKUP(H109,metric_dict!A:AA,7,0) -> 22
A110: 229 | B110: 230 | C110: 229 | D110: 228 | E110: CX | F110: СберПрайм | G110: 35 | H110: Discovery ≥40% бэклога | I110: 0.5 | J110: 1 | K110: =VLOOKUP(H110,metric_dict!A:B,2,0) -> Гипотезы и инициативы | L110: =IF(VLOOKUP(H110,metric_dict!A:C,3,0)=0,"",VLOOKUP(H110,metric_dict!A:C,3,0)) | M110: =VLOOKUP(H110,metric_dict!A:AA,4,0) -> Доля исследовательских задач DA | N110: =VLOOKUP(H110,metric_dict!A:AA,5,0) -> Сфокусировать бэклог аналитиков на research-задачи | O110: =VLOOKUP(H110,metric_dict!A:AA,6,0) -> 5 | P110: product | Q110: =VLOOKUP(H110,metric_dict!A:AA,7,0) -> 1
A111: 229 | B111: 230 | C111: 229 | D111: 228 | E111: CX | F111: СберПрайм | G111: 36 | H111: Нет собственных аналитиков | I111: 0 | J111: 0 | K111: =VLOOKUP(H111,metric_dict!A:B,2,0) -> #N/A | L111: =IF(VLOOKUP(H111,metric_dict!A:C,3,0)=0,"",VLOOKUP(H111,metric_dict!A:C,3,0)) -> #N/A | M111: =VLOOKUP(H111,metric_dict!A:AA,4,0) -> #N/A | N111: =VLOOKUP(H111,metric_dict!A:AA,5,0) -> #N/A | O111: =VLOOKUP(H111,metric_dict!A:AA,6,0) -> #N/A | P111: product | Q111: =VLOOKUP(H111,metric_dict!A:AA,7,0) -> #N/A
A112: 229 | B112: 230 | C112: 229 | D112: 228 | E112: CX | F112: СберПрайм | G112: 38 | H112: Запуски кампаний за квартал | I112: 0.5 | J112: 0.5 | K112: =VLOOKUP(H112,metric_dict!A:B,2,0) -> Воронка привлечения | L112: =IF(VLOOKUP(H112,metric_dict!A:C,3,0)=0,"",VLOOKUP(H112,metric_dict!A:C,3,0)) | M112: =VLOOKUP(H112,metric_dict!A:AA,4,0) -> Self-service / кампейнинг, успешность | N112: =VLOOKUP(H112,metric_dict!A:AA,5,0) -> Развитие кампейнинга | O112: =VLOOKUP(H112,metric_dict!A:AA,6,0) -> 2 | P112: product | Q112: =VLOOKUP(H112,metric_dict!A:AA,7,0) -> 6
A113: 229 | B113: 230 | C113: 229 | D113: 228 | E113: CX | F113: СберПрайм | G113: 39 | H113: Запуски кампаний за квартал | I113: 0 | J113: 0.5 | K113: =VLOOKUP(H113,metric_dict!A:B,2,0) -> Воронка привлечения | L113: =IF(VLOOKUP(H113,metric_dict!A:C,3,0)=0,"",VLOOKUP(H113,metric_dict!A:C,3,0)) | M113: =VLOOKUP(H113,metric_dict!A:AA,4,0) -> Self-service / кампейнинг, успешность | N113: =VLOOKUP(H113,metric_dict!A:AA,5,0) -> Развитие кампейнинга | O113: =VLOOKUP(H113,metric_dict!A:AA,6,0) -> 2 | P113: product | Q113: =VLOOKUP(H113,metric_dict!A:AA,7,0) -> 6
A114: 229 | B114: 230 | C114: 229 | D114: 228 | E114: CX | F114: СберПрайм | G114: 40 | H114: Запуски кампаний за квартал | I114: 0.5 | J114: 0.5 | K114: =VLOOKUP(H114,metric_dict!A:B,2,0) -> Воронка привлечения | L114: =IF(VLOOKUP(H114,metric_dict!A:C,3,0)=0,"",VLOOKUP(H114,metric_dict!A:C,3,0)) | M114: =VLOOKUP(H114,metric_dict!A:AA,4,0) -> Self-service / кампейнинг, успешность | N114: =VLOOKUP(H114,metric_dict!A:AA,5,0) -> Развитие кампейнинга | O114: =VLOOKUP(H114,metric_dict!A:AA,6,0) -> 2 | P114: product | Q114: =VLOOKUP(H114,metric_dict!A:AA,7,0) -> 6
A115: 229 | B115: 230 | C115: 229 | D115: 228 | E115: CX | F115: СберПрайм | G115: 41 | H115: Черновики в СБОЛ ≥70% | I115: 0.5 | J115: 1 | K115: =VLOOKUP(H115,metric_dict!A:B,2,0) -> Воронка привлечения | L115: =IF(VLOOKUP(H115,metric_dict!A:C,3,0)=0,"",VLOOKUP(H115,metric_dict!A:C,3,0)) | M115: =VLOOKUP(H115,metric_dict!A:AA,4,0) -> Покрытие черновиков коммуникациями | N115: =VLOOKUP(H115,metric_dict!A:AA,5,0) -> Увеличить покрытие черновиков | O115: =VLOOKUP(H115,metric_dict!A:AA,6,0) -> 5 | P115: product | Q115: =VLOOKUP(H115,metric_dict!A:AA,7,0) -> 7
A116: 229 | B116: 230 | C116: 229 | D116: 228 | E116: CX | F116: СберПрайм | G116: 42 | H116: CX Score | I116: 0.5 | J116: 1 | K116: =VLOOKUP(H116,metric_dict!A:B,2,0) -> Клиентский опыт | L116: =IF(VLOOKUP(H116,metric_dict!A:C,3,0)=0,"",VLOOKUP(H116,metric_dict!A:C,3,0)) | M116: =VLOOKUP(H116,metric_dict!A:AA,4,0) -> Зелёная зона клиентского пути | N116: =VLOOKUP(H116,metric_dict!A:AA,5,0) -> Достигнуть целевого CX Score | O116: =VLOOKUP(H116,metric_dict!A:AA,6,0) -> 5 | P116: product | Q116: =VLOOKUP(H116,metric_dict!A:AA,7,0) -> 1
A117: 229 | B117: 230 | C117: 229 | D117: 228 | E117: CX | F117: СберПрайм | G117: 43 | H117: A/B-тесты | I117: 0 | J117: 0 | K117: =VLOOKUP(H117,metric_dict!A:B,2,0) -> Гипотезы и инициативы | L117: =IF(VLOOKUP(H117,metric_dict!A:C,3,0)=0,"",VLOOKUP(H117,metric_dict!A:C,3,0)) | M117: =VLOOKUP(H117,metric_dict!A:AA,4,0) -> Проведение A/B тестов | N117: =VLOOKUP(H117,metric_dict!A:AA,5,0) -> Запустить A/B-тестирование | O117: =VLOOKUP(H117,metric_dict!A:AA,6,0) -> 5 | P117: product | Q117: =VLOOKUP(H117,metric_dict!A:AA,7,0) -> 3
... A128: 239 | B128: 240 | C128: 239 | D128: 238 | E128: CX | F128: Пакет услуг СберПервый | G128: 53 | H128: Ссылка на воронку оттока | I128: 0 | J128: 0 | K128: =VLOOKUP(H128,metric_dict!A:B,2,0) -> #N/A | L128: =IF(VLOOKUP(H128,metric_dict!A:C,3,0)=0,"",VLOOKUP(H128,metric_dict!A:C,3,0)) -> #N/A | M128: =VLOOKUP(H128,metric_dict!A:AA,4,0) -> #N/A | N128: =VLOOKUP(H128,metric_dict!A:AA,5,0) -> #N/A | O128: =VLOOKUP(H128,metric_dict!A:AA,6,0) -> #N/A | P128: product | Q128: =VLOOKUP(H128,metric_dict!A:AA,7,0) -> #N/A
A129: 229 | B129: 230 | C129: 229 | D129: 228 | E129: CX | F129: СберПрайм | G129: 53 | H129: Ссылка на воронку оттока | I129: 0 | J129: https://confluence.sberbank.ru/pages/viewpage.action?pageId=14212498623 | K129: =VLOOKUP(H129,metric_dict!A:B,2,0) -> #N/A | L129: =IF(VLOOKUP(H129,metric_dict!A:C,3,0)=0,"",VLOOKUP(H129,metric_dict!A:C,3,0)) -> #N/A | M129: =VLOOKUP(H129,metric_dict!A:AA,4,0) -> #N/A | N129: =VLOOKUP(H129,metric_dict!A:AA,5,0) -> #N/A | O129: =VLOOKUP(H129,metric_dict!A:AA,6,0) -> #N/A | P129: product | Q129: =VLOOKUP(H129,metric_dict!A:AA,7,0) -> #N/A
A130: 239 | B130: 240 | C130: 239 | D130: 238 | E130: CX | F130: Пакет услуг СберПервый | G130: 54 | H130: Ссылка на бэклог | I130: 0 | J130: https://sbertrack.sberbank.ru/swtr/board/b5380d96-6b2a-4846-9a42-ac7e877607cf?space=PSDA&tenant=default&spaces=%5B%7B%22label%22%3A%22Premium_Solutions_DA%22%2C%22value%22%3A%22PSDA%22%7D%5D (аналитик Шеремет А) | K130: =VLOOKUP(H130,metric_dict!A:B,2,0) -> #N/A | L130: =IF(VLOOKUP(H130,metric_dict!A:C,3,0)=0,"",VLOOKUP(H130,metric_dict!A:C,3,0)) -> #N/A | M130: =VLOOKUP(H130,metric_dict!A:AA,4,0) -> #N/A | N130: =VLOOKUP(H130,metric_dict!A:AA,5,0) -> #N/A | O130: =VLOOKUP(H130,metric_dict!A:AA,6,0) -> #N/A | P130: product | Q130: =VLOOKUP(H130,metric_dict!A:AA,7,0) -> #N/A
A131: 229 | B131: 230 | C131: 229 | D131: 228 | E131: CX | F131: СберПрайм | G131: 52 | H131: Ссылка на коронку привлечения | I131: 0 | J131: https://confluence.sberbank.ru/pages/viewpage.action?pageId=14212498623 | K131: =VLOOKUP(H131,metric_dict!A:B,2,0) -> #N/A | L131: =IF(VLOOKUP(H131,metric_dict!A:C,3,0)=0,"",VLOOKUP(H131,metric_dict!A:C,3,0)) -> #N/A | M131: =VLOOKUP(H131,metric_dict!A:AA,4,0) -> #N/A | N131: =VLOOKUP(H131,metric_dict!A:AA,5,0) -> #N/A | O131: =VLOOKUP(H131,metric_dict!A:AA,6,0) -> #N/A | P131: product | Q131: =VLOOKUP(H131,metric_dict!A:AA,7,0) -> #N/A
A132: 239 | B132: 240 | C132: 239 | D132: 238 | E132: CX | F132: Пакет услуг СберПервый | G132: 101 | H132: Цифр.цели | I132: 0 | J132: 1 | K132: =VLOOKUP(H132,metric_dict!A:B,2,0) -> #N/A | L132: =IF(VLOOKUP(H132,metric_dict!A:C,3,0)=0,"",VLOOKUP(H132,metric_dict!A:C,3,0)) -> #N/A | M132: =VLOOKUP(H132,metric_dict!A:AA,4,0) -> #N/A | N132: =VLOOKUP(H132,metric_dict!A:AA,5,0) -> #N/A | O132: =VLOOKUP(H132,metric_dict!A:AA,6,0) -> #N/A | P132: product | Q132: =VLOOKUP(H132,metric_dict!A:AA,7,0) -> #N/A
A133: 229 | B133: 230 | C133: 229 | D133: 228 | E133: CX | F133: СберПрайм | G133: 101 | H133: Цифр.цели | I133: 1 | J133: 1 | K133: =VLOOKUP(H133,metric_dict!A:B,2,0) -> #N/A | L133: =IF(VLOOKUP(H133,metric_dict!A:C,3,0)=0,"",VLOOKUP(H133,metric_dict!A:C,3,0)) -> #N/A | M133: =VLOOKUP(H133,metric_dict!A:AA,4,0) -> #N/A | N133: =VLOOKUP(H133,metric_dict!A:AA,5,0) -> #N/A | O133: =VLOOKUP(H133,metric_dict!A:AA,6,0) -> #N/A | P133: product | Q133: =VLOOKUP(H133,metric_dict!A:AA,7,0) -> #N/A
A134: 239 | B134: 240 | C134: 239 | D134: 238 | E134: CX | F134: Пакет услуг СберПервый | G134: 102 | H134: Цифр.факторы | I134: 0 | J134: 1 | K134: =VLOOKUP(H134,metric_dict!A:B,2,0) -> #N/A | L134: =IF(VLOOKUP(H134,metric_dict!A:C,3,0)=0,"",VLOOKUP(H134,metric_dict!A:C,3,0)) -> #N/A | M134: =VLOOKUP(H134,metric_dict!A:AA,4,0) -> #N/A | N134: =VLOOKUP(H134,metric_dict!A:AA,5,0) -> #N/A | O134: =VLOOKUP(H134,metric_dict!A:AA,6,0) -> #N/A | P134: product | Q134: =VLOOKUP(H134,metric_dict!A:AA,7,0) -> #N/A
A135: 229 | B135: 230 | C135: 229 | D135: 228 | E135: CX | F135: СберПрайм | G135: 102 | H135: Цифр.факторы | I135: 0 | J135: 1 | K135: =VLOOKUP(H135,metric_dict!A:B,2,0) -> #N/A | L135: =IF(VLOOKUP(H135,metric_dict!A:C,3,0)=0,"",VLOOKUP(H135,metric_dict!A:C,3,0)) -> #N/A | M135: =VLOOKUP(H135,metric_dict!A:AA,4,0) -> #N/A | N135: =VLOOKUP(H135,metric_dict!A:AA,5,0) -> #N/A | O135: =VLOOKUP(H135,metric_dict!A:AA,6,0) -> #N/A | P135: product | Q135: =VLOOKUP(H135,metric_dict!A:AA,7,0) -> #N/A
A136: 239 | B136: 240 | C136: 239 | D136: 238 | E136: CX | F136: Пакет услуг СберПервый | G136: 103 | H136: Цифр.прогнозы | I136: 0 | J136: 1 | K136: =VLOOKUP(H136,metric_dict!A:B,2,0) -> #N/A | L136: =IF(VLOOKUP(H136,metric_dict!A:C,3,0)=0,"",VLOOKUP(H136,metric_dict!A:C,3,0)) -> #N/A | M136: =VLOOKUP(H136,metric_dict!A:AA,4,0) -> #N/A | N136: =VLOOKUP(H136,metric_dict!A:AA,5,0) -> #N/A | O136: =VLOOKUP(H136,metric_dict!A:AA,6,0) -> #N/A | P136: product | Q136: =VLOOKUP(H136,metric_dict!A:AA,7,0) -> #N/A
A137: 229 | B137: 230 | C137: 229 | D137: 228 | E137: CX | F137: СберПрайм | G137: 103 | H137: Цифр.прогнозы | I137: 0 | J137: 1 | K137: =VLOOKUP(H137,metric_dict!A:B,2,0) -> #N/A | L137: =IF(VLOOKUP(H137,metric_dict!A:C,3,0)=0,"",VLOOKUP(H137,metric_dict!A:C,3,0)) -> #N/A | M137: =VLOOKUP(H137,metric_dict!A:AA,4,0) -> #N/A | N137: =VLOOKUP(H137,metric_dict!A:AA,5,0) -> #N/A | O137: =VLOOKUP(H137,metric_dict!A:AA,6,0) -> #N/A | P137: product | Q137: =VLOOKUP(H137,metric_dict!A:AA,7,0) -> #N/A
A138: 13 | B138: 14 | C138: 13 | D138: 12 | E138: CX | F138: Дети | G138: 99 | H138: Активная клиентская база | I138: 0.3 | J138: 0.3 | K138: =VLOOKUP(H138,metric_dict!A:B,2,0) -> Знание ключевых метрик | L138: =IF(VLOOKUP(H138,metric_dict!A:C,3,0)=0,"",VLOOKUP(H138,metric_dict!A:C,3,0)) | M138: =VLOOKUP(H138,metric_dict!A:AA,4,0) -> Знание значения метрики активной клиентской базы | N138: =VLOOKUP(H138,metric_dict!A:AA,5,0) -> Знание метрик и инструментов | O138: =VLOOKUP(H138,metric_dict!A:AA,6,0) -> 1 | P138: segment | Q138: =VLOOKUP(H138,metric_dict!A:AA,7,0) -> 5
A139: 13 | B139: 14 | C139: 13 | D139: 12 | E139: CX | F139: Дети | G139: 98 | H139: Кол-во Major клиентов | I139: 0.15 | J139: 0.3 | K139: =VLOOKUP(H139,metric_dict!A:B,2,0) -> Знание ключевых метрик | L139: =IF(VLOOKUP(H139,metric_dict!A:C,3,0)=0,"",VLOOKUP(H139,metric_dict!A:C,3,0)) | M139: =VLOOKUP(H139,metric_dict!A:AA,4,0) -> Знание метрики Major | N139: =VLOOKUP(H139,metric_dict!A:AA,5,0) -> Знание метрик и инструментов | O139: =VLOOKUP(H139,metric_dict!A:AA,6,0) -> 1 | P139: segment | Q139: =VLOOKUP(H139,metric_dict!A:AA,7,0) -> 6
A140: 13 | B140: 14 | C140: 13 | D140: 12 | E140: CX | F140: Дети | G140: 97 | H140: Кол-во клиентов с 2+ нефин. сервисов | I140: 0 | J140: 0 | K140: =VLOOKUP(H140,metric_dict!A:B,2,0) -> Знание ключевых метрик | L140: =IF(VLOOKUP(H140,metric_dict!A:C,3,0)=0,"",VLOOKUP(H140,metric_dict!A:C,3,0)) | M140: =VLOOKUP(H140,metric_dict!A:AA,4,0) -> Знание метрики кол-во клиентов с 2+ нефин.сервисов | N140: =VLOOKUP(H140,metric_dict!A:AA,5,0) -> Знание метрик и инструментов | O140: =VLOOKUP(H140,metric_dict!A:AA,6,0) -> 1 | P140: segment | Q140: =VLOOKUP(H140,metric_dict!A:AA,7,0) -> 7
A141: 13 | B141: 14 | C141: 13 | D141: 12 | E141: CX | F141: Дети | G141: 2 | H141: Знание об отчетности в Навигаторе | I141: 0.25 | J141: 0.5 | K141: =VLOOKUP(H141,metric_dict!A:B,2,0) -> Знание ключевых метрик | L141: =IF(VLOOKUP(H141,metric_dict!A:C,3,0)=0,"",VLOOKUP(H141,metric_dict!A:C,3,0)) | M141: =VLOOKUP(H141,metric_dict!A:AA,4,0) -> Понимание доступной отчетности и регулярного мониторинга | N141: =VLOOKUP(H141,metric_dict!A:AA,5,0) -> Знание метрик и инструментов | O141: =VLOOKUP(H141,metric_dict!A:AA,6,0) -> 1 | P141: segment | Q141: =VLOOKUP(H141,metric_dict!A:AA,7,0) -> 13
A142: 13 | B142: 14 | C142: 13 | D142: 12 | E142: CX | F142: Дети | G142: 3 | H142: Цели выведены на мониторинг | I142: 0.5 | J142: 1 | K142: =VLOOKUP(H142,metric_dict!A:B,2,0) -> Цели | L142: =IF(VLOOKUP(H142,metric_dict!A:C,3,0)=0,"",VLOOKUP(H142,metric_dict!A:C,3,0)) | M142: =VLOOKUP(H142,metric_dict!A:AA,4,0) -> Регулярное обновление в Навигаторе | N142: =VLOOKUP(H142,metric_dict!A:AA,5,0) -> Обогащение целей/драйверов/прогнозов в Навигаторе | O142: =VLOOKUP(H142,metric_dict!A:AA,6,0) -> 2 | P142: segment | Q142: =VLOOKUP(H142,metric_dict!A:AA,7,0) -> 1
A143: 13 | B143: 14 | C143: 13 | D143: 12 | E143: CX | F143: Дети | G143: 4 | H143: Факторный анализ — драйверы 1–2 ур. | I143: 1 | J143: 1 | K143: =VLOOKUP(H143,metric_dict!A:B,2,0) -> Цели | L143: =IF(VLOOKUP(H143,metric_dict!A:C,3,0)=0,"",VLOOKUP(H143,metric_dict!A:C,3,0)) | M143: =VLOOKUP(H143,metric_dict!A:AA,4,0) -> Согласно модели бизнес-процесса | N143: =VLOOKUP(H143,metric_dict!A:AA,5,0) -> Декомпозировать значения целей на драйверы | O143: =VLOOKUP(H143,metric_dict!A:AA,6,0) -> 7 | P143: segment | Q143: =VLOOKUP(H143,metric_dict!A:AA,7,0) -> 2
... A366: 234 | B366: 235 | C366: 234 | D366: 233 | E366: CX | F366: Пакет услуг СберПремьер | G366: 98 | H366: Гибкое изменение условий продукта | I366: 1 | J366: 1 | K366: =VLOOKUP(H366,metric_dict!A:B,2,0) -> Механики | L366: =IF(VLOOKUP(H366,metric_dict!A:C,3,0)=0,"",VLOOKUP(H366,metric_dict!A:C,3,0)) | M366: =VLOOKUP(H366,metric_dict!A:AA,4,0) -> Возможность изменить набор опций по продукту без IT-разработки | N366: =VLOOKUP(H366,metric_dict!A:AA,5,0) -> Выстроить процесс гибкого изменения условий без IT | O366: =VLOOKUP(H366,metric_dict!A:AA,6,0) -> 10 | P366: product | Q366: =VLOOKUP(H366,metric_dict!A:AA,7,0) -> 7
A367: 420 | B367: =A367+1 -> 421 | C367: =A367 -> 420 | D367: =A367-1 -> 419 | E367: CX | F367: СберСпасибо | G367: 1 | H367: Объем целевого рынка в России | I367: 0.2 | J367: 0.2 | K367: =VLOOKUP(H367,metric_dict!A:B,2,0) -> Знание ключевых метрик | L367: =IF(VLOOKUP(H367,metric_dict!A:C,3,0)=0,"",VLOOKUP(H367,metric_dict!A:C,3,0)) | M367: =VLOOKUP(H367,metric_dict!A:AA,4,0) -> Оценка потенциального объема клиентов в России | N367: =VLOOKUP(H367,metric_dict!A:AA,5,0) -> Знание метрик и инструментов | O367: =VLOOKUP(H367,metric_dict!A:AA,6,0) -> 1 | P367: product | Q367: =VLOOKUP(H367,metric_dict!A:AA,7,0) -> 1
A368: 420 | B368: =A368+1 -> 421 | C368: =A368 -> 420 | D368: =A368-1 -> 419 | E368: CX | F368: СберСпасибо | G368: 2 | H368: Знание об отчетности в Навигаторе | I368: 0.25 | J368: 0.5 | K368: =VLOOKUP(H368,metric_dict!A:B,2,0) -> Знание ключевых метрик | L368: =IF(VLOOKUP(H368,metric_dict!A:C,3,0)=0,"",VLOOKUP(H368,metric_dict!A:C,3,0)) | M368: =VLOOKUP(H368,metric_dict!A:AA,4,0) -> Понимание доступной отчетности и регулярного мониторинга | N368: =VLOOKUP(H368,metric_dict!A:AA,5,0) -> Знание метрик и инструментов | O368: =VLOOKUP(H368,metric_dict!A:AA,6,0) -> 1 | P368: product | Q368: =VLOOKUP(H368,metric_dict!A:AA,7,0) -> 13
A369: 420 | B369: =A369+1 -> 421 | C369: =A369 -> 420 | D369: =A369-1 -> 419 | E369: CX | F369: СберСпасибо | G369: 3 | H369: Цели выведены на мониторинг | I369: 1 | J369: 1 | K369: =VLOOKUP(H369,metric_dict!A:B,2,0) -> Цели | L369: =IF(VLOOKUP(H369,metric_dict!A:C,3,0)=0,"",VLOOKUP(H369,metric_dict!A:C,3,0)) | M369: =VLOOKUP(H369,metric_dict!A:AA,4,0) -> Регулярное обновление в Навигаторе | N369: =VLOOKUP(H369,metric_dict!A:AA,5,0) -> Обогащение целей/драйверов/прогнозов в Навигаторе | O369: =VLOOKUP(H369,metric_dict!A:AA,6,0) -> 2 | P369: product | Q369: =VLOOKUP(H369,metric_dict!A:AA,7,0) -> 1
A370: 420 | B370: =A370+1 -> 421 | C370: =A370 -> 420 | D370: =A370-1 -> 419 | E370: CX | F370: СберСпасибо | G370: 4 | H370: Факторный анализ — драйверы 1–2 ур. | I370: 0.5 | J370: 1 | K370: =VLOOKUP(H370,metric_dict!A:B,2,0) -> Цели | L370: =IF(VLOOKUP(H370,metric_dict!A:C,3,0)=0,"",VLOOKUP(H370,metric_dict!A:C,3,0)) | M370: =VLOOKUP(H370,metric_dict!A:AA,4,0) -> Согласно модели бизнес-процесса | N370: =VLOOKUP(H370,metric_dict!A:AA,5,0) -> Декомпозировать значения целей на драйверы | O370: =VLOOKUP(H370,metric_dict!A:AA,6,0) -> 7 | P370: product | Q370: =VLOOKUP(H370,metric_dict!A:AA,7,0) -> 2
A371: 420 | B371: =A371+1 -> 421 | C371: =A371 -> 420 | D371: =A371-1 -> 419 | E371: CX | F371: СберСпасибо | G371: 5 | H371: Прогноз по целям | I371: 0 | J371: 1 | K371: =VLOOKUP(H371,metric_dict!A:B,2,0) -> Цели | L371: =IF(VLOOKUP(H371,metric_dict!A:C,3,0)=0,"",VLOOKUP(H371,metric_dict!A:C,3,0)) | M371: =VLOOKUP(H371,metric_dict!A:AA,4,0) -> Прогноз выведен в Навигатор | N371: =VLOOKUP(H371,metric_dict!A:AA,5,0) -> Сформировать прогнозные значения по целям | O371: =VLOOKUP(H371,metric_dict!A:AA,6,0) -> 8 | P371: product | Q371: =VLOOKUP(H371,metric_dict!A:AA,7,0) -> 3
A372: 420 | B372: =A372+1 -> 421 | C372: =A372 -> 420 | D372: =A372-1 -> 419 | E372: CX | F372: СберСпасибо | G372: 9 | H372: Привлечение.Регулярная отчётность | I372: 0.25 | J372: 0.5 | K372: =VLOOKUP(H372,metric_dict!A:B,2,0) -> Воронка привлечения | L372: =IF(VLOOKUP(H372,metric_dict!A:C,3,0)=0,"",VLOOKUP(H372,metric_dict!A:C,3,0)) -> Отчетность | M372: =VLOOKUP(H372,metric_dict!A:AA,4,0) -> Настроена по воронке | N372: =VLOOKUP(H372,metric_dict!A:AA,5,0) -> Настроить мониторинг по воронке привлечения | O372: =VLOOKUP(H372,metric_dict!A:AA,6,0) -> 2 | P372: product | Q372: =VLOOKUP(H372,metric_dict!A:AA,7,0) -> 1
A373: 420 | B373: =A373+1 -> 421 | C373: =A373 -> 420 | D373: =A373-1 -> 419 | E373: CX | F373: СберСпасибо | G373: 10 | H373: Привлечение.Полнота отчёта | I373: 0.25 | J373: 0.5 | K373: =VLOOKUP(H373,metric_dict!A:B,2,0) -> Воронка привлечения | L373: =IF(VLOOKUP(H373,metric_dict!A:C,3,0)=0,"",VLOOKUP(H373,metric_dict!A:C,3,0)) -> Отчетность | M373: =VLOOKUP(H373,metric_dict!A:AA,4,0) -> Источники, CR, объёмы, сегменты | N373: =VLOOKUP(H373,metric_dict!A:AA,5,0) -> Донасытить метриками мониторинг по воронке привлечения | O373: =VLOOKUP(H373,metric_dict!A:AA,6,0) -> 3 | P373: product | Q373: =VLOOKUP(H373,metric_dict!A:AA,7,0) -> 2
A374: 420 | B374: =A374+1 -> 421 | C374: =A374 -> 420 | D374: =A374-1 -> 419 | E374: CX | F374: СберСпасибо | G374: 11 | H374: Привлечение.Регулярность (авто) | I374: 0.5 | J374: 1 | K374: =VLOOKUP(H374,metric_dict!A:B,2,0) -> Воронка привлечения | L374: =IF(VLOOKUP(H374,metric_dict!A:C,3,0)=0,"",VLOOKUP(H374,metric_dict!A:C,3,0)) -> Отчетность | M374: =VLOOKUP(H374,metric_dict!A:AA,4,0) -> Daily / weekly | N374: =VLOOKUP(H374,metric_dict!A:AA,5,0) -> Автоматизировать расчет воронки привлечения | O374: =VLOOKUP(H374,metric_dict!A:AA,6,0) -> 4 | P374: product | Q374: =VLOOKUP(H374,metric_dict!A:AA,7,0) -> 3
A375: 420 | B375: =A375+1 -> 421 | C375: =A375 -> 420 | D375: =A375-1 -> 419 | E375: CX | F375: СберСпасибо | G375: 12 | H375: Отток.Регулярная отчётность | I375: 0 | J375: Не релевантно | K375: =VLOOKUP(H375,metric_dict!A:B,2,0) -> Воронка оттока | L375: =IF(VLOOKUP(H375,metric_dict!A:C,3,0)=0,"",VLOOKUP(H375,metric_dict!A:C,3,0)) -> Отчетность | M375: =VLOOKUP(H375,metric_dict!A:AA,4,0) -> Настроена по воронке | N375: =VLOOKUP(H375,metric_dict!A:AA,5,0) -> Настроить мониторинг по воронке оттока | O375: =VLOOKUP(H375,metric_dict!A:AA,6,0) -> 2 | P375: product | Q375: =VLOOKUP(H375,metric_dict!A:AA,7,0) -> 1
A376: 420 | B376: =A376+1 -> 421 | C376: =A376 -> 420 | D376: =A376-1 -> 419 | E376: CX | F376: СберСпасибо | G376: 13 | H376: Отток.Полнота отчёта | I376: 0 | J376: Не релевантно | K376: =VLOOKUP(H376,metric_dict!A:B,2,0) -> Воронка оттока | L376: =IF(VLOOKUP(H376,metric_dict!A:C,3,0)=0,"",VLOOKUP(H376,metric_dict!A:C,3,0)) -> Отчетность | M376: =VLOOKUP(H376,metric_dict!A:AA,4,0) -> Retention, CR, удержание | N376: =VLOOKUP(H376,metric_dict!A:AA,5,0) -> Донасытить метриками мониторинг по воронке оттока | O376: =VLOOKUP(H376,metric_dict!A:AA,6,0) -> 3 | P376: product | Q376: =VLOOKUP(H376,metric_dict!A:AA,7,0) -> 2
A377: 420 | B377: =A377+1 -> 421 | C377: =A377 -> 420 | D377: =A377-1 -> 419 | E377: CX | F377: СберСпасибо | G377: 14 | H377: Отток.Регулярность (авто) | I377: 0.5 | J377: 1 | K377: =VLOOKUP(H377,metric_dict!A:B,2,0) -> Воронка оттока | L377: =IF(VLOOKUP(H377,metric_dict!A:C,3,0)=0,"",VLOOKUP(H377,metric_dict!A:C,3,0)) -> Отчетность | M377: =VLOOKUP(H377,metric_dict!A:AA,4,0) -> Daily / weekly | N377: =VLOOKUP(H377,metric_dict!A:AA,5,0) -> Автоматизировать расчет воронки оттока | O377: =VLOOKUP(H377,metric_dict!A:AA,6,0) -> 4 | P377: product | Q377: =VLOOKUP(H377,metric_dict!A:AA,7,0) -> 3
A378: 420 | B378: =A378+1 -> 421 | C378: =A378 -> 420 | D378: =A378-1 -> 419 | E378: CX | F378: СберСпасибо | G378: 15 | H378: Наличие бенчмарков | I378: 0 | J378: 1 | K378: =VLOOKUP(H378,metric_dict!A:B,2,0) -> BENCHMARKS | L378: =IF(VLOOKUP(H378,metric_dict!A:C,3,0)=0,"",VLOOKUP(H378,metric_dict!A:C,3,0)) | M378: =VLOOKUP(H378,metric_dict!A:AA,4,0) -> Цели / динамика / рынок | N378: =VLOOKUP(H378,metric_dict!A:AA,5,0) -> Сформировать бенчмарки по продуктовым метрикам | O378: =VLOOKUP(H378,metric_dict!A:AA,6,0) -> 5 | P378: product | Q378: =VLOOKUP(H378,metric_dict!A:AA,7,0) -> 6
A379: 420 | B379: =A379+1 -> 421 | C379: =A379 -> 420 | D379: =A379-1 -> 419 | E379: CX | F379: СберСпасибо | G379: 16 | H379: Опишите, какие бенчмарки используются | I379: 0 | J379: 0 | K379: =VLOOKUP(H379,metric_dict!A:B,2,0) -> #N/A | L379: =IF(VLOOKUP(H379,metric_dict!A:C,3,0)=0,"",VLOOKUP(H379,metric_dict!A:C,3,0)) -> #N/A | M379: =VLOOKUP(H379,metric_dict!A:AA,4,0) -> #N/A | N379: =VLOOKUP(H379,metric_dict!A:AA,5,0) -> #N/A | O379: =VLOOKUP(H379,metric_dict!A:AA,6,0) -> #N/A | P379: product | Q379: =VLOOKUP(H379,metric_dict!A:AA,7,0) -> #N/A
A380: 420 | B380: =A380+1 -> 421 | C380: =A380 -> 420 | D380: =A380-1 -> 419 | E380: CX | F380: СберСпасибо | G380: 17 | H380: Проведение анализа воронки привлечения | I380: 0.5 | J380: 1 | K380: =VLOOKUP(H380,metric_dict!A:B,2,0) -> Воронка привлечения | L380: =IF(VLOOKUP(H380,metric_dict!A:C,3,0)=0,"",VLOOKUP(H380,metric_dict!A:C,3,0)) | M380: =VLOOKUP(H380,metric_dict!A:AA,4,0) -> Оценка эффективности, поиск точек роста | N380: =VLOOKUP(H380,metric_dict!A:AA,5,0) -> Провести анализ привлечения, выявить точки роста | O380: =VLOOKUP(H380,metric_dict!A:AA,6,0) -> 5 | P380: product | Q380: =VLOOKUP(H380,metric_dict!A:AA,7,0) -> 4
A381: 420 | B381: =A381+1 -> 421 | C381: =A381 -> 420 | D381: =A381-1 -> 419 | E381: CX | F381: СберСпасибо | G381: 18 | H381: Составлен перечень инициатив по привлечению | I381: 1 | J381: 1 | K381: =VLOOKUP(H381,metric_dict!A:B,2,0) -> Воронка привлечения | L381: =IF(VLOOKUP(H381,metric_dict!A:C,3,0)=0,"",VLOOKUP(H381,metric_dict!A:C,3,0)) | M381: =VLOOKUP(H381,metric_dict!A:AA,4,0) -> План действий по росту | N381: =VLOOKUP(H381,metric_dict!A:AA,5,0) -> Сформировать перечень инициатив | O381: =VLOOKUP(H381,metric_dict!A:AA,6,0) -> 5 | P381: product | Q381: =VLOOKUP(H381,metric_dict!A:AA,7,0) -> 5
A382: 420 | B382: =A382+1 -> 421 | C382: =A382 -> 420 | D382: =A382-1 -> 419 | E382: CX | F382: СберСпасибо | G382: 19 | H382: Проведение анализа воронки оттока | I382: 0 | J382: Не релевантно | K382: =VLOOKUP(H382,metric_dict!A:B,2,0) -> Воронка оттока | L382: =IF(VLOOKUP(H382,metric_dict!A:C,3,0)=0,"",VLOOKUP(H382,metric_dict!A:C,3,0)) | M382: =VLOOKUP(H382,metric_dict!A:AA,4,0) -> Оценка причин и узких мест | N382: =VLOOKUP(H382,metric_dict!A:AA,5,0) -> Провести анализ оттока, выявить точки роста | O382: =VLOOKUP(H382,metric_dict!A:AA,6,0) -> 5 | P382: product | Q382: =VLOOKUP(H382,metric_dict!A:AA,7,0) -> 4
A383: 420 | B383: =A383+1 -> 421 | C383: =A383 -> 420 | D383: =A383-1 -> 419 | E383: CX | F383: СберСпасибо | G383: 20 | H383: Мероприятия по работе с отклонениями | I383: 0 | J383: Не релевантно | K383: =VLOOKUP(H383,metric_dict!A:B,2,0) -> Воронка оттока | L383: =IF(VLOOKUP(H383,metric_dict!A:C,3,0)=0,"",VLOOKUP(H383,metric_dict!A:C,3,0)) | M383: =VLOOKUP(H383,metric_dict!A:AA,4,0) -> План действий по отклонениям | N383: =VLOOKUP(H383,metric_dict!A:AA,5,0) -> Сформировать список мероприятий по снижению оттока | O383: =VLOOKUP(H383,metric_dict!A:AA,6,0) -> 4 | P383: product | Q383: =VLOOKUP(H383,metric_dict!A:AA,7,0) -> 5
A384: 420 | B384: =A384+1 -> 421 | C384: =A384 -> 420 | D384: =A384-1 -> 419 | E384: CX | F384: СберСпасибо | G384: 21 | H384: Оповещения по системным сбоям | I384: 1 | J384: 1 | K384: =VLOOKUP(H384,metric_dict!A:B,2,0) -> Алерты | L384: =IF(VLOOKUP(H384,metric_dict!A:C,3,0)=0,"",VLOOKUP(H384,metric_dict!A:C,3,0)) | M384: =VLOOKUP(H384,metric_dict!A:AA,4,0) -> Авто-алерты по IT-инфраструктуре | N384: =VLOOKUP(H384,metric_dict!A:AA,5,0) -> Внедрить систему оповещений | O384: =VLOOKUP(H384,metric_dict!A:AA,6,0) -> 5 | P384: product | Q384: =VLOOKUP(H384,metric_dict!A:AA,7,0) -> 1
A385: 420 | B385: =A385+1 -> 421 | C385: =A385 -> 420 | D385: =A385-1 -> 419 | E385: CX | F385: СберСпасибо | G385: 22 | H385: Оповещения по бизнес-метрикам | I385: 0.5 | J385: 1 | K385: =VLOOKUP(H385,metric_dict!A:B,2,0) -> Алерты | L385: =IF(VLOOKUP(H385,metric_dict!A:C,3,0)=0,"",VLOOKUP(H385,metric_dict!A:C,3,0)) | M385: =VLOOKUP(H385,metric_dict!A:AA,4,0) -> Светофоры целей, драйверов, воронок | N385: =VLOOKUP(H385,metric_dict!A:AA,5,0) -> Внедрить систему оповещений | O385: =VLOOKUP(H385,metric_dict!A:AA,6,0) -> 3 | P385: product | Q385: =VLOOKUP(H385,metric_dict!A:AA,7,0) -> 2
A386: 420 | B386: =A386+1 -> 421 | C386: =A386 -> 420 | D386: =A386-1 -> 419 | E386: CX | F386: СберСпасибо | G386: 23 | H386: Допродажи (upsell) | I386: 1 | J386: 1 | K386: =VLOOKUP(H386,metric_dict!A:B,2,0) -> Механики | L386: =IF(VLOOKUP(H386,metric_dict!A:C,3,0)=0,"",VLOOKUP(H386,metric_dict!A:C,3,0)) | M386: =VLOOKUP(H386,metric_dict!A:AA,4,0) -> Переход клиента на более ценный продукт или расширенный пакет услуг | N386: =VLOOKUP(H386,metric_dict!A:AA,5,0) -> Настроить мониторинг по ключевым механикам | O386: =VLOOKUP(H386,metric_dict!A:AA,6,0) -> 5 | P386: product | Q386: =VLOOKUP(H386,metric_dict!A:AA,7,0) -> 10
A387: 420 | B387: =A387+1 -> 421 | C387: =A387 -> 420 | D387: =A387-1 -> 419 | E387: CX | F387: СберСпасибо | G387: 24 | H387: Удержание клиентов | I387: 0 | J387: Не релевантно | K387: =VLOOKUP(H387,metric_dict!A:B,2,0) -> Механики | L387: =IF(VLOOKUP(H387,metric_dict!A:C,3,0)=0,"",VLOOKUP(H387,metric_dict!A:C,3,0)) | M387: =VLOOKUP(H387,metric_dict!A:AA,4,0) -> Коммуникация + ценность | N387: =VLOOKUP(H387,metric_dict!A:AA,5,0) -> Проработать механики удержания клиентов | O387: =VLOOKUP(H387,metric_dict!A:AA,6,0) -> 5 | P387: product | Q387: =VLOOKUP(H387,metric_dict!A:AA,7,0) -> 6
A388: 420 | B388: =A388+1 -> 421 | C388: =A388 -> 420 | D388: =A388-1 -> 419 | E388: CX | F388: СберСпасибо | G388: 25 | H388: Удержание клиентов | I388: 0 | J388: Не релевантно | K388: =VLOOKUP(H388,metric_dict!A:B,2,0) -> Механики | L388: =IF(VLOOKUP(H388,metric_dict!A:C,3,0)=0,"",VLOOKUP(H388,metric_dict!A:C,3,0)) | M388: =VLOOKUP(H388,metric_dict!A:AA,4,0) -> Коммуникация + ценность | N388: =VLOOKUP(H388,metric_dict!A:AA,5,0) -> Проработать механики удержания клиентов | O388: =VLOOKUP(H388,metric_dict!A:AA,6,0) -> 5 | P388: product | Q388: =VLOOKUP(H388,metric_dict!A:AA,7,0) -> 6
A389: 420 | B389: =A389+1 -> 421 | C389: =A389 -> 420 | D389: =A389-1 -> 419 | E389: CX | F389: СберСпасибо | G389: 225 | H389: Мониторинг механик | I389: 0.25 | J389: 0.25 | K389: =VLOOKUP(H389,metric_dict!A:B,2,0) -> Механики | L389: =IF(VLOOKUP(H389,metric_dict!A:C,3,0)=0,"",VLOOKUP(H389,metric_dict!A:C,3,0)) | M389: =VLOOKUP(H389,metric_dict!A:AA,4,0) -> Настроен по ключевым механикам работы с клиентской базой | N389: =VLOOKUP(H389,metric_dict!A:AA,5,0) -> Настроить мониторинг по ключевым механикам | O389: =VLOOKUP(H389,metric_dict!A:AA,6,0) -> 2 | P389: product | Q389: =VLOOKUP(H389,metric_dict!A:AA,7,0) -> 22
A390: 420 | B390: =A390+1 -> 421 | C390: =A390 -> 420 | D390: =A390-1 -> 419 | E390: CX | F390: СберСпасибо | G390: 27 | H390: Возврат клиентов | I390: 0 | J390: Не релевантно | K390: =VLOOKUP(H390,metric_dict!A:B,2,0) -> Механики | L390: =IF(VLOOKUP(H390,metric_dict!A:C,3,0)=0,"",VLOOKUP(H390,metric_dict!A:C,3,0)) | M390: =VLOOKUP(H390,metric_dict!A:AA,4,0) -> Реактивация оттекающих клиентов | N390: =VLOOKUP(H390,metric_dict!A:AA,5,0) -> Проработать механики реактивации клиентов | O390: =VLOOKUP(H390,metric_dict!A:AA,6,0) -> 5 | P390: product | Q390: =VLOOKUP(H390,metric_dict!A:AA,7,0) -> 4
A391: 420 | B391: =A391+1 -> 421 | C391: =A391 -> 420 | D391: =A391-1 -> 419 | E391: CX | F391: СберСпасибо | G391: 28 | H391: Возврат клиентов | I391: 0 | J391: Не релевантно | K391: =VLOOKUP(H391,metric_dict!A:B,2,0) -> Механики | L391: =IF(VLOOKUP(H391,metric_dict!A:C,3,0)=0,"",VLOOKUP(H391,metric_dict!A:C,3,0)) | M391: =VLOOKUP(H391,metric_dict!A:AA,4,0) -> Реактивация оттекающих клиентов | N391: =VLOOKUP(H391,metric_dict!A:AA,5,0) -> Проработать механики реактивации клиентов | O391: =VLOOKUP(H391,metric_dict!A:AA,6,0) -> 5 | P391: product | Q391: =VLOOKUP(H391,metric_dict!A:AA,7,0) -> 4
A392: 420 | B392: =A392+1 -> 421 | C392: =A392 -> 420 | D392: =A392-1 -> 419 | E392: CX | F392: СберСпасибо | G392: 29 | H392: Мониторинг механик | I392: 0 | J392: 0 | K392: =VLOOKUP(H392,metric_dict!A:B,2,0) -> Механики | L392: =IF(VLOOKUP(H392,metric_dict!A:C,3,0)=0,"",VLOOKUP(H392,metric_dict!A:C,3,0)) | M392: =VLOOKUP(H392,metric_dict!A:AA,4,0) -> Настроен по ключевым механикам работы с клиентской базой | N392: =VLOOKUP(H392,metric_dict!A:AA,5,0) -> Настроить мониторинг по ключевым механикам | O392: =VLOOKUP(H392,metric_dict!A:AA,6,0) -> 2 | P392: product | Q392: =VLOOKUP(H392,metric_dict!A:AA,7,0) -> 22
A393: 420 | B393: =A393+1 -> 421 | C393: =A393 -> 420 | D393: =A393-1 -> 419 | E393: CX | F393: СберСпасибо | G393: 30 | H393: Cross-sell | I393: 1 | J393: 1 | K393: =VLOOKUP(H393,metric_dict!A:B,2,0) -> Механики | L393: =IF(VLOOKUP(H393,metric_dict!A:C,3,0)=0,"",VLOOKUP(H393,metric_dict!A:C,3,0)) | M393: =VLOOKUP(H393,metric_dict!A:AA,4,0) -> В оформлении и после покупки | N393: =VLOOKUP(H393,metric_dict!A:AA,5,0) -> Проработать механики кросс-продаж | O393: =VLOOKUP(H393,metric_dict!A:AA,6,0) -> 5 | P393: product | Q393: =VLOOKUP(H393,metric_dict!A:AA,7,0) -> 8
A394: 420 | B394: =A394+1 -> 421 | C394: =A394 -> 420 | D394: =A394-1 -> 419 | E394: CX | F394: СберСпасибо | G394: 33 | H394: Допродажи (upsell) | J394: 0 | K394: =VLOOKUP(H394,metric_dict!A:B,2,0) -> Механики | L394: =IF(VLOOKUP(H394,metric_dict!A:C,3,0)=0,"",VLOOKUP(H394,metric_dict!A:C,3,0)) | M394: =VLOOKUP(H394,metric_dict!A:AA,4,0) -> Переход клиента на более ценный продукт или расширенный пакет услуг | N394: =VLOOKUP(H394,metric_dict!A:AA,5,0) -> Настроить мониторинг по ключевым механикам | O394: =VLOOKUP(H394,metric_dict!A:AA,6,0) -> 5 | P394: product | Q394: =VLOOKUP(H394,metric_dict!A:AA,7,0) -> 10
A395: 420 | B395: =A395+1 -> 421 | C395: =A395 -> 420 | D395: =A395-1 -> 419 | E395: CX | F395: СберСпасибо | G395: 34 | H395: Мониторинг механик | J395: 0 | K395: =VLOOKUP(H395,metric_dict!A:B,2,0) -> Механики | L395: =IF(VLOOKUP(H395,metric_dict!A:C,3,0)=0,"",VLOOKUP(H395,metric_dict!A:C,3,0)) | M395: =VLOOKUP(H395,metric_dict!A:AA,4,0) -> Настроен по ключевым механикам работы с клиентской базой | N395: =VLOOKUP(H395,metric_dict!A:AA,5,0) -> Настроить мониторинг по ключевым механикам | O395: =VLOOKUP(H395,metric_dict!A:AA,6,0) -> 2 | P395: product | Q395: =VLOOKUP(H395,metric_dict!A:AA,7,0) -> 22
A396: 420 | B396: =A396+1 -> 421 | C396: =A396 -> 420 | D396: =A396-1 -> 419 | E396: CX | F396: СберСпасибо | G396: 35 | H396: Discovery ≥40% бэклога | I396: 1 | J396: 1 | K396: =VLOOKUP(H396,metric_dict!A:B,2,0) -> Гипотезы и инициативы | L396: =IF(VLOOKUP(H396,metric_dict!A:C,3,0)=0,"",VLOOKUP(H396,metric_dict!A:C,3,0)) | M396: =VLOOKUP(H396,metric_dict!A:AA,4,0) -> Доля исследовательских задач DA | N396: =VLOOKUP(H396,metric_dict!A:AA,5,0) -> Сфокусировать бэклог аналитиков на research-задачи | O396: =VLOOKUP(H396,metric_dict!A:AA,6,0) -> 5 | P396: product | Q396: =VLOOKUP(H396,metric_dict!A:AA,7,0) -> 1
A397: 420 | B397: =A397+1 -> 421 | C397: =A397 -> 420 | D397: =A397-1 -> 419 | E397: CX | F397: СберСпасибо | G397: 36 | H397: Нет собственных аналитиков | J397: 0 | K397: =VLOOKUP(H397,metric_dict!A:B,2,0) -> #N/A | L397: =IF(VLOOKUP(H397,metric_dict!A:C,3,0)=0,"",VLOOKUP(H397,metric_dict!A:C,3,0)) -> #N/A | M397: =VLOOKUP(H397,metric_dict!A:AA,4,0) -> #N/A | N397: =VLOOKUP(H397,metric_dict!A:AA,5,0) -> #N/A | O397: =VLOOKUP(H397,metric_dict!A:AA,6,0) -> #N/A | P397: product | Q397: =VLOOKUP(H397,metric_dict!A:AA,7,0) -> #N/A
A398: 420 | B398: =A398+1 -> 421 | C398: =A398 -> 420 | D398: =A398-1 -> 419 | E398: CX | F398: СберСпасибо | G398: 38 | H398: Запуски кампаний за квартал | I398: 0.5 | J398: 0.5 | K398: =VLOOKUP(H398,metric_dict!A:B,2,0) -> Воронка привлечения | L398: =IF(VLOOKUP(H398,metric_dict!A:C,3,0)=0,"",VLOOKUP(H398,metric_dict!A:C,3,0)) | M398: =VLOOKUP(H398,metric_dict!A:AA,4,0) -> Self-service / кампейнинг, успешность | N398: =VLOOKUP(H398,metric_dict!A:AA,5,0) -> Развитие кампейнинга | O398: =VLOOKUP(H398,metric_dict!A:AA,6,0) -> 2 | P398: product | Q398: =VLOOKUP(H398,metric_dict!A:AA,7,0) -> 6
A399: 420 | B399: =A399+1 -> 421 | C399: =A399 -> 420 | D399: =A399-1 -> 419 | E399: CX | F399: СберСпасибо | G399: 39 | H399: Запуски кампаний за квартал | I399: 0 | J399: 0.5 | K399: =VLOOKUP(H399,metric_dict!A:B,2,0) -> Воронка привлечения | L399: =IF(VLOOKUP(H399,metric_dict!A:C,3,0)=0,"",VLOOKUP(H399,metric_dict!A:C,3,0)) | M399: =VLOOKUP(H399,metric_dict!A:AA,4,0) -> Self-service / кампейнинг, успешность | N399: =VLOOKUP(H399,metric_dict!A:AA,5,0) -> Развитие кампейнинга | O399: =VLOOKUP(H399,metric_dict!A:AA,6,0) -> 2 | P399: product | Q399: =VLOOKUP(H399,metric_dict!A:AA,7,0) -> 6
A400: 420 | B400: =A400+1 -> 421 | C400: =A400 -> 420 | D400: =A400-1 -> 419 | E400: CX | F400: СберСпасибо | G400: 40 | H400: Запуски кампаний за квартал | I400: 0.5 | J400: 0.5 | K400: =VLOOKUP(H400,metric_dict!A:B,2,0) -> Воронка привлечения | L400: =IF(VLOOKUP(H400,metric_dict!A:C,3,0)=0,"",VLOOKUP(H400,metric_dict!A:C,3,0)) | M400: =VLOOKUP(H400,metric_dict!A:AA,4,0) -> Self-service / кампейнинг, успешность | N400: =VLOOKUP(H400,metric_dict!A:AA,5,0) -> Развитие кампейнинга | O400: =VLOOKUP(H400,metric_dict!A:AA,6,0) -> 2 | P400: product | Q400: =VLOOKUP(H400,metric_dict!A:AA,7,0) -> 6
A401: 420 | B401: =A401+1 -> 421 | C401: =A401 -> 420 | D401: =A401-1 -> 419 | E401: CX | F401: СберСпасибо | G401: 41 | H401: Черновики в СБОЛ ≥70% | I401: Не релевантно | J401: Не релевантно | K401: =VLOOKUP(H401,metric_dict!A:B,2,0) -> Воронка привлечения | L401: =IF(VLOOKUP(H401,metric_dict!A:C,3,0)=0,"",VLOOKUP(H401,metric_dict!A:C,3,0)) | M401: =VLOOKUP(H401,metric_dict!A:AA,4,0) -> Покрытие черновиков коммуникациями | N401: =VLOOKUP(H401,metric_dict!A:AA,5,0) -> Увеличить покрытие черновиков | O401: =VLOOKUP(H401,metric_dict!A:AA,6,0) -> 5 | P401: product | Q401: =VLOOKUP(H401,metric_dict!A:AA,7,0) -> 7
A402: 420 | B402: =A402+1 -> 421 | C402: =A402 -> 420 | D402: =A402-1 -> 419 | E402: CX | F402: СберСпасибо | G402: 42 | H402: CX Score | I402: нет продукта | J402: нет продукта | K402: =VLOOKUP(H402,metric_dict!A:B,2,0) -> Клиентский опыт | L402: =IF(VLOOKUP(H402,metric_dict!A:C,3,0)=0,"",VLOOKUP(H402,metric_dict!A:C,3,0)) | M402: =VLOOKUP(H402,metric_dict!A:AA,4,0) -> Зелёная зона клиентского пути | N402: =VLOOKUP(H402,metric_dict!A:AA,5,0) -> Достигнуть целевого CX Score | O402: =VLOOKUP(H402,metric_dict!A:AA,6,0) -> 5 | P402: product | Q402: =VLOOKUP(H402,metric_dict!A:AA,7,0) -> 1
A403: 420 | B403: =A403+1 -> 421 | C403: =A403 -> 420 | D403: =A403-1 -> 419 | E403: CX | F403: СберСпасибо | G403: 43 | H403: A/B-тесты | J403: 0 | K403: =VLOOKUP(H403,metric_dict!A:B,2,0) -> Гипотезы и инициативы | L403: =IF(VLOOKUP(H403,metric_dict!A:C,3,0)=0,"",VLOOKUP(H403,metric_dict!A:C,3,0)) | M403: =VLOOKUP(H403,metric_dict!A:AA,4,0) -> Проведение A/B тестов | N403: =VLOOKUP(H403,metric_dict!A:AA,5,0) -> Запустить A/B-тестирование | O403: =VLOOKUP(H403,metric_dict!A:AA,6,0) -> 5 | P403: product | Q403: =VLOOKUP(H403,metric_dict!A:AA,7,0) -> 3
A404: 420 | B404: =A404+1 -> 421 | C404: =A404 -> 420 | D404: =A404-1 -> 419 | E404: CX | F404: СберСпасибо | G404: 44 | H404: Рейтинг DataDriven ≥7,5 | I404: 1 | J404: 1 | K404: =VLOOKUP(H404,metric_dict!A:B,2,0) -> Гипотезы и инициативы | L404: =IF(VLOOKUP(H404,metric_dict!A:C,3,0)=0,"",VLOOKUP(H404,metric_dict!A:C,3,0)) | M404: =VLOOKUP(H404,metric_dict!A:AA,4,0) -> Средняя оценка проведенных исследований | N404: =VLOOKUP(H404,metric_dict!A:AA,5,0) -> Повысить качество проведенных исследований | O404: =VLOOKUP(H404,metric_dict!A:AA,6,0) -> 5 | P404: product | Q404: =VLOOKUP(H404,metric_dict!A:AA,7,0) -> 2
A405: 420 | B405: =A405+1 -> 421 | C405: =A405 -> 420 | D405: =A405-1 -> 419 | E405: CX | F405: СберСпасибо | G405: 45 | H405: Доп. инициативы сверх БП | I405: 1 | J405: 1 | K405: =VLOOKUP(H405,metric_dict!A:B,2,0) -> Гипотезы и инициативы | L405: =IF(VLOOKUP(H405,metric_dict!A:C,3,0)=0,"",VLOOKUP(H405,metric_dict!A:C,3,0)) | M405: =VLOOKUP(H405,metric_dict!A:AA,4,0) -> В реестре инициатив | N405: =VLOOKUP(H405,metric_dict!A:AA,5,0) -> Сформировать перечень инициатив | O405: =VLOOKUP(H405,metric_dict!A:AA,6,0) -> 3 | P405: product | Q405: =VLOOKUP(H405,metric_dict!A:AA,7,0) -> 4
A406: 420 | B406: =A406+1 -> 421 | C406: =A406 -> 420 | D406: =A406-1 -> 419 | E406: CX | F406: СберСпасибо | G406: 47 | H406: Объем целевого рынка в Сбере | I406: 0.2 | J406: 0.2 | K406: =VLOOKUP(H406,metric_dict!A:B,2,0) -> Знание ключевых метрик | L406: =IF(VLOOKUP(H406,metric_dict!A:C,3,0)=0,"",VLOOKUP(H406,metric_dict!A:C,3,0)) | M406: =VLOOKUP(H406,metric_dict!A:AA,4,0) -> Оценка потенциального объема клиентов в Сбере | N406: =VLOOKUP(H406,metric_dict!A:AA,5,0) -> Знание метрик и инструментов | O406: =VLOOKUP(H406,metric_dict!A:AA,6,0) -> 1 | P406: product | Q406: =VLOOKUP(H406,metric_dict!A:AA,7,0) -> 2
A407: 420 | B407: =A407+1 -> 421 | C407: =A407 -> 420 | D407: =A407-1 -> 419 | E407: CX | F407: СберСпасибо | G407: 48 | H407: Клиенты с продуктом | I407: 0.2 | J407: 0.2 | K407: =VLOOKUP(H407,metric_dict!A:B,2,0) -> Знание ключевых метрик | L407: =IF(VLOOKUP(H407,metric_dict!A:C,3,0)=0,"",VLOOKUP(H407,metric_dict!A:C,3,0)) | M407: =VLOOKUP(H407,metric_dict!A:AA,4,0) -> Фактическая база клиентов продукта | N407: =VLOOKUP(H407,metric_dict!A:AA,5,0) -> Знание метрик и инструментов | O407: =VLOOKUP(H407,metric_dict!A:AA,6,0) -> 1 | P407: product | Q407: =VLOOKUP(H407,metric_dict!A:AA,7,0) -> 3
A408: 420 | B408: =A408+1 -> 421 | C408: =A408 -> 420 | D408: =A408-1 -> 419 | E408: CX | F408: СберСпасибо | G408: 49 | H408: MAU продукта | I408: 0.2 | J408: 0.2 | K408: =VLOOKUP(H408,metric_dict!A:B,2,0) -> Знание ключевых метрик | L408: =IF(VLOOKUP(H408,metric_dict!A:C,3,0)=0,"",VLOOKUP(H408,metric_dict!A:C,3,0)) | M408: =VLOOKUP(H408,metric_dict!A:AA,4,0) -> Активная месячная аудитория продукта | N408: =VLOOKUP(H408,metric_dict!A:AA,5,0) -> Знание метрик и инструментов | O408: =VLOOKUP(H408,metric_dict!A:AA,6,0) -> 1 | P408: product | Q408: =VLOOKUP(H408,metric_dict!A:AA,7,0) -> 4
A409: 420 | B409: =A409+1 -> 421 | C409: =A409 -> 420 | D409: =A409-1 -> 419 | E409: CX | F409: СберСпасибо | G409: 50 | H409: Знание продуктов спутников | I409: 0.1 | J409: 0.1 | K409: =VLOOKUP(H409,metric_dict!A:B,2,0) -> Знание ключевых метрик | L409: =IF(VLOOKUP(H409,metric_dict!A:C,3,0)=0,"",VLOOKUP(H409,metric_dict!A:C,3,0)) | M409: =VLOOKUP(H409,metric_dict!A:AA,4,0) -> Понимание связанных продуктов и сценариев | N409: =VLOOKUP(H409,metric_dict!A:AA,5,0) -> Знание метрик и инструментов | O409: =VLOOKUP(H409,metric_dict!A:AA,6,0) -> 1 | P409: product | Q409: =VLOOKUP(H409,metric_dict!A:AA,7,0) -> 12
A410: 420 | B410: =A410+1 -> 421 | C410: =A410 -> 420 | D410: =A410-1 -> 419 | E410: CX | F410: СберСпасибо | G410: 51 | H410: Знание продуктов спутников | I410: 0.1 | J410: 0.1 | K410: =VLOOKUP(H410,metric_dict!A:B,2,0) -> Знание ключевых метрик | L410: =IF(VLOOKUP(H410,metric_dict!A:C,3,0)=0,"",VLOOKUP(H410,metric_dict!A:C,3,0)) | M410: =VLOOKUP(H410,metric_dict!A:AA,4,0) -> Понимание связанных продуктов и сценариев | N410: =VLOOKUP(H410,metric_dict!A:AA,5,0) -> Знание метрик и инструментов | O410: =VLOOKUP(H410,metric_dict!A:AA,6,0) -> 1 | P410: product | Q410: =VLOOKUP(H410,metric_dict!A:AA,7,0) -> 12
A411: 420 | B411: =A411+1 -> 421 | C411: =A411 -> 420 | D411: =A411-1 -> 419 | E411: CX | F411: СберСпасибо | G411: 96 | H411: Мониторинг механик | J411: 0 | K411: =VLOOKUP(H411,metric_dict!A:B,2,0) -> Механики | L411: =IF(VLOOKUP(H411,metric_dict!A:C,3,0)=0,"",VLOOKUP(H411,metric_dict!A:C,3,0)) | M411: =VLOOKUP(H411,metric_dict!A:AA,4,0) -> Настроен по ключевым механикам работы с клиентской базой | N411: =VLOOKUP(H411,metric_dict!A:AA,5,0) -> Настроить мониторинг по ключевым механикам | O411: =VLOOKUP(H411,metric_dict!A:AA,6,0) -> 2 | P411: product | Q411: =VLOOKUP(H411,metric_dict!A:AA,7,0) -> 22
A412: 420 | B412: =A412+1 -> 421 | C412: =A412 -> 420 | D412: =A412-1 -> 419 | E412: CX | F412: СберСпасибо | G412: 99 | H412: Мониторинг механик | J412: 0 | K412: =VLOOKUP(H412,metric_dict!A:B,2,0) -> Механики | L412: =IF(VLOOKUP(H412,metric_dict!A:C,3,0)=0,"",VLOOKUP(H412,metric_dict!A:C,3,0)) | M412: =VLOOKUP(H412,metric_dict!A:AA,4,0) -> Настроен по ключевым механикам работы с клиентской базой | N412: =VLOOKUP(H412,metric_dict!A:AA,5,0) -> Настроить мониторинг по ключевым механикам | O412: =VLOOKUP(H412,metric_dict!A:AA,6,0) -> 2 | P412: product | Q412: =VLOOKUP(H412,metric_dict!A:AA,7,0) -> 22
A413: 420 | B413: =A413+1 -> 421 | C413: =A413 -> 420 | D413: =A413-1 -> 419 | E413: CX | F413: СберСпасибо | G413: 98 | H413: Гибкое изменение условий продукта | I413: 0 | J413: 1 | K413: =VLOOKUP(H413,metric_dict!A:B,2,0) -> Механики | L413: =IF(VLOOKUP(H413,metric_dict!A:C,3,0)=0,"",VLOOKUP(H413,metric_dict!A:C,3,0)) | M413: =VLOOKUP(H413,metric_dict!A:AA,4,0) -> Возможность изменить набор опций по продукту без IT-разработки | N413: =VLOOKUP(H413,metric_dict!A:AA,5,0) -> Выстроить процесс гибкого изменения условий без IT | O413: =VLOOKUP(H413,metric_dict!A:AA,6,0) -> 10 | P413: product | Q413: =VLOOKUP(H413,metric_dict!A:AA,7,0) -> 7
A414: 420 | B414: =A414+1 -> 421 | C414: =A414 -> 420 | D414: =A414-1 -> 419 | E414: CX | F414: СберСпасибо | G414: 53 | H414: Ссылка на воронку оттока | J414: https://confluence.sberbank.ru/pages/viewpage.action?pageId=14212498623 | K414: =VLOOKUP(H414,metric_dict!A:B,2,0) -> #N/A | L414: =IF(VLOOKUP(H414,metric_dict!A:C,3,0)=0,"",VLOOKUP(H414,metric_dict!A:C,3,0)) -> #N/A | M414: =VLOOKUP(H414,metric_dict!A:AA,4,0) -> #N/A | N414: =VLOOKUP(H414,metric_dict!A:AA,5,0) -> #N/A | O414: =VLOOKUP(H414,metric_dict!A:AA,6,0) -> #N/A | P414: product | Q414: =VLOOKUP(H414,metric_dict!A:AA,7,0) -> #N/A
A415: 420 | B415: =A415+1 -> 421 | C415: =A415 -> 420 | D415: =A415-1 -> 419 | E415: CX | F415: СберСпасибо | G415: 52 | H415: Ссылка на коронку привлечения | J415: https://confluence.sberbank.ru/pages/viewpage.action?pageId=14212498623 | K415: =VLOOKUP(H415,metric_dict!A:B,2,0) -> #N/A | L415: =IF(VLOOKUP(H415,metric_dict!A:C,3,0)=0,"",VLOOKUP(H415,metric_dict!A:C,3,0)) -> #N/A | M415: =VLOOKUP(H415,metric_dict!A:AA,4,0) -> #N/A | N415: =VLOOKUP(H415,metric_dict!A:AA,5,0) -> #N/A | O415: =VLOOKUP(H415,metric_dict!A:AA,6,0) -> #N/A | P415: product | Q415: =VLOOKUP(H415,metric_dict!A:AA,7,0) -> #N/A
A416: 420 | B416: =A416+1 -> 421 | C416: =A416 -> 420 | D416: =A416-1 -> 419 | E416: CX | F416: СберСпасибо | G416: 101 | H416: Цифр.цели | I416: 1 | J416: 1 | K416: =VLOOKUP(H416,metric_dict!A:B,2,0) -> #N/A | L416: =IF(VLOOKUP(H416,metric_dict!A:C,3,0)=0,"",VLOOKUP(H416,metric_dict!A:C,3,0)) -> #N/A | M416: =VLOOKUP(H416,metric_dict!A:AA,4,0) -> #N/A | N416: =VLOOKUP(H416,metric_dict!A:AA,5,0) -> #N/A | O416: =VLOOKUP(H416,metric_dict!A:AA,6,0) -> #N/A | P416: product | Q416: =VLOOKUP(H416,metric_dict!A:AA,7,0) -> #N/A
A417: 420 | B417: =A417+1 -> 421 | C417: =A417 -> 420 | D417: =A417-1 -> 419 | E417: CX | F417: СберСпасибо | G417: 102 | H417: Цифр.факторы | I417: 0 | J417: 1 | K417: =VLOOKUP(H417,metric_dict!A:B,2,0) -> #N/A | L417: =IF(VLOOKUP(H417,metric_dict!A:C,3,0)=0,"",VLOOKUP(H417,metric_dict!A:C,3,0)) -> #N/A | M417: =VLOOKUP(H417,metric_dict!A:AA,4,0) -> #N/A | N417: =VLOOKUP(H417,metric_dict!A:AA,5,0) -> #N/A | O417: =VLOOKUP(H417,metric_dict!A:AA,6,0) -> #N/A | P417: product | Q417: =VLOOKUP(H417,metric_dict!A:AA,7,0) -> #N/A
A418: 420 | B418: =A418+1 -> 421 | C418: =A418 -> 420 | D418: =A418-1 -> 419 | E418: CX | F418: СберСпасибо | G418: 103 | H418: Цифр.прогнозы | I418: 0 | J418: 1 | K418: =VLOOKUP(H418,metric_dict!A:B,2,0) -> #N/A | L418: =IF(VLOOKUP(H418,metric_dict!A:C,3,0)=0,"",VLOOKUP(H418,metric_dict!A:C,3,0)) -> #N/A | M418: =VLOOKUP(H418,metric_dict!A:AA,4,0) -> #N/A | N418: =VLOOKUP(H418,metric_dict!A:AA,5,0) -> #N/A | O418: =VLOOKUP(H418,metric_dict!A:AA,6,0) -> #N/A | P418: product | Q418: =VLOOKUP(H418,metric_dict!A:AA,7,0) -> #N/A
A419: 18 | B419: 19 | C419: 18 | D419: 17 | E419: CX | F419: Молодежь | G419: 54 | H419: Ссылка на бэклог | J419: https://jira.sberbank.ru/secure/RapidBoard.jspa?rapidView=41166&projectKey=SDRSA | K419: =VLOOKUP(H419,metric_dict!A:B,2,0) -> #N/A | L419: =IF(VLOOKUP(H419,metric_dict!A:C,3,0)=0,"",VLOOKUP(H419,metric_dict!A:C,3,0)) -> #N/A | M419: =VLOOKUP(H419,metric_dict!A:AA,4,0) -> #N/A | N419: =VLOOKUP(H419,metric_dict!A:AA,5,0) -> #N/A | O419: =VLOOKUP(H419,metric_dict!A:AA,6,0) -> #N/A | P419: segment | Q419: =VLOOKUP(H419,metric_dict!A:AA,7,0) -> #N/A
A420: 33 | B420: 34 | C420: 33 | D420: 32 | E420: CX | F420: Top Affluent | G420: 44 | H420: Ссылка на коронку привлечения | J420: https://navigator.sigma.sbrf.ru/gdash/1000000135/1000046561 | K420: =VLOOKUP(H420,metric_dict!A:B,2,0) -> #N/A | L420: =IF(VLOOKUP(H420,metric_dict!A:C,3,0)=0,"",VLOOKUP(H420,metric_dict!A:C,3,0)) -> #N/A | M420: =VLOOKUP(H420,metric_dict!A:AA,4,0) -> #N/A | N420: =VLOOKUP(H420,metric_dict!A:AA,5,0) -> #N/A | O420: =VLOOKUP(H420,metric_dict!A:AA,6,0) -> #N/A | P420: segment | Q420: =VLOOKUP(H420,metric_dict!A:AA,7,0) -> #N/A
A421: 43 | B421: 44 | C421: 43 | D421: 42 | E421: CX | F421: МВС | G421: 44 | H421: Ссылка на коронку привлечения | J421: https://confluence.sberbank.ru/pages/viewpage.action?pageId=6699321962 | K421: =VLOOKUP(H421,metric_dict!A:B,2,0) -> #N/A | L421: =IF(VLOOKUP(H421,metric_dict!A:C,3,0)=0,"",VLOOKUP(H421,metric_dict!A:C,3,0)) -> #N/A | M421: =VLOOKUP(H421,metric_dict!A:AA,4,0) -> #N/A | N421: =VLOOKUP(H421,metric_dict!A:AA,5,0) -> #N/A | O421: =VLOOKUP(H421,metric_dict!A:AA,6,0) -> #N/A | P421: segment | Q421: =VLOOKUP(H421,metric_dict!A:AA,7,0) -> #N/A
A422: 38 | B422: 39 | C422: 38 | D422: 37 | E422: CX | F422: PB | G422: 53 | H422: Ссылка на воронку оттока | J422: https://navigator.sigma.sbrf.ru/gdash/1000000301/1000003047?segment=PB | K422: =VLOOKUP(H422,metric_dict!A:B,2,0) -> #N/A | L422: =IF(VLOOKUP(H422,metric_dict!A:C,3,0)=0,"",VLOOKUP(H422,metric_dict!A:C,3,0)) -> #N/A | M422: =VLOOKUP(H422,metric_dict!A:AA,4,0) -> #N/A | N422: =VLOOKUP(H422,metric_dict!A:AA,5,0) -> #N/A | O422: =VLOOKUP(H422,metric_dict!A:AA,6,0) -> #N/A | P422: segment | Q422: =VLOOKUP(H422,metric_dict!A:AA,7,0) -> #N/A
...

Sheet metric_dict
A1: metric_name | B1: metric_group | C1: metric_subgroup | D1: metric_footer | E1: recommendation | F1: recommendation_group | G1: sort
A2: Отток.Регулярность (авто) | B2: Воронка оттока | C2: Отчетность | D2: Daily / weekly | E2: Автоматизировать расчет воронки оттока | F2: 4 | G2: 3
A3: Привлечение.Регулярность (авто) | B3: Воронка привлечения | C3: Отчетность | D3: Daily / weekly | E3: Автоматизировать расчет воронки привлечения | F3: 4 | G3: 3
A4: Оповещения по бизнес-метрикам | B4: Алерты | D4: Светофоры целей, драйверов, воронок | E4: Внедрить систему оповещений | F4: 3 | G4: 2
A5: Оповещения по системным сбоям | B5: Алерты | D5: Авто-алерты по IT-инфраструктуре | E5: Внедрить систему оповещений | F5: 5 | G5: 1
A6: Гибкое изменение условий продукта | B6: Механики | D6: Возможность изменить набор опций по продукту без IT-разработки | E6: Выстроить процесс гибкого изменения условий без IT | F6: 10 | G6: 7
A7: Факторный анализ — драйверы 1–2 ур. | B7: Цели | D7: Согласно модели бизнес-процесса | E7: Декомпозировать значения целей на драйверы | F7: 7 | G7: 2
A8: Отток.Полнота отчёта | B8: Воронка оттока | C8: Отчетность | D8: Retention, CR, удержание | E8: Донасытить метриками мониторинг по воронке оттока | F8: 3 | G8: 2
A9: Привлечение.Полнота отчёта | B9: Воронка привлечения | C9: Отчетность | D9: Источники, CR, объёмы, сегменты | E9: Донасытить метриками мониторинг по воронке привлечения | F9: 3 | G9: 2
A10: CX Score | B10: Клиентский опыт | D10: Зелёная зона клиентского пути | E10: Достигнуть целевого CX Score | F10: 5 | G10: 1
A11: A/B-тесты | B11: Гипотезы и инициативы | D11: Проведение A/B тестов | E11: Запустить A/B-тестирование | F11: 5 | G11: 3
A12: Отток.Регулярная отчётность | B12: Воронка оттока | C12: Отчетность | D12: Настроена по воронке | E12: Настроить мониторинг по воронке оттока | F12: 2 | G12: 1
A13: Привлечение.Регулярная отчётность | B13: Воронка привлечения | C13: Отчетность | D13: Настроена по воронке | E13: Настроить мониторинг по воронке привлечения | F13: 2 | G13: 1
A14: Мониторинг механик | B14: Механики | D14: Настроен по ключевым механикам работы с клиентской базой | E14: Настроить мониторинг по ключевым механикам | F14: 2 | G14: 22
A15: Цели выведены на мониторинг | B15: Цели | D15: Регулярное обновление в Навигаторе | E15: Обогащение целей/драйверов/прогнозов в Навигаторе | F15: 2 | G15: 1
A16: MAU продукта | B16: Знание ключевых метрик | D16: Активная месячная аудитория продукта | E16: Знание метрик и инструментов | F16: 1 | G16: 4
A17: Активная клиентская база | B17: Знание ключевых метрик | D17: Знание значения метрики активной клиентской базы | E17: Знание метрик и инструментов | F17: 1 | G17: 5
A18: Доля рынка ФОТ, % | B18: Знание ключевых метрик | D18: Знание метрики доля рынка ФОТ, % | E18: Знание метрик и инструментов | F18: 1 | G18: 9
A19: Знание об отчетности в Навигаторе | B19: Знание ключевых метрик | D19: Понимание доступной отчетности и регулярного мониторинга | E19: Знание метрик и инструментов | F19: 1 | G19: 13
A20: Знание продуктов спутников | B20: Знание ключевых метрик | D20: Понимание связанных продуктов и сценариев | E20: Знание метрик и инструментов | F20: 1 | G20: 12
A21: Клиенты с продуктом | B21: Знание ключевых метрик | D21: Фактическая база клиентов продукта | E21: Знание метрик и инструментов | F21: 1 | G21: 3
A22: Кол-во Major клиентов | B22: Знание ключевых метрик | D22: Знание метрики Major | E22: Знание метрик и инструментов | F22: 1 | G22: 6
A23: Кол-во клиентов с 2+ нефин. сервисов | B23: Знание ключевых метрик | D23: Знание метрики кол-во клиентов с 2+ нефин.сервисов | E23: Знание метрик и инструментов | F23: 1 | G23: 7
A24: Кол-во получателей ЗП | B24: Знание ключевых метрик | D24: Знание метрики кол-во получателей ЗП | E24: Знание метрик и инструментов | F24: 1 | G24: 8
A25: Объем зачислений ФОТ | B25: Знание ключевых метрик | D25: Знание метрики объем зачислений ФОТ | E25: Знание метрик и инструментов | F25: 1 | G25: 10
... A49: Допродажи (upsell) | B49: Механики | D49: Переход клиента на более ценный продукт или расширенный пакет услуг | E49: Настроить мониторинг по ключевым механикам | F49: 5 | G49: 10

Sheet резерв
A1: fake_id | B1: perc_id | C1: value_id | D1: max_value_id | E1: Юнит | F1: Продукт | G1: metric | H1: metric_name | I1: value | J1: max_value | K1: metric_group | L1: metric_footer | M1: recommendation | N1: recommendation_group | O1: type
A2: 75 | B2: 76 | C2: 75 | D2: 74 | E2: УБ | F2: Осаго | G2: 1 | H2: Объем целевого рынка в России | I2: 0 | J2: 0.2 | K2: Самооценка знания продуктовых метрик | L2: Оценка потенциального объема клиентов в России | M2: Ознакомиться со значениями ключевых метрик | N2: easy | O2: product
A3: 75 | B3: 76 | C3: 75 | D3: 74 | E3: УБ | F3: Осаго | G3: 2 | H3: Знание об отчетности в Навигаторе | I3: 0.25 | J3: 0.5 | K3: Самооценка знания продуктовых метрик | L3: Понимание доступной отчетности и регулярного мониторинга | M3: Ознакомиться со значениями ключевых метрик | N3: easy | O3: product
A4: 75 | B4: 76 | C4: 75 | D4: 74 | E4: УБ | F4: Осаго | G4: 3 | H4: Цели выведены на мониторинг | I4: 0.5 | J4: 1 | K4: Цели | L4: Регулярное обновление в Навигаторе | M4: Настроить мониторинг целей в Навигаторе | N4: easy | O4: product
A5: 75 | B5: 76 | C5: 75 | D5: 74 | E5: УБ | F5: Осаго | G5: 4 | H5: Факторный анализ — драйверы 1–2 ур. | I5: 0.5 | J5: 1 | K5: Цели | L5: Согласно модели бизнес-процесса | M5: Декомпозировать значения целей на драйверы | N5: medium | O5: product
A6: 75 | B6: 76 | C6: 75 | D6: 74 | E6: УБ | F6: Осаго | G6: 5 | H6: Прогноз по целям | I6: 0.5 | J6: 1 | K6: Цели | L6: Прогноз выведен в Навигатор | M6: Сформировать прогнозные значения по целям | N6: medium | O6: product
A7: 75 | B7: 76 | C7: 75 | D7: 74 | E7: УБ | F7: Осаго | G7: 9 | H7: Привлечение.Регулярная отчётность | I7: 0.5 | J7: 0.5 | K7: Воронка привлечения | L7: Настроена по воронке | M7: Настроить мониторинг по воронке привлечения | N7: easy | O7: product
A8: 75 | B8: 76 | C8: 75 | D8: 74 | E8: УБ | F8: Осаго | G8: 10 | H8: Привлечение.Полнота отчёта | I8: 0.5 | J8: 0.5 | K8: Воронка привлечения | L8: Источники, CR, объёмы, сегменты | M8: Донасытить метриками мониторинг по воронке привлечения | N8: easy | O8: product
A9: 75 | B9: 76 | C9: 75 | D9: 74 | E9: УБ | F9: Осаго | G9: 11 | H9: Привлечение.Регулярность (авто) | I9: 1 | J9: 1 | K9: Воронка привлечения | L9: Daily / weekly | M9: Автоматизировать расчет воронки привлечения | N9: medium | O9: product
A10: 75 | B10: 76 | C10: 75 | D10: 74 | E10: УБ | F10: Осаго | G10: 12 | H10: Отток.Регулярная отчётность | I10: 0.5 | J10: 0.5 | K10: Воронка оттока | L10: Настроена по воронке | M10: Настроить мониторинг по воронке оттока | N10: easy | O10: product
A11: 75 | B11: 76 | C11: 75 | D11: 74 | E11: УБ | F11: Осаго | G11: 13 | H11: Отток.Полнота отчёта | I11: 0 | J11: 0.5 | K11: Воронка оттока | L11: Retention, CR, удержание | M11: Донасытить метриками мониторинг по воронке оттока | N11: easy | O11: product
A12: 75 | B12: 76 | C12: 75 | D12: 74 | E12: УБ | F12: Осаго | G12: 14 | H12: Отток.Регулярность (авто) | I12: 1 | J12: 1 | K12: Воронка оттока | L12: Daily / weekly | M12: Автоматизировать расчет воронки оттока | N12: medium | O12: product
A13: 75 | B13: 76 | C13: 75 | D13: 74 | E13: УБ | F13: Осаго | G13: 15 | H13: Наличие бенчмарков | I13: 1 | J13: 1 | K13: BENCHMARKS | L13: Цели / динамика / рынок | M13: Сформировать бенчмарки по продуктовым метрикам | N13: medium | O13: product
A14: 75 | B14: 76 | C14: 75 | D14: 74 | E14: УБ | F14: Осаго | G14: 16 | H14: Опишите, какие бенчмарки используются | I14: 0 | J14: 0 | K14: #N/A | L14: #N/A | M14: #N/A | N14: #N/A | O14: product
A15: 75 | B15: 76 | C15: 75 | D15: 74 | E15: УБ | F15: Осаго | G15: 17 | H15: Проведение анализа воронки привлечения | I15: 1 | J15: 1 | K15: Воронка привлечения | L15: Оценка эффективности, поиск точек роста | M15: Провести анализ привлечения, выявить точки роста | N15: medium | O15: product
A16: 75 | B16: 76 | C16: 75 | D16: 74 | E16: УБ | F16: Осаго | G16: 18 | H16: Составлен перечень инициатив по привлечению | I16: 1 | J16: 1 | K16: Воронка привлечения | L16: План действий по росту | M16: Сформировать перечень инициатив | N16: medium | O16: product
A17: 75 | B17: 76 | C17: 75 | D17: 74 | E17: УБ | F17: Осаго | G17: 19 | H17: Проведение анализа воронки оттока | I17: 1 | J17: 1 | K17: Воронка оттока | L17: Оценка причин и узких мест | M17: Провести анализ оттока, выявить точки роста | N17: medium | O17: product
A18: 75 | B18: 76 | C18: 75 | D18: 74 | E18: УБ | F18: Осаго | G18: 20 | H18: Мероприятия по работе с отклонениями | I18: 1 | J18: 1 | K18: Воронка оттока | L18: План действий по отклонениям | M18: Сформировать список мероприятий по снижению оттока | N18: medium | O18: product
A19: 75 | B19: 76 | C19: 75 | D19: 74 | E19: УБ | F19: Осаго | G19: 21 | H19: Оповещения по системным сбоям | I19: 1 | J19: 1 | K19: Алерты | L19: Авто-алерты по IT-инфраструктуре | M19: Внедрить систему оповещений | N19: easy | O19: product
A20: 75 | B20: 76 | C20: 75 | D20: 74 | E20: УБ | F20: Осаго | G20: 22 | H20: Оповещения по бизнес-метрикам | I20: 1 | J20: 1 | K20: Алерты | L20: Светофоры целей, драйверов, воронок | M20: Внедрить систему оповещений | N20: medium | O20: product
A21: 75 | B21: 76 | C21: 75 | D21: 74 | E21: УБ | F21: Осаго | G21: 23 | H21: Полнота продуктовых механик | I21: 0 | J21: 0 | K21: Клиентский опыт | L21: Механики, влияющие на клиентский опыт | M21: Увеличить покрытие механиками | N21: medium | O21: product
A22: 75 | B22: 76 | C22: 75 | D22: 74 | E22: УБ | F22: Осаго | G22: 24 | H22: Удержание клиентов | I22: 0.5 | J22: 0.5 | K22: Воронка оттока | L22: Коммуникация + ценность | M22: Проработать механики удержания клиентов | N22: medium | O22: product
A23: 75 | B23: 76 | C23: 75 | D23: 74 | E23: УБ | F23: Осаго | G23: 25 | H23: Удержание клиентов | I23: 0.5 | J23: 0.5 | K23: Воронка оттока | L23: Коммуникация + ценность | M23: Проработать механики удержания клиентов | N23: medium | O23: product
A24: 75 | B24: 76 | C24: 75 | D24: 74 | E24: УБ | F24: Осаго | G24: 26 | H24: Полнота продуктовых механик | I24: 0 | J24: 0 | K24: Клиентский опыт | L24: Механики, влияющие на клиентский опыт | M24: Увеличить покрытие механиками | N24: medium | O24: product
A25: 75 | B25: 76 | C25: 75 | D25: 74 | E25: УБ | F25: Осаго | G25: 27 | H25: Возврат клиентов | I25: 0.5 | J25: 0.5 | K25: Воронка оттока | L25: Реактивация оттекающих клиентов | M25: Проработать механики реактивации клиентов | N25: medium | O25: product
A26: 75 | B26: 76 | C26: 75 | D26: 74 | E26: УБ | F26: Осаго | G26: 28 | H26: Возврат клиентов | I26: 0.5 | J26: 0.5 | K26: Воронка оттока | L26: Реактивация оттекающих клиентов | M26: Проработать механики реактивации клиентов | N26: medium | O26: product
... A33: 75 | B33: 76 | C33: 75 | D33: 74 | E33: УБ | F33: Осаго | G33: 35 | H33: Discovery ≥40% бэклога | I33: 0.5 | J33: 1 | K33: Гипотезы и инициативы | L33: Доля исследовательских задач DA | M33: Сфокусировать бэклог аналитиков на research-задачи | N33: medium | O33: product
A34: 75 | B34: 76 | C34: 75 | D34: 74 | E34: УБ | F34: Осаго | G34: 36 | H34: Нет собственных аналитиков | I34: 0 | J34: 0 | K34: #N/A | L34: #N/A | M34: #N/A | N34: #N/A | O34: product
A35: 75 | B35: 76 | C35: 75 | D35: 74 | E35: УБ | F35: Осаго | G35: 38 | H35: Запуски кампаний за квартал | I35: 0.5 | J35: 0.5 | K35: Воронка привлечения | L35: Self-service / кампейнинг, покрытие | M35: Запустить кампании | N35: easy | O35: product
A36: 75 | B36: 76 | C36: 75 | D36: 74 | E36: УБ | F36: Осаго | G36: 39 | H36: Запуски кампаний за квартал | I36: 0 | J36: 0.5 | K36: Воронка привлечения | L36: Self-service / кампейнинг, покрытие | M36: Запустить кампании | N36: easy | O36: product
A37: 75 | B37: 76 | C37: 75 | D37: 74 | E37: УБ | F37: Осаго | G37: 40 | H37: Запуски кампаний за квартал | I37: 0.5 | J37: 0.5 | K37: Воронка привлечения | L37: Self-service / кампейнинг, покрытие | M37: Запустить кампании | N37: easy | O37: product
A38: 75 | B38: 76 | C38: 75 | D38: 74 | E38: УБ | F38: Осаго | G38: 41 | H38: Черновики в СБОЛ ≥70% | I38: 0.5 | J38: 1 | K38: Гипотезы и инициативы | L38: Покрытие черновиками | M38: Увеличить покрытие черновиков | N38: medium | O38: product
A39: 75 | B39: 76 | C39: 75 | D39: 74 | E39: УБ | F39: Осаго | G39: 42 | H39: CX Score | I39: 0.5 | J39: 1 | K39: Клиентский опыт | L39: Зелёная зона клиентского пути | M39: Достигнуть целевого CX Score | N39: medium | O39: product
A40: 75 | B40: 76 | C40: 75 | D40: 74 | E40: УБ | F40: Осаго | G40: 43 | H40: A/B-тесты | I40: 0 | J40: 0 | K40: Гипотезы и инициативы | L40: Проведение A/B тестов | M40: Запустить A/B-тестирование | N40: medium | O40: product
A41: 75 | B41: 76 | C41: 75 | D41: 74 | E41: УБ | F41: Осаго | G41: 44 | H41: Рейтинг DataDriven ≥7,5 | I41: 0 | J41: 1 | K41: Гипотезы и инициативы | L41: Средняя оценка проведенных исследований | M41: Повысить качество проведенных исследований | N41: medium | O41: product
A42: 75 | B42: 76 | C42: 75 | D42: 74 | E42: УБ | F42: Осаго | G42: 45 | H42: Доп. инициативы сверх БП | I42: 0 | J42: 1 | K42: Гипотезы и инициативы | L42: В реестре инициатив | M42: Сформировать перечень инициатив | N42: medium | O42: product
A43: 75 | B43: 76 | C43: 75 | D43: 74 | E43: УБ | F43: Осаго | G43: 47 | H43: Объем целевого рынка в Сбере | I43: 0 | J43: 0.2 | K43: Самооценка знания продуктовых метрик | L43: Оценка потенциального объема клиентов в Сбере | M43: Ознакомиться со значениями ключевых метрик | N43: easy | O43: product
A44: 75 | B44: 76 | C44: 75 | D44: 74 | E44: УБ | F44: Осаго | G44: 48 | H44: Клиенты с продуктом | I44: 0 | J44: 0.2 | K44: Самооценка знания продуктовых метрик | L44: Фактическая база клиентов продукта | M44: Ознакомиться со значениями ключевых метрик | N44: easy | O44: product
A45: 75 | B45: 76 | C45: 75 | D45: 74 | E45: УБ | F45: Осаго | G45: 49 | H45: MAU продукта | I45: 0.2 | J45: 0.2 | K45: Самооценка знания продуктовых метрик | L45: Активная месячная аудитория продукта | M45: Ознакомиться со значениями ключевых метрик | N45: easy | O45: product
A46: 75 | B46: 76 | C46: 75 | D46: 74 | E46: УБ | F46: Осаго | G46: 50 | H46: Знание продуктов спутников | I46: 0.1 | J46: 0.1 | K46: Самооценка знания продуктовых метрик | L46: Понимание связанных продуктов и сценариев | M46: Ознакомиться со значениями ключевых метрик | N46: easy | O46: product
... A59: 80 | B59: 81 | C59: 80 | D59: 79 | E59: УБ | F59: КАСКО | G59: 15 | H59: Наличие бенчмарков | I59: 1 | J59: 1 | K59: BENCHMARKS | L59: Цели / динамика / рынок | M59: Сформировать бенчмарки по продуктовым метрикам | N59: medium | O59: product
A60: 80 | B60: 81 | C60: 80 | D60: 79 | E60: УБ | F60: КАСКО | G60: 16 | H60: Опишите, какие бенчмарки используются | I60: 0 | J60: 0 | K60: #N/A | L60: #N/A | M60: #N/A | N60: #N/A | O60: product
A61: 80 | B61: 81 | C61: 80 | D61: 79 | E61: УБ | F61: КАСКО | G61: 17 | H61: Проведение анализа воронки привлечения | I61: 1 | J61: 1 | K61: Воронка привлечения | L61: Оценка эффективности, поиск точек роста | M61: Провести анализ привлечения, выявить точки роста | N61: medium | O61: product
A62: 80 | B62: 81 | C62: 80 | D62: 79 | E62: УБ | F62: КАСКО | G62: 18 | H62: Составлен перечень инициатив по привлечению | I62: 1 | J62: 1 | K62: Воронка привлечения | L62: План действий по росту | M62: Сформировать перечень инициатив | N62: medium | O62: product
A63: 80 | B63: 81 | C63: 80 | D63: 79 | E63: УБ | F63: КАСКО | G63: 19 | H63: Проведение анализа воронки оттока | I63: 1 | J63: 1 | K63: Воронка оттока | L63: Оценка причин и узких мест | M63: Провести анализ оттока, выявить точки роста | N63: medium | O63: product
A64: 80 | B64: 81 | C64: 80 | D64: 79 | E64: УБ | F64: КАСКО | G64: 20 | H64: Мероприятия по работе с отклонениями | I64: 1 | J64: 1 | K64: Воронка оттока | L64: План действий по отклонениям | M64: Сформировать список мероприятий по снижению оттока | N64: medium | O64: product
A65: 80 | B65: 81 | C65: 80 | D65: 79 | E65: УБ | F65: КАСКО | G65: 21 | H65: Оповещения по системным сбоям | I65: 1 | J65: 1 | K65: Алерты | L65: Авто-алерты по IT-инфраструктуре | M65: Внедрить систему оповещений | N65: easy | O65: product
A66: 80 | B66: 81 | C66: 80 | D66: 79 | E66: УБ | F66: КАСКО | G66: 22 | H66: Оповещения по бизнес-метрикам | I66: 1 | J66: 1 | K66: Алерты | L66: Светофоры целей, драйверов, воронок | M66: Внедрить систему оповещений | N66: medium | O66: product
A67: 80 | B67: 81 | C67: 80 | D67: 79 | E67: УБ | F67: КАСКО | G67: 23 | H67: Полнота продуктовых механик | I67: 0 | J67: 0 | K67: Клиентский опыт | L67: Механики, влияющие на клиентский опыт | M67: Увеличить покрытие механиками | N67: medium | O67: product
A68: 80 | B68: 81 | C68: 80 | D68: 79 | E68: УБ | F68: КАСКО | G68: 24 | H68: Удержание клиентов | I68: 0.5 | J68: 0.5 | K68: Воронка оттока | L68: Коммуникация + ценность | M68: Проработать механики удержания клиентов | N68: medium | O68: product
A69: 80 | B69: 81 | C69: 80 | D69: 79 | E69: УБ | F69: КАСКО | G69: 25 | H69: Удержание клиентов | I69: 0.5 | J69: 0.5 | K69: Воронка оттока | L69: Коммуникация + ценность | M69: Проработать механики удержания клиентов | N69: medium | O69: product
A70: 80 | B70: 81 | C70: 80 | D70: 79 | E70: УБ | F70: КАСКО | G70: 26 | H70: Полнота продуктовых механик | I70: 0 | J70: 0 | K70: Клиентский опыт | L70: Механики, влияющие на клиентский опыт | M70: Увеличить покрытие механиками | N70: medium | O70: product
A71: 80 | B71: 81 | C71: 80 | D71: 79 | E71: УБ | F71: КАСКО | G71: 27 | H71: Возврат клиентов | I71: 0.5 | J71: 0.5 | K71: Воронка оттока | L71: Реактивация оттекающих клиентов | M71: Проработать механики реактивации клиентов | N71: medium | O71: product
A72: 80 | B72: 81 | C72: 80 | D72: 79 | E72: УБ | F72: КАСКО | G72: 28 | H72: Возврат клиентов | I72: 0.5 | J72: 0.5 | K72: Воронка оттока | L72: Реактивация оттекающих клиентов | M72: Проработать механики реактивации клиентов | N72: medium | O72: product
... A79: 80 | B79: 81 | C79: 80 | D79: 79 | E79: УБ | F79: КАСКО | G79: 35 | H79: Discovery ≥40% бэклога | I79: 0.5 | J79: 1 | K79: Гипотезы и инициативы | L79: Доля исследовательских задач DA | M79: Сфокусировать бэклог аналитиков на research-задачи | N79: medium | O79: product
A80: 80 | B80: 81 | C80: 80 | D80: 79 | E80: УБ | F80: КАСКО | G80: 36 | H80: Нет собственных аналитиков | I80: 0 | J80: 0 | K80: #N/A | L80: #N/A | M80: #N/A | N80: #N/A | O80: product
A81: 80 | B81: 81 | C81: 80 | D81: 79 | E81: УБ | F81: КАСКО | G81: 38 | H81: Запуски кампаний за квартал | I81: 0.5 | J81: 0.5 | K81: Воронка привлечения | L81: Self-service / кампейнинг, покрытие | M81: Запустить кампании | N81: easy | O81: product
A82: 80 | B82: 81 | C82: 80 | D82: 79 | E82: УБ | F82: КАСКО | G82: 39 | H82: Запуски кампаний за квартал | I82: 0 | J82: 0.5 | K82: Воронка привлечения | L82: Self-service / кампейнинг, покрытие | M82: Запустить кампании | N82: easy | O82: product
A83: 80 | B83: 81 | C83: 80 | D83: 79 | E83: УБ | F83: КАСКО | G83: 40 | H83: Запуски кампаний за квартал | I83: 0.5 | J83: 0.5 | K83: Воронка привлечения | L83: Self-service / кампейнинг, покрытие | M83: Запустить кампании | N83: easy | O83: product
A84: 80 | B84: 81 | C84: 80 | D84: 79 | E84: УБ | F84: КАСКО | G84: 41 | H84: Черновики в СБОЛ ≥70% | I84: 0.5 | J84: 1 | K84: Гипотезы и инициативы | L84: Покрытие черновиками | M84: Увеличить покрытие черновиков | N84: medium | O84: product
A85: 80 | B85: 81 | C85: 80 | D85: 79 | E85: УБ | F85: КАСКО | G85: 42 | H85: CX Score | I85: 0.5 | J85: 1 | K85: Клиентский опыт | L85: Зелёная зона клиентского пути | M85: Достигнуть целевого CX Score | N85: medium | O85: product
A86: 80 | B86: 81 | C86: 80 | D86: 79 | E86: УБ | F86: КАСКО | G86: 43 | H86: A/B-тесты | I86: 0 | J86: 0 | K86: Гипотезы и инициативы | L86: Проведение A/B тестов | M86: Запустить A/B-тестирование | N86: medium | O86: product
A87: 80 | B87: 81 | C87: 80 | D87: 79 | E87: УБ | F87: КАСКО | G87: 44 | H87: Рейтинг DataDriven ≥7,5 | I87: 0 | J87: 1 | K87: Гипотезы и инициативы | L87: Средняя оценка проведенных исследований | M87: Повысить качество проведенных исследований | N87: medium | O87: product
A88: 80 | B88: 81 | C88: 80 | D88: 79 | E88: УБ | F88: КАСКО | G88: 45 | H88: Доп. инициативы сверх БП | I88: 0 | J88: 1 | K88: Гипотезы и инициативы | L88: В реестре инициатив | M88: Сформировать перечень инициатив | N88: medium | O88: product
A89: 80 | B89: 81 | C89: 80 | D89: 79 | E89: УБ | F89: КАСКО | G89: 47 | H89: Объем целевого рынка в Сбере | I89: 0 | J89: 0.2 | K89: Самооценка знания продуктовых метрик | L89: Оценка потенциального объема клиентов в Сбере | M89: Ознакомиться со значениями ключевых метрик | N89: easy | O89: product
A90: 80 | B90: 81 | C90: 80 | D90: 79 | E90: УБ | F90: КАСКО | G90: 48 | H90: Клиенты с продуктом | I90: 0.2 | J90: 0.2 | K90: Самооценка знания продуктовых метрик | L90: Фактическая база клиентов продукта | M90: Ознакомиться со значениями ключевых метрик | N90: easy | O90: product
A91: 80 | B91: 81 | C91: 80 | D91: 79 | E91: УБ | F91: КАСКО | G91: 49 | H91: MAU продукта | I91: 0 | J91: 0.2 | K91: Самооценка знания продуктовых метрик | L91: Активная месячная аудитория продукта | M91: Ознакомиться со значениями ключевых метрик | N91: easy | O91: product
A92: 80 | B92: 81 | C92: 80 | D92: 79 | E92: УБ | F92: КАСКО | G92: 50 | H92: Знание продуктов спутников | I92: 0.1 | J92: 0.1 | K92: Самооценка знания продуктовых метрик | L92: Понимание связанных продуктов и сценариев | M92: Ознакомиться со значениями ключевых метрик | N92: easy | O92: product
... A101: 90 | B101: 91 | C101: 90 | D101: 89 | E101: УБ | F101: СберСова | G101: 11 | H101: Привлечение.Регулярность (авто) | I101: 0.5 | J101: 1 | K101: Воронка привлечения | L101: Daily / weekly | M101: Автоматизировать расчет воронки привлечения | N101: medium | O101: product
A102: 90 | B102: 91 | C102: 90 | D102: 89 | E102: УБ | F102: СберСова | G102: 12 | H102: Отток.Регулярная отчётность | I102: 0 | J102: не релевантно | K102: Воронка оттока | L102: Настроена по воронке | M102: Настроить мониторинг по воронке оттока | N102: easy | O102: product
A103: 90 | B103: 91 | C103: 90 | D103: 89 | E103: УБ | F103: СберСова | G103: 13 | H103: Отток.Полнота отчёта | I103: 0 | J103: Не релевантно | K103: Воронка оттока | L103: Retention, CR, удержание | M103: Донасытить метриками мониторинг по воронке оттока | N103: easy | O103: product
A104: 90 | B104: 91 | C104: 90 | D104: 89 | E104: УБ | F104: СберСова | G104: 14 | H104: Отток.Регулярность (авто) | I104: 0.5 | J104: 1 | K104: Воронка оттока | L104: Daily / weekly | M104: Автоматизировать расчет воронки оттока | N104: medium | O104: product
A105: 90 | B105: 91 | C105: 90 | D105: 89 | E105: УБ | F105: СберСова | G105: 15 | H105: Наличие бенчмарков | I105: 1 | J105: 1 | K105: BENCHMARKS | L105: Цели / динамика / рынок | M105: Сформировать бенчмарки по продуктовым метрикам | N105: medium | O105: product
A106: 90 | B106: 91 | C106: 90 | D106: 89 | E106: УБ | F106: СберСова | G106: 16 | H106: Опишите, какие бенчмарки используются | I106: 0 | J106: Маркетинговые отчеты и аналитика | K106: #N/A | L106: #N/A | M106: #N/A | N106: #N/A | O106: product
A107: 90 | B107: 91 | C107: 90 | D107: 89 | E107: УБ | F107: СберСова | G107: 17 | H107: Проведение анализа воронки привлечения | I107: 0.5 | J107: 1 | K107: Воронка привлечения | L107: Оценка эффективности, поиск точек роста | M107: Провести анализ привлечения, выявить точки роста | N107: medium | O107: product
A108: 90 | B108: 91 | C108: 90 | D108: 89 | E108: УБ | F108: СберСова | G108: 18 | H108: Составлен перечень инициатив по привлечению | I108: 1 | J108: 1 | K108: Воронка привлечения | L108: План действий по росту | M108: Сформировать перечень инициатив | N108: medium | O108: product
A109: 90 | B109: 91 | C109: 90 | D109: 89 | E109: УБ | F109: СберСова | G109: 19 | H109: Проведение анализа воронки оттока | I109: 0 | J109: не релевантно | K109: Воронка оттока | L109: Оценка причин и узких мест | M109: Провести анализ оттока, выявить точки роста | N109: medium | O109: product
A110: 90 | B110: 91 | C110: 90 | D110: 89 | E110: УБ | F110: СберСова | G110: 20 | H110: Мероприятия по работе с отклонениями | I110: 0 | J110: 1 | K110: Воронка оттока | L110: План действий по отклонениям | M110: Сформировать список мероприятий по снижению оттока | N110: medium | O110: product
A111: 90 | B111: 91 | C111: 90 | D111: 89 | E111: УБ | F111: СберСова | G111: 21 | H111: Оповещения по системным сбоям | I111: 1 | J111: 1 | K111: Алерты | L111: Авто-алерты по IT-инфраструктуре | M111: Внедрить систему оповещений | N111: easy | O111: product
A112: 90 | B112: 91 | C112: 90 | D112: 89 | E112: УБ | F112: СберСова | G112: 22 | H112: Оповещения по бизнес-метрикам | I112: 0.5 | J112: 1 | K112: Алерты | L112: Светофоры целей, драйверов, воронок | M112: Внедрить систему оповещений | N112: medium | O112: product
A113: 90 | B113: 91 | C113: 90 | D113: 89 | E113: УБ | F113: СберСова | G113: 23 | H113: Полнота продуктовых механик | I113: 0 | J113: 0 | K113: Клиентский опыт | L113: Механики, влияющие на клиентский опыт | M113: Увеличить покрытие механиками | N113: medium | O113: product
A114: 90 | B114: 91 | C114: 90 | D114: 89 | E114: УБ | F114: СберСова | G114: 24 | H114: Удержание клиентов | I114: 0 | J114: 0 | K114: Воронка оттока | L114: Коммуникация + ценность | M114: Проработать механики удержания клиентов | N114: medium | O114: product
A115: 90 | B115: 91 | C115: 90 | D115: 89 | E115: УБ | F115: СберСова | G115: 25 | H115: Удержание клиентов | I115: 1 | J115: 1 | K115: Воронка оттока | L115: Коммуникация + ценность | M115: Проработать механики удержания клиентов | N115: medium | O115: product
A116: 90 | B116: 91 | C116: 90 | D116: 89 | E116: УБ | F116: СберСова | G116: 26 | H116: Полнота продуктовых механик | I116: 0 | J116: 0 | K116: Клиентский опыт | L116: Механики, влияющие на клиентский опыт | M116: Увеличить покрытие механиками | N116: medium | O116: product
A117: 90 | B117: 91 | C117: 90 | D117: 89 | E117: УБ | F117: СберСова | G117: 27 | H117: Возврат клиентов | I117: 0 | J117: 0 | K117: Воронка оттока | L117: Реактивация оттекающих клиентов | M117: Проработать механики реактивации клиентов | N117: medium | O117: product
A118: 90 | B118: 91 | C118: 90 | D118: 89 | E118: УБ | F118: СберСова | G118: 28 | H118: Возврат клиентов | I118: 1 | J118: 1 | K118: Воронка оттока | L118: Реактивация оттекающих клиентов | M118: Проработать механики реактивации клиентов | N118: medium | O118: product
A119: 90 | B119: 91 | C119: 90 | D119: 89 | E119: УБ | F119: СберСова | G119: 29 | H119: Полнота продуктовых механик | I119: 0 | J119: 0 | K119: Клиентский опыт | L119: Механики, влияющие на клиентский опыт | M119: Увеличить покрытие механиками | N119: medium | O119: product
A120: 90 | B120: 91 | C120: 90 | D120: 89 | E120: УБ | F120: СберСова | G120: 30 | H120: Cross-sell | I120: 0.5 | J120: 1 | K120: Воронка привлечения | L120: В оформлении и после покупки | M120: Проработать механики кросс-продаж | N120: medium | O120: product
A121: 90 | B121: 91 | C121: 90 | D121: 89 | E121: УБ | F121: СберСова | G121: 31 | H121: Cross-sell | I121: 0 | J121: 0 | K121: Воронка привлечения | L121: В оформлении и после покупки | M121: Проработать механики кросс-продаж | N121: medium | O121: product
... A125: 90 | B125: 91 | C125: 90 | D125: 89 | E125: УБ | F125: СберСова | G125: 35 | H125: Discovery ≥40% бэклога | I125: 0 | J125: 1 | K125: Гипотезы и инициативы | L125: Доля исследовательских задач DA | M125: Сфокусировать бэклог аналитиков на research-задачи | N125: medium | O125: product
A126: 90 | B126: 91 | C126: 90 | D126: 89 | E126: УБ | F126: СберСова | G126: 36 | H126: Нет собственных аналитиков | I126: 0 | J126: 0 | K126: #N/A | L126: #N/A | M126: #N/A | N126: #N/A | O126: product
A127: 90 | B127: 91 | C127: 90 | D127: 89 | E127: УБ | F127: СберСова | G127: 38 | H127: Запуски кампаний за квартал | I127: 0 | J127: 0.5 | K127: Воронка привлечения | L127: Self-service / кампейнинг, покрытие | M127: Запустить кампании | N127: easy | O127: product
A128: 90 | B128: 91 | C128: 90 | D128: 89 | E128: УБ | F128: СберСова | G128: 39 | H128: Запуски кампаний за квартал | I128: 0 | J128: 0.5 | K128: Воронка привлечения | L128: Self-service / кампейнинг, покрытие | M128: Запустить кампании | N128: easy | O128: product
A129: 90 | B129: 91 | C129: 90 | D129: 89 | E129: УБ | F129: СберСова | G129: 40 | H129: Запуски кампаний за квартал | I129: 0 | J129: 0.5 | K129: Воронка привлечения | L129: Self-service / кампейнинг, покрытие | M129: Запустить кампании | N129: easy | O129: product
A130: 90 | B130: 91 | C130: 90 | D130: 89 | E130: УБ | F130: СберСова | G130: 41 | H130: Черновики в СБОЛ ≥70% | I130: 0 | J130: не релевантно | K130: Гипотезы и инициативы | L130: Покрытие черновиками | M130: Увеличить покрытие черновиков | N130: medium | O130: product
A131: 90 | B131: 91 | C131: 90 | D131: 89 | E131: УБ | F131: СберСова | G131: 42 | H131: CX Score | I131: 0 | J131: нет продукта | K131: Клиентский опыт | L131: Зелёная зона клиентского пути | M131: Достигнуть целевого CX Score | N131: medium | O131: product
A132: 90 | B132: 91 | C132: 90 | D132: 89 | E132: УБ | F132: СберСова | G132: 43 | H132: A/B-тесты | I132: 0 | J132: 0 | K132: Гипотезы и инициативы | L132: Проведение A/B тестов | M132: Запустить A/B-тестирование | N132: medium | O132: product
A133: 90 | B133: 91 | C133: 90 | D133: 89 | E133: УБ | F133: СберСова | G133: 44 | H133: Рейтинг DataDriven ≥7,5 | I133: 0 | J133: 1 | K133: Гипотезы и инициативы | L133: Средняя оценка проведенных исследований | M133: Повысить качество проведенных исследований | N133: medium | O133: product
A134: 90 | B134: 91 | C134: 90 | D134: 89 | E134: УБ | F134: СберСова | G134: 45 | H134: Доп. инициативы сверх БП | I134: 0 | J134: не релевантно | K134: Гипотезы и инициативы | L134: В реестре инициатив | M134: Сформировать перечень инициатив | N134: medium | O134: product
A135: 90 | B135: 91 | C135: 90 | D135: 89 | E135: УБ | F135: СберСова | G135: 47 | H135: Объем целевого рынка в Сбере | I135: 0.2 | J135: 0.2 | K135: Самооценка знания продуктовых метрик | L135: Оценка потенциального объема клиентов в Сбере | M135: Ознакомиться со значениями ключевых метрик | N135: easy | O135: product
...
